Workbook

Sheet Start Here
A1: Dental Practice Numbers Workbook
A2: by Knackdesk · knackdesk.com
A4: HOW TO USE
A5: 1. Settings: chairs, opening hours and days, dentists and hygienists, payroll taxes and benefits, owner compensation, your target overhead % and hygiene margin %, and new-patient retention and first-year value. Available chair hours and provider hours follow and every other sheet reads them.
A6: 2. Monthly P&L: one row per month with gross production, adjustments, collections, staff wages, rent and facilities, supplies and lab, marketing and other overhead. Net production, collection rate, loaded payroll, total overhead, overhead % of collections, profit before and after owner pay, profit margin and the gap to your target overhead are calculated, with totals.
A7: 3. Provider Production: one row per dentist per month with hours, days, gross production and adjustments. Net production, production per hour and per day, overhead per provider hour and profit per hour are calculated.
A8: 4. Hygiene: one row per month with hygiene production, hygienist wages, supplies, hygienist hours and your own overhead allocation. Loaded wages, total cost, department profit, margin %, production and cost per hour and the gap to your target margin are calculated, with totals.
A9: 5. Chairs & New Patients: scheduled chair hours per month against available chair hours give utilization %, idle hours and the production left unrealised (production per hour defaults from the Monthly P&L; type your own to override). Below, marketing spend (defaults from the Monthly P&L) and new patients give cost per new patient, lifetime value, value-to-cost ratio and break-even new patients.
A10: 6. Summary: year-to-date collections, net production, collection rate, overhead % against target, profit before and after owner pay, best and worst month, production per provider hour, hygiene margin, chair utilization and unrealised production, cost per new patient and months above your overhead target.
A12: LEGEND
A13: Blue text = a cell you type into. Black text = a formula, leave it alone. Yellow fill = key inputs.
A15: DEFINITIONS
... A25: Arithmetic only; not financial advice.

Sheet Settings
A1: Settings
A2: Chairs (operatories) | B2: 4 | C2: Example default 4. Treatment chairs you can book, dentist and hygiene chairs together.
A3: Hours open per day | B3: 8 | C3: Example default 8. Clinical hours a chair can be booked each day you are open.
A4: Days open per month | B4: 20 | C4: Example default 20. Clinical days open in a typical month.
A5: Providers (dentists) count | B5: 2 | C5: Example default 2. Dentists producing chairside, full-time equivalents.
A6: Hygienists count | B6: 2 | C6: Example default 2. Hygienists, full-time equivalents; gives hygienist hours available below.
A7: Payroll taxes and benefits % | B7: 15 | C7: Default 15. Employer payroll taxes, pension, health cover and other benefits on top of wages.
A8: Owner compensation per month | B8: 12000 | C8: Example default 12,000 a month. What the owner dentist pays themselves; kept out of overhead and shown separately.
A9: Target overhead % of collections | B9: 60 | C9: Default 60. A placeholder for your own target, not a recommendation or an industry benchmark.
A10: Target hygiene margin % | B10: 30 | C10: Default 30. A placeholder for your own target, not a recommendation or an industry benchmark.
A11: New-patient retention % | B11: 60 | C11: Default 60. Share of new patients still coming each year after the first; use your own recall data.
A12: Years retained | B12: 3 | C12: Default 3. How many years a retained patient typically stays, including the first.
A13: Average first-year value per new patient | B13: 900 | C13: Example default 900. Average collections from a new patient in their first year.
A14: Available chair hours per month | B14: =ROUND(B2*B3*B4,2) -> 640 | C14: formula: chairs × hours open per day × days open per month
A15: Provider hours per month | B15: =ROUND(B5*B3*B4,2) -> 320 | C15: formula: providers × hours open per day × days open per month
A16: Hygienist hours available per month | B16: =ROUND(B6*B3*B4,2) -> 320 | C16: formula: hygienists × hours open per day × days open per month
A17: Clinical hours open per month | B17: =ROUND(B3*B4,2) -> 160 | C17: formula: hours open per day × days open per month (one chair or one person)
A18: Lifetime value per new patient | B18: =ROUND(B13+B13*B11/100*(B12-1),2) -> 1980 | C18: formula: first-year value + first-year value × retention % × (years retained − 1); collections, not profit

Sheet Monthly P&L
A1: Monthly P&L
A2: One row per month, filled top down. Owner compensation comes from Settings and is kept out of overhead.
A4: Month | B4: Gross production | C4: Adjustments | D4: Collections | E4: Staff wages | F4: Payroll loaded | G4: Rent and facilities | H4: Supplies and lab | I4: Marketing | J4: Other overhead | K4: Net production | L4: Collection rate % | M4: Total overhead | N4: Overhead % of collections | O4: Profit before owner | P4: Profit after owner | Q4: Profit margin after owner % | R4: Overhead % vs target
A5: 46023 | B5: 120000 | C5: 18000 | D5: 98000 | E5: 26000 | F5: =IF(A5="","",ROUND(E5*(1+Settings!$B$7/100),2)) -> 29900 | G5: 7500 | H5: 7200 | I5: 3000 | J5: 4200 | K5: =IF(A5="","",ROUND(B5-C5,2)) -> 102000 | L5: =IF(A5="","",IFERROR(ROUND(D5/K5*100,2),0)) -> 96.08 | M5: =IF(A5="","",ROUND(F5+G5+H5+I5+J5,2)) -> 51800 | N5: =IF(A5="","",IFERROR(ROUND(M5/D5*100,2),0)) -> 52.86 | O5: =IF(A5="","",ROUND(D5-M5,2)) -> 46200 | P5: =IF(A5="","",ROUND(O5-Settings!$B$8,2)) -> 34200 | Q5: =IF(A5="","",IFERROR(ROUND(P5/D5*100,2),0)) -> 34.9 | R5: =IF(A5="","",ROUND(N5-Settings!$B$9,2)) -> -7.14
A6: 46054 | B6: 112000 | C6: 16500 | D6: 92000 | E6: 26000 | F6: =IF(A6="","",ROUND(E6*(1+Settings!$B$7/100),2)) -> 29900 | G6: 7500 | H6: 6800 | I6: 3500 | J6: 4000 | K6: =IF(A6="","",ROUND(B6-C6,2)) -> 95500 | L6: =IF(A6="","",IFERROR(ROUND(D6/K6*100,2),0)) -> 96.34 | M6: =IF(A6="","",ROUND(F6+G6+H6+I6+J6,2)) -> 51700 | N6: =IF(A6="","",IFERROR(ROUND(M6/D6*100,2),0)) -> 56.2 | O6: =IF(A6="","",ROUND(D6-M6,2)) -> 40300 | P6: =IF(A6="","",ROUND(O6-Settings!$B$8,2)) -> 28300 | Q6: =IF(A6="","",IFERROR(ROUND(P6/D6*100,2),0)) -> 30.76 | R6: =IF(A6="","",ROUND(N6-Settings!$B$9,2)) -> -3.8
A7: 46082 | B7: 128000 | C7: 19000 | D7: 104000 | E7: 27500 | F7: =IF(A7="","",ROUND(E7*(1+Settings!$B$7/100),2)) -> 31625 | G7: 7500 | H7: 7900 | I7: 3000 | J7: 4300 | K7: =IF(A7="","",ROUND(B7-C7,2)) -> 109000 | L7: =IF(A7="","",IFERROR(ROUND(D7/K7*100,2),0)) -> 95.41 | M7: =IF(A7="","",ROUND(F7+G7+H7+I7+J7,2)) -> 54325 | N7: =IF(A7="","",IFERROR(ROUND(M7/D7*100,2),0)) -> 52.24 | O7: =IF(A7="","",ROUND(D7-M7,2)) -> 49675 | P7: =IF(A7="","",ROUND(O7-Settings!$B$8,2)) -> 37675 | Q7: =IF(A7="","",IFERROR(ROUND(P7/D7*100,2),0)) -> 36.23 | R7: =IF(A7="","",ROUND(N7-Settings!$B$9,2)) -> -7.76
A8: 46113 | B8: 105000 | C8: 15800 | D8: 84500 | E8: 27500 | F8: =IF(A8="","",ROUND(E8*(1+Settings!$B$7/100),2)) -> 31625 | G8: 7500 | H8: 6900 | I8: 4500 | J8: 4600 | K8: =IF(A8="","",ROUND(B8-C8,2)) -> 89200 | L8: =IF(A8="","",IFERROR(ROUND(D8/K8*100,2),0)) -> 94.73 | M8: =IF(A8="","",ROUND(F8+G8+H8+I8+J8,2)) -> 55125 | N8: =IF(A8="","",IFERROR(ROUND(M8/D8*100,2),0)) -> 65.24 | O8: =IF(A8="","",ROUND(D8-M8,2)) -> 29375 | P8: =IF(A8="","",ROUND(O8-Settings!$B$8,2)) -> 17375 | Q8: =IF(A8="","",IFERROR(ROUND(P8/D8*100,2),0)) -> 20.56 | R8: =IF(A8="","",ROUND(N8-Settings!$B$9,2)) -> 5.24
A9: 46143 | B9: 124000 | C9: 18500 | D9: 101000 | E9: 27500 | F9: =IF(A9="","",ROUND(E9*(1+Settings!$B$7/100),2)) -> 31625 | G9: 7500 | H9: 7400 | I9: 3200 | J9: 4100 | K9: =IF(A9="","",ROUND(B9-C9,2)) -> 105500 | L9: =IF(A9="","",IFERROR(ROUND(D9/K9*100,2),0)) -> 95.73 | M9: =IF(A9="","",ROUND(F9+G9+H9+I9+J9,2)) -> 53825 | N9: =IF(A9="","",IFERROR(ROUND(M9/D9*100,2),0)) -> 53.29 | O9: =IF(A9="","",ROUND(D9-M9,2)) -> 47175 | P9: =IF(A9="","",ROUND(O9-Settings!$B$8,2)) -> 35175 | Q9: =IF(A9="","",IFERROR(ROUND(P9/D9*100,2),0)) -> 34.83 | R9: =IF(A9="","",ROUND(N9-Settings!$B$9,2)) -> -6.71
A10: 46174 | B10: 131000 | C10: 19500 | D10: 108000 | E10: 28000 | F10: =IF(A10="","",ROUND(E10*(1+Settings!$B$7/100),2)) -> 32200 | G10: 7500 | H10: 8100 | I10: 3000 | J10: 4400 | K10: =IF(A10="","",ROUND(B10-C10,2)) -> 111500 | L10: =IF(A10="","",IFERROR(ROUND(D10/K10*100,2),0)) -> 96.86 | M10: =IF(A10="","",ROUND(F10+G10+H10+I10+J10,2)) -> 55200 | N10: =IF(A10="","",IFERROR(ROUND(M10/D10*100,2),0)) -> 51.11 | O10: =IF(A10="","",ROUND(D10-M10,2)) -> 52800 | P10: =IF(A10="","",ROUND(O10-Settings!$B$8,2)) -> 40800 | Q10: =IF(A10="","",IFERROR(ROUND(P10/D10*100,2),0)) -> 37.78 | R10: =IF(A10="","",ROUND(N10-Settings!$B$9,2)) -> -8.89
F11: =IF(A11="","",ROUND(E11*(1+Settings!$B$7/100),2)) | K11: =IF(A11="","",ROUND(B11-C11,2)) | L11: =IF(A11="","",IFERROR(ROUND(D11/K11*100,2),0)) | M11: =IF(A11="","",ROUND(F11+G11+H11+I11+J11,2)) | N11: =IF(A11="","",IFERROR(ROUND(M11/D11*100,2),0)) | O11: =IF(A11="","",ROUND(D11-M11,2)) | P11: =IF(A11="","",ROUND(O11-Settings!$B$8,2)) | Q11: =IF(A11="","",IFERROR(ROUND(P11/D11*100,2),0)) | R11: =IF(A11="","",ROUND(N11-Settings!$B$9,2))
F12: =IF(A12="","",ROUND(E12*(1+Settings!$B$7/100),2)) | K12: =IF(A12="","",ROUND(B12-C12,2)) | L12: =IF(A12="","",IFERROR(ROUND(D12/K12*100,2),0)) | M12: =IF(A12="","",ROUND(F12+G12+H12+I12+J12,2)) | N12: =IF(A12="","",IFERROR(ROUND(M12/D12*100,2),0)) | O12: =IF(A12="","",ROUND(D12-M12,2)) | P12: =IF(A12="","",ROUND(O12-Settings!$B$8,2)) | Q12: =IF(A12="","",IFERROR(ROUND(P12/D12*100,2),0)) | R12: =IF(A12="","",ROUND(N12-Settings!$B$9,2))
F13: =IF(A13="","",ROUND(E13*(1+Settings!$B$7/100),2)) | K13: =IF(A13="","",ROUND(B13-C13,2)) | L13: =IF(A13="","",IFERROR(ROUND(D13/K13*100,2),0)) | M13: =IF(A13="","",ROUND(F13+G13+H13+I13+J13,2)) | N13: =IF(A13="","",IFERROR(ROUND(M13/D13*100,2),0)) | O13: =IF(A13="","",ROUND(D13-M13,2)) | P13: =IF(A13="","",ROUND(O13-Settings!$B$8,2)) | Q13: =IF(A13="","",IFERROR(ROUND(P13/D13*100,2),0)) | R13: =IF(A13="","",ROUND(N13-Settings!$B$9,2))
F14: =IF(A14="","",ROUND(E14*(1+Settings!$B$7/100),2)) | K14: =IF(A14="","",ROUND(B14-C14,2)) | L14: =IF(A14="","",IFERROR(ROUND(D14/K14*100,2),0)) | M14: =IF(A14="","",ROUND(F14+G14+H14+I14+J14,2)) | N14: =IF(A14="","",IFERROR(ROUND(M14/D14*100,2),0)) | O14: =IF(A14="","",ROUND(D14-M14,2)) | P14: =IF(A14="","",ROUND(O14-Settings!$B$8,2)) | Q14: =IF(A14="","",IFERROR(ROUND(P14/D14*100,2),0)) | R14: =IF(A14="","",ROUND(N14-Settings!$B$9,2))
F15: =IF(A15="","",ROUND(E15*(1+Settings!$B$7/100),2)) | K15: =IF(A15="","",ROUND(B15-C15,2)) | L15: =IF(A15="","",IFERROR(ROUND(D15/K15*100,2),0)) | M15: =IF(A15="","",ROUND(F15+G15+H15+I15+J15,2)) | N15: =IF(A15="","",IFERROR(ROUND(M15/D15*100,2),0)) | O15: =IF(A15="","",ROUND(D15-M15,2)) | P15: =IF(A15="","",ROUND(O15-Settings!$B$8,2)) | Q15: =IF(A15="","",IFERROR(ROUND(P15/D15*100,2),0)) | R15: =IF(A15="","",ROUND(N15-Settings!$B$9,2))
F16: =IF(A16="","",ROUND(E16*(1+Settings!$B$7/100),2)) | K16: =IF(A16="","",ROUND(B16-C16,2)) | L16: =IF(A16="","",IFERROR(ROUND(D16/K16*100,2),0)) | M16: =IF(A16="","",ROUND(F16+G16+H16+I16+J16,2)) | N16: =IF(A16="","",IFERROR(ROUND(M16/D16*100,2),0)) | O16: =IF(A16="","",ROUND(D16-M16,2)) | P16: =IF(A16="","",ROUND(O16-Settings!$B$8,2)) | Q16: =IF(A16="","",IFERROR(ROUND(P16/D16*100,2),0)) | R16: =IF(A16="","",ROUND(N16-Settings!$B$9,2))
A17: Total | B17: =SUM(B5:B16) -> 720000 | C17: =SUM(C5:C16) -> 107300 | D17: =SUM(D5:D16) -> 587500 | E17: =SUM(E5:E16) -> 162500 | F17: =SUM(F5:F16) -> 186875 | G17: =SUM(G5:G16) -> 45000 | H17: =SUM(H5:H16) -> 44300 | I17: =SUM(I5:I16) -> 20200 | ... K17: =SUM(K5:K16) -> 612700 | L17: =IFERROR(ROUND(D17/K17*100,2),0) -> 95.89 | M17: =SUM(M5:M16) -> 321975 | N17: =IFERROR(ROUND(M17/D17*100,2),0) -> 54.8 | O17: =SUM(O5:O16) -> 265525 | P17: =SUM(P5:P16) -> 193525 | Q17: =IFERROR(ROUND(P17/D17*100,2),0) -> 32.94 | R17: =ROUND(N17-Settings!$B$9,2) -> -5.2
A18: Overhead % vs target: positive = overhead above your own target in Settings; negative = below it.

Sheet Provider Production
A1: Provider Production
A2: One row per dentist per month. Overhead per hour = that month's total overhead on the Monthly P&L ÷ provider hours per month in Settings.
A4: Month | B4: Provider | C4: Hours worked | D4: Days worked | E4: Gross production | F4: Adjustments | G4: Net production | H4: Production per hour | I4: Production per day | J4: Overhead per provider hour | K4: Profit per hour
A5: 46023 | B5: Dr. Patel | C5: 150 | D5: 19 | E5: 62000 | F5: 9000 | G5: =IF(A5="","",ROUND(E5-F5,2)) -> 53000 | H5: =IF(A5="","",IFERROR(ROUND(G5/C5,2),0)) -> 353.33 | I5: =IF(A5="","",IFERROR(ROUND(G5/D5,2),0)) -> 2789.47 | J5: =IF(A5="","",IFERROR(ROUND(INDEX('Monthly P&L'!$M$5:$M$16,MATCH(A5,'Monthly P&L'!$A$5:$A$16,0))/Settings!$B$15,2),0)) -> 161.88 | K5: =IF(A5="","",ROUND(H5-J5,2)) -> 191.45
A6: 46023 | B6: Dr. Moreno | C6: 140 | D6: 18 | E6: 40000 | F6: 6500 | G6: =IF(A6="","",ROUND(E6-F6,2)) -> 33500 | H6: =IF(A6="","",IFERROR(ROUND(G6/C6,2),0)) -> 239.29 | I6: =IF(A6="","",IFERROR(ROUND(G6/D6,2),0)) -> 1861.11 | J6: =IF(A6="","",IFERROR(ROUND(INDEX('Monthly P&L'!$M$5:$M$16,MATCH(A6,'Monthly P&L'!$A$5:$A$16,0))/Settings!$B$15,2),0)) -> 161.88 | K6: =IF(A6="","",ROUND(H6-J6,2)) -> 77.41
A7: 46054 | B7: Dr. Patel | C7: 148 | D7: 19 | E7: 58000 | F7: 8500 | G7: =IF(A7="","",ROUND(E7-F7,2)) -> 49500 | H7: =IF(A7="","",IFERROR(ROUND(G7/C7,2),0)) -> 334.46 | I7: =IF(A7="","",IFERROR(ROUND(G7/D7,2),0)) -> 2605.26 | J7: =IF(A7="","",IFERROR(ROUND(INDEX('Monthly P&L'!$M$5:$M$16,MATCH(A7,'Monthly P&L'!$A$5:$A$16,0))/Settings!$B$15,2),0)) -> 161.56 | K7: =IF(A7="","",ROUND(H7-J7,2)) -> 172.9
A8: 46054 | B8: Dr. Moreno | C8: 136 | D8: 18 | E8: 37000 | F8: 6000 | G8: =IF(A8="","",ROUND(E8-F8,2)) -> 31000 | H8: =IF(A8="","",IFERROR(ROUND(G8/C8,2),0)) -> 227.94 | I8: =IF(A8="","",IFERROR(ROUND(G8/D8,2),0)) -> 1722.22 | J8: =IF(A8="","",IFERROR(ROUND(INDEX('Monthly P&L'!$M$5:$M$16,MATCH(A8,'Monthly P&L'!$A$5:$A$16,0))/Settings!$B$15,2),0)) -> 161.56 | K8: =IF(A8="","",ROUND(H8-J8,2)) -> 66.38
A9: 46082 | B9: Dr. Patel | C9: 156 | D9: 20 | E9: 66000 | F9: 9500 | G9: =IF(A9="","",ROUND(E9-F9,2)) -> 56500 | H9: =IF(A9="","",IFERROR(ROUND(G9/C9,2),0)) -> 362.18 | I9: =IF(A9="","",IFERROR(ROUND(G9/D9,2),0)) -> 2825 | J9: =IF(A9="","",IFERROR(ROUND(INDEX('Monthly P&L'!$M$5:$M$16,MATCH(A9,'Monthly P&L'!$A$5:$A$16,0))/Settings!$B$15,2),0)) -> 169.77 | K9: =IF(A9="","",ROUND(H9-J9,2)) -> 192.41
A10: 46082 | B10: Dr. Moreno | C10: 144 | D10: 19 | E10: 42000 | F10: 6800 | G10: =IF(A10="","",ROUND(E10-F10,2)) -> 35200 | H10: =IF(A10="","",IFERROR(ROUND(G10/C10,2),0)) -> 244.44 | I10: =IF(A10="","",IFERROR(ROUND(G10/D10,2),0)) -> 1852.63 | J10: =IF(A10="","",IFERROR(ROUND(INDEX('Monthly P&L'!$M$5:$M$16,MATCH(A10,'Monthly P&L'!$A$5:$A$16,0))/Settings!$B$15,2),0)) -> 169.77 | K10: =IF(A10="","",ROUND(H10-J10,2)) -> 74.67
A11: 46113 | B11: Dr. Patel | C11: 142 | D11: 18 | E11: 54000 | F11: 8200 | G11: =IF(A11="","",ROUND(E11-F11,2)) -> 45800 | H11: =IF(A11="","",IFERROR(ROUND(G11/C11,2),0)) -> 322.54 | I11: =IF(A11="","",IFERROR(ROUND(G11/D11,2),0)) -> 2544.44 | J11: =IF(A11="","",IFERROR(ROUND(INDEX('Monthly P&L'!$M$5:$M$16,MATCH(A11,'Monthly P&L'!$A$5:$A$16,0))/Settings!$B$15,2),0)) -> 172.27 | K11: =IF(A11="","",ROUND(H11-J11,2)) -> 150.27
A12: 46113 | B12: Dr. Moreno | C12: 130 | D12: 17 | E12: 34000 | F12: 5600 | G12: =IF(A12="","",ROUND(E12-F12,2)) -> 28400 | H12: =IF(A12="","",IFERROR(ROUND(G12/C12,2),0)) -> 218.46 | I12: =IF(A12="","",IFERROR(ROUND(G12/D12,2),0)) -> 1670.59 | J12: =IF(A12="","",IFERROR(ROUND(INDEX('Monthly P&L'!$M$5:$M$16,MATCH(A12,'Monthly P&L'!$A$5:$A$16,0))/Settings!$B$15,2),0)) -> 172.27 | K12: =IF(A12="","",ROUND(H12-J12,2)) -> 46.19
G13: =IF(A13="","",ROUND(E13-F13,2)) | H13: =IF(A13="","",IFERROR(ROUND(G13/C13,2),0)) | I13: =IF(A13="","",IFERROR(ROUND(G13/D13,2),0)) | J13: =IF(A13="","",IFERROR(ROUND(INDEX('Monthly P&L'!$M$5:$M$16,MATCH(A13,'Monthly P&L'!$A$5:$A$16,0))/Settings!$B$15,2),0)) | K13: =IF(A13="","",ROUND(H13-J13,2))
G14: =IF(A14="","",ROUND(E14-F14,2)) | H14: =IF(A14="","",IFERROR(ROUND(G14/C14,2),0)) | I14: =IF(A14="","",IFERROR(ROUND(G14/D14,2),0)) | J14: =IF(A14="","",IFERROR(ROUND(INDEX('Monthly P&L'!$M$5:$M$16,MATCH(A14,'Monthly P&L'!$A$5:$A$16,0))/Settings!$B$15,2),0)) | K14: =IF(A14="","",ROUND(H14-J14,2))
G15: =IF(A15="","",ROUND(E15-F15,2)) | H15: =IF(A15="","",IFERROR(ROUND(G15/C15,2),0)) | I15: =IF(A15="","",IFERROR(ROUND(G15/D15,2),0)) | J15: =IF(A15="","",IFERROR(ROUND(INDEX('Monthly P&L'!$M$5:$M$16,MATCH(A15,'Monthly P&L'!$A$5:$A$16,0))/Settings!$B$15,2),0)) | K15: =IF(A15="","",ROUND(H15-J15,2))
G16: =IF(A16="","",ROUND(E16-F16,2)) | H16: =IF(A16="","",IFERROR(ROUND(G16/C16,2),0)) | I16: =IF(A16="","",IFERROR(ROUND(G16/D16,2),0)) | J16: =IF(A16="","",IFERROR(ROUND(INDEX('Monthly P&L'!$M$5:$M$16,MATCH(A16,'Monthly P&L'!$A$5:$A$16,0))/Settings!$B$15,2),0)) | K16: =IF(A16="","",ROUND(H16-J16,2))
G17: =IF(A17="","",ROUND(E17-F17,2)) | H17: =IF(A17="","",IFERROR(ROUND(G17/C17,2),0)) | I17: =IF(A17="","",IFERROR(ROUND(G17/D17,2),0)) | J17: =IF(A17="","",IFERROR(ROUND(INDEX('Monthly P&L'!$M$5:$M$16,MATCH(A17,'Monthly P&L'!$A$5:$A$16,0))/Settings!$B$15,2),0)) | K17: =IF(A17="","",ROUND(H17-J17,2))
G18: =IF(A18="","",ROUND(E18-F18,2)) | H18: =IF(A18="","",IFERROR(ROUND(G18/C18,2),0)) | I18: =IF(A18="","",IFERROR(ROUND(G18/D18,2),0)) | J18: =IF(A18="","",IFERROR(ROUND(INDEX('Monthly P&L'!$M$5:$M$16,MATCH(A18,'Monthly P&L'!$A$5:$A$16,0))/Settings!$B$15,2),0)) | K18: =IF(A18="","",ROUND(H18-J18,2))
G19: =IF(A19="","",ROUND(E19-F19,2)) | H19: =IF(A19="","",IFERROR(ROUND(G19/C19,2),0)) | I19: =IF(A19="","",IFERROR(ROUND(G19/D19,2),0)) | J19: =IF(A19="","",IFERROR(ROUND(INDEX('Monthly P&L'!$M$5:$M$16,MATCH(A19,'Monthly P&L'!$A$5:$A$16,0))/Settings!$B$15,2),0)) | K19: =IF(A19="","",ROUND(H19-J19,2))
G20: =IF(A20="","",ROUND(E20-F20,2)) | H20: =IF(A20="","",IFERROR(ROUND(G20/C20,2),0)) | I20: =IF(A20="","",IFERROR(ROUND(G20/D20,2),0)) | J20: =IF(A20="","",IFERROR(ROUND(INDEX('Monthly P&L'!$M$5:$M$16,MATCH(A20,'Monthly P&L'!$A$5:$A$16,0))/Settings!$B$15,2),0)) | K20: =IF(A20="","",ROUND(H20-J20,2))
G21: =IF(A21="","",ROUND(E21-F21,2)) | H21: =IF(A21="","",IFERROR(ROUND(G21/C21,2),0)) | I21: =IF(A21="","",IFERROR(ROUND(G21/D21,2),0)) | J21: =IF(A21="","",IFERROR(ROUND(INDEX('Monthly P&L'!$M$5:$M$16,MATCH(A21,'Monthly P&L'!$A$5:$A$16,0))/Settings!$B$15,2),0)) | K21: =IF(A21="","",ROUND(H21-J21,2))
G22: =IF(A22="","",ROUND(E22-F22,2)) | H22: =IF(A22="","",IFERROR(ROUND(G22/C22,2),0)) | I22: =IF(A22="","",IFERROR(ROUND(G22/D22,2),0)) | J22: =IF(A22="","",IFERROR(ROUND(INDEX('Monthly P&L'!$M$5:$M$16,MATCH(A22,'Monthly P&L'!$A$5:$A$16,0))/Settings!$B$15,2),0)) | K22: =IF(A22="","",ROUND(H22-J22,2))
G23: =IF(A23="","",ROUND(E23-F23,2)) | H23: =IF(A23="","",IFERROR(ROUND(G23/C23,2),0)) | I23: =IF(A23="","",IFERROR(ROUND(G23/D23,2),0)) | J23: =IF(A23="","",IFERROR(ROUND(INDEX('Monthly P&L'!$M$5:$M$16,MATCH(A23,'Monthly P&L'!$A$5:$A$16,0))/Settings!$B$15,2),0)) | K23: =IF(A23="","",ROUND(H23-J23,2))
G24: =IF(A24="","",ROUND(E24-F24,2)) | H24: =IF(A24="","",IFERROR(ROUND(G24/C24,2),0)) | I24: =IF(A24="","",IFERROR(ROUND(G24/D24,2),0)) | J24: =IF(A24="","",IFERROR(ROUND(INDEX('Monthly P&L'!$M$5:$M$16,MATCH(A24,'Monthly P&L'!$A$5:$A$16,0))/Settings!$B$15,2),0)) | K24: =IF(A24="","",ROUND(H24-J24,2))
A25: Total | C25: =SUM(C5:C24) -> 1146 | D25: =SUM(D5:D24) -> 148 | E25: =SUM(E5:E24) -> 393000 | F25: =SUM(F5:F24) -> 60100 | G25: =SUM(G5:G24) -> 332900 | H25: =IFERROR(ROUND(G25/C25,2),0) -> 290.49 | I25: =IFERROR(ROUND(G25/D25,2),0) -> 2249.32

Sheet Hygiene
A1: Hygiene
A2: One row per month. Wages are loaded with payroll taxes and benefits from Settings; the overhead allocation is your own share for the hygiene department.
A4: Month | B4: Hygiene production | C4: Hygienist wages | D4: Hygiene supplies | E4: Hygienist hours | F4: Overhead allocation | G4: Loaded wages | H4: Total cost | I4: Department profit | J4: Margin % | K4: Production per hour | L4: Cost per hour | M4: Margin % vs target
A5: 46023 | B5: 18000 | C5: 7800 | D5: 900 | E5: 300 | F5: 2500 | G5: =IF(A5="","",ROUND(C5*(1+Settings!$B$7/100),2)) -> 8970 | H5: =IF(A5="","",ROUND(G5+D5+F5,2)) -> 12370 | I5: =IF(A5="","",ROUND(B5-H5,2)) -> 5630 | J5: =IF(A5="","",IFERROR(ROUND(I5/B5*100,2),0)) -> 31.28 | K5: =IF(A5="","",IFERROR(ROUND(B5/E5,2),0)) -> 60 | L5: =IF(A5="","",IFERROR(ROUND(H5/E5,2),0)) -> 41.23 | M5: =IF(A5="","",ROUND(J5-Settings!$B$10,2)) -> 1.28
A6: 46054 | B6: 17000 | C6: 7800 | D6: 850 | E6: 290 | F6: 2500 | G6: =IF(A6="","",ROUND(C6*(1+Settings!$B$7/100),2)) -> 8970 | H6: =IF(A6="","",ROUND(G6+D6+F6,2)) -> 12320 | I6: =IF(A6="","",ROUND(B6-H6,2)) -> 4680 | J6: =IF(A6="","",IFERROR(ROUND(I6/B6*100,2),0)) -> 27.53 | K6: =IF(A6="","",IFERROR(ROUND(B6/E6,2),0)) -> 58.62 | L6: =IF(A6="","",IFERROR(ROUND(H6/E6,2),0)) -> 42.48 | M6: =IF(A6="","",ROUND(J6-Settings!$B$10,2)) -> -2.47
A7: 46082 | B7: 20000 | C7: 8200 | D7: 950 | E7: 310 | F7: 2500 | G7: =IF(A7="","",ROUND(C7*(1+Settings!$B$7/100),2)) -> 9430 | H7: =IF(A7="","",ROUND(G7+D7+F7,2)) -> 12880 | I7: =IF(A7="","",ROUND(B7-H7,2)) -> 7120 | J7: =IF(A7="","",IFERROR(ROUND(I7/B7*100,2),0)) -> 35.6 | K7: =IF(A7="","",IFERROR(ROUND(B7/E7,2),0)) -> 64.52 | L7: =IF(A7="","",IFERROR(ROUND(H7/E7,2),0)) -> 41.55 | M7: =IF(A7="","",ROUND(J7-Settings!$B$10,2)) -> 5.6
A8: 46113 | B8: 17000 | C8: 8200 | D8: 900 | E8: 300 | F8: 2500 | G8: =IF(A8="","",ROUND(C8*(1+Settings!$B$7/100),2)) -> 9430 | H8: =IF(A8="","",ROUND(G8+D8+F8,2)) -> 12830 | I8: =IF(A8="","",ROUND(B8-H8,2)) -> 4170 | J8: =IF(A8="","",IFERROR(ROUND(I8/B8*100,2),0)) -> 24.53 | K8: =IF(A8="","",IFERROR(ROUND(B8/E8,2),0)) -> 56.67 | L8: =IF(A8="","",IFERROR(ROUND(H8/E8,2),0)) -> 42.77 | M8: =IF(A8="","",ROUND(J8-Settings!$B$10,2)) -> -5.47
A9: 46143 | B9: 19500 | C9: 8200 | D9: 950 | E9: 305 | F9: 2500 | G9: =IF(A9="","",ROUND(C9*(1+Settings!$B$7/100),2)) -> 9430 | H9: =IF(A9="","",ROUND(G9+D9+F9,2)) -> 12880 | I9: =IF(A9="","",ROUND(B9-H9,2)) -> 6620 | J9: =IF(A9="","",IFERROR(ROUND(I9/B9*100,2),0)) -> 33.95 | K9: =IF(A9="","",IFERROR(ROUND(B9/E9,2),0)) -> 63.93 | L9: =IF(A9="","",IFERROR(ROUND(H9/E9,2),0)) -> 42.23 | M9: =IF(A9="","",ROUND(J9-Settings!$B$10,2)) -> 3.95
A10: 46174 | B10: 21000 | C10: 8400 | D10: 1000 | E10: 320 | F10: 2500 | G10: =IF(A10="","",ROUND(C10*(1+Settings!$B$7/100),2)) -> 9660 | H10: =IF(A10="","",ROUND(G10+D10+F10,2)) -> 13160 | I10: =IF(A10="","",ROUND(B10-H10,2)) -> 7840 | J10: =IF(A10="","",IFERROR(ROUND(I10/B10*100,2),0)) -> 37.33 | K10: =IF(A10="","",IFERROR(ROUND(B10/E10,2),0)) -> 65.63 | L10: =IF(A10="","",IFERROR(ROUND(H10/E10,2),0)) -> 41.13 | M10: =IF(A10="","",ROUND(J10-Settings!$B$10,2)) -> 7.33
G11: =IF(A11="","",ROUND(C11*(1+Settings!$B$7/100),2)) | H11: =IF(A11="","",ROUND(G11+D11+F11,2)) | I11: =IF(A11="","",ROUND(B11-H11,2)) | J11: =IF(A11="","",IFERROR(ROUND(I11/B11*100,2),0)) | K11: =IF(A11="","",IFERROR(ROUND(B11/E11,2),0)) | L11: =IF(A11="","",IFERROR(ROUND(H11/E11,2),0)) | M11: =IF(A11="","",ROUND(J11-Settings!$B$10,2))
G12: =IF(A12="","",ROUND(C12*(1+Settings!$B$7/100),2)) | H12: =IF(A12="","",ROUND(G12+D12+F12,2)) | I12: =IF(A12="","",ROUND(B12-H12,2)) | J12: =IF(A12="","",IFERROR(ROUND(I12/B12*100,2),0)) | K12: =IF(A12="","",IFERROR(ROUND(B12/E12,2),0)) | L12: =IF(A12="","",IFERROR(ROUND(H12/E12,2),0)) | M12: =IF(A12="","",ROUND(J12-Settings!$B$10,2))
G13: =IF(A13="","",ROUND(C13*(1+Settings!$B$7/100),2)) | H13: =IF(A13="","",ROUND(G13+D13+F13,2)) | I13: =IF(A13="","",ROUND(B13-H13,2)) | J13: =IF(A13="","",IFERROR(ROUND(I13/B13*100,2),0)) | K13: =IF(A13="","",IFERROR(ROUND(B13/E13,2),0)) | L13: =IF(A13="","",IFERROR(ROUND(H13/E13,2),0)) | M13: =IF(A13="","",ROUND(J13-Settings!$B$10,2))
G14: =IF(A14="","",ROUND(C14*(1+Settings!$B$7/100),2)) | H14: =IF(A14="","",ROUND(G14+D14+F14,2)) | I14: =IF(A14="","",ROUND(B14-H14,2)) | J14: =IF(A14="","",IFERROR(ROUND(I14/B14*100,2),0)) | K14: =IF(A14="","",IFERROR(ROUND(B14/E14,2),0)) | L14: =IF(A14="","",IFERROR(ROUND(H14/E14,2),0)) | M14: =IF(A14="","",ROUND(J14-Settings!$B$10,2))
G15: =IF(A15="","",ROUND(C15*(1+Settings!$B$7/100),2)) | H15: =IF(A15="","",ROUND(G15+D15+F15,2)) | I15: =IF(A15="","",ROUND(B15-H15,2)) | J15: =IF(A15="","",IFERROR(ROUND(I15/B15*100,2),0)) | K15: =IF(A15="","",IFERROR(ROUND(B15/E15,2),0)) | L15: =IF(A15="","",IFERROR(ROUND(H15/E15,2),0)) | M15: =IF(A15="","",ROUND(J15-Settings!$B$10,2))
G16: =IF(A16="","",ROUND(C16*(1+Settings!$B$7/100),2)) | H16: =IF(A16="","",ROUND(G16+D16+F16,2)) | I16: =IF(A16="","",ROUND(B16-H16,2)) | J16: =IF(A16="","",IFERROR(ROUND(I16/B16*100,2),0)) | K16: =IF(A16="","",IFERROR(ROUND(B16/E16,2),0)) | L16: =IF(A16="","",IFERROR(ROUND(H16/E16,2),0)) | M16: =IF(A16="","",ROUND(J16-Settings!$B$10,2))
A17: Total | B17: =SUM(B5:B16) -> 112500 | C17: =SUM(C5:C16) -> 48600 | D17: =SUM(D5:D16) -> 5550 | E17: =SUM(E5:E16) -> 1825 | F17: =SUM(F5:F16) -> 15000 | G17: =SUM(G5:G16) -> 55890 | H17: =SUM(H5:H16) -> 76440 | I17: =SUM(I5:I16) -> 36060 | J17: =IFERROR(ROUND(I17/B17*100,2),0) -> 32.05 | K17: =IFERROR(ROUND(B17/E17,2),0) -> 61.64 | L17: =IFERROR(ROUND(H17/E17,2),0) -> 41.88 | M17: =ROUND(J17-Settings!$B$10,2) -> 2.05

Sheet Chairs & New Patients
A1: Chairs & New Patients
A2: Chair utilization: production per scheduled hour defaults to that month's net production on the Monthly P&L ÷ scheduled hours; type your own in column D to override it.
A4: Month | B4: Scheduled chair hours | C4: Production per scheduled hour (Monthly P&L) | D4: or type your own | E4: Production per hour used | F4: Available chair hours | G4: Utilization % | H4: Idle chair hours | I4: Production at full chairs | J4: Unrealised production
A5: 46023 | B5: 470 | C5: =IF(A5="","",IFERROR(ROUND(INDEX('Monthly P&L'!$K$5:$K$16,MATCH(A5,'Monthly P&L'!$A$5:$A$16,0))/B5,2),0)) -> 217.02 | E5: =IF(A5="","",IF(D5<>"",D5,C5)) -> 217.02 | F5: =IF(A5="","",Settings!$B$14) -> 640 | G5: =IF(A5="","",IFERROR(ROUND(B5/F5*100,2),0)) -> 73.44 | H5: =IF(A5="","",ROUND(F5-B5,2)) -> 170 | I5: =IF(A5="","",ROUND(F5*E5,2)) -> 138892.8 | J5: =IF(A5="","",ROUND(H5*E5,2)) -> 36893.4
A6: 46054 | B6: 455 | C6: =IF(A6="","",IFERROR(ROUND(INDEX('Monthly P&L'!$K$5:$K$16,MATCH(A6,'Monthly P&L'!$A$5:$A$16,0))/B6,2),0)) -> 209.89 | E6: =IF(A6="","",IF(D6<>"",D6,C6)) -> 209.89 | F6: =IF(A6="","",Settings!$B$14) -> 640 | G6: =IF(A6="","",IFERROR(ROUND(B6/F6*100,2),0)) -> 71.09 | H6: =IF(A6="","",ROUND(F6-B6,2)) -> 185 | I6: =IF(A6="","",ROUND(F6*E6,2)) -> 134329.6 | J6: =IF(A6="","",ROUND(H6*E6,2)) -> 38829.65
A7: 46082 | B7: 500 | C7: =IF(A7="","",IFERROR(ROUND(INDEX('Monthly P&L'!$K$5:$K$16,MATCH(A7,'Monthly P&L'!$A$5:$A$16,0))/B7,2),0)) -> 218 | E7: =IF(A7="","",IF(D7<>"",D7,C7)) -> 218 | F7: =IF(A7="","",Settings!$B$14) -> 640 | G7: =IF(A7="","",IFERROR(ROUND(B7/F7*100,2),0)) -> 78.13 | H7: =IF(A7="","",ROUND(F7-B7,2)) -> 140 | I7: =IF(A7="","",ROUND(F7*E7,2)) -> 139520 | J7: =IF(A7="","",ROUND(H7*E7,2)) -> 30520
A8: 46113 | B8: 430 | C8: =IF(A8="","",IFERROR(ROUND(INDEX('Monthly P&L'!$K$5:$K$16,MATCH(A8,'Monthly P&L'!$A$5:$A$16,0))/B8,2),0)) -> 207.44 | D8: 230 | E8: =IF(A8="","",IF(D8<>"",D8,C8)) -> 230 | F8: =IF(A8="","",Settings!$B$14) -> 640 | G8: =IF(A8="","",IFERROR(ROUND(B8/F8*100,2),0)) -> 67.19 | H8: =IF(A8="","",ROUND(F8-B8,2)) -> 210 | I8: =IF(A8="","",ROUND(F8*E8,2)) -> 147200 | J8: =IF(A8="","",ROUND(H8*E8,2)) -> 48300
A9: 46143 | B9: 480 | C9: =IF(A9="","",IFERROR(ROUND(INDEX('Monthly P&L'!$K$5:$K$16,MATCH(A9,'Monthly P&L'!$A$5:$A$16,0))/B9,2),0)) -> 219.79 | E9: =IF(A9="","",IF(D9<>"",D9,C9)) -> 219.79 | F9: =IF(A9="","",Settings!$B$14) -> 640 | G9: =IF(A9="","",IFERROR(ROUND(B9/F9*100,2),0)) -> 75 | H9: =IF(A9="","",ROUND(F9-B9,2)) -> 160 | I9: =IF(A9="","",ROUND(F9*E9,2)) -> 140665.6 | J9: =IF(A9="","",ROUND(H9*E9,2)) -> 35166.4
A10: 46174 | B10: 510 | C10: =IF(A10="","",IFERROR(ROUND(INDEX('Monthly P&L'!$K$5:$K$16,MATCH(A10,'Monthly P&L'!$A$5:$A$16,0))/B10,2),0)) -> 218.63 | E10: =IF(A10="","",IF(D10<>"",D10,C10)) -> 218.63 | F10: =IF(A10="","",Settings!$B$14) -> 640 | G10: =IF(A10="","",IFERROR(ROUND(B10/F10*100,2),0)) -> 79.69 | H10: =IF(A10="","",ROUND(F10-B10,2)) -> 130 | I10: =IF(A10="","",ROUND(F10*E10,2)) -> 139923.2 | J10: =IF(A10="","",ROUND(H10*E10,2)) -> 28421.9
C11: =IF(A11="","",IFERROR(ROUND(INDEX('Monthly P&L'!$K$5:$K$16,MATCH(A11,'Monthly P&L'!$A$5:$A$16,0))/B11,2),0)) | E11: =IF(A11="","",IF(D11<>"",D11,C11)) | F11: =IF(A11="","",Settings!$B$14) | G11: =IF(A11="","",IFERROR(ROUND(B11/F11*100,2),0)) | H11: =IF(A11="","",ROUND(F11-B11,2)) | I11: =IF(A11="","",ROUND(F11*E11,2)) | J11: =IF(A11="","",ROUND(H11*E11,2))
C12: =IF(A12="","",IFERROR(ROUND(INDEX('Monthly P&L'!$K$5:$K$16,MATCH(A12,'Monthly P&L'!$A$5:$A$16,0))/B12,2),0)) | E12: =IF(A12="","",IF(D12<>"",D12,C12)) | F12: =IF(A12="","",Settings!$B$14) | G12: =IF(A12="","",IFERROR(ROUND(B12/F12*100,2),0)) | H12: =IF(A12="","",ROUND(F12-B12,2)) | I12: =IF(A12="","",ROUND(F12*E12,2)) | J12: =IF(A12="","",ROUND(H12*E12,2))
C13: =IF(A13="","",IFERROR(ROUND(INDEX('Monthly P&L'!$K$5:$K$16,MATCH(A13,'Monthly P&L'!$A$5:$A$16,0))/B13,2),0)) | E13: =IF(A13="","",IF(D13<>"",D13,C13)) | F13: =IF(A13="","",Settings!$B$14) | G13: =IF(A13="","",IFERROR(ROUND(B13/F13*100,2),0)) | H13: =IF(A13="","",ROUND(F13-B13,2)) | I13: =IF(A13="","",ROUND(F13*E13,2)) | J13: =IF(A13="","",ROUND(H13*E13,2))
C14: =IF(A14="","",IFERROR(ROUND(INDEX('Monthly P&L'!$K$5:$K$16,MATCH(A14,'Monthly P&L'!$A$5:$A$16,0))/B14,2),0)) | E14: =IF(A14="","",IF(D14<>"",D14,C14)) | F14: =IF(A14="","",Settings!$B$14) | G14: =IF(A14="","",IFERROR(ROUND(B14/F14*100,2),0)) | H14: =IF(A14="","",ROUND(F14-B14,2)) | I14: =IF(A14="","",ROUND(F14*E14,2)) | J14: =IF(A14="","",ROUND(H14*E14,2))
C15: =IF(A15="","",IFERROR(ROUND(INDEX('Monthly P&L'!$K$5:$K$16,MATCH(A15,'Monthly P&L'!$A$5:$A$16,0))/B15,2),0)) | E15: =IF(A15="","",IF(D15<>"",D15,C15)) | F15: =IF(A15="","",Settings!$B$14) | G15: =IF(A15="","",IFERROR(ROUND(B15/F15*100,2),0)) | H15: =IF(A15="","",ROUND(F15-B15,2)) | I15: =IF(A15="","",ROUND(F15*E15,2)) | J15: =IF(A15="","",ROUND(H15*E15,2))
C16: =IF(A16="","",IFERROR(ROUND(INDEX('Monthly P&L'!$K$5:$K$16,MATCH(A16,'Monthly P&L'!$A$5:$A$16,0))/B16,2),0)) | E16: =IF(A16="","",IF(D16<>"",D16,C16)) | F16: =IF(A16="","",Settings!$B$14) | G16: =IF(A16="","",IFERROR(ROUND(B16/F16*100,2),0)) | H16: =IF(A16="","",ROUND(F16-B16,2)) | I16: =IF(A16="","",ROUND(F16*E16,2)) | J16: =IF(A16="","",ROUND(H16*E16,2))
A17: Total | B17: =SUM(B5:B16) -> 2845 | F17: =SUM(F5:F16) -> 3840 | G17: =IFERROR(ROUND(B17/F17*100,2),0) -> 74.09 | H17: =SUM(H5:H16) -> 995 | I17: =SUM(I5:I16) -> 840531.2 | J17: =SUM(J5:J16) -> 218131.35
A19: New patients
A20: Marketing spend defaults to that month's marketing on the Monthly P&L; type your own in column C to override it. Lifetime value uses retention, years and first-year value from Settings.
A21: Month | B21: Marketing spend (Monthly P&L) | C21: or type your own | D21: Marketing spend used | E21: New patients | F21: Cost per new patient | G21: Lifetime value per patient | H21: Value-to-cost ratio | I21: Net value per patient | J21: Break-even new patients
A22: 46023 | B22: =IF(A22="","",IFERROR(INDEX('Monthly P&L'!$I$5:$I$16,MATCH(A22,'Monthly P&L'!$A$5:$A$16,0)),0)) -> 3000 | D22: =IF(A22="","",IF(C22<>"",C22,B22)) -> 3000 | E22: 40 | F22: =IF(A22="","",IFERROR(ROUND(D22/E22,2),0)) -> 75 | G22: =IF(A22="","",ROUND(Settings!$B$13+Settings!$B$13*Settings!$B$11/100*(Settings!$B$12-1),2)) -> 1980 | H22: =IF(A22="","",IFERROR(ROUND(G22/F22,2),0)) -> 26.4 | I22: =IF(A22="","",ROUND(G22-F22,2)) -> 1905 | J22: =IF(A22="","",IFERROR(ROUND(D22/Settings!$B$13,2),0)) -> 3.33
A23: 46054 | B23: =IF(A23="","",IFERROR(INDEX('Monthly P&L'!$I$5:$I$16,MATCH(A23,'Monthly P&L'!$A$5:$A$16,0)),0)) -> 3500 | C23: 4200 | D23: =IF(A23="","",IF(C23<>"",C23,B23)) -> 4200 | E23: 38 | F23: =IF(A23="","",IFERROR(ROUND(D23/E23,2),0)) -> 110.53 | G23: =IF(A23="","",ROUND(Settings!$B$13+Settings!$B$13*Settings!$B$11/100*(Settings!$B$12-1),2)) -> 1980 | H23: =IF(A23="","",IFERROR(ROUND(G23/F23,2),0)) -> 17.91 | I23: =IF(A23="","",ROUND(G23-F23,2)) -> 1869.47 | J23: =IF(A23="","",IFERROR(ROUND(D23/Settings!$B$13,2),0)) -> 4.67
A24: 46082 | B24: =IF(A24="","",IFERROR(INDEX('Monthly P&L'!$I$5:$I$16,MATCH(A24,'Monthly P&L'!$A$5:$A$16,0)),0)) -> 3000 | D24: =IF(A24="","",IF(C24<>"",C24,B24)) -> 3000 | E24: 45 | F24: =IF(A24="","",IFERROR(ROUND(D24/E24,2),0)) -> 66.67 | G24: =IF(A24="","",ROUND(Settings!$B$13+Settings!$B$13*Settings!$B$11/100*(Settings!$B$12-1),2)) -> 1980 | H24: =IF(A24="","",IFERROR(ROUND(G24/F24,2),0)) -> 29.7 | I24: =IF(A24="","",ROUND(G24-F24,2)) -> 1913.33 | J24: =IF(A24="","",IFERROR(ROUND(D24/Settings!$B$13,2),0)) -> 3.33
A25: 46113 | B25: =IF(A25="","",IFERROR(INDEX('Monthly P&L'!$I$5:$I$16,MATCH(A25,'Monthly P&L'!$A$5:$A$16,0)),0)) -> 4500 | D25: =IF(A25="","",IF(C25<>"",C25,B25)) -> 4500 | E25: 52 | F25: =IF(A25="","",IFERROR(ROUND(D25/E25,2),0)) -> 86.54 | G25: =IF(A25="","",ROUND(Settings!$B$13+Settings!$B$13*Settings!$B$11/100*(Settings!$B$12-1),2)) -> 1980 | H25: =IF(A25="","",IFERROR(ROUND(G25/F25,2),0)) -> 22.88 | I25: =IF(A25="","",ROUND(G25-F25,2)) -> 1893.46 | J25: =IF(A25="","",IFERROR(ROUND(D25/Settings!$B$13,2),0)) -> 5
A26: 46143 | B26: =IF(A26="","",IFERROR(INDEX('Monthly P&L'!$I$5:$I$16,MATCH(A26,'Monthly P&L'!$A$5:$A$16,0)),0)) -> 3200 | D26: =IF(A26="","",IF(C26<>"",C26,B26)) -> 3200 | E26: 42 | F26: =IF(A26="","",IFERROR(ROUND(D26/E26,2),0)) -> 76.19 | G26: =IF(A26="","",ROUND(Settings!$B$13+Settings!$B$13*Settings!$B$11/100*(Settings!$B$12-1),2)) -> 1980 | H26: =IF(A26="","",IFERROR(ROUND(G26/F26,2),0)) -> 25.99 | I26: =IF(A26="","",ROUND(G26-F26,2)) -> 1903.81 | J26: =IF(A26="","",IFERROR(ROUND(D26/Settings!$B$13,2),0)) -> 3.56
A27: 46174 | B27: =IF(A27="","",IFERROR(INDEX('Monthly P&L'!$I$5:$I$16,MATCH(A27,'Monthly P&L'!$A$5:$A$16,0)),0)) -> 3000 | D27: =IF(A27="","",IF(C27<>"",C27,B27)) -> 3000 | E27: 47 | F27: =IF(A27="","",IFERROR(ROUND(D27/E27,2),0)) -> 63.83 | G27: =IF(A27="","",ROUND(Settings!$B$13+Settings!$B$13*Settings!$B$11/100*(Settings!$B$12-1),2)) -> 1980 | H27: =IF(A27="","",IFERROR(ROUND(G27/F27,2),0)) -> 31.02 | I27: =IF(A27="","",ROUND(G27-F27,2)) -> 1916.17 | J27: =IF(A27="","",IFERROR(ROUND(D27/Settings!$B$13,2),0)) -> 3.33
B28: =IF(A28="","",IFERROR(INDEX('Monthly P&L'!$I$5:$I$16,MATCH(A28,'Monthly P&L'!$A$5:$A$16,0)),0)) | D28: =IF(A28="","",IF(C28<>"",C28,B28)) | F28: =IF(A28="","",IFERROR(ROUND(D28/E28,2),0)) | G28: =IF(A28="","",ROUND(Settings!$B$13+Settings!$B$13*Settings!$B$11/100*(Settings!$B$12-1),2)) | H28: =IF(A28="","",IFERROR(ROUND(G28/F28,2),0)) | I28: =IF(A28="","",ROUND(G28-F28,2)) | J28: =IF(A28="","",IFERROR(ROUND(D28/Settings!$B$13,2),0))
B29: =IF(A29="","",IFERROR(INDEX('Monthly P&L'!$I$5:$I$16,MATCH(A29,'Monthly P&L'!$A$5:$A$16,0)),0)) | D29: =IF(A29="","",IF(C29<>"",C29,B29)) | F29: =IF(A29="","",IFERROR(ROUND(D29/E29,2),0)) | G29: =IF(A29="","",ROUND(Settings!$B$13+Settings!$B$13*Settings!$B$11/100*(Settings!$B$12-1),2)) | H29: =IF(A29="","",IFERROR(ROUND(G29/F29,2),0)) | I29: =IF(A29="","",ROUND(G29-F29,2)) | J29: =IF(A29="","",IFERROR(ROUND(D29/Settings!$B$13,2),0))
B30: =IF(A30="","",IFERROR(INDEX('Monthly P&L'!$I$5:$I$16,MATCH(A30,'Monthly P&L'!$A$5:$A$16,0)),0)) | D30: =IF(A30="","",IF(C30<>"",C30,B30)) | F30: =IF(A30="","",IFERROR(ROUND(D30/E30,2),0)) | G30: =IF(A30="","",ROUND(Settings!$B$13+Settings!$B$13*Settings!$B$11/100*(Settings!$B$12-1),2)) | H30: =IF(A30="","",IFERROR(ROUND(G30/F30,2),0)) | I30: =IF(A30="","",ROUND(G30-F30,2)) | J30: =IF(A30="","",IFERROR(ROUND(D30/Settings!$B$13,2),0))
B31: =IF(A31="","",IFERROR(INDEX('Monthly P&L'!$I$5:$I$16,MATCH(A31,'Monthly P&L'!$A$5:$A$16,0)),0)) | D31: =IF(A31="","",IF(C31<>"",C31,B31)) | F31: =IF(A31="","",IFERROR(ROUND(D31/E31,2),0)) | G31: =IF(A31="","",ROUND(Settings!$B$13+Settings!$B$13*Settings!$B$11/100*(Settings!$B$12-1),2)) | H31: =IF(A31="","",IFERROR(ROUND(G31/F31,2),0)) | I31: =IF(A31="","",ROUND(G31-F31,2)) | J31: =IF(A31="","",IFERROR(ROUND(D31/Settings!$B$13,2),0))
B32: =IF(A32="","",IFERROR(INDEX('Monthly P&L'!$I$5:$I$16,MATCH(A32,'Monthly P&L'!$A$5:$A$16,0)),0)) | D32: =IF(A32="","",IF(C32<>"",C32,B32)) | F32: =IF(A32="","",IFERROR(ROUND(D32/E32,2),0)) | G32: =IF(A32="","",ROUND(Settings!$B$13+Settings!$B$13*Settings!$B$11/100*(Settings!$B$12-1),2)) | H32: =IF(A32="","",IFERROR(ROUND(G32/F32,2),0)) | I32: =IF(A32="","",ROUND(G32-F32,2)) | J32: =IF(A32="","",IFERROR(ROUND(D32/Settings!$B$13,2),0))
B33: =IF(A33="","",IFERROR(INDEX('Monthly P&L'!$I$5:$I$16,MATCH(A33,'Monthly P&L'!$A$5:$A$16,0)),0)) | D33: =IF(A33="","",IF(C33<>"",C33,B33)) | F33: =IF(A33="","",IFERROR(ROUND(D33/E33,2),0)) | G33: =IF(A33="","",ROUND(Settings!$B$13+Settings!$B$13*Settings!$B$11/100*(Settings!$B$12-1),2)) | H33: =IF(A33="","",IFERROR(ROUND(G33/F33,2),0)) | I33: =IF(A33="","",ROUND(G33-F33,2)) | J33: =IF(A33="","",IFERROR(ROUND(D33/Settings!$B$13,2),0))
A34: Total | D34: =SUM(D22:D33) -> 20900 | E34: =SUM(E22:E33) -> 264 | F34: =IFERROR(ROUND(D34/E34,2),0) -> 79.17 | J34: =IFERROR(ROUND(D34/Settings!$B$13,2),0) -> 23.22

Sheet Summary
A1: Summary
A2: Year-to-date collections | B2: ='Monthly P&L'!D17 -> 587500 | C2: Monthly P&L totals
A3: Year-to-date net production | B3: ='Monthly P&L'!K17 -> 612700 | C3: gross production − adjustments
A4: Collection rate % | B4: ='Monthly P&L'!L17 -> 95.89 | C4: collections ÷ net production
A5: Overhead % of collections | B5: ='Monthly P&L'!N17 -> 54.8 | C5: total overhead ÷ collections, owner pay excluded
A6: Your target overhead % | B6: =Settings!$B$9 -> 60 | C6: from Settings; your own target, not a benchmark
A7: Overhead % vs target | B7: ='Monthly P&L'!R17 -> -5.2 | C7: positive = above your target
A8: Profit before owner pay | B8: ='Monthly P&L'!O17 -> 265525 | C8: collections − overhead
A9: Profit after owner pay | B9: ='Monthly P&L'!P17 -> 193525 | C9: profit before owner pay − owner compensation
A10: Best month by profit | B10: =IFERROR(INDEX('Monthly P&L'!$A$5:$A$16,MATCH(MAX('Monthly P&L'!$P$5:$P$16),'Monthly P&L'!$P$5:$P$16,0)),"") -> 46174 | C10: highest profit after owner pay
A11: Worst month by profit | B11: =IFERROR(INDEX('Monthly P&L'!$A$5:$A$16,MATCH(MIN('Monthly P&L'!$P$5:$P$16),'Monthly P&L'!$P$5:$P$16,0)),"") -> 46113 | C11: lowest profit after owner pay
A12: Average production per provider hour | B12: ='Provider Production'!H25 -> 290.49 | C12: Provider Production: total net production ÷ total hours
A13: Hygiene year-to-date margin % | B13: =Hygiene!J17 -> 32.05 | C13: department profit ÷ hygiene production
A14: Hygiene margin % vs target | B14: =Hygiene!M17 -> 2.05 | C14: positive = above your target
A15: Average chair utilization % | B15: ='Chairs & New Patients'!G17 -> 74.09 | C15: total scheduled ÷ total available chair hours
A16: Total unrealised production | B16: ='Chairs & New Patients'!J17 -> 218131.35 | C16: idle chair hours × production per hour
A17: Year-to-date cost per new patient | B17: ='Chairs & New Patients'!F34 -> 79.17 | C17: total marketing spend ÷ total new patients
A18: Total new patients | B18: ='Chairs & New Patients'!E34 -> 264
A19: Months with overhead above target | B19: =COUNTIF('Monthly P&L'!$R$5:$R$16,">0") -> 1 | C19: overhead % above your target in Settings
A20: Lifetime value per new patient | B20: =Settings!$B$18 -> 1980 | C20: from Settings
A21: Hygienist hours available per month | B21: =Settings!$B$16 -> 320 | C21: from Settings
