Workbook

Sheet Start Here
A1: Restaurant Numbers Workbook
A2: by Knackdesk · knackdesk.com
A4: HOW TO USE
A5: 1. Settings: your target food cost %, target labour cost %, payroll taxes and benefits, waste allowance, seats, hours open, dining minutes and days open. Every other sheet reads them.
A6: 2. Recipes: one row per ingredient line, with the recipe name repeated on each line. Enter portions on the first line of each recipe to get the cost per portion, waste allowance included.
A7: 3. Menu: one row per dish. Cost per portion is looked up from Recipes by dish name (type over it to use your own figure). Add the menu price and weekly units to get food cost %, gross profit and the price at your target food cost.
A8: 4. Weekly P&L: one row per week with sales, food, beverage and labour cost and other operating costs. Prime cost, food cost %, labour % and operating margin are calculated, with totals in row 17.
A9: 5. Labour: one row per staff member for a typical week with role, hours and wage. Loaded weekly cost, labour % against projected sales and the hours over or under your target are calculated.
A10: 6. Summary: menu items, blended food cost %, best margin dish, highest food cost dish, weekly menu revenue, projected labour %, latest week prime cost % and seat capacity.
A12: LEGEND
A13: Blue text = a cell you type into. Black text = a formula, leave it alone. Yellow fill = key inputs.
A15: DEFINITIONS
... A22: Arithmetic only; not financial advice.

Sheet Settings
A1: Settings
A2: Target food cost % | B2: 30 | C2: Your own target: ingredient cost as a share of the menu price.
A3: Target labour cost % | B3: 28 | C3: Your own target: loaded labour cost as a share of sales.
A4: Payroll taxes and benefits % | B4: 12 | C4: Added on top of wages for the true cost of each hour.
A5: Waste allowance % | B5: 5 | C5: Added to recipe ingredient cost for trim, spoilage and over-portioning.
A6: Seats | B6: 60 | C6: Seats available for diners.
A7: Hours open per day | B7: 8 | C7: Service hours per day.
A8: Average dining minutes | B8: 75 | C8: How long a table is typically occupied.
A9: Days open per week | B9: 6 | C9: Used for covers per week on the Summary.

Sheet Recipes
A1: Recipes
A2: One row per ingredient line. Repeat the recipe name on each line; enter portions on the first line only.
A4: Recipe | B4: Ingredient | C4: Quantity | D4: Unit cost | E4: Line cost | F4: Portions | G4: Cost per portion
A5: Pasta pomodoro | B5: Pasta (kg) | C5: 0.12 | D5: 2.4 | E5: =IF(A5="","",ROUND(C5*D5,2)) -> 0.29 | F5: 1 | G5: =IF(OR(A5="",F5=""),"",ROUND(SUMIF($A$5:$A$44,A5,$E$5:$E$44)*(1+Settings!$B$5/100)/F5,2)) -> 1.16
A6: Pasta pomodoro | B6: Tomato sauce (kg) | C6: 0.15 | D6: 3 | E6: =IF(A6="","",ROUND(C6*D6,2)) -> 0.45 | G6: =IF(OR(A6="",F6=""),"",ROUND(SUMIF($A$5:$A$44,A6,$E$5:$E$44)*(1+Settings!$B$5/100)/F6,2))
A7: Pasta pomodoro | B7: Cheese (kg) | C7: 0.03 | D7: 12 | E7: =IF(A7="","",ROUND(C7*D7,2)) -> 0.36 | G7: =IF(OR(A7="",F7=""),"",ROUND(SUMIF($A$5:$A$44,A7,$E$5:$E$44)*(1+Settings!$B$5/100)/F7,2))
A8: Steak frites | B8: Steak (kg) | C8: 0.25 | D8: 28 | E8: =IF(A8="","",ROUND(C8*D8,2)) -> 7 | F8: 1 | G8: =IF(OR(A8="",F8=""),"",ROUND(SUMIF($A$5:$A$44,A8,$E$5:$E$44)*(1+Settings!$B$5/100)/F8,2)) -> 8.01
A9: Steak frites | B9: Potatoes (kg) | C9: 0.3 | D9: 1.2 | E9: =IF(A9="","",ROUND(C9*D9,2)) -> 0.36 | G9: =IF(OR(A9="",F9=""),"",ROUND(SUMIF($A$5:$A$44,A9,$E$5:$E$44)*(1+Settings!$B$5/100)/F9,2))
A10: Steak frites | B10: Butter (kg) | C10: 0.03 | D10: 9 | E10: =IF(A10="","",ROUND(C10*D10,2)) -> 0.27 | G10: =IF(OR(A10="",F10=""),"",ROUND(SUMIF($A$5:$A$44,A10,$E$5:$E$44)*(1+Settings!$B$5/100)/F10,2))
E11: =IF(A11="","",ROUND(C11*D11,2)) | G11: =IF(OR(A11="",F11=""),"",ROUND(SUMIF($A$5:$A$44,A11,$E$5:$E$44)*(1+Settings!$B$5/100)/F11,2))
E12: =IF(A12="","",ROUND(C12*D12,2)) | G12: =IF(OR(A12="",F12=""),"",ROUND(SUMIF($A$5:$A$44,A12,$E$5:$E$44)*(1+Settings!$B$5/100)/F12,2))
E13: =IF(A13="","",ROUND(C13*D13,2)) | G13: =IF(OR(A13="",F13=""),"",ROUND(SUMIF($A$5:$A$44,A13,$E$5:$E$44)*(1+Settings!$B$5/100)/F13,2))
E14: =IF(A14="","",ROUND(C14*D14,2)) | G14: =IF(OR(A14="",F14=""),"",ROUND(SUMIF($A$5:$A$44,A14,$E$5:$E$44)*(1+Settings!$B$5/100)/F14,2))
E15: =IF(A15="","",ROUND(C15*D15,2)) | G15: =IF(OR(A15="",F15=""),"",ROUND(SUMIF($A$5:$A$44,A15,$E$5:$E$44)*(1+Settings!$B$5/100)/F15,2))
E16: =IF(A16="","",ROUND(C16*D16,2)) | G16: =IF(OR(A16="",F16=""),"",ROUND(SUMIF($A$5:$A$44,A16,$E$5:$E$44)*(1+Settings!$B$5/100)/F16,2))
E17: =IF(A17="","",ROUND(C17*D17,2)) | G17: =IF(OR(A17="",F17=""),"",ROUND(SUMIF($A$5:$A$44,A17,$E$5:$E$44)*(1+Settings!$B$5/100)/F17,2))
E18: =IF(A18="","",ROUND(C18*D18,2)) | G18: =IF(OR(A18="",F18=""),"",ROUND(SUMIF($A$5:$A$44,A18,$E$5:$E$44)*(1+Settings!$B$5/100)/F18,2))
E19: =IF(A19="","",ROUND(C19*D19,2)) | G19: =IF(OR(A19="",F19=""),"",ROUND(SUMIF($A$5:$A$44,A19,$E$5:$E$44)*(1+Settings!$B$5/100)/F19,2))
E20: =IF(A20="","",ROUND(C20*D20,2)) | G20: =IF(OR(A20="",F20=""),"",ROUND(SUMIF($A$5:$A$44,A20,$E$5:$E$44)*(1+Settings!$B$5/100)/F20,2))
E21: =IF(A21="","",ROUND(C21*D21,2)) | G21: =IF(OR(A21="",F21=""),"",ROUND(SUMIF($A$5:$A$44,A21,$E$5:$E$44)*(1+Settings!$B$5/100)/F21,2))
E22: =IF(A22="","",ROUND(C22*D22,2)) | G22: =IF(OR(A22="",F22=""),"",ROUND(SUMIF($A$5:$A$44,A22,$E$5:$E$44)*(1+Settings!$B$5/100)/F22,2))
... E44: =IF(A44="","",ROUND(C44*D44,2)) | G44: =IF(OR(A44="",F44=""),"",ROUND(SUMIF($A$5:$A$44,A44,$E$5:$E$44)*(1+Settings!$B$5/100)/F44,2))

Sheet Menu
A1: Menu
A2: Cost per portion is looked up from Recipes by dish name; it is blue because you may type over it with your own figure.
A4: Dish | B4: Cost per portion | C4: Menu price | D4: Food cost % | E4: Gross profit | F4: Price at target food cost | G4: Units sold per week | H4: Weekly food cost | I4: Weekly revenue | J4: Weekly gross profit
A5: Pasta pomodoro | B5: =IF(A5="","",IFERROR(INDEX(Recipes!$G$5:$G$44,MATCH(A5,Recipes!$A$5:$A$44,0)),"")) -> 1.16 | C5: 12.5 | D5: =IF(A5="","",IFERROR(ROUND(B5/C5*100,2),"")) -> 9.28 | E5: =IF(A5="","",IFERROR(C5-B5,"")) -> 11.34 | F5: =IF(A5="","",IFERROR(ROUND(B5/(Settings!$B$2/100),2),"")) -> 3.87 | G5: 180 | H5: =IF(A5="","",IFERROR(ROUND(B5*G5,2),"")) -> 208.8 | I5: =IF(A5="","",IFERROR(ROUND(C5*G5,2),"")) -> 2250 | J5: =IF(A5="","",IFERROR(I5-H5,"")) -> 2041.2
A6: Steak frites | B6: =IF(A6="","",IFERROR(INDEX(Recipes!$G$5:$G$44,MATCH(A6,Recipes!$A$5:$A$44,0)),"")) -> 8.01 | C6: 24 | D6: =IF(A6="","",IFERROR(ROUND(B6/C6*100,2),"")) -> 33.38 | E6: =IF(A6="","",IFERROR(C6-B6,"")) -> 15.99 | F6: =IF(A6="","",IFERROR(ROUND(B6/(Settings!$B$2/100),2),"")) -> 26.7 | G6: 60 | H6: =IF(A6="","",IFERROR(ROUND(B6*G6,2),"")) -> 480.6 | I6: =IF(A6="","",IFERROR(ROUND(C6*G6,2),"")) -> 1440 | J6: =IF(A6="","",IFERROR(I6-H6,"")) -> 959.4
A7: House salad | B7: 1.8 | C7: 7.5 | D7: =IF(A7="","",IFERROR(ROUND(B7/C7*100,2),"")) -> 24 | E7: =IF(A7="","",IFERROR(C7-B7,"")) -> 5.7 | F7: =IF(A7="","",IFERROR(ROUND(B7/(Settings!$B$2/100),2),"")) -> 6 | G7: 90 | H7: =IF(A7="","",IFERROR(ROUND(B7*G7,2),"")) -> 162 | I7: =IF(A7="","",IFERROR(ROUND(C7*G7,2),"")) -> 675 | J7: =IF(A7="","",IFERROR(I7-H7,"")) -> 513
B8: =IF(A8="","",IFERROR(INDEX(Recipes!$G$5:$G$44,MATCH(A8,Recipes!$A$5:$A$44,0)),"")) | D8: =IF(A8="","",IFERROR(ROUND(B8/C8*100,2),"")) | E8: =IF(A8="","",IFERROR(C8-B8,"")) | F8: =IF(A8="","",IFERROR(ROUND(B8/(Settings!$B$2/100),2),"")) | H8: =IF(A8="","",IFERROR(ROUND(B8*G8,2),"")) | I8: =IF(A8="","",IFERROR(ROUND(C8*G8,2),"")) | J8: =IF(A8="","",IFERROR(I8-H8,""))
B9: =IF(A9="","",IFERROR(INDEX(Recipes!$G$5:$G$44,MATCH(A9,Recipes!$A$5:$A$44,0)),"")) | D9: =IF(A9="","",IFERROR(ROUND(B9/C9*100,2),"")) | E9: =IF(A9="","",IFERROR(C9-B9,"")) | F9: =IF(A9="","",IFERROR(ROUND(B9/(Settings!$B$2/100),2),"")) | H9: =IF(A9="","",IFERROR(ROUND(B9*G9,2),"")) | I9: =IF(A9="","",IFERROR(ROUND(C9*G9,2),"")) | J9: =IF(A9="","",IFERROR(I9-H9,""))
B10: =IF(A10="","",IFERROR(INDEX(Recipes!$G$5:$G$44,MATCH(A10,Recipes!$A$5:$A$44,0)),"")) | D10: =IF(A10="","",IFERROR(ROUND(B10/C10*100,2),"")) | E10: =IF(A10="","",IFERROR(C10-B10,"")) | F10: =IF(A10="","",IFERROR(ROUND(B10/(Settings!$B$2/100),2),"")) | H10: =IF(A10="","",IFERROR(ROUND(B10*G10,2),"")) | I10: =IF(A10="","",IFERROR(ROUND(C10*G10,2),"")) | J10: =IF(A10="","",IFERROR(I10-H10,""))
B11: =IF(A11="","",IFERROR(INDEX(Recipes!$G$5:$G$44,MATCH(A11,Recipes!$A$5:$A$44,0)),"")) | D11: =IF(A11="","",IFERROR(ROUND(B11/C11*100,2),"")) | E11: =IF(A11="","",IFERROR(C11-B11,"")) | F11: =IF(A11="","",IFERROR(ROUND(B11/(Settings!$B$2/100),2),"")) | H11: =IF(A11="","",IFERROR(ROUND(B11*G11,2),"")) | I11: =IF(A11="","",IFERROR(ROUND(C11*G11,2),"")) | J11: =IF(A11="","",IFERROR(I11-H11,""))
B12: =IF(A12="","",IFERROR(INDEX(Recipes!$G$5:$G$44,MATCH(A12,Recipes!$A$5:$A$44,0)),"")) | D12: =IF(A12="","",IFERROR(ROUND(B12/C12*100,2),"")) | E12: =IF(A12="","",IFERROR(C12-B12,"")) | F12: =IF(A12="","",IFERROR(ROUND(B12/(Settings!$B$2/100),2),"")) | H12: =IF(A12="","",IFERROR(ROUND(B12*G12,2),"")) | I12: =IF(A12="","",IFERROR(ROUND(C12*G12,2),"")) | J12: =IF(A12="","",IFERROR(I12-H12,""))
B13: =IF(A13="","",IFERROR(INDEX(Recipes!$G$5:$G$44,MATCH(A13,Recipes!$A$5:$A$44,0)),"")) | D13: =IF(A13="","",IFERROR(ROUND(B13/C13*100,2),"")) | E13: =IF(A13="","",IFERROR(C13-B13,"")) | F13: =IF(A13="","",IFERROR(ROUND(B13/(Settings!$B$2/100),2),"")) | H13: =IF(A13="","",IFERROR(ROUND(B13*G13,2),"")) | I13: =IF(A13="","",IFERROR(ROUND(C13*G13,2),"")) | J13: =IF(A13="","",IFERROR(I13-H13,""))
B14: =IF(A14="","",IFERROR(INDEX(Recipes!$G$5:$G$44,MATCH(A14,Recipes!$A$5:$A$44,0)),"")) | D14: =IF(A14="","",IFERROR(ROUND(B14/C14*100,2),"")) | E14: =IF(A14="","",IFERROR(C14-B14,"")) | F14: =IF(A14="","",IFERROR(ROUND(B14/(Settings!$B$2/100),2),"")) | H14: =IF(A14="","",IFERROR(ROUND(B14*G14,2),"")) | I14: =IF(A14="","",IFERROR(ROUND(C14*G14,2),"")) | J14: =IF(A14="","",IFERROR(I14-H14,""))
B15: =IF(A15="","",IFERROR(INDEX(Recipes!$G$5:$G$44,MATCH(A15,Recipes!$A$5:$A$44,0)),"")) | D15: =IF(A15="","",IFERROR(ROUND(B15/C15*100,2),"")) | E15: =IF(A15="","",IFERROR(C15-B15,"")) | F15: =IF(A15="","",IFERROR(ROUND(B15/(Settings!$B$2/100),2),"")) | H15: =IF(A15="","",IFERROR(ROUND(B15*G15,2),"")) | I15: =IF(A15="","",IFERROR(ROUND(C15*G15,2),"")) | J15: =IF(A15="","",IFERROR(I15-H15,""))
B16: =IF(A16="","",IFERROR(INDEX(Recipes!$G$5:$G$44,MATCH(A16,Recipes!$A$5:$A$44,0)),"")) | D16: =IF(A16="","",IFERROR(ROUND(B16/C16*100,2),"")) | E16: =IF(A16="","",IFERROR(C16-B16,"")) | F16: =IF(A16="","",IFERROR(ROUND(B16/(Settings!$B$2/100),2),"")) | H16: =IF(A16="","",IFERROR(ROUND(B16*G16,2),"")) | I16: =IF(A16="","",IFERROR(ROUND(C16*G16,2),"")) | J16: =IF(A16="","",IFERROR(I16-H16,""))
B17: =IF(A17="","",IFERROR(INDEX(Recipes!$G$5:$G$44,MATCH(A17,Recipes!$A$5:$A$44,0)),"")) | D17: =IF(A17="","",IFERROR(ROUND(B17/C17*100,2),"")) | E17: =IF(A17="","",IFERROR(C17-B17,"")) | F17: =IF(A17="","",IFERROR(ROUND(B17/(Settings!$B$2/100),2),"")) | H17: =IF(A17="","",IFERROR(ROUND(B17*G17,2),"")) | I17: =IF(A17="","",IFERROR(ROUND(C17*G17,2),"")) | J17: =IF(A17="","",IFERROR(I17-H17,""))
B18: =IF(A18="","",IFERROR(INDEX(Recipes!$G$5:$G$44,MATCH(A18,Recipes!$A$5:$A$44,0)),"")) | D18: =IF(A18="","",IFERROR(ROUND(B18/C18*100,2),"")) | E18: =IF(A18="","",IFERROR(C18-B18,"")) | F18: =IF(A18="","",IFERROR(ROUND(B18/(Settings!$B$2/100),2),"")) | H18: =IF(A18="","",IFERROR(ROUND(B18*G18,2),"")) | I18: =IF(A18="","",IFERROR(ROUND(C18*G18,2),"")) | J18: =IF(A18="","",IFERROR(I18-H18,""))
B19: =IF(A19="","",IFERROR(INDEX(Recipes!$G$5:$G$44,MATCH(A19,Recipes!$A$5:$A$44,0)),"")) | D19: =IF(A19="","",IFERROR(ROUND(B19/C19*100,2),"")) | E19: =IF(A19="","",IFERROR(C19-B19,"")) | F19: =IF(A19="","",IFERROR(ROUND(B19/(Settings!$B$2/100),2),"")) | H19: =IF(A19="","",IFERROR(ROUND(B19*G19,2),"")) | I19: =IF(A19="","",IFERROR(ROUND(C19*G19,2),"")) | J19: =IF(A19="","",IFERROR(I19-H19,""))
... B34: =IF(A34="","",IFERROR(INDEX(Recipes!$G$5:$G$44,MATCH(A34,Recipes!$A$5:$A$44,0)),"")) | D34: =IF(A34="","",IFERROR(ROUND(B34/C34*100,2),"")) | E34: =IF(A34="","",IFERROR(C34-B34,"")) | F34: =IF(A34="","",IFERROR(ROUND(B34/(Settings!$B$2/100),2),"")) | H34: =IF(A34="","",IFERROR(ROUND(B34*G34,2),"")) | I34: =IF(A34="","",IFERROR(ROUND(C34*G34,2),"")) | J34: =IF(A34="","",IFERROR(I34-H34,""))
A35: Total | G35: =SUM(G5:G34) -> 330 | H35: =SUM(H5:H34) -> 851.4 | I35: =SUM(I5:I34) -> 4365 | J35: =SUM(J5:J34) -> 3513.6
A36: Blended food cost % | D36: =IFERROR(ROUND(H35/I35*100,2),0) -> 19.51 | E36: weekly food cost ÷ weekly revenue, weighted by units sold

Sheet Weekly P&L
A1: Weekly P&L
A2: One row per week. Labour cost is typed from your payroll; the Labour sheet gives a typical week for comparison.
A4: Week ending | B4: Food sales | C4: Beverage sales | D4: Total sales | E4: Food cost | F4: Beverage cost | G4: Labour cost | H4: Prime cost | I4: Prime cost % | J4: Food cost % | K4: Labour % | L4: Other operating costs | M4: Operating profit | N4: Margin %
A5: 46271 | B5: 4400 | C5: 1500 | D5: =IF(A5="","",B5+C5) -> 5900 | E5: 1350 | F5: 380 | G5: 1650 | H5: =IF(A5="","",E5+F5+G5) -> 3380 | I5: =IF(A5="","",IFERROR(ROUND(H5/D5*100,2),"")) -> 57.29 | J5: =IF(A5="","",IFERROR(ROUND(E5/B5*100,2),"")) -> 30.68 | K5: =IF(A5="","",IFERROR(ROUND(G5/D5*100,2),"")) -> 27.97 | L5: 1200 | M5: =IF(A5="","",D5-H5-L5) -> 1320 | N5: =IF(A5="","",IFERROR(ROUND(M5/D5*100,2),"")) -> 22.37
A6: 46278 | B6: 4650 | C6: 1620 | D6: =IF(A6="","",B6+C6) -> 6270 | E6: 1420 | F6: 410 | G6: 1700 | H6: =IF(A6="","",E6+F6+G6) -> 3530 | I6: =IF(A6="","",IFERROR(ROUND(H6/D6*100,2),"")) -> 56.3 | J6: =IF(A6="","",IFERROR(ROUND(E6/B6*100,2),"")) -> 30.54 | K6: =IF(A6="","",IFERROR(ROUND(G6/D6*100,2),"")) -> 27.11 | L6: 1200 | M6: =IF(A6="","",D6-H6-L6) -> 1540 | N6: =IF(A6="","",IFERROR(ROUND(M6/D6*100,2),"")) -> 24.56
A7: 46285 | B7: 4300 | C7: 1480 | D7: =IF(A7="","",B7+C7) -> 5780 | E7: 1390 | F7: 395 | G7: 1720 | H7: =IF(A7="","",E7+F7+G7) -> 3505 | I7: =IF(A7="","",IFERROR(ROUND(H7/D7*100,2),"")) -> 60.64 | J7: =IF(A7="","",IFERROR(ROUND(E7/B7*100,2),"")) -> 32.33 | K7: =IF(A7="","",IFERROR(ROUND(G7/D7*100,2),"")) -> 29.76 | L7: 1250 | M7: =IF(A7="","",D7-H7-L7) -> 1025 | N7: =IF(A7="","",IFERROR(ROUND(M7/D7*100,2),"")) -> 17.73
D8: =IF(A8="","",B8+C8) | H8: =IF(A8="","",E8+F8+G8) | I8: =IF(A8="","",IFERROR(ROUND(H8/D8*100,2),"")) | J8: =IF(A8="","",IFERROR(ROUND(E8/B8*100,2),"")) | K8: =IF(A8="","",IFERROR(ROUND(G8/D8*100,2),"")) | M8: =IF(A8="","",D8-H8-L8) | N8: =IF(A8="","",IFERROR(ROUND(M8/D8*100,2),""))
D9: =IF(A9="","",B9+C9) | H9: =IF(A9="","",E9+F9+G9) | I9: =IF(A9="","",IFERROR(ROUND(H9/D9*100,2),"")) | J9: =IF(A9="","",IFERROR(ROUND(E9/B9*100,2),"")) | K9: =IF(A9="","",IFERROR(ROUND(G9/D9*100,2),"")) | M9: =IF(A9="","",D9-H9-L9) | N9: =IF(A9="","",IFERROR(ROUND(M9/D9*100,2),""))
D10: =IF(A10="","",B10+C10) | H10: =IF(A10="","",E10+F10+G10) | I10: =IF(A10="","",IFERROR(ROUND(H10/D10*100,2),"")) | J10: =IF(A10="","",IFERROR(ROUND(E10/B10*100,2),"")) | K10: =IF(A10="","",IFERROR(ROUND(G10/D10*100,2),"")) | M10: =IF(A10="","",D10-H10-L10) | N10: =IF(A10="","",IFERROR(ROUND(M10/D10*100,2),""))
D11: =IF(A11="","",B11+C11) | H11: =IF(A11="","",E11+F11+G11) | I11: =IF(A11="","",IFERROR(ROUND(H11/D11*100,2),"")) | J11: =IF(A11="","",IFERROR(ROUND(E11/B11*100,2),"")) | K11: =IF(A11="","",IFERROR(ROUND(G11/D11*100,2),"")) | M11: =IF(A11="","",D11-H11-L11) | N11: =IF(A11="","",IFERROR(ROUND(M11/D11*100,2),""))
D12: =IF(A12="","",B12+C12) | H12: =IF(A12="","",E12+F12+G12) | I12: =IF(A12="","",IFERROR(ROUND(H12/D12*100,2),"")) | J12: =IF(A12="","",IFERROR(ROUND(E12/B12*100,2),"")) | K12: =IF(A12="","",IFERROR(ROUND(G12/D12*100,2),"")) | M12: =IF(A12="","",D12-H12-L12) | N12: =IF(A12="","",IFERROR(ROUND(M12/D12*100,2),""))
D13: =IF(A13="","",B13+C13) | H13: =IF(A13="","",E13+F13+G13) | I13: =IF(A13="","",IFERROR(ROUND(H13/D13*100,2),"")) | J13: =IF(A13="","",IFERROR(ROUND(E13/B13*100,2),"")) | K13: =IF(A13="","",IFERROR(ROUND(G13/D13*100,2),"")) | M13: =IF(A13="","",D13-H13-L13) | N13: =IF(A13="","",IFERROR(ROUND(M13/D13*100,2),""))
D14: =IF(A14="","",B14+C14) | H14: =IF(A14="","",E14+F14+G14) | I14: =IF(A14="","",IFERROR(ROUND(H14/D14*100,2),"")) | J14: =IF(A14="","",IFERROR(ROUND(E14/B14*100,2),"")) | K14: =IF(A14="","",IFERROR(ROUND(G14/D14*100,2),"")) | M14: =IF(A14="","",D14-H14-L14) | N14: =IF(A14="","",IFERROR(ROUND(M14/D14*100,2),""))
D15: =IF(A15="","",B15+C15) | H15: =IF(A15="","",E15+F15+G15) | I15: =IF(A15="","",IFERROR(ROUND(H15/D15*100,2),"")) | J15: =IF(A15="","",IFERROR(ROUND(E15/B15*100,2),"")) | K15: =IF(A15="","",IFERROR(ROUND(G15/D15*100,2),"")) | M15: =IF(A15="","",D15-H15-L15) | N15: =IF(A15="","",IFERROR(ROUND(M15/D15*100,2),""))
D16: =IF(A16="","",B16+C16) | H16: =IF(A16="","",E16+F16+G16) | I16: =IF(A16="","",IFERROR(ROUND(H16/D16*100,2),"")) | J16: =IF(A16="","",IFERROR(ROUND(E16/B16*100,2),"")) | K16: =IF(A16="","",IFERROR(ROUND(G16/D16*100,2),"")) | M16: =IF(A16="","",D16-H16-L16) | N16: =IF(A16="","",IFERROR(ROUND(M16/D16*100,2),""))
A17: Total | B17: =SUM(B5:B16) -> 13350 | C17: =SUM(C5:C16) -> 4600 | D17: =SUM(D5:D16) -> 17950 | E17: =SUM(E5:E16) -> 4160 | F17: =SUM(F5:F16) -> 1185 | G17: =SUM(G5:G16) -> 5070 | H17: =SUM(H5:H16) -> 10415 | I17: =IFERROR(ROUND(H17/D17*100,2),0) -> 58.02 | J17: =IFERROR(ROUND(E17/B17*100,2),0) -> 31.16 | K17: =IFERROR(ROUND(G17/D17*100,2),0) -> 28.25 | L17: =SUM(L5:L16) -> 3650 | M17: =SUM(M5:M16) -> 3885 | N17: =IFERROR(ROUND(M17/D17*100,2),0) -> 21.64

Sheet Labour
A1: Labour
A2: One row per staff member for a typical week. Weekly cost includes payroll taxes and benefits from Settings.
A4: Name | B4: Role | C4: Hours | D4: Hourly wage | E4: Weekly cost
A5: Head chef | B5: kitchen | C5: 24 | D5: 18 | E5: =IF(A5="","",ROUND(C5*D5*(1+Settings!$B$4/100),2)) -> 483.84
A6: Line cook | B6: kitchen | C6: 20 | D6: 14 | E6: =IF(A6="","",ROUND(C6*D6*(1+Settings!$B$4/100),2)) -> 313.6
A7: Server A | B7: front of house | C7: 16 | D7: 12 | E7: =IF(A7="","",ROUND(C7*D7*(1+Settings!$B$4/100),2)) -> 215.04
A8: Server B | B8: front of house | C8: 12 | D8: 12 | E8: =IF(A8="","",ROUND(C8*D8*(1+Settings!$B$4/100),2)) -> 161.28
A9: Bartender | B9: bar | C9: 10 | D9: 13 | E9: =IF(A9="","",ROUND(C9*D9*(1+Settings!$B$4/100),2)) -> 145.6
A10: Manager | B10: management | C10: 8 | D10: 20 | E10: =IF(A10="","",ROUND(C10*D10*(1+Settings!$B$4/100),2)) -> 179.2
E11: =IF(A11="","",ROUND(C11*D11*(1+Settings!$B$4/100),2))
E12: =IF(A12="","",ROUND(C12*D12*(1+Settings!$B$4/100),2))
E13: =IF(A13="","",ROUND(C13*D13*(1+Settings!$B$4/100),2))
E14: =IF(A14="","",ROUND(C14*D14*(1+Settings!$B$4/100),2))
E15: =IF(A15="","",ROUND(C15*D15*(1+Settings!$B$4/100),2))
E16: =IF(A16="","",ROUND(C16*D16*(1+Settings!$B$4/100),2))
E17: =IF(A17="","",ROUND(C17*D17*(1+Settings!$B$4/100),2))
E18: =IF(A18="","",ROUND(C18*D18*(1+Settings!$B$4/100),2))
E19: =IF(A19="","",ROUND(C19*D19*(1+Settings!$B$4/100),2))
E20: =IF(A20="","",ROUND(C20*D20*(1+Settings!$B$4/100),2))
E21: =IF(A21="","",ROUND(C21*D21*(1+Settings!$B$4/100),2))
E22: =IF(A22="","",ROUND(C22*D22*(1+Settings!$B$4/100),2))
... E24: =IF(A24="","",ROUND(C24*D24*(1+Settings!$B$4/100),2))
A25: Total | C25: =SUM(C5:C24) -> 90 | E25: =SUM(E5:E24) -> 1498.56
A27: Projected weekly sales | B27: =Menu!I35 -> 4365 | C27: defaults to Menu weekly revenue; type over it
A28: Labour % | B28: =IFERROR(ROUND(E25/B27*100,2),0) -> 34.33 | C28: weekly cost ÷ projected sales
A29: Allowed labour cost at target | B29: =ROUND(B27*Settings!$B$3/100,2) -> 1222.2 | C29: projected sales × target labour %
A30: Hours over (+) or under (−) target | B30: =IFERROR(ROUND((E25-B29)/(AVERAGE(D5:D24)*(1+Settings!$B$4/100)),1),0) -> 16.6 | C30: (weekly cost − allowed) ÷ average loaded hourly wage

Sheet Summary
A1: Summary
A2: Menu items | B2: =COUNTA(Menu!A5:A34) -> 3
A3: Blended food cost % | B3: =Menu!D36 -> 19.51 | C3: weighted by units sold
A4: Best margin dish | B4: =IFERROR(INDEX(Menu!A5:A34,MATCH(MAX(Menu!E5:E34),Menu!E5:E34,0)),"") -> Steak frites | C4: highest gross profit per portion
A5: Highest food cost % dish | B5: =IFERROR(INDEX(Menu!A5:A34,MATCH(MAX(Menu!D5:D34),Menu!D5:D34,0)),"") -> Steak frites | C5: the dish to re-price or re-cost first
A6: Weekly revenue from menu | B6: =Menu!I35 -> 4365
A7: Projected labour % | B7: =Labour!B28 -> 34.33 | C7: from the Labour sheet
A8: Latest week prime cost % | B8: =IF(COUNT('Weekly P&L'!D5:D16)=0,"",INDEX('Weekly P&L'!I5:I16,COUNT('Weekly P&L'!D5:D16))) -> 60.64 | C8: last filled week on Weekly P&L (fill weeks top down)
A10: Seat capacity
A11: Occupancy % | B11: 70 | C11: share of seats filled on an average turn
A12: Turns per day | B12: =IFERROR(ROUND(Settings!$B$7*60/Settings!$B$8,2),0) -> 6.4 | C12: hours open × 60 ÷ average dining minutes
A13: Covers per day | B13: =ROUND(Settings!$B$6*B12*B11/100,0) -> 269 | C13: seats × turns × occupancy
A14: Covers per week | B14: =B13*Settings!$B$9 -> 1614 | C14: covers per day × days open
