Workbook

Sheet Start Here
A1: MSP Contract Pricing Workbook
A2: by Knackdesk · knackdesk.com
A4: HOW TO USE
A5: 1. Settings: technician count, salary, payroll taxes and benefits, productive hours, overhead line by line, target margin, block hours discount, expected unused block hours and your default hourly rate. Your loaded hourly cost follows and every other sheet reads it.
A6: 2. Tool Stack: one row per tool with its billing basis, unit cost and units in use. Monthly cost, the stack total, the fixed tool cost and the per-unit tool cost shared across contracts are calculated.
A7: 3. Contracts: one row per client with plan, users, devices, monthly fee, support hours, dedicated tool costs, onboarding fee and contract months. Shared tool cost, labour cost, total cost, gross profit, margin %, fee and cost per user, the price per user at your target margin and break-even hours are calculated.
A8: 4. Tickets: one row per month with tickets closed and average minutes per ticket. Technician cost and tool and overhead cost default from Settings and the Tool Stack (type your own to override). Cost per ticket, labour cost per ticket, tickets per technician and the share of productive hours spent on tickets are calculated, with totals.
A9: 5. Blocks & Onboarding: block hours quotes (hours, rate, discount, expiry, expected unused hours) with block price, effective rate and effective rate on used hours; and onboarding quotes (hours, rate, setup costs, margin) with the onboarding fee, amortised per month and its share of the contract value.
A10: 6. Summary: loaded hourly cost, technicians and productive hours, tool stack total, monthly recurring revenue, cost, gross profit and overall margin, contracts below target margin, most and least profitable contract, cost per ticket, block and onboarding revenue.
A12: LEGEND
A13: Blue text = a cell you type into. Black text = a formula, leave it alone. Yellow fill = key inputs.
A15: DEFINITIONS
... A25: Arithmetic only; not financial advice.

Sheet Settings
A1: Settings
A2: Technician count | B2: 3 | C2: Example default 3. Technicians who work client tickets and projects (full-time equivalents).
A3: Average technician salary per month | B3: 4500 | C3: Example default 4,500 a month. Gross salary per technician before payroll taxes and benefits.
A4: Payroll taxes and benefits % | B4: 20 | C4: Default 20. Employer payroll taxes, pension, health cover and other benefits on top of salary.
A5: Productive hours per technician per month | B5: 130 | C5: Default 130 of about 173 paid hours: the rest is holidays, sickness, training, meetings and admin.
A6: Office (monthly) | B6: 1200 | C6: Example default 1,200 a month. Rent, utilities and cleaning.
A7: Insurance (monthly) | B7: 300 | C7: Example default 300 a month. Professional indemnity, cyber and liability cover.
A8: Vehicles and travel (monthly) | B8: 400 | C8: Example default 400 a month. Fuel, leases, parking and travel to client sites.
A9: Admin and sales staff (monthly) | B9: 3500 | C9: Example default 3,500 a month. Non-technical staff: service desk coordinator, sales, accounts.
A10: Software not billed to clients (monthly) | B10: 250 | C10: Example default 250 a month. Accounting, office suite, phones; client tools belong on the Tool Stack.
A11: Other overhead (monthly) | B11: 300 | C11: Example default 300 a month. Marketing, training, bank charges, anything else.
A12: Total monthly overhead | B12: =SUM(B6:B11) -> 5950 | C12: formula: sum of the six overhead rows above
A13: Target margin % on price | B13: 30 | C13: Default 30. Your own target gross margin on each contract's monthly fee (profit ÷ price, not markup on cost).
A14: Block hours discount % | B14: 10 | C14: Default 10. Discount off the hourly rate for prepaid block hours; each block can override it.
A15: Expected unused block hours % | B15: 15 | C15: Default 15. Share of prepaid block hours you expect to expire unused; each block can override it.
A16: Default hourly rate for billed work | B16: 120 | C16: Default 120. Your rate for out-of-contract work, blocks and onboarding; keep it well above the loaded hourly cost.
A17: Loaded technician cost per month | B17: =ROUND(B2*B3*(1+B4/100),2) -> 16200 | C17: formula: technician count × salary × (1 + payroll taxes and benefits %)
A18: Total productive hours per month | B18: =ROUND(B2*B5,2) -> 390 | C18: formula: technician count × productive hours per technician
A19: Loaded hourly cost | B19: =IFERROR(ROUND((B17+B12)/B18,2),0) -> 56.79 | C19: formula: (loaded technician cost + total overhead) ÷ productive hours; what each productive hour costs you
A20: Rate per minute | B20: =ROUND(B19/60,4) -> 0.9465 | C20: formula: loaded hourly cost ÷ 60

Sheet Tool Stack
A1: Tool Stack
A2: One row per tool you pay for to serve clients. Per-user, per-device and per-site tools are shared across contracts by users + devices; fixed tools stay in overhead.
A4: Tool | B4: Billing basis | C4: Unit cost per month | D4: Units in use | E4: Monthly cost
A5: RMM agent | B5: per device | C5: 3 | D5: 180 | E5: =IF(A5="","",ROUND(C5*D5,2)) -> 540
A6: EDR / antivirus | B6: per device | C6: 4.5 | D6: 180 | E6: =IF(A6="","",ROUND(C6*D6,2)) -> 810
A7: Email security | B7: per user | C7: 2 | D7: 150 | E7: =IF(A7="","",ROUND(C7*D7,2)) -> 300
A8: Backup | B8: per device | C8: 6 | D8: 60 | E8: =IF(A8="","",ROUND(C8*D8,2)) -> 360
A9: PSA (per technician seat) | B9: fixed | C9: 45 | D9: 3 | E9: =IF(A9="","",ROUND(C9*D9,2)) -> 135
A10: Documentation platform | B10: fixed | C10: 120 | D10: 1 | E10: =IF(A10="","",ROUND(C10*D10,2)) -> 120
A11: Password manager | B11: per user | C11: 3 | D11: 150 | E11: =IF(A11="","",ROUND(C11*D11,2)) -> 450
A12: Remote support | B12: fixed | C12: 60 | D12: 1 | E12: =IF(A12="","",ROUND(C12*D12,2)) -> 60
E13: =IF(A13="","",ROUND(C13*D13,2))
E14: =IF(A14="","",ROUND(C14*D14,2))
E15: =IF(A15="","",ROUND(C15*D15,2))
E16: =IF(A16="","",ROUND(C16*D16,2))
E17: =IF(A17="","",ROUND(C17*D17,2))
E18: =IF(A18="","",ROUND(C18*D18,2))
E19: =IF(A19="","",ROUND(C19*D19,2))
E20: =IF(A20="","",ROUND(C20*D20,2))
E21: =IF(A21="","",ROUND(C21*D21,2))
E22: =IF(A22="","",ROUND(C22*D22,2))
E23: =IF(A23="","",ROUND(C23*D23,2))
E24: =IF(A24="","",ROUND(C24*D24,2))
A25: Total | D25: =SUM(D5:D24) -> 725 | E25: =SUM(E5:E24) -> 2775
A27: Tool stack total per month | B27: =E25 -> 2775
A28: Fixed tool cost per month | B28: =SUMIF(B5:B24,"fixed",E5:E24) -> 315 | C28: basis = fixed; counted in Tickets cost, not allocated to contracts
A29: Per-unit tool cost per month | B29: =B27-B28 -> 2460 | C29: total − fixed; shared across contracts by users + devices

Sheet Contracts
A1: Contracts
A2: One row per client contract. Labour uses the loaded hourly cost from Settings; shared tools come from the Tool Stack per-unit total, split by users + devices.
A4: Client | B4: Plan | C4: Users | D4: Devices | E4: Monthly fee | F4: Support hours per month | G4: Dedicated tool costs per month | H4: Onboarding fee charged | I4: Contract months | J4: Users + devices | K4: Shared tool cost allocated | L4: Labour cost | M4: Total cost | N4: Gross profit | O4: Margin % | P4: Fee per user | Q4: Cost per user | R4: Price per user at target margin | S4: Break-even hours | T4: Hours over (+) / under (−) break-even | U4: Contract value
A5: Harbour Dental Group | B5: per user | C5: 25 | D5: 30 | E5: 2750 | F5: 14 | G5: 0 | H5: 1500 | I5: 24 | J5: =IF(A5="","",C5+D5) -> 55 | K5: =IF(A5="","",IFERROR(ROUND('Tool Stack'!$B$29/$J$35*J5,2),0)) -> 218.23 | L5: =IF(A5="","",ROUND(F5*Settings!$B$19,2)) -> 795.06 | M5: =IF(A5="","",K5+G5+L5) -> 1013.29 | N5: =IF(A5="","",ROUND(E5-M5,2)) -> 1736.71 | O5: =IF(A5="","",IFERROR(ROUND(N5/E5*100,2),0)) -> 63.15 | P5: =IF(A5="","",IFERROR(ROUND(E5/C5,2),0)) -> 110 | Q5: =IF(A5="","",IFERROR(ROUND(M5/C5,2),0)) -> 40.53 | R5: =IF(A5="","",IFERROR(ROUND(Q5/(1-Settings!$B$13/100),2),0)) -> 57.9 | S5: =IF(A5="","",IFERROR(ROUND((E5-K5-G5)/Settings!$B$19,2),0)) -> 44.58 | T5: =IF(A5="","",ROUND(F5-S5,2)) -> -30.58 | U5: =IF(A5="","",ROUND(E5*I5+H5,2)) -> 67500
A6: Northgate Logistics | B6: hybrid | C6: 60 | D6: 75 | E6: 6200 | F6: 38 | G6: 150 | H6: 3000 | I6: 36 | J6: =IF(A6="","",C6+D6) -> 135 | K6: =IF(A6="","",IFERROR(ROUND('Tool Stack'!$B$29/$J$35*J6,2),0)) -> 535.65 | L6: =IF(A6="","",ROUND(F6*Settings!$B$19,2)) -> 2158.02 | M6: =IF(A6="","",K6+G6+L6) -> 2843.67 | N6: =IF(A6="","",ROUND(E6-M6,2)) -> 3356.33 | O6: =IF(A6="","",IFERROR(ROUND(N6/E6*100,2),0)) -> 54.13 | P6: =IF(A6="","",IFERROR(ROUND(E6/C6,2),0)) -> 103.33 | Q6: =IF(A6="","",IFERROR(ROUND(M6/C6,2),0)) -> 47.39 | R6: =IF(A6="","",IFERROR(ROUND(Q6/(1-Settings!$B$13/100),2),0)) -> 67.7 | S6: =IF(A6="","",IFERROR(ROUND((E6-K6-G6)/Settings!$B$19,2),0)) -> 97.1 | T6: =IF(A6="","",ROUND(F6-S6,2)) -> -59.1 | U6: =IF(A6="","",ROUND(E6*I6+H6,2)) -> 226200
A7: Bluewater Law LLP | B7: per user | C7: 18 | D7: 22 | E7: 1980 | F7: 12 | G7: 80 | H7: 1200 | I7: 24 | J7: =IF(A7="","",C7+D7) -> 40 | K7: =IF(A7="","",IFERROR(ROUND('Tool Stack'!$B$29/$J$35*J7,2),0)) -> 158.71 | L7: =IF(A7="","",ROUND(F7*Settings!$B$19,2)) -> 681.48 | M7: =IF(A7="","",K7+G7+L7) -> 920.19 | N7: =IF(A7="","",ROUND(E7-M7,2)) -> 1059.81 | O7: =IF(A7="","",IFERROR(ROUND(N7/E7*100,2),0)) -> 53.53 | P7: =IF(A7="","",IFERROR(ROUND(E7/C7,2),0)) -> 110 | Q7: =IF(A7="","",IFERROR(ROUND(M7/C7,2),0)) -> 51.12 | R7: =IF(A7="","",IFERROR(ROUND(Q7/(1-Settings!$B$13/100),2),0)) -> 73.03 | S7: =IF(A7="","",IFERROR(ROUND((E7-K7-G7)/Settings!$B$19,2),0)) -> 30.66 | T7: =IF(A7="","",ROUND(F7-S7,2)) -> -18.66 | U7: =IF(A7="","",ROUND(E7*I7+H7,2)) -> 48720
A8: Ridge Architects | B8: per device | C8: 12 | D8: 20 | E8: 950 | F8: 16 | G8: 0 | H8: 800 | I8: 12 | J8: =IF(A8="","",C8+D8) -> 32 | K8: =IF(A8="","",IFERROR(ROUND('Tool Stack'!$B$29/$J$35*J8,2),0)) -> 126.97 | L8: =IF(A8="","",ROUND(F8*Settings!$B$19,2)) -> 908.64 | M8: =IF(A8="","",K8+G8+L8) -> 1035.61 | N8: =IF(A8="","",ROUND(E8-M8,2)) -> -85.61 | O8: =IF(A8="","",IFERROR(ROUND(N8/E8*100,2),0)) -> -9.01 | P8: =IF(A8="","",IFERROR(ROUND(E8/C8,2),0)) -> 79.17 | Q8: =IF(A8="","",IFERROR(ROUND(M8/C8,2),0)) -> 86.3 | R8: =IF(A8="","",IFERROR(ROUND(Q8/(1-Settings!$B$13/100),2),0)) -> 123.29 | S8: =IF(A8="","",IFERROR(ROUND((E8-K8-G8)/Settings!$B$19,2),0)) -> 14.49 | T8: =IF(A8="","",ROUND(F8-S8,2)) -> 1.51 | U8: =IF(A8="","",ROUND(E8*I8+H8,2)) -> 12200
A9: Summit Accounting | B9: per user | C9: 30 | D9: 35 | E9: 3150 | F9: 18 | G9: 60 | H9: 1800 | I9: 36 | J9: =IF(A9="","",C9+D9) -> 65 | K9: =IF(A9="","",IFERROR(ROUND('Tool Stack'!$B$29/$J$35*J9,2),0)) -> 257.9 | L9: =IF(A9="","",ROUND(F9*Settings!$B$19,2)) -> 1022.22 | M9: =IF(A9="","",K9+G9+L9) -> 1340.12 | N9: =IF(A9="","",ROUND(E9-M9,2)) -> 1809.88 | O9: =IF(A9="","",IFERROR(ROUND(N9/E9*100,2),0)) -> 57.46 | P9: =IF(A9="","",IFERROR(ROUND(E9/C9,2),0)) -> 105 | Q9: =IF(A9="","",IFERROR(ROUND(M9/C9,2),0)) -> 44.67 | R9: =IF(A9="","",IFERROR(ROUND(Q9/(1-Settings!$B$13/100),2),0)) -> 63.81 | S9: =IF(A9="","",IFERROR(ROUND((E9-K9-G9)/Settings!$B$19,2),0)) -> 49.87 | T9: =IF(A9="","",ROUND(F9-S9,2)) -> -31.87 | U9: =IF(A9="","",ROUND(E9*I9+H9,2)) -> 115200
A10: Oakfield Veterinary | B10: per device | C10: 15 | D10: 28 | E10: 1250 | F10: 10 | G10: 0 | H10: 900 | I10: 12 | J10: =IF(A10="","",C10+D10) -> 43 | K10: =IF(A10="","",IFERROR(ROUND('Tool Stack'!$B$29/$J$35*J10,2),0)) -> 170.61 | L10: =IF(A10="","",ROUND(F10*Settings!$B$19,2)) -> 567.9 | M10: =IF(A10="","",K10+G10+L10) -> 738.51 | N10: =IF(A10="","",ROUND(E10-M10,2)) -> 511.49 | O10: =IF(A10="","",IFERROR(ROUND(N10/E10*100,2),0)) -> 40.92 | P10: =IF(A10="","",IFERROR(ROUND(E10/C10,2),0)) -> 83.33 | Q10: =IF(A10="","",IFERROR(ROUND(M10/C10,2),0)) -> 49.23 | R10: =IF(A10="","",IFERROR(ROUND(Q10/(1-Settings!$B$13/100),2),0)) -> 70.33 | S10: =IF(A10="","",IFERROR(ROUND((E10-K10-G10)/Settings!$B$19,2),0)) -> 19.01 | T10: =IF(A10="","",ROUND(F10-S10,2)) -> -9.01 | U10: =IF(A10="","",ROUND(E10*I10+H10,2)) -> 15900
A11: Kestrel Manufacturing | B11: hybrid | C11: 40 | D11: 90 | E11: 3200 | F11: 45 | G11: 200 | H11: 2500 | I11: 36 | J11: =IF(A11="","",C11+D11) -> 130 | K11: =IF(A11="","",IFERROR(ROUND('Tool Stack'!$B$29/$J$35*J11,2),0)) -> 515.81 | L11: =IF(A11="","",ROUND(F11*Settings!$B$19,2)) -> 2555.55 | M11: =IF(A11="","",K11+G11+L11) -> 3271.36 | N11: =IF(A11="","",ROUND(E11-M11,2)) -> -71.36 | O11: =IF(A11="","",IFERROR(ROUND(N11/E11*100,2),0)) -> -2.23 | P11: =IF(A11="","",IFERROR(ROUND(E11/C11,2),0)) -> 80 | Q11: =IF(A11="","",IFERROR(ROUND(M11/C11,2),0)) -> 81.78 | R11: =IF(A11="","",IFERROR(ROUND(Q11/(1-Settings!$B$13/100),2),0)) -> 116.83 | S11: =IF(A11="","",IFERROR(ROUND((E11-K11-G11)/Settings!$B$19,2),0)) -> 43.74 | T11: =IF(A11="","",ROUND(F11-S11,2)) -> 1.26 | U11: =IF(A11="","",ROUND(E11*I11+H11,2)) -> 117700
A12: Pinecrest School Trust | B12: per user | C12: 50 | D12: 70 | E12: 4800 | F12: 30 | G12: 120 | H12: 2000 | I12: 24 | J12: =IF(A12="","",C12+D12) -> 120 | K12: =IF(A12="","",IFERROR(ROUND('Tool Stack'!$B$29/$J$35*J12,2),0)) -> 476.13 | L12: =IF(A12="","",ROUND(F12*Settings!$B$19,2)) -> 1703.7 | M12: =IF(A12="","",K12+G12+L12) -> 2299.83 | N12: =IF(A12="","",ROUND(E12-M12,2)) -> 2500.17 | O12: =IF(A12="","",IFERROR(ROUND(N12/E12*100,2),0)) -> 52.09 | P12: =IF(A12="","",IFERROR(ROUND(E12/C12,2),0)) -> 96 | Q12: =IF(A12="","",IFERROR(ROUND(M12/C12,2),0)) -> 46 | R12: =IF(A12="","",IFERROR(ROUND(Q12/(1-Settings!$B$13/100),2),0)) -> 65.71 | S12: =IF(A12="","",IFERROR(ROUND((E12-K12-G12)/Settings!$B$19,2),0)) -> 74.02 | T12: =IF(A12="","",ROUND(F12-S12,2)) -> -44.02 | U12: =IF(A12="","",ROUND(E12*I12+H12,2)) -> 117200
J13: =IF(A13="","",C13+D13) | K13: =IF(A13="","",IFERROR(ROUND('Tool Stack'!$B$29/$J$35*J13,2),0)) | L13: =IF(A13="","",ROUND(F13*Settings!$B$19,2)) | M13: =IF(A13="","",K13+G13+L13) | N13: =IF(A13="","",ROUND(E13-M13,2)) | O13: =IF(A13="","",IFERROR(ROUND(N13/E13*100,2),0)) | P13: =IF(A13="","",IFERROR(ROUND(E13/C13,2),0)) | Q13: =IF(A13="","",IFERROR(ROUND(M13/C13,2),0)) | R13: =IF(A13="","",IFERROR(ROUND(Q13/(1-Settings!$B$13/100),2),0)) | S13: =IF(A13="","",IFERROR(ROUND((E13-K13-G13)/Settings!$B$19,2),0)) | T13: =IF(A13="","",ROUND(F13-S13,2)) | U13: =IF(A13="","",ROUND(E13*I13+H13,2))
J14: =IF(A14="","",C14+D14) | K14: =IF(A14="","",IFERROR(ROUND('Tool Stack'!$B$29/$J$35*J14,2),0)) | L14: =IF(A14="","",ROUND(F14*Settings!$B$19,2)) | M14: =IF(A14="","",K14+G14+L14) | N14: =IF(A14="","",ROUND(E14-M14,2)) | O14: =IF(A14="","",IFERROR(ROUND(N14/E14*100,2),0)) | P14: =IF(A14="","",IFERROR(ROUND(E14/C14,2),0)) | Q14: =IF(A14="","",IFERROR(ROUND(M14/C14,2),0)) | R14: =IF(A14="","",IFERROR(ROUND(Q14/(1-Settings!$B$13/100),2),0)) | S14: =IF(A14="","",IFERROR(ROUND((E14-K14-G14)/Settings!$B$19,2),0)) | T14: =IF(A14="","",ROUND(F14-S14,2)) | U14: =IF(A14="","",ROUND(E14*I14+H14,2))
J15: =IF(A15="","",C15+D15) | K15: =IF(A15="","",IFERROR(ROUND('Tool Stack'!$B$29/$J$35*J15,2),0)) | L15: =IF(A15="","",ROUND(F15*Settings!$B$19,2)) | M15: =IF(A15="","",K15+G15+L15) | N15: =IF(A15="","",ROUND(E15-M15,2)) | O15: =IF(A15="","",IFERROR(ROUND(N15/E15*100,2),0)) | P15: =IF(A15="","",IFERROR(ROUND(E15/C15,2),0)) | Q15: =IF(A15="","",IFERROR(ROUND(M15/C15,2),0)) | R15: =IF(A15="","",IFERROR(ROUND(Q15/(1-Settings!$B$13/100),2),0)) | S15: =IF(A15="","",IFERROR(ROUND((E15-K15-G15)/Settings!$B$19,2),0)) | T15: =IF(A15="","",ROUND(F15-S15,2)) | U15: =IF(A15="","",ROUND(E15*I15+H15,2))
J16: =IF(A16="","",C16+D16) | K16: =IF(A16="","",IFERROR(ROUND('Tool Stack'!$B$29/$J$35*J16,2),0)) | L16: =IF(A16="","",ROUND(F16*Settings!$B$19,2)) | M16: =IF(A16="","",K16+G16+L16) | N16: =IF(A16="","",ROUND(E16-M16,2)) | O16: =IF(A16="","",IFERROR(ROUND(N16/E16*100,2),0)) | P16: =IF(A16="","",IFERROR(ROUND(E16/C16,2),0)) | Q16: =IF(A16="","",IFERROR(ROUND(M16/C16,2),0)) | R16: =IF(A16="","",IFERROR(ROUND(Q16/(1-Settings!$B$13/100),2),0)) | S16: =IF(A16="","",IFERROR(ROUND((E16-K16-G16)/Settings!$B$19,2),0)) | T16: =IF(A16="","",ROUND(F16-S16,2)) | U16: =IF(A16="","",ROUND(E16*I16+H16,2))
J17: =IF(A17="","",C17+D17) | K17: =IF(A17="","",IFERROR(ROUND('Tool Stack'!$B$29/$J$35*J17,2),0)) | L17: =IF(A17="","",ROUND(F17*Settings!$B$19,2)) | M17: =IF(A17="","",K17+G17+L17) | N17: =IF(A17="","",ROUND(E17-M17,2)) | O17: =IF(A17="","",IFERROR(ROUND(N17/E17*100,2),0)) | P17: =IF(A17="","",IFERROR(ROUND(E17/C17,2),0)) | Q17: =IF(A17="","",IFERROR(ROUND(M17/C17,2),0)) | R17: =IF(A17="","",IFERROR(ROUND(Q17/(1-Settings!$B$13/100),2),0)) | S17: =IF(A17="","",IFERROR(ROUND((E17-K17-G17)/Settings!$B$19,2),0)) | T17: =IF(A17="","",ROUND(F17-S17,2)) | U17: =IF(A17="","",ROUND(E17*I17+H17,2))
J18: =IF(A18="","",C18+D18) | K18: =IF(A18="","",IFERROR(ROUND('Tool Stack'!$B$29/$J$35*J18,2),0)) | L18: =IF(A18="","",ROUND(F18*Settings!$B$19,2)) | M18: =IF(A18="","",K18+G18+L18) | N18: =IF(A18="","",ROUND(E18-M18,2)) | O18: =IF(A18="","",IFERROR(ROUND(N18/E18*100,2),0)) | P18: =IF(A18="","",IFERROR(ROUND(E18/C18,2),0)) | Q18: =IF(A18="","",IFERROR(ROUND(M18/C18,2),0)) | R18: =IF(A18="","",IFERROR(ROUND(Q18/(1-Settings!$B$13/100),2),0)) | S18: =IF(A18="","",IFERROR(ROUND((E18-K18-G18)/Settings!$B$19,2),0)) | T18: =IF(A18="","",ROUND(F18-S18,2)) | U18: =IF(A18="","",ROUND(E18*I18+H18,2))
J19: =IF(A19="","",C19+D19) | K19: =IF(A19="","",IFERROR(ROUND('Tool Stack'!$B$29/$J$35*J19,2),0)) | L19: =IF(A19="","",ROUND(F19*Settings!$B$19,2)) | M19: =IF(A19="","",K19+G19+L19) | N19: =IF(A19="","",ROUND(E19-M19,2)) | O19: =IF(A19="","",IFERROR(ROUND(N19/E19*100,2),0)) | P19: =IF(A19="","",IFERROR(ROUND(E19/C19,2),0)) | Q19: =IF(A19="","",IFERROR(ROUND(M19/C19,2),0)) | R19: =IF(A19="","",IFERROR(ROUND(Q19/(1-Settings!$B$13/100),2),0)) | S19: =IF(A19="","",IFERROR(ROUND((E19-K19-G19)/Settings!$B$19,2),0)) | T19: =IF(A19="","",ROUND(F19-S19,2)) | U19: =IF(A19="","",ROUND(E19*I19+H19,2))
J20: =IF(A20="","",C20+D20) | K20: =IF(A20="","",IFERROR(ROUND('Tool Stack'!$B$29/$J$35*J20,2),0)) | L20: =IF(A20="","",ROUND(F20*Settings!$B$19,2)) | M20: =IF(A20="","",K20+G20+L20) | N20: =IF(A20="","",ROUND(E20-M20,2)) | O20: =IF(A20="","",IFERROR(ROUND(N20/E20*100,2),0)) | P20: =IF(A20="","",IFERROR(ROUND(E20/C20,2),0)) | Q20: =IF(A20="","",IFERROR(ROUND(M20/C20,2),0)) | R20: =IF(A20="","",IFERROR(ROUND(Q20/(1-Settings!$B$13/100),2),0)) | S20: =IF(A20="","",IFERROR(ROUND((E20-K20-G20)/Settings!$B$19,2),0)) | T20: =IF(A20="","",ROUND(F20-S20,2)) | U20: =IF(A20="","",ROUND(E20*I20+H20,2))
J21: =IF(A21="","",C21+D21) | K21: =IF(A21="","",IFERROR(ROUND('Tool Stack'!$B$29/$J$35*J21,2),0)) | L21: =IF(A21="","",ROUND(F21*Settings!$B$19,2)) | M21: =IF(A21="","",K21+G21+L21) | N21: =IF(A21="","",ROUND(E21-M21,2)) | O21: =IF(A21="","",IFERROR(ROUND(N21/E21*100,2),0)) | P21: =IF(A21="","",IFERROR(ROUND(E21/C21,2),0)) | Q21: =IF(A21="","",IFERROR(ROUND(M21/C21,2),0)) | R21: =IF(A21="","",IFERROR(ROUND(Q21/(1-Settings!$B$13/100),2),0)) | S21: =IF(A21="","",IFERROR(ROUND((E21-K21-G21)/Settings!$B$19,2),0)) | T21: =IF(A21="","",ROUND(F21-S21,2)) | U21: =IF(A21="","",ROUND(E21*I21+H21,2))
J22: =IF(A22="","",C22+D22) | K22: =IF(A22="","",IFERROR(ROUND('Tool Stack'!$B$29/$J$35*J22,2),0)) | L22: =IF(A22="","",ROUND(F22*Settings!$B$19,2)) | M22: =IF(A22="","",K22+G22+L22) | N22: =IF(A22="","",ROUND(E22-M22,2)) | O22: =IF(A22="","",IFERROR(ROUND(N22/E22*100,2),0)) | P22: =IF(A22="","",IFERROR(ROUND(E22/C22,2),0)) | Q22: =IF(A22="","",IFERROR(ROUND(M22/C22,2),0)) | R22: =IF(A22="","",IFERROR(ROUND(Q22/(1-Settings!$B$13/100),2),0)) | S22: =IF(A22="","",IFERROR(ROUND((E22-K22-G22)/Settings!$B$19,2),0)) | T22: =IF(A22="","",ROUND(F22-S22,2)) | U22: =IF(A22="","",ROUND(E22*I22+H22,2))
J23: =IF(A23="","",C23+D23) | K23: =IF(A23="","",IFERROR(ROUND('Tool Stack'!$B$29/$J$35*J23,2),0)) | L23: =IF(A23="","",ROUND(F23*Settings!$B$19,2)) | M23: =IF(A23="","",K23+G23+L23) | N23: =IF(A23="","",ROUND(E23-M23,2)) | O23: =IF(A23="","",IFERROR(ROUND(N23/E23*100,2),0)) | P23: =IF(A23="","",IFERROR(ROUND(E23/C23,2),0)) | Q23: =IF(A23="","",IFERROR(ROUND(M23/C23,2),0)) | R23: =IF(A23="","",IFERROR(ROUND(Q23/(1-Settings!$B$13/100),2),0)) | S23: =IF(A23="","",IFERROR(ROUND((E23-K23-G23)/Settings!$B$19,2),0)) | T23: =IF(A23="","",ROUND(F23-S23,2)) | U23: =IF(A23="","",ROUND(E23*I23+H23,2))
J24: =IF(A24="","",C24+D24) | K24: =IF(A24="","",IFERROR(ROUND('Tool Stack'!$B$29/$J$35*J24,2),0)) | L24: =IF(A24="","",ROUND(F24*Settings!$B$19,2)) | M24: =IF(A24="","",K24+G24+L24) | N24: =IF(A24="","",ROUND(E24-M24,2)) | O24: =IF(A24="","",IFERROR(ROUND(N24/E24*100,2),0)) | P24: =IF(A24="","",IFERROR(ROUND(E24/C24,2),0)) | Q24: =IF(A24="","",IFERROR(ROUND(M24/C24,2),0)) | R24: =IF(A24="","",IFERROR(ROUND(Q24/(1-Settings!$B$13/100),2),0)) | S24: =IF(A24="","",IFERROR(ROUND((E24-K24-G24)/Settings!$B$19,2),0)) | T24: =IF(A24="","",ROUND(F24-S24,2)) | U24: =IF(A24="","",ROUND(E24*I24+H24,2))
... J34: =IF(A34="","",C34+D34) | K34: =IF(A34="","",IFERROR(ROUND('Tool Stack'!$B$29/$J$35*J34,2),0)) | L34: =IF(A34="","",ROUND(F34*Settings!$B$19,2)) | M34: =IF(A34="","",K34+G34+L34) | N34: =IF(A34="","",ROUND(E34-M34,2)) | O34: =IF(A34="","",IFERROR(ROUND(N34/E34*100,2),0)) | P34: =IF(A34="","",IFERROR(ROUND(E34/C34,2),0)) | Q34: =IF(A34="","",IFERROR(ROUND(M34/C34,2),0)) | R34: =IF(A34="","",IFERROR(ROUND(Q34/(1-Settings!$B$13/100),2),0)) | S34: =IF(A34="","",IFERROR(ROUND((E34-K34-G34)/Settings!$B$19,2),0)) | T34: =IF(A34="","",ROUND(F34-S34,2)) | U34: =IF(A34="","",ROUND(E34*I34+H34,2))
A35: Total | B35: =COUNTA(A5:A34) -> 8 | C35: =SUM(C5:C34) -> 250 | D35: =SUM(D5:D34) -> 370 | E35: =SUM(E5:E34) -> 24280 | F35: =SUM(F5:F34) -> 183 | G35: =SUM(G5:G34) -> 610 | H35: =SUM(H5:H34) -> 13700 | J35: =SUM(J5:J34) -> 620 | K35: =SUM(K5:K34) -> 2460.01 | L35: =SUM(L5:L34) -> 10392.57 | M35: =SUM(M5:M34) -> 13462.58 | N35: =SUM(N5:N34) -> 10817.42 | O35: =IFERROR(ROUND(N35/E35*100,2),0) -> 44.55 | U35: =SUM(U5:U34) -> 720620
A36: Total row: monthly recurring revenue (column E), monthly cost (column M), gross profit (column N) and overall margin % (column O).

Sheet Tickets
A1: Tickets
A2: One row per month, filled top down. Costs default from Settings and the Tool Stack; type your own in columns E and H to override them for that month.
A4: Month | B4: Tickets closed | C4: Average minutes per ticket | D4: Technician cost (Settings) | E4: or type your own | F4: Technician cost used | G4: Tool and overhead cost (Settings + Tool Stack) | H4: or type your own | I4: Tool and overhead cost used | J4: Total cost | K4: Cost per ticket | L4: Labour cost per ticket | M4: Tickets per technician | N4: Labour hours on tickets | O4: Share of productive hours on tickets %
A5: 46023 | B5: 310 | C5: 32 | D5: =IF(A5="","",Settings!$B$17) -> 16200 | F5: =IF(A5="","",IF(E5<>"",E5,D5)) -> 16200 | G5: =IF(A5="","",'Tool Stack'!$E$25+Settings!$B$12) -> 8725 | I5: =IF(A5="","",IF(H5<>"",H5,G5)) -> 8725 | J5: =IF(A5="","",F5+I5) -> 24925 | K5: =IF(A5="","",IFERROR(ROUND(J5/B5,2),0)) -> 80.4 | L5: =IF(A5="","",ROUND(C5*Settings!$B$20,2)) -> 30.29 | M5: =IF(A5="","",IFERROR(ROUND(B5/Settings!$B$2,2),0)) -> 103.33 | N5: =IF(A5="","",ROUND(B5*C5/60,2)) -> 165.33 | O5: =IF(A5="","",IFERROR(ROUND(N5/Settings!$B$18*100,2),0)) -> 42.39
A6: 46054 | B6: 295 | C6: 35 | D6: =IF(A6="","",Settings!$B$17) -> 16200 | F6: =IF(A6="","",IF(E6<>"",E6,D6)) -> 16200 | G6: =IF(A6="","",'Tool Stack'!$E$25+Settings!$B$12) -> 8725 | I6: =IF(A6="","",IF(H6<>"",H6,G6)) -> 8725 | J6: =IF(A6="","",F6+I6) -> 24925 | K6: =IF(A6="","",IFERROR(ROUND(J6/B6,2),0)) -> 84.49 | L6: =IF(A6="","",ROUND(C6*Settings!$B$20,2)) -> 33.13 | M6: =IF(A6="","",IFERROR(ROUND(B6/Settings!$B$2,2),0)) -> 98.33 | N6: =IF(A6="","",ROUND(B6*C6/60,2)) -> 172.08 | O6: =IF(A6="","",IFERROR(ROUND(N6/Settings!$B$18*100,2),0)) -> 44.12
A7: 46082 | B7: 340 | C7: 30 | D7: =IF(A7="","",Settings!$B$17) -> 16200 | E7: 17500 | F7: =IF(A7="","",IF(E7<>"",E7,D7)) -> 17500 | G7: =IF(A7="","",'Tool Stack'!$E$25+Settings!$B$12) -> 8725 | I7: =IF(A7="","",IF(H7<>"",H7,G7)) -> 8725 | J7: =IF(A7="","",F7+I7) -> 26225 | K7: =IF(A7="","",IFERROR(ROUND(J7/B7,2),0)) -> 77.13 | L7: =IF(A7="","",ROUND(C7*Settings!$B$20,2)) -> 28.4 | M7: =IF(A7="","",IFERROR(ROUND(B7/Settings!$B$2,2),0)) -> 113.33 | N7: =IF(A7="","",ROUND(B7*C7/60,2)) -> 170 | O7: =IF(A7="","",IFERROR(ROUND(N7/Settings!$B$18*100,2),0)) -> 43.59
A8: 46113 | B8: 280 | C8: 34 | D8: =IF(A8="","",Settings!$B$17) -> 16200 | F8: =IF(A8="","",IF(E8<>"",E8,D8)) -> 16200 | G8: =IF(A8="","",'Tool Stack'!$E$25+Settings!$B$12) -> 8725 | I8: =IF(A8="","",IF(H8<>"",H8,G8)) -> 8725 | J8: =IF(A8="","",F8+I8) -> 24925 | K8: =IF(A8="","",IFERROR(ROUND(J8/B8,2),0)) -> 89.02 | L8: =IF(A8="","",ROUND(C8*Settings!$B$20,2)) -> 32.18 | M8: =IF(A8="","",IFERROR(ROUND(B8/Settings!$B$2,2),0)) -> 93.33 | N8: =IF(A8="","",ROUND(B8*C8/60,2)) -> 158.67 | O8: =IF(A8="","",IFERROR(ROUND(N8/Settings!$B$18*100,2),0)) -> 40.68
A9: 46143 | B9: 325 | C9: 31 | D9: =IF(A9="","",Settings!$B$17) -> 16200 | F9: =IF(A9="","",IF(E9<>"",E9,D9)) -> 16200 | G9: =IF(A9="","",'Tool Stack'!$E$25+Settings!$B$12) -> 8725 | I9: =IF(A9="","",IF(H9<>"",H9,G9)) -> 8725 | J9: =IF(A9="","",F9+I9) -> 24925 | K9: =IF(A9="","",IFERROR(ROUND(J9/B9,2),0)) -> 76.69 | L9: =IF(A9="","",ROUND(C9*Settings!$B$20,2)) -> 29.34 | M9: =IF(A9="","",IFERROR(ROUND(B9/Settings!$B$2,2),0)) -> 108.33 | N9: =IF(A9="","",ROUND(B9*C9/60,2)) -> 167.92 | O9: =IF(A9="","",IFERROR(ROUND(N9/Settings!$B$18*100,2),0)) -> 43.06
A10: 46174 | B10: 300 | C10: 33 | D10: =IF(A10="","",Settings!$B$17) -> 16200 | F10: =IF(A10="","",IF(E10<>"",E10,D10)) -> 16200 | G10: =IF(A10="","",'Tool Stack'!$E$25+Settings!$B$12) -> 8725 | I10: =IF(A10="","",IF(H10<>"",H10,G10)) -> 8725 | J10: =IF(A10="","",F10+I10) -> 24925 | K10: =IF(A10="","",IFERROR(ROUND(J10/B10,2),0)) -> 83.08 | L10: =IF(A10="","",ROUND(C10*Settings!$B$20,2)) -> 31.23 | M10: =IF(A10="","",IFERROR(ROUND(B10/Settings!$B$2,2),0)) -> 100 | N10: =IF(A10="","",ROUND(B10*C10/60,2)) -> 165 | O10: =IF(A10="","",IFERROR(ROUND(N10/Settings!$B$18*100,2),0)) -> 42.31
D11: =IF(A11="","",Settings!$B$17) | F11: =IF(A11="","",IF(E11<>"",E11,D11)) | G11: =IF(A11="","",'Tool Stack'!$E$25+Settings!$B$12) | I11: =IF(A11="","",IF(H11<>"",H11,G11)) | J11: =IF(A11="","",F11+I11) | K11: =IF(A11="","",IFERROR(ROUND(J11/B11,2),0)) | L11: =IF(A11="","",ROUND(C11*Settings!$B$20,2)) | M11: =IF(A11="","",IFERROR(ROUND(B11/Settings!$B$2,2),0)) | N11: =IF(A11="","",ROUND(B11*C11/60,2)) | O11: =IF(A11="","",IFERROR(ROUND(N11/Settings!$B$18*100,2),0))
D12: =IF(A12="","",Settings!$B$17) | F12: =IF(A12="","",IF(E12<>"",E12,D12)) | G12: =IF(A12="","",'Tool Stack'!$E$25+Settings!$B$12) | I12: =IF(A12="","",IF(H12<>"",H12,G12)) | J12: =IF(A12="","",F12+I12) | K12: =IF(A12="","",IFERROR(ROUND(J12/B12,2),0)) | L12: =IF(A12="","",ROUND(C12*Settings!$B$20,2)) | M12: =IF(A12="","",IFERROR(ROUND(B12/Settings!$B$2,2),0)) | N12: =IF(A12="","",ROUND(B12*C12/60,2)) | O12: =IF(A12="","",IFERROR(ROUND(N12/Settings!$B$18*100,2),0))
D13: =IF(A13="","",Settings!$B$17) | F13: =IF(A13="","",IF(E13<>"",E13,D13)) | G13: =IF(A13="","",'Tool Stack'!$E$25+Settings!$B$12) | I13: =IF(A13="","",IF(H13<>"",H13,G13)) | J13: =IF(A13="","",F13+I13) | K13: =IF(A13="","",IFERROR(ROUND(J13/B13,2),0)) | L13: =IF(A13="","",ROUND(C13*Settings!$B$20,2)) | M13: =IF(A13="","",IFERROR(ROUND(B13/Settings!$B$2,2),0)) | N13: =IF(A13="","",ROUND(B13*C13/60,2)) | O13: =IF(A13="","",IFERROR(ROUND(N13/Settings!$B$18*100,2),0))
D14: =IF(A14="","",Settings!$B$17) | F14: =IF(A14="","",IF(E14<>"",E14,D14)) | G14: =IF(A14="","",'Tool Stack'!$E$25+Settings!$B$12) | I14: =IF(A14="","",IF(H14<>"",H14,G14)) | J14: =IF(A14="","",F14+I14) | K14: =IF(A14="","",IFERROR(ROUND(J14/B14,2),0)) | L14: =IF(A14="","",ROUND(C14*Settings!$B$20,2)) | M14: =IF(A14="","",IFERROR(ROUND(B14/Settings!$B$2,2),0)) | N14: =IF(A14="","",ROUND(B14*C14/60,2)) | O14: =IF(A14="","",IFERROR(ROUND(N14/Settings!$B$18*100,2),0))
D15: =IF(A15="","",Settings!$B$17) | F15: =IF(A15="","",IF(E15<>"",E15,D15)) | G15: =IF(A15="","",'Tool Stack'!$E$25+Settings!$B$12) | I15: =IF(A15="","",IF(H15<>"",H15,G15)) | J15: =IF(A15="","",F15+I15) | K15: =IF(A15="","",IFERROR(ROUND(J15/B15,2),0)) | L15: =IF(A15="","",ROUND(C15*Settings!$B$20,2)) | M15: =IF(A15="","",IFERROR(ROUND(B15/Settings!$B$2,2),0)) | N15: =IF(A15="","",ROUND(B15*C15/60,2)) | O15: =IF(A15="","",IFERROR(ROUND(N15/Settings!$B$18*100,2),0))
D16: =IF(A16="","",Settings!$B$17) | F16: =IF(A16="","",IF(E16<>"",E16,D16)) | G16: =IF(A16="","",'Tool Stack'!$E$25+Settings!$B$12) | I16: =IF(A16="","",IF(H16<>"",H16,G16)) | J16: =IF(A16="","",F16+I16) | K16: =IF(A16="","",IFERROR(ROUND(J16/B16,2),0)) | L16: =IF(A16="","",ROUND(C16*Settings!$B$20,2)) | M16: =IF(A16="","",IFERROR(ROUND(B16/Settings!$B$2,2),0)) | N16: =IF(A16="","",ROUND(B16*C16/60,2)) | O16: =IF(A16="","",IFERROR(ROUND(N16/Settings!$B$18*100,2),0))
A17: Total | B17: =SUM(B5:B16) -> 1850 | C17: =IFERROR(ROUND(N17*60/B17,1),0) -> 32.4 | F17: =SUM(F5:F16) -> 98500 | I17: =SUM(I5:I16) -> 52350 | J17: =SUM(J5:J16) -> 150850 | K17: =IFERROR(ROUND(J17/B17,2),0) -> 81.54 | L17: =ROUND(C17*Settings!$B$20,2) -> 30.67 | M17: =IFERROR(ROUND(B17/Settings!$B$2,2),0) -> 616.67 | N17: =SUM(N5:N16) -> 999 | O17: =IFERROR(ROUND(N17/(Settings!$B$18*COUNT(A5:A16))*100,2),0) -> 42.69

Sheet Blocks & Onboarding
A1: Blocks & Onboarding
A2: Block hours quotes: rate, discount and expected unused % default from Settings; type your own in the 'or type your own' columns to override them.
A4: Client | B4: Hours in block | C4: Default rate (Settings) | D4: or type your own rate | E4: Rate used | F4: Default discount % (Settings) | G4: or type your own discount % | H4: Discount % used | I4: Expiry months | J4: Default unused % (Settings) | K4: or type your own unused % | L4: Unused % used | M4: List price | N4: Block price | O4: Effective rate | P4: Expected used hours | Q4: Effective rate on used hours | R4: Per month
A5: Coastal Realty | B5: 20 | C5: =IF(A5="","",Settings!$B$16) -> 120 | E5: =IF(A5="","",IF(D5<>"",D5,C5)) -> 120 | F5: =IF(A5="","",Settings!$B$14) -> 10 | H5: =IF(A5="","",IF(G5<>"",G5,F5)) -> 10 | I5: 6 | J5: =IF(A5="","",Settings!$B$15) -> 15 | L5: =IF(A5="","",IF(K5<>"",K5,J5)) -> 15 | M5: =IF(A5="","",ROUND(B5*E5,2)) -> 2400 | N5: =IF(A5="","",ROUND(M5*(1-H5/100),2)) -> 2160 | O5: =IF(A5="","",IFERROR(ROUND(N5/B5,2),0)) -> 108 | P5: =IF(A5="","",ROUND(B5*(1-L5/100),2)) -> 17 | Q5: =IF(A5="","",IFERROR(ROUND(N5/P5,2),0)) -> 127.06 | R5: =IF(A5="","",IFERROR(ROUND(N5/I5,2),0)) -> 360
A6: Meridian Studio | B6: 40 | C6: =IF(A6="","",Settings!$B$16) -> 120 | D6: 110 | E6: =IF(A6="","",IF(D6<>"",D6,C6)) -> 110 | F6: =IF(A6="","",Settings!$B$14) -> 10 | G6: 15 | H6: =IF(A6="","",IF(G6<>"",G6,F6)) -> 15 | I6: 12 | J6: =IF(A6="","",Settings!$B$15) -> 15 | L6: =IF(A6="","",IF(K6<>"",K6,J6)) -> 15 | M6: =IF(A6="","",ROUND(B6*E6,2)) -> 4400 | N6: =IF(A6="","",ROUND(M6*(1-H6/100),2)) -> 3740 | O6: =IF(A6="","",IFERROR(ROUND(N6/B6,2),0)) -> 93.5 | P6: =IF(A6="","",ROUND(B6*(1-L6/100),2)) -> 34 | Q6: =IF(A6="","",IFERROR(ROUND(N6/P6,2),0)) -> 110 | R6: =IF(A6="","",IFERROR(ROUND(N6/I6,2),0)) -> 311.67
A7: Fenwick & Sons | B7: 10 | C7: =IF(A7="","",Settings!$B$16) -> 120 | E7: =IF(A7="","",IF(D7<>"",D7,C7)) -> 120 | F7: =IF(A7="","",Settings!$B$14) -> 10 | H7: =IF(A7="","",IF(G7<>"",G7,F7)) -> 10 | I7: 3 | J7: =IF(A7="","",Settings!$B$15) -> 15 | K7: 5 | L7: =IF(A7="","",IF(K7<>"",K7,J7)) -> 5 | M7: =IF(A7="","",ROUND(B7*E7,2)) -> 1200 | N7: =IF(A7="","",ROUND(M7*(1-H7/100),2)) -> 1080 | O7: =IF(A7="","",IFERROR(ROUND(N7/B7,2),0)) -> 108 | P7: =IF(A7="","",ROUND(B7*(1-L7/100),2)) -> 9.5 | Q7: =IF(A7="","",IFERROR(ROUND(N7/P7,2),0)) -> 113.68 | R7: =IF(A7="","",IFERROR(ROUND(N7/I7,2),0)) -> 360
C8: =IF(A8="","",Settings!$B$16) | E8: =IF(A8="","",IF(D8<>"",D8,C8)) | F8: =IF(A8="","",Settings!$B$14) | H8: =IF(A8="","",IF(G8<>"",G8,F8)) | J8: =IF(A8="","",Settings!$B$15) | L8: =IF(A8="","",IF(K8<>"",K8,J8)) | M8: =IF(A8="","",ROUND(B8*E8,2)) | N8: =IF(A8="","",ROUND(M8*(1-H8/100),2)) | O8: =IF(A8="","",IFERROR(ROUND(N8/B8,2),0)) | P8: =IF(A8="","",ROUND(B8*(1-L8/100),2)) | Q8: =IF(A8="","",IFERROR(ROUND(N8/P8,2),0)) | R8: =IF(A8="","",IFERROR(ROUND(N8/I8,2),0))
C9: =IF(A9="","",Settings!$B$16) | E9: =IF(A9="","",IF(D9<>"",D9,C9)) | F9: =IF(A9="","",Settings!$B$14) | H9: =IF(A9="","",IF(G9<>"",G9,F9)) | J9: =IF(A9="","",Settings!$B$15) | L9: =IF(A9="","",IF(K9<>"",K9,J9)) | M9: =IF(A9="","",ROUND(B9*E9,2)) | N9: =IF(A9="","",ROUND(M9*(1-H9/100),2)) | O9: =IF(A9="","",IFERROR(ROUND(N9/B9,2),0)) | P9: =IF(A9="","",ROUND(B9*(1-L9/100),2)) | Q9: =IF(A9="","",IFERROR(ROUND(N9/P9,2),0)) | R9: =IF(A9="","",IFERROR(ROUND(N9/I9,2),0))
C10: =IF(A10="","",Settings!$B$16) | E10: =IF(A10="","",IF(D10<>"",D10,C10)) | F10: =IF(A10="","",Settings!$B$14) | H10: =IF(A10="","",IF(G10<>"",G10,F10)) | J10: =IF(A10="","",Settings!$B$15) | L10: =IF(A10="","",IF(K10<>"",K10,J10)) | M10: =IF(A10="","",ROUND(B10*E10,2)) | N10: =IF(A10="","",ROUND(M10*(1-H10/100),2)) | O10: =IF(A10="","",IFERROR(ROUND(N10/B10,2),0)) | P10: =IF(A10="","",ROUND(B10*(1-L10/100),2)) | Q10: =IF(A10="","",IFERROR(ROUND(N10/P10,2),0)) | R10: =IF(A10="","",IFERROR(ROUND(N10/I10,2),0))
C11: =IF(A11="","",Settings!$B$16) | E11: =IF(A11="","",IF(D11<>"",D11,C11)) | F11: =IF(A11="","",Settings!$B$14) | H11: =IF(A11="","",IF(G11<>"",G11,F11)) | J11: =IF(A11="","",Settings!$B$15) | L11: =IF(A11="","",IF(K11<>"",K11,J11)) | M11: =IF(A11="","",ROUND(B11*E11,2)) | N11: =IF(A11="","",ROUND(M11*(1-H11/100),2)) | O11: =IF(A11="","",IFERROR(ROUND(N11/B11,2),0)) | P11: =IF(A11="","",ROUND(B11*(1-L11/100),2)) | Q11: =IF(A11="","",IFERROR(ROUND(N11/P11,2),0)) | R11: =IF(A11="","",IFERROR(ROUND(N11/I11,2),0))
C12: =IF(A12="","",Settings!$B$16) | E12: =IF(A12="","",IF(D12<>"",D12,C12)) | F12: =IF(A12="","",Settings!$B$14) | H12: =IF(A12="","",IF(G12<>"",G12,F12)) | J12: =IF(A12="","",Settings!$B$15) | L12: =IF(A12="","",IF(K12<>"",K12,J12)) | M12: =IF(A12="","",ROUND(B12*E12,2)) | N12: =IF(A12="","",ROUND(M12*(1-H12/100),2)) | O12: =IF(A12="","",IFERROR(ROUND(N12/B12,2),0)) | P12: =IF(A12="","",ROUND(B12*(1-L12/100),2)) | Q12: =IF(A12="","",IFERROR(ROUND(N12/P12,2),0)) | R12: =IF(A12="","",IFERROR(ROUND(N12/I12,2),0))
C13: =IF(A13="","",Settings!$B$16) | E13: =IF(A13="","",IF(D13<>"",D13,C13)) | F13: =IF(A13="","",Settings!$B$14) | H13: =IF(A13="","",IF(G13<>"",G13,F13)) | J13: =IF(A13="","",Settings!$B$15) | L13: =IF(A13="","",IF(K13<>"",K13,J13)) | M13: =IF(A13="","",ROUND(B13*E13,2)) | N13: =IF(A13="","",ROUND(M13*(1-H13/100),2)) | O13: =IF(A13="","",IFERROR(ROUND(N13/B13,2),0)) | P13: =IF(A13="","",ROUND(B13*(1-L13/100),2)) | Q13: =IF(A13="","",IFERROR(ROUND(N13/P13,2),0)) | R13: =IF(A13="","",IFERROR(ROUND(N13/I13,2),0))
C14: =IF(A14="","",Settings!$B$16) | E14: =IF(A14="","",IF(D14<>"",D14,C14)) | F14: =IF(A14="","",Settings!$B$14) | H14: =IF(A14="","",IF(G14<>"",G14,F14)) | J14: =IF(A14="","",Settings!$B$15) | L14: =IF(A14="","",IF(K14<>"",K14,J14)) | M14: =IF(A14="","",ROUND(B14*E14,2)) | N14: =IF(A14="","",ROUND(M14*(1-H14/100),2)) | O14: =IF(A14="","",IFERROR(ROUND(N14/B14,2),0)) | P14: =IF(A14="","",ROUND(B14*(1-L14/100),2)) | Q14: =IF(A14="","",IFERROR(ROUND(N14/P14,2),0)) | R14: =IF(A14="","",IFERROR(ROUND(N14/I14,2),0))
A15: Total | B15: =SUM(B5:B14) -> 70 | M15: =SUM(M5:M14) -> 8000 | N15: =SUM(N5:N14) -> 6980 | P15: =SUM(P5:P14) -> 60.5
A17: Onboarding quotes
A18: The default rate comes from Settings; type your own rate in column D to override it for that quote.
A19: Client | B19: Onboarding hours | C19: Default rate (Settings) | D19: or type your own rate | E19: Rate used | F19: Setup costs | G19: Margin on costs % | H19: Contract months | I19: Monthly fee | J19: Labour | K19: Costs with margin | L19: Onboarding fee | M19: Amortised per month | N19: Contract value | O19: Fee share of contract %
A20: Harbour Dental Group | B20: 16 | C20: =IF(A20="","",Settings!$B$16) -> 120 | E20: =IF(A20="","",IF(D20<>"",D20,C20)) -> 120 | F20: 600 | G20: 15 | H20: 24 | I20: 2750 | J20: =IF(A20="","",ROUND(B20*E20,2)) -> 1920 | K20: =IF(A20="","",ROUND(F20*(1+G20/100),2)) -> 690 | L20: =IF(A20="","",J20+K20) -> 2610 | M20: =IF(A20="","",IFERROR(ROUND(L20/H20,2),0)) -> 108.75 | N20: =IF(A20="","",ROUND(I20*H20+L20,2)) -> 68610 | O20: =IF(A20="","",IFERROR(ROUND(L20/N20*100,2),0)) -> 3.8
A21: Brightwell Clinic | B21: 24 | C21: =IF(A21="","",Settings!$B$16) -> 120 | E21: =IF(A21="","",IF(D21<>"",D21,C21)) -> 120 | F21: 1200 | G21: 20 | H21: 36 | I21: 3900 | J21: =IF(A21="","",ROUND(B21*E21,2)) -> 2880 | K21: =IF(A21="","",ROUND(F21*(1+G21/100),2)) -> 1440 | L21: =IF(A21="","",J21+K21) -> 4320 | M21: =IF(A21="","",IFERROR(ROUND(L21/H21,2),0)) -> 120 | N21: =IF(A21="","",ROUND(I21*H21+L21,2)) -> 144720 | O21: =IF(A21="","",IFERROR(ROUND(L21/N21*100,2),0)) -> 2.99
A22: Vega Creative | B22: 8 | C22: =IF(A22="","",Settings!$B$16) -> 120 | D22: 100 | E22: =IF(A22="","",IF(D22<>"",D22,C22)) -> 100 | F22: 250 | G22: 10 | H22: 12 | I22: 900 | J22: =IF(A22="","",ROUND(B22*E22,2)) -> 800 | K22: =IF(A22="","",ROUND(F22*(1+G22/100),2)) -> 275 | L22: =IF(A22="","",J22+K22) -> 1075 | M22: =IF(A22="","",IFERROR(ROUND(L22/H22,2),0)) -> 89.58 | N22: =IF(A22="","",ROUND(I22*H22+L22,2)) -> 11875 | O22: =IF(A22="","",IFERROR(ROUND(L22/N22*100,2),0)) -> 9.05
C23: =IF(A23="","",Settings!$B$16) | E23: =IF(A23="","",IF(D23<>"",D23,C23)) | J23: =IF(A23="","",ROUND(B23*E23,2)) | K23: =IF(A23="","",ROUND(F23*(1+G23/100),2)) | L23: =IF(A23="","",J23+K23) | M23: =IF(A23="","",IFERROR(ROUND(L23/H23,2),0)) | N23: =IF(A23="","",ROUND(I23*H23+L23,2)) | O23: =IF(A23="","",IFERROR(ROUND(L23/N23*100,2),0))
C24: =IF(A24="","",Settings!$B$16) | E24: =IF(A24="","",IF(D24<>"",D24,C24)) | J24: =IF(A24="","",ROUND(B24*E24,2)) | K24: =IF(A24="","",ROUND(F24*(1+G24/100),2)) | L24: =IF(A24="","",J24+K24) | M24: =IF(A24="","",IFERROR(ROUND(L24/H24,2),0)) | N24: =IF(A24="","",ROUND(I24*H24+L24,2)) | O24: =IF(A24="","",IFERROR(ROUND(L24/N24*100,2),0))
C25: =IF(A25="","",Settings!$B$16) | E25: =IF(A25="","",IF(D25<>"",D25,C25)) | J25: =IF(A25="","",ROUND(B25*E25,2)) | K25: =IF(A25="","",ROUND(F25*(1+G25/100),2)) | L25: =IF(A25="","",J25+K25) | M25: =IF(A25="","",IFERROR(ROUND(L25/H25,2),0)) | N25: =IF(A25="","",ROUND(I25*H25+L25,2)) | O25: =IF(A25="","",IFERROR(ROUND(L25/N25*100,2),0))
C26: =IF(A26="","",Settings!$B$16) | E26: =IF(A26="","",IF(D26<>"",D26,C26)) | J26: =IF(A26="","",ROUND(B26*E26,2)) | K26: =IF(A26="","",ROUND(F26*(1+G26/100),2)) | L26: =IF(A26="","",J26+K26) | M26: =IF(A26="","",IFERROR(ROUND(L26/H26,2),0)) | N26: =IF(A26="","",ROUND(I26*H26+L26,2)) | O26: =IF(A26="","",IFERROR(ROUND(L26/N26*100,2),0))
C27: =IF(A27="","",Settings!$B$16) | E27: =IF(A27="","",IF(D27<>"",D27,C27)) | J27: =IF(A27="","",ROUND(B27*E27,2)) | K27: =IF(A27="","",ROUND(F27*(1+G27/100),2)) | L27: =IF(A27="","",J27+K27) | M27: =IF(A27="","",IFERROR(ROUND(L27/H27,2),0)) | N27: =IF(A27="","",ROUND(I27*H27+L27,2)) | O27: =IF(A27="","",IFERROR(ROUND(L27/N27*100,2),0))
C28: =IF(A28="","",Settings!$B$16) | E28: =IF(A28="","",IF(D28<>"",D28,C28)) | J28: =IF(A28="","",ROUND(B28*E28,2)) | K28: =IF(A28="","",ROUND(F28*(1+G28/100),2)) | L28: =IF(A28="","",J28+K28) | M28: =IF(A28="","",IFERROR(ROUND(L28/H28,2),0)) | N28: =IF(A28="","",ROUND(I28*H28+L28,2)) | O28: =IF(A28="","",IFERROR(ROUND(L28/N28*100,2),0))
C29: =IF(A29="","",Settings!$B$16) | E29: =IF(A29="","",IF(D29<>"",D29,C29)) | J29: =IF(A29="","",ROUND(B29*E29,2)) | K29: =IF(A29="","",ROUND(F29*(1+G29/100),2)) | L29: =IF(A29="","",J29+K29) | M29: =IF(A29="","",IFERROR(ROUND(L29/H29,2),0)) | N29: =IF(A29="","",ROUND(I29*H29+L29,2)) | O29: =IF(A29="","",IFERROR(ROUND(L29/N29*100,2),0))
A30: Total | B30: =SUM(B20:B29) -> 48 | J30: =SUM(J20:J29) -> 5600 | K30: =SUM(K20:K29) -> 2405 | L30: =SUM(L20:L29) -> 8005 | N30: =SUM(N20:N29) -> 225205

Sheet Summary
A1: Summary
A2: Loaded hourly cost | B2: =Settings!$B$19 -> 56.79 | C2: from Settings
A3: Technicians | B3: =Settings!$B$2 -> 3 | C3: from Settings
A4: Productive hours per month | B4: =Settings!$B$18 -> 390 | C4: from Settings
A5: Tool stack monthly total | B5: ='Tool Stack'!$E$25 -> 2775 | C5: from the Tool Stack
A6: Fixed tool cost (not allocated to contracts) | B6: ='Tool Stack'!$B$28 -> 315 | C6: from the Tool Stack; counted in the Tickets cost
A7: Contracts | B7: =COUNTA(Contracts!$A$5:$A$34) -> 8
A8: Monthly recurring revenue | B8: =Contracts!E35 -> 24280 | C8: sum of monthly fees
A9: Total monthly contract cost | B9: =Contracts!M35 -> 13462.58 | C9: shared tools + dedicated tools + labour
A10: Monthly gross profit | B10: =Contracts!N35 -> 10817.42
A11: Overall margin % | B11: =Contracts!O35 -> 44.55 | C11: gross profit ÷ monthly recurring revenue
A12: Contracts below target margin | B12: =SUMPRODUCT((Contracts!$A$5:$A$34<>"")*(Contracts!$O$5:$O$34<Settings!$B$13)) -> 2 | C12: margin % below your target in Settings
A13: Most profitable contract | B13: =IFERROR(INDEX(Contracts!$A$5:$A$34,MATCH(MAX(Contracts!$N$5:$N$34),Contracts!$N$5:$N$34,0)),"") -> Northgate Logistics | C13: highest monthly gross profit
A14: Least profitable contract | B14: =IFERROR(INDEX(Contracts!$A$5:$A$34,MATCH(MIN(Contracts!$N$5:$N$34),Contracts!$N$5:$N$34,0)),"") -> Ridge Architects | C14: lowest monthly gross profit; re-price first
A15: Latest month cost per ticket | B15: =IFERROR(INDEX(Tickets!$K$5:$K$16,MATCH(MAX(Tickets!$A$5:$A$16),Tickets!$A$5:$A$16,0)),0) -> 83.08 | C15: the most recent month on Tickets
A16: Year-to-date tickets | B16: =Tickets!B17 -> 1850 | C16: Tickets totals
A17: Year-to-date cost per ticket | B17: =Tickets!K17 -> 81.54 | C17: Tickets totals
A18: Block hours revenue | B18: ='Blocks & Onboarding'!N15 -> 6980 | C18: sum of block prices
A19: Onboarding revenue | B19: ='Blocks & Onboarding'!L30 -> 8005 | C19: sum of onboarding fees
