Workbook

Sheet Start Here
A1: Freelance Pricing Kit
A2: by Knackdesk · knackdesk.com
A4: HOW TO USE
A5: 1. Rates: fill the yellow cells once. Your hourly, day and week rates are calculated from them.
A6: 2. Rate Card: adjust the multipliers for rush and weekend work; the card updates from your rates.
A7: 3. Quote Builder: enter the client, date and line items. Discount, VAT, deposit and milestones are calculated.
A8: 4. Retainer: enter an hour block and a commitment discount to price a monthly retainer.
A9: 5. Revenue Plan: enter an annual goal and your averages to see how many proposals to send.
A11: LEGEND
A12: Blue text = a cell you type into. Black text = a formula, leave it alone. Yellow fill = key inputs to set first.
A13: Blue cells that already contain a formula (for example the unit rate on a quote line) are defaults you may overwrite.
A15: NOTES
... A18: Support: hello@knackdesk.com

Sheet Rates
A1: Rates
A2: Target income per year | B2: 60000 | C2: What you want to keep after business expenses.
A3: Business expenses per year | B3: 6000 | C3: Software, insurance, equipment, accountant, training.
A4: Tax rate to gross up for (%) | B4: 0 | C4: Leave 0 if the target income is pre-tax.
A5: Weeks off per year | B5: 6 | C5: Holiday, sick days, public holidays, gaps between projects.
A6: Hours worked per week | B6: 40
A7: Billable share of hours (%) | B7: 60 | C7: Most solo freelancers bill 50-70% of their hours.
A8: Hours in a billable day | B8: 8
A9: VAT rate on quotes (%) | B9: 20 | C9: Set 0 if you do not charge VAT.
A10: Default deposit on quotes (%) | B10: 30
A11: Currency label | B11: USD | C11: Text only; the kit does not convert currencies.
A13: Working weeks | B13: =52-B5 -> 46
A14: Billable hours per year | B14: =ROUND(B13*B6*B7/100,2) -> 1104
A15: Revenue needed | B15: =B3+B2/(1-B4/100) -> 66000
A16: Hourly rate | B16: =IFERROR(ROUND(B15/B14,2),0) -> 59.78 | C16: revenue needed ÷ billable hours; this drives every other sheet
A17: Day rate | B17: =ROUND(B16*B8,2) -> 478.24
A18: Week rate (5 days) | B18: =ROUND(B17*5,2) -> 2391.2

Sheet Rate Card
A1: Rate Card
A2: Multipliers are yours to change; rates come from the Rates sheet.
A4: Service tier | B4: Multiplier | C4: Hourly | D4: Day | E4: Week
A5: Standard | B5: 1 | C5: =ROUND(Rates!$B$16*B5,2) -> 59.78 | D5: =ROUND(Rates!$B$17*B5,2) -> 478.24 | E5: =ROUND(Rates!$B$18*B5,2) -> 2391.2
A6: Rush (48-hour turnaround) | B6: 1.5 | C6: =ROUND(Rates!$B$16*B6,2) -> 89.67 | D6: =ROUND(Rates!$B$17*B6,2) -> 717.36 | E6: =ROUND(Rates!$B$18*B6,2) -> 3586.8
A7: Weekend or evening | B7: 2 | C7: =ROUND(Rates!$B$16*B7,2) -> 119.56 | D7: =ROUND(Rates!$B$17*B7,2) -> 956.48 | E7: =ROUND(Rates!$B$18*B7,2) -> 4782.4
A8: Existing client (loyalty) | B8: 0.9 | C8: =ROUND(Rates!$B$16*B8,2) -> 53.8 | D8: =ROUND(Rates!$B$17*B8,2) -> 430.42 | E8: =ROUND(Rates!$B$18*B8,2) -> 2152.08
A10: Minimum charge (hours) | B10: 1 | C10: =ROUND(Rates!$B$16*B10,2) -> 59.78 | D10: smallest job you will invoice

Sheet Quote Builder
A1: Quote Builder
A2: Client | B2: Example Client Ltd
A3: Quote date | B3: 46296
A4: Valid for (days) | B4: 30
A5: Valid until | B5: =B3+B4 -> 46326
A7: Line item | B7: Qty or hours | C7: Unit | D7: Unit rate | E7: Amount
A8: Discovery workshop | B8: 4 | C8: hours | D8: =Rates!$B$16 -> 59.78 | E8: =IF(OR(A8="",B8=""),"",ROUND(B8*D8,2)) -> 239.12
A9: Design and build | B9: 30 | C9: hours | D9: =Rates!$B$16 -> 59.78 | E9: =IF(OR(A9="",B9=""),"",ROUND(B9*D9,2)) -> 1793.4
D10: =Rates!$B$16 -> 59.78 | E10: =IF(OR(A10="",B10=""),"",ROUND(B10*D10,2))
D11: =Rates!$B$16 -> 59.78 | E11: =IF(OR(A11="",B11=""),"",ROUND(B11*D11,2))
D12: =Rates!$B$16 -> 59.78 | E12: =IF(OR(A12="",B12=""),"",ROUND(B12*D12,2))
D13: =Rates!$B$16 -> 59.78 | E13: =IF(OR(A13="",B13=""),"",ROUND(B13*D13,2))
D14: =Rates!$B$16 -> 59.78 | E14: =IF(OR(A14="",B14=""),"",ROUND(B14*D14,2))
D15: =Rates!$B$16 -> 59.78 | E15: =IF(OR(A15="",B15=""),"",ROUND(B15*D15,2))
D16: =Rates!$B$16 -> 59.78 | E16: =IF(OR(A16="",B16=""),"",ROUND(B16*D16,2))
D17: =Rates!$B$16 -> 59.78 | E17: =IF(OR(A17="",B17=""),"",ROUND(B17*D17,2))
D18: =Rates!$B$16 -> 59.78 | E18: =IF(OR(A18="",B18=""),"",ROUND(B18*D18,2))
D19: =Rates!$B$16 -> 59.78 | E19: =IF(OR(A19="",B19=""),"",ROUND(B19*D19,2))
A21: Subtotal | F21: =SUM(E8:E19) -> 2032.52
A22: Discount (%) | B22: 0 | F22: =-ROUND(F21*B22/100,2) -> 0
A23: VAT (%) | B23: =Rates!$B$9 -> 20 | F23: =ROUND((F21+F22)*B23/100,2) -> 406.5
A24: Total | F24: =F21+F22+F23 -> 2439.02
A26: Deposit (%) | B26: =Rates!$B$10 -> 30 | F26: =ROUND(F24*B26/100,2) -> 731.71
A27: Balance after deposit | F27: =F24-F26 -> 1707.31
A28: Number of milestones for the balance | B28: 2 | F28: =IF(B28>0,ROUND(F27/B28,2),"") -> 853.66
A29: Per milestone (last one absorbs rounding) | F29: =IF(B28>0,F27-F28*(B28-1),"") -> 853.65

Sheet Retainer
A1: Retainer
A2: Hours reserved per month | B2: 20
A3: Hourly rate | B3: =Rates!$B$16 -> 59.78
A4: Commitment discount (%) | B4: 10
A5: Term (months) | B5: 12
A7: List price per month | B7: =ROUND(B2*B3,2) -> 1195.6
A8: Monthly retainer fee | B8: =ROUND(B7*(1-B4/100),2) -> 1076.04
A9: Effective hourly rate | B9: =ROUND(B8/B2,2) -> 53.8 | C9: compare with the Rates sheet hourly rate; do not go below your floor
A10: Total over the term | B10: =B8*B5 -> 12912.48
A11: Discount given over the term | B11: =(B7-B8)*B5 -> 1434.72

Sheet Revenue Plan
A1: Revenue Plan
A2: Annual revenue goal | B2: 120000
A3: Average project value | B3: 5000
A4: Projects a typical client buys per year | B4: 2
A5: Proposal win rate (%) | B5: 25
B7: Per year | C7: Per month
A8: Projects to deliver | B8: =ROUNDUP(B2/B3,0) -> 24 | C8: =ROUND(B8/12,1) -> 2
A9: Clients to win | B9: =ROUNDUP(B8/B4,0) -> 12 | C9: =ROUND(B9/12,1) -> 1
A10: Proposals to send | B10: =ROUNDUP(B9/(B5/100),0) -> 48 | C10: =ROUND(B10/12,1) -> 4
