Workbook

Sheet Start Here
A1: Online Seller Profit Tracker
A2: by Knackdesk · knackdesk.com
A4: HOW TO USE
A5: 1. Settings: enter your platform fee, payment fee and fixed fee per order, and a default packaging cost. These apply to every order.
A6: 2. Products: one row per SKU with its cost and selling price. Orders look these up by SKU.
A7: 3. Orders: one row per order: date, SKU, quantity, shipping charged to the customer and shipping you paid. Price, cost, fees, revenue, profit and margin are calculated. Overwrite the price or cost on a row if that order differed.
A8: 4. Summary: revenue, fees, shipping, profit and margin by month (set the start month), and profit by product.
A9: 5. Ads: monthly ad spend against revenue gives ROAS, and the break-even ROAS from the month's real margin shows whether the spend paid off.
A11: LEGEND
A12: Blue text = a cell you type into. Black text = a formula, leave it alone. Yellow fill = key inputs.
A13: Blue cells that already contain a formula (price and cost on order rows) are defaults you may overwrite.
A15: FORMULAS
... A18: Arithmetic only; not tax or financial advice. Support: hello@knackdesk.com

Sheet Settings
A1: Settings
A2: Platform or marketplace fee (% of revenue) | B2: 10 | C2: Charged on price plus shipping on most marketplaces.
A3: Payment processing fee (%) | B3: 3
A4: Payment processing fixed fee per order | B4: 0.3
A5: Default packaging cost per order | B5: 1 | C5: Box, filler, label, inserts.
A6: Currency label | B6: USD | C6: Text only.

Sheet Products
A1: Products
A4: SKU | B4: Name | C4: Cost per unit | D4: Price per unit | E4: Unit margin | F4: Unit margin %
A5: SKU-001 | B5: Example candle, large | C5: 15 | D5: 40 | E5: =IF(A5="","",D5-C5) -> 25 | F5: =IF(OR(A5="",D5=0),"",ROUND((D5-C5)/D5*100,2)) -> 62.5
A6: SKU-002 | B6: Example candle, small | C6: 8 | D6: 22 | E6: =IF(A6="","",D6-C6) -> 14 | F6: =IF(OR(A6="",D6=0),"",ROUND((D6-C6)/D6*100,2)) -> 63.64
E7: =IF(A7="","",D7-C7) | F7: =IF(OR(A7="",D7=0),"",ROUND((D7-C7)/D7*100,2))
E8: =IF(A8="","",D8-C8) | F8: =IF(OR(A8="",D8=0),"",ROUND((D8-C8)/D8*100,2))
E9: =IF(A9="","",D9-C9) | F9: =IF(OR(A9="",D9=0),"",ROUND((D9-C9)/D9*100,2))
E10: =IF(A10="","",D10-C10) | F10: =IF(OR(A10="",D10=0),"",ROUND((D10-C10)/D10*100,2))
E11: =IF(A11="","",D11-C11) | F11: =IF(OR(A11="",D11=0),"",ROUND((D11-C11)/D11*100,2))
E12: =IF(A12="","",D12-C12) | F12: =IF(OR(A12="",D12=0),"",ROUND((D12-C12)/D12*100,2))
E13: =IF(A13="","",D13-C13) | F13: =IF(OR(A13="",D13=0),"",ROUND((D13-C13)/D13*100,2))
E14: =IF(A14="","",D14-C14) | F14: =IF(OR(A14="",D14=0),"",ROUND((D14-C14)/D14*100,2))
E15: =IF(A15="","",D15-C15) | F15: =IF(OR(A15="",D15=0),"",ROUND((D15-C15)/D15*100,2))
E16: =IF(A16="","",D16-C16) | F16: =IF(OR(A16="",D16=0),"",ROUND((D16-C16)/D16*100,2))
E17: =IF(A17="","",D17-C17) | F17: =IF(OR(A17="",D17=0),"",ROUND((D17-C17)/D17*100,2))
E18: =IF(A18="","",D18-C18) | F18: =IF(OR(A18="",D18=0),"",ROUND((D18-C18)/D18*100,2))
... E54: =IF(A54="","",D54-C54) | F54: =IF(OR(A54="",D54=0),"",ROUND((D54-C54)/D54*100,2))

Sheet Orders
A1: Orders
A2: Total profit | B2: =SUM(J5:J504) -> 33.33 | C2: Orders | D2: =COUNTA(A5:A504) -> 2
A4: Date | B4: SKU | C4: Quantity | D4: Price per unit | E4: Cost per unit | F4: Shipping charged | G4: Shipping paid | H4: Packaging | I4: Fees | J4: Profit | K4: Revenue | L4: Margin % | M4: Month
A5: 46287 | B5: SKU-001 | C5: 1 | D5: =IF(B5="","",IFERROR(INDEX(Products!$D$5:$D$54,MATCH(B5,Products!$A$5:$A$54,0)),0)) -> 40 | E5: =IF(B5="","",IFERROR(INDEX(Products!$C$5:$C$54,MATCH(B5,Products!$A$5:$A$54,0)),0)) -> 15 | F5: 5 | G5: 6 | H5: =IF(A5="","",Settings!$B$5) -> 1 | I5: =IF(A5="","",ROUND(K5*(Settings!$B$2+Settings!$B$3)/100+Settings!$B$4,2)) -> 6.15 | J5: =IF(A5="","",ROUND(K5-E5*C5-H5-G5-I5,2)) -> 16.85 | K5: =IF(A5="","",D5*C5+F5) -> 45 | L5: =IF(OR(A5="",K5=0),"",ROUND(J5/K5*100,2)) -> 37.44 | M5: =IF(A5="","",TEXT(A5,"yyyy-mm")) -> 2026-09
A6: 46292 | B6: SKU-002 | C6: 2 | D6: =IF(B6="","",IFERROR(INDEX(Products!$D$5:$D$54,MATCH(B6,Products!$A$5:$A$54,0)),0)) -> 22 | E6: =IF(B6="","",IFERROR(INDEX(Products!$C$5:$C$54,MATCH(B6,Products!$A$5:$A$54,0)),0)) -> 8 | F6: 0 | G6: 4.5 | H6: =IF(A6="","",Settings!$B$5) -> 1 | I6: =IF(A6="","",ROUND(K6*(Settings!$B$2+Settings!$B$3)/100+Settings!$B$4,2)) -> 6.02 | J6: =IF(A6="","",ROUND(K6-E6*C6-H6-G6-I6,2)) -> 16.48 | K6: =IF(A6="","",D6*C6+F6) -> 44 | L6: =IF(OR(A6="",K6=0),"",ROUND(J6/K6*100,2)) -> 37.45 | M6: =IF(A6="","",TEXT(A6,"yyyy-mm")) -> 2026-09
D7: =IF(B7="","",IFERROR(INDEX(Products!$D$5:$D$54,MATCH(B7,Products!$A$5:$A$54,0)),0)) | E7: =IF(B7="","",IFERROR(INDEX(Products!$C$5:$C$54,MATCH(B7,Products!$A$5:$A$54,0)),0)) | H7: =IF(A7="","",Settings!$B$5) | I7: =IF(A7="","",ROUND(K7*(Settings!$B$2+Settings!$B$3)/100+Settings!$B$4,2)) | J7: =IF(A7="","",ROUND(K7-E7*C7-H7-G7-I7,2)) | K7: =IF(A7="","",D7*C7+F7) | L7: =IF(OR(A7="",K7=0),"",ROUND(J7/K7*100,2)) | M7: =IF(A7="","",TEXT(A7,"yyyy-mm"))
D8: =IF(B8="","",IFERROR(INDEX(Products!$D$5:$D$54,MATCH(B8,Products!$A$5:$A$54,0)),0)) | E8: =IF(B8="","",IFERROR(INDEX(Products!$C$5:$C$54,MATCH(B8,Products!$A$5:$A$54,0)),0)) | H8: =IF(A8="","",Settings!$B$5) | I8: =IF(A8="","",ROUND(K8*(Settings!$B$2+Settings!$B$3)/100+Settings!$B$4,2)) | J8: =IF(A8="","",ROUND(K8-E8*C8-H8-G8-I8,2)) | K8: =IF(A8="","",D8*C8+F8) | L8: =IF(OR(A8="",K8=0),"",ROUND(J8/K8*100,2)) | M8: =IF(A8="","",TEXT(A8,"yyyy-mm"))
D9: =IF(B9="","",IFERROR(INDEX(Products!$D$5:$D$54,MATCH(B9,Products!$A$5:$A$54,0)),0)) | E9: =IF(B9="","",IFERROR(INDEX(Products!$C$5:$C$54,MATCH(B9,Products!$A$5:$A$54,0)),0)) | H9: =IF(A9="","",Settings!$B$5) | I9: =IF(A9="","",ROUND(K9*(Settings!$B$2+Settings!$B$3)/100+Settings!$B$4,2)) | J9: =IF(A9="","",ROUND(K9-E9*C9-H9-G9-I9,2)) | K9: =IF(A9="","",D9*C9+F9) | L9: =IF(OR(A9="",K9=0),"",ROUND(J9/K9*100,2)) | M9: =IF(A9="","",TEXT(A9,"yyyy-mm"))
D10: =IF(B10="","",IFERROR(INDEX(Products!$D$5:$D$54,MATCH(B10,Products!$A$5:$A$54,0)),0)) | E10: =IF(B10="","",IFERROR(INDEX(Products!$C$5:$C$54,MATCH(B10,Products!$A$5:$A$54,0)),0)) | H10: =IF(A10="","",Settings!$B$5) | I10: =IF(A10="","",ROUND(K10*(Settings!$B$2+Settings!$B$3)/100+Settings!$B$4,2)) | J10: =IF(A10="","",ROUND(K10-E10*C10-H10-G10-I10,2)) | K10: =IF(A10="","",D10*C10+F10) | L10: =IF(OR(A10="",K10=0),"",ROUND(J10/K10*100,2)) | M10: =IF(A10="","",TEXT(A10,"yyyy-mm"))
D11: =IF(B11="","",IFERROR(INDEX(Products!$D$5:$D$54,MATCH(B11,Products!$A$5:$A$54,0)),0)) | E11: =IF(B11="","",IFERROR(INDEX(Products!$C$5:$C$54,MATCH(B11,Products!$A$5:$A$54,0)),0)) | H11: =IF(A11="","",Settings!$B$5) | I11: =IF(A11="","",ROUND(K11*(Settings!$B$2+Settings!$B$3)/100+Settings!$B$4,2)) | J11: =IF(A11="","",ROUND(K11-E11*C11-H11-G11-I11,2)) | K11: =IF(A11="","",D11*C11+F11) | L11: =IF(OR(A11="",K11=0),"",ROUND(J11/K11*100,2)) | M11: =IF(A11="","",TEXT(A11,"yyyy-mm"))
D12: =IF(B12="","",IFERROR(INDEX(Products!$D$5:$D$54,MATCH(B12,Products!$A$5:$A$54,0)),0)) | E12: =IF(B12="","",IFERROR(INDEX(Products!$C$5:$C$54,MATCH(B12,Products!$A$5:$A$54,0)),0)) | H12: =IF(A12="","",Settings!$B$5) | I12: =IF(A12="","",ROUND(K12*(Settings!$B$2+Settings!$B$3)/100+Settings!$B$4,2)) | J12: =IF(A12="","",ROUND(K12-E12*C12-H12-G12-I12,2)) | K12: =IF(A12="","",D12*C12+F12) | L12: =IF(OR(A12="",K12=0),"",ROUND(J12/K12*100,2)) | M12: =IF(A12="","",TEXT(A12,"yyyy-mm"))
D13: =IF(B13="","",IFERROR(INDEX(Products!$D$5:$D$54,MATCH(B13,Products!$A$5:$A$54,0)),0)) | E13: =IF(B13="","",IFERROR(INDEX(Products!$C$5:$C$54,MATCH(B13,Products!$A$5:$A$54,0)),0)) | H13: =IF(A13="","",Settings!$B$5) | I13: =IF(A13="","",ROUND(K13*(Settings!$B$2+Settings!$B$3)/100+Settings!$B$4,2)) | J13: =IF(A13="","",ROUND(K13-E13*C13-H13-G13-I13,2)) | K13: =IF(A13="","",D13*C13+F13) | L13: =IF(OR(A13="",K13=0),"",ROUND(J13/K13*100,2)) | M13: =IF(A13="","",TEXT(A13,"yyyy-mm"))
D14: =IF(B14="","",IFERROR(INDEX(Products!$D$5:$D$54,MATCH(B14,Products!$A$5:$A$54,0)),0)) | E14: =IF(B14="","",IFERROR(INDEX(Products!$C$5:$C$54,MATCH(B14,Products!$A$5:$A$54,0)),0)) | H14: =IF(A14="","",Settings!$B$5) | I14: =IF(A14="","",ROUND(K14*(Settings!$B$2+Settings!$B$3)/100+Settings!$B$4,2)) | J14: =IF(A14="","",ROUND(K14-E14*C14-H14-G14-I14,2)) | K14: =IF(A14="","",D14*C14+F14) | L14: =IF(OR(A14="",K14=0),"",ROUND(J14/K14*100,2)) | M14: =IF(A14="","",TEXT(A14,"yyyy-mm"))
D15: =IF(B15="","",IFERROR(INDEX(Products!$D$5:$D$54,MATCH(B15,Products!$A$5:$A$54,0)),0)) | E15: =IF(B15="","",IFERROR(INDEX(Products!$C$5:$C$54,MATCH(B15,Products!$A$5:$A$54,0)),0)) | H15: =IF(A15="","",Settings!$B$5) | I15: =IF(A15="","",ROUND(K15*(Settings!$B$2+Settings!$B$3)/100+Settings!$B$4,2)) | J15: =IF(A15="","",ROUND(K15-E15*C15-H15-G15-I15,2)) | K15: =IF(A15="","",D15*C15+F15) | L15: =IF(OR(A15="",K15=0),"",ROUND(J15/K15*100,2)) | M15: =IF(A15="","",TEXT(A15,"yyyy-mm"))
D16: =IF(B16="","",IFERROR(INDEX(Products!$D$5:$D$54,MATCH(B16,Products!$A$5:$A$54,0)),0)) | E16: =IF(B16="","",IFERROR(INDEX(Products!$C$5:$C$54,MATCH(B16,Products!$A$5:$A$54,0)),0)) | H16: =IF(A16="","",Settings!$B$5) | I16: =IF(A16="","",ROUND(K16*(Settings!$B$2+Settings!$B$3)/100+Settings!$B$4,2)) | J16: =IF(A16="","",ROUND(K16-E16*C16-H16-G16-I16,2)) | K16: =IF(A16="","",D16*C16+F16) | L16: =IF(OR(A16="",K16=0),"",ROUND(J16/K16*100,2)) | M16: =IF(A16="","",TEXT(A16,"yyyy-mm"))
D17: =IF(B17="","",IFERROR(INDEX(Products!$D$5:$D$54,MATCH(B17,Products!$A$5:$A$54,0)),0)) | E17: =IF(B17="","",IFERROR(INDEX(Products!$C$5:$C$54,MATCH(B17,Products!$A$5:$A$54,0)),0)) | H17: =IF(A17="","",Settings!$B$5) | I17: =IF(A17="","",ROUND(K17*(Settings!$B$2+Settings!$B$3)/100+Settings!$B$4,2)) | J17: =IF(A17="","",ROUND(K17-E17*C17-H17-G17-I17,2)) | K17: =IF(A17="","",D17*C17+F17) | L17: =IF(OR(A17="",K17=0),"",ROUND(J17/K17*100,2)) | M17: =IF(A17="","",TEXT(A17,"yyyy-mm"))
D18: =IF(B18="","",IFERROR(INDEX(Products!$D$5:$D$54,MATCH(B18,Products!$A$5:$A$54,0)),0)) | E18: =IF(B18="","",IFERROR(INDEX(Products!$C$5:$C$54,MATCH(B18,Products!$A$5:$A$54,0)),0)) | H18: =IF(A18="","",Settings!$B$5) | I18: =IF(A18="","",ROUND(K18*(Settings!$B$2+Settings!$B$3)/100+Settings!$B$4,2)) | J18: =IF(A18="","",ROUND(K18-E18*C18-H18-G18-I18,2)) | K18: =IF(A18="","",D18*C18+F18) | L18: =IF(OR(A18="",K18=0),"",ROUND(J18/K18*100,2)) | M18: =IF(A18="","",TEXT(A18,"yyyy-mm"))
... D504: =IF(B504="","",IFERROR(INDEX(Products!$D$5:$D$54,MATCH(B504,Products!$A$5:$A$54,0)),0)) | E504: =IF(B504="","",IFERROR(INDEX(Products!$C$5:$C$54,MATCH(B504,Products!$A$5:$A$54,0)),0)) | H504: =IF(A504="","",Settings!$B$5) | I504: =IF(A504="","",ROUND(K504*(Settings!$B$2+Settings!$B$3)/100+Settings!$B$4,2)) | J504: =IF(A504="","",ROUND(K504-E504*C504-H504-G504-I504,2)) | K504: =IF(A504="","",D504*C504+F504) | L504: =IF(OR(A504="",K504=0),"",ROUND(J504/K504*100,2)) | M504: =IF(A504="","",TEXT(A504,"yyyy-mm"))

Sheet Summary
A1: Summary
A2: Start month | B2: 46266
A4: Month | B4: Orders | C4: Revenue | D4: Fees | E4: Shipping paid | F4: Profit | G4: Margin %
A5: =TEXT(EDATE($B$2,0),"yyyy-mm") -> 2026-09 | B5: =COUNTIF(Orders!$M$5:$M$504,A5) -> 2 | C5: =SUMIF(Orders!$M$5:$M$504,A5,Orders!$K$5:$K$504) -> 89 | D5: =SUMIF(Orders!$M$5:$M$504,A5,Orders!$I$5:$I$504) -> 12.17 | E5: =SUMIF(Orders!$M$5:$M$504,A5,Orders!$G$5:$G$504) -> 10.5 | F5: =SUMIF(Orders!$M$5:$M$504,A5,Orders!$J$5:$J$504) -> 33.33 | G5: =IF(C5=0,"",ROUND(F5/C5*100,2)) -> 37.45
A6: =TEXT(EDATE($B$2,1),"yyyy-mm") -> 2026-10 | B6: =COUNTIF(Orders!$M$5:$M$504,A6) -> 0 | C6: =SUMIF(Orders!$M$5:$M$504,A6,Orders!$K$5:$K$504) -> 0 | D6: =SUMIF(Orders!$M$5:$M$504,A6,Orders!$I$5:$I$504) -> 0 | E6: =SUMIF(Orders!$M$5:$M$504,A6,Orders!$G$5:$G$504) -> 0 | F6: =SUMIF(Orders!$M$5:$M$504,A6,Orders!$J$5:$J$504) -> 0 | G6: =IF(C6=0,"",ROUND(F6/C6*100,2))
A7: =TEXT(EDATE($B$2,2),"yyyy-mm") -> 2026-11 | B7: =COUNTIF(Orders!$M$5:$M$504,A7) -> 0 | C7: =SUMIF(Orders!$M$5:$M$504,A7,Orders!$K$5:$K$504) -> 0 | D7: =SUMIF(Orders!$M$5:$M$504,A7,Orders!$I$5:$I$504) -> 0 | E7: =SUMIF(Orders!$M$5:$M$504,A7,Orders!$G$5:$G$504) -> 0 | F7: =SUMIF(Orders!$M$5:$M$504,A7,Orders!$J$5:$J$504) -> 0 | G7: =IF(C7=0,"",ROUND(F7/C7*100,2))
A8: =TEXT(EDATE($B$2,3),"yyyy-mm") -> 2026-12 | B8: =COUNTIF(Orders!$M$5:$M$504,A8) -> 0 | C8: =SUMIF(Orders!$M$5:$M$504,A8,Orders!$K$5:$K$504) -> 0 | D8: =SUMIF(Orders!$M$5:$M$504,A8,Orders!$I$5:$I$504) -> 0 | E8: =SUMIF(Orders!$M$5:$M$504,A8,Orders!$G$5:$G$504) -> 0 | F8: =SUMIF(Orders!$M$5:$M$504,A8,Orders!$J$5:$J$504) -> 0 | G8: =IF(C8=0,"",ROUND(F8/C8*100,2))
A9: =TEXT(EDATE($B$2,4),"yyyy-mm") -> 2027-01 | B9: =COUNTIF(Orders!$M$5:$M$504,A9) -> 0 | C9: =SUMIF(Orders!$M$5:$M$504,A9,Orders!$K$5:$K$504) -> 0 | D9: =SUMIF(Orders!$M$5:$M$504,A9,Orders!$I$5:$I$504) -> 0 | E9: =SUMIF(Orders!$M$5:$M$504,A9,Orders!$G$5:$G$504) -> 0 | F9: =SUMIF(Orders!$M$5:$M$504,A9,Orders!$J$5:$J$504) -> 0 | G9: =IF(C9=0,"",ROUND(F9/C9*100,2))
A10: =TEXT(EDATE($B$2,5),"yyyy-mm") -> 2027-02 | B10: =COUNTIF(Orders!$M$5:$M$504,A10) -> 0 | C10: =SUMIF(Orders!$M$5:$M$504,A10,Orders!$K$5:$K$504) -> 0 | D10: =SUMIF(Orders!$M$5:$M$504,A10,Orders!$I$5:$I$504) -> 0 | E10: =SUMIF(Orders!$M$5:$M$504,A10,Orders!$G$5:$G$504) -> 0 | F10: =SUMIF(Orders!$M$5:$M$504,A10,Orders!$J$5:$J$504) -> 0 | G10: =IF(C10=0,"",ROUND(F10/C10*100,2))
A11: =TEXT(EDATE($B$2,6),"yyyy-mm") -> 2027-03 | B11: =COUNTIF(Orders!$M$5:$M$504,A11) -> 0 | C11: =SUMIF(Orders!$M$5:$M$504,A11,Orders!$K$5:$K$504) -> 0 | D11: =SUMIF(Orders!$M$5:$M$504,A11,Orders!$I$5:$I$504) -> 0 | E11: =SUMIF(Orders!$M$5:$M$504,A11,Orders!$G$5:$G$504) -> 0 | F11: =SUMIF(Orders!$M$5:$M$504,A11,Orders!$J$5:$J$504) -> 0 | G11: =IF(C11=0,"",ROUND(F11/C11*100,2))
A12: =TEXT(EDATE($B$2,7),"yyyy-mm") -> 2027-04 | B12: =COUNTIF(Orders!$M$5:$M$504,A12) -> 0 | C12: =SUMIF(Orders!$M$5:$M$504,A12,Orders!$K$5:$K$504) -> 0 | D12: =SUMIF(Orders!$M$5:$M$504,A12,Orders!$I$5:$I$504) -> 0 | E12: =SUMIF(Orders!$M$5:$M$504,A12,Orders!$G$5:$G$504) -> 0 | F12: =SUMIF(Orders!$M$5:$M$504,A12,Orders!$J$5:$J$504) -> 0 | G12: =IF(C12=0,"",ROUND(F12/C12*100,2))
A13: =TEXT(EDATE($B$2,8),"yyyy-mm") -> 2027-05 | B13: =COUNTIF(Orders!$M$5:$M$504,A13) -> 0 | C13: =SUMIF(Orders!$M$5:$M$504,A13,Orders!$K$5:$K$504) -> 0 | D13: =SUMIF(Orders!$M$5:$M$504,A13,Orders!$I$5:$I$504) -> 0 | E13: =SUMIF(Orders!$M$5:$M$504,A13,Orders!$G$5:$G$504) -> 0 | F13: =SUMIF(Orders!$M$5:$M$504,A13,Orders!$J$5:$J$504) -> 0 | G13: =IF(C13=0,"",ROUND(F13/C13*100,2))
A14: =TEXT(EDATE($B$2,9),"yyyy-mm") -> 2027-06 | B14: =COUNTIF(Orders!$M$5:$M$504,A14) -> 0 | C14: =SUMIF(Orders!$M$5:$M$504,A14,Orders!$K$5:$K$504) -> 0 | D14: =SUMIF(Orders!$M$5:$M$504,A14,Orders!$I$5:$I$504) -> 0 | E14: =SUMIF(Orders!$M$5:$M$504,A14,Orders!$G$5:$G$504) -> 0 | F14: =SUMIF(Orders!$M$5:$M$504,A14,Orders!$J$5:$J$504) -> 0 | G14: =IF(C14=0,"",ROUND(F14/C14*100,2))
A15: =TEXT(EDATE($B$2,10),"yyyy-mm") -> 2027-07 | B15: =COUNTIF(Orders!$M$5:$M$504,A15) -> 0 | C15: =SUMIF(Orders!$M$5:$M$504,A15,Orders!$K$5:$K$504) -> 0 | D15: =SUMIF(Orders!$M$5:$M$504,A15,Orders!$I$5:$I$504) -> 0 | E15: =SUMIF(Orders!$M$5:$M$504,A15,Orders!$G$5:$G$504) -> 0 | F15: =SUMIF(Orders!$M$5:$M$504,A15,Orders!$J$5:$J$504) -> 0 | G15: =IF(C15=0,"",ROUND(F15/C15*100,2))
A16: =TEXT(EDATE($B$2,11),"yyyy-mm") -> 2027-08 | B16: =COUNTIF(Orders!$M$5:$M$504,A16) -> 0 | C16: =SUMIF(Orders!$M$5:$M$504,A16,Orders!$K$5:$K$504) -> 0 | D16: =SUMIF(Orders!$M$5:$M$504,A16,Orders!$I$5:$I$504) -> 0 | E16: =SUMIF(Orders!$M$5:$M$504,A16,Orders!$G$5:$G$504) -> 0 | F16: =SUMIF(Orders!$M$5:$M$504,A16,Orders!$J$5:$J$504) -> 0 | G16: =IF(C16=0,"",ROUND(F16/C16*100,2))
A17: 12 months | B17: =SUM(B5:B16) -> 2 | C17: =SUM(C5:C16) -> 89 | D17: =SUM(D5:D16) -> 12.17 | E17: =SUM(E5:E16) -> 10.5 | F17: =SUM(F5:F16) -> 33.33 | G17: =IF(C17=0,"",ROUND(F17/C17*100,2)) -> 37.45
A20: SKU | B20: Name | C20: Units sold | D20: Revenue | E20: Profit | F20: Margin %
A21: =IF(Products!A5="","",Products!A5) -> SKU-001 | B21: =IF(Products!A5="","",Products!B5) -> Example candle, large | C21: =IF(A21="","",SUMIF(Orders!$B$5:$B$504,A21,Orders!$C$5:$C$504)) -> 1 | D21: =IF(A21="","",SUMIF(Orders!$B$5:$B$504,A21,Orders!$K$5:$K$504)) -> 45 | E21: =IF(A21="","",SUMIF(Orders!$B$5:$B$504,A21,Orders!$J$5:$J$504)) -> 16.85 | F21: =IF(OR(A21="",D21=0),"",ROUND(E21/D21*100,2)) -> 37.44
A22: =IF(Products!A6="","",Products!A6) -> SKU-002 | B22: =IF(Products!A6="","",Products!B6) -> Example candle, small | C22: =IF(A22="","",SUMIF(Orders!$B$5:$B$504,A22,Orders!$C$5:$C$504)) -> 2 | D22: =IF(A22="","",SUMIF(Orders!$B$5:$B$504,A22,Orders!$K$5:$K$504)) -> 44 | E22: =IF(A22="","",SUMIF(Orders!$B$5:$B$504,A22,Orders!$J$5:$J$504)) -> 16.48 | F22: =IF(OR(A22="",D22=0),"",ROUND(E22/D22*100,2)) -> 37.45
A23: =IF(Products!A7="","",Products!A7) | B23: =IF(Products!A7="","",Products!B7) | C23: =IF(A23="","",SUMIF(Orders!$B$5:$B$504,A23,Orders!$C$5:$C$504)) | D23: =IF(A23="","",SUMIF(Orders!$B$5:$B$504,A23,Orders!$K$5:$K$504)) | E23: =IF(A23="","",SUMIF(Orders!$B$5:$B$504,A23,Orders!$J$5:$J$504)) | F23: =IF(OR(A23="",D23=0),"",ROUND(E23/D23*100,2))
A24: =IF(Products!A8="","",Products!A8) | B24: =IF(Products!A8="","",Products!B8) | C24: =IF(A24="","",SUMIF(Orders!$B$5:$B$504,A24,Orders!$C$5:$C$504)) | D24: =IF(A24="","",SUMIF(Orders!$B$5:$B$504,A24,Orders!$K$5:$K$504)) | E24: =IF(A24="","",SUMIF(Orders!$B$5:$B$504,A24,Orders!$J$5:$J$504)) | F24: =IF(OR(A24="",D24=0),"",ROUND(E24/D24*100,2))
A25: =IF(Products!A9="","",Products!A9) | B25: =IF(Products!A9="","",Products!B9) | C25: =IF(A25="","",SUMIF(Orders!$B$5:$B$504,A25,Orders!$C$5:$C$504)) | D25: =IF(A25="","",SUMIF(Orders!$B$5:$B$504,A25,Orders!$K$5:$K$504)) | E25: =IF(A25="","",SUMIF(Orders!$B$5:$B$504,A25,Orders!$J$5:$J$504)) | F25: =IF(OR(A25="",D25=0),"",ROUND(E25/D25*100,2))
A26: =IF(Products!A10="","",Products!A10) | B26: =IF(Products!A10="","",Products!B10) | C26: =IF(A26="","",SUMIF(Orders!$B$5:$B$504,A26,Orders!$C$5:$C$504)) | D26: =IF(A26="","",SUMIF(Orders!$B$5:$B$504,A26,Orders!$K$5:$K$504)) | E26: =IF(A26="","",SUMIF(Orders!$B$5:$B$504,A26,Orders!$J$5:$J$504)) | F26: =IF(OR(A26="",D26=0),"",ROUND(E26/D26*100,2))
A27: =IF(Products!A11="","",Products!A11) | B27: =IF(Products!A11="","",Products!B11) | C27: =IF(A27="","",SUMIF(Orders!$B$5:$B$504,A27,Orders!$C$5:$C$504)) | D27: =IF(A27="","",SUMIF(Orders!$B$5:$B$504,A27,Orders!$K$5:$K$504)) | E27: =IF(A27="","",SUMIF(Orders!$B$5:$B$504,A27,Orders!$J$5:$J$504)) | F27: =IF(OR(A27="",D27=0),"",ROUND(E27/D27*100,2))
A28: =IF(Products!A12="","",Products!A12) | B28: =IF(Products!A12="","",Products!B12) | C28: =IF(A28="","",SUMIF(Orders!$B$5:$B$504,A28,Orders!$C$5:$C$504)) | D28: =IF(A28="","",SUMIF(Orders!$B$5:$B$504,A28,Orders!$K$5:$K$504)) | E28: =IF(A28="","",SUMIF(Orders!$B$5:$B$504,A28,Orders!$J$5:$J$504)) | F28: =IF(OR(A28="",D28=0),"",ROUND(E28/D28*100,2))
A29: =IF(Products!A13="","",Products!A13) | B29: =IF(Products!A13="","",Products!B13) | C29: =IF(A29="","",SUMIF(Orders!$B$5:$B$504,A29,Orders!$C$5:$C$504)) | D29: =IF(A29="","",SUMIF(Orders!$B$5:$B$504,A29,Orders!$K$5:$K$504)) | E29: =IF(A29="","",SUMIF(Orders!$B$5:$B$504,A29,Orders!$J$5:$J$504)) | F29: =IF(OR(A29="",D29=0),"",ROUND(E29/D29*100,2))
A30: =IF(Products!A14="","",Products!A14) | B30: =IF(Products!A14="","",Products!B14) | C30: =IF(A30="","",SUMIF(Orders!$B$5:$B$504,A30,Orders!$C$5:$C$504)) | D30: =IF(A30="","",SUMIF(Orders!$B$5:$B$504,A30,Orders!$K$5:$K$504)) | E30: =IF(A30="","",SUMIF(Orders!$B$5:$B$504,A30,Orders!$J$5:$J$504)) | F30: =IF(OR(A30="",D30=0),"",ROUND(E30/D30*100,2))
A31: =IF(Products!A15="","",Products!A15) | B31: =IF(Products!A15="","",Products!B15) | C31: =IF(A31="","",SUMIF(Orders!$B$5:$B$504,A31,Orders!$C$5:$C$504)) | D31: =IF(A31="","",SUMIF(Orders!$B$5:$B$504,A31,Orders!$K$5:$K$504)) | E31: =IF(A31="","",SUMIF(Orders!$B$5:$B$504,A31,Orders!$J$5:$J$504)) | F31: =IF(OR(A31="",D31=0),"",ROUND(E31/D31*100,2))
A32: =IF(Products!A16="","",Products!A16) | B32: =IF(Products!A16="","",Products!B16) | C32: =IF(A32="","",SUMIF(Orders!$B$5:$B$504,A32,Orders!$C$5:$C$504)) | D32: =IF(A32="","",SUMIF(Orders!$B$5:$B$504,A32,Orders!$K$5:$K$504)) | E32: =IF(A32="","",SUMIF(Orders!$B$5:$B$504,A32,Orders!$J$5:$J$504)) | F32: =IF(OR(A32="",D32=0),"",ROUND(E32/D32*100,2))
... A40: =IF(Products!A24="","",Products!A24) | B40: =IF(Products!A24="","",Products!B24) | C40: =IF(A40="","",SUMIF(Orders!$B$5:$B$504,A40,Orders!$C$5:$C$504)) | D40: =IF(A40="","",SUMIF(Orders!$B$5:$B$504,A40,Orders!$K$5:$K$504)) | E40: =IF(A40="","",SUMIF(Orders!$B$5:$B$504,A40,Orders!$J$5:$J$504)) | F40: =IF(OR(A40="",D40=0),"",ROUND(E40/D40*100,2))
A42: Profit by product covers the first 20 SKUs on the Products sheet.

Sheet Ads
A1: Ads
A2: Enter monthly ad spend. Revenue and profit come from the Summary sheet; break-even ROAS is revenue ÷ profit before ads.
A4: Month | B4: Ad spend | C4: Revenue | D4: Profit before ads | E4: ROAS | F4: Break-even ROAS | G4: Profit after ads | H4: Verdict
A5: =Summary!A5 -> 2026-09 | B5: 150 | C5: =Summary!C5 -> 89 | D5: =Summary!F5 -> 33.33 | E5: =IF(B5=0,"",ROUND(C5/B5,2)) -> 0.59 | F5: =IF(OR(C5=0,D5<=0),"",ROUND(C5/D5,2)) -> 2.67 | G5: =D5-B5 -> -116.67 | H5: =IF(B5=0,"",IF(G5>=0,"Profitable","Loss after ads")) -> Loss after ads
A6: =Summary!A6 -> 2026-10 | B6: 0 | C6: =Summary!C6 -> 0 | D6: =Summary!F6 -> 0 | E6: =IF(B6=0,"",ROUND(C6/B6,2)) | F6: =IF(OR(C6=0,D6<=0),"",ROUND(C6/D6,2)) | G6: =D6-B6 -> 0 | H6: =IF(B6=0,"",IF(G6>=0,"Profitable","Loss after ads"))
A7: =Summary!A7 -> 2026-11 | B7: 0 | C7: =Summary!C7 -> 0 | D7: =Summary!F7 -> 0 | E7: =IF(B7=0,"",ROUND(C7/B7,2)) | F7: =IF(OR(C7=0,D7<=0),"",ROUND(C7/D7,2)) | G7: =D7-B7 -> 0 | H7: =IF(B7=0,"",IF(G7>=0,"Profitable","Loss after ads"))
A8: =Summary!A8 -> 2026-12 | B8: 0 | C8: =Summary!C8 -> 0 | D8: =Summary!F8 -> 0 | E8: =IF(B8=0,"",ROUND(C8/B8,2)) | F8: =IF(OR(C8=0,D8<=0),"",ROUND(C8/D8,2)) | G8: =D8-B8 -> 0 | H8: =IF(B8=0,"",IF(G8>=0,"Profitable","Loss after ads"))
A9: =Summary!A9 -> 2027-01 | B9: 0 | C9: =Summary!C9 -> 0 | D9: =Summary!F9 -> 0 | E9: =IF(B9=0,"",ROUND(C9/B9,2)) | F9: =IF(OR(C9=0,D9<=0),"",ROUND(C9/D9,2)) | G9: =D9-B9 -> 0 | H9: =IF(B9=0,"",IF(G9>=0,"Profitable","Loss after ads"))
A10: =Summary!A10 -> 2027-02 | B10: 0 | C10: =Summary!C10 -> 0 | D10: =Summary!F10 -> 0 | E10: =IF(B10=0,"",ROUND(C10/B10,2)) | F10: =IF(OR(C10=0,D10<=0),"",ROUND(C10/D10,2)) | G10: =D10-B10 -> 0 | H10: =IF(B10=0,"",IF(G10>=0,"Profitable","Loss after ads"))
A11: =Summary!A11 -> 2027-03 | B11: 0 | C11: =Summary!C11 -> 0 | D11: =Summary!F11 -> 0 | E11: =IF(B11=0,"",ROUND(C11/B11,2)) | F11: =IF(OR(C11=0,D11<=0),"",ROUND(C11/D11,2)) | G11: =D11-B11 -> 0 | H11: =IF(B11=0,"",IF(G11>=0,"Profitable","Loss after ads"))
A12: =Summary!A12 -> 2027-04 | B12: 0 | C12: =Summary!C12 -> 0 | D12: =Summary!F12 -> 0 | E12: =IF(B12=0,"",ROUND(C12/B12,2)) | F12: =IF(OR(C12=0,D12<=0),"",ROUND(C12/D12,2)) | G12: =D12-B12 -> 0 | H12: =IF(B12=0,"",IF(G12>=0,"Profitable","Loss after ads"))
A13: =Summary!A13 -> 2027-05 | B13: 0 | C13: =Summary!C13 -> 0 | D13: =Summary!F13 -> 0 | E13: =IF(B13=0,"",ROUND(C13/B13,2)) | F13: =IF(OR(C13=0,D13<=0),"",ROUND(C13/D13,2)) | G13: =D13-B13 -> 0 | H13: =IF(B13=0,"",IF(G13>=0,"Profitable","Loss after ads"))
A14: =Summary!A14 -> 2027-06 | B14: 0 | C14: =Summary!C14 -> 0 | D14: =Summary!F14 -> 0 | E14: =IF(B14=0,"",ROUND(C14/B14,2)) | F14: =IF(OR(C14=0,D14<=0),"",ROUND(C14/D14,2)) | G14: =D14-B14 -> 0 | H14: =IF(B14=0,"",IF(G14>=0,"Profitable","Loss after ads"))
A15: =Summary!A15 -> 2027-07 | B15: 0 | C15: =Summary!C15 -> 0 | D15: =Summary!F15 -> 0 | E15: =IF(B15=0,"",ROUND(C15/B15,2)) | F15: =IF(OR(C15=0,D15<=0),"",ROUND(C15/D15,2)) | G15: =D15-B15 -> 0 | H15: =IF(B15=0,"",IF(G15>=0,"Profitable","Loss after ads"))
A16: =Summary!A16 -> 2027-08 | B16: 0 | C16: =Summary!C16 -> 0 | D16: =Summary!F16 -> 0 | E16: =IF(B16=0,"",ROUND(C16/B16,2)) | F16: =IF(OR(C16=0,D16<=0),"",ROUND(C16/D16,2)) | G16: =D16-B16 -> 0 | H16: =IF(B16=0,"",IF(G16>=0,"Profitable","Loss after ads"))
