Workbook

Sheet Start Here
A1: Law Firm Pricing Workbook
A2: by Knackdesk · knackdesk.com
A4: HOW TO USE
A5: 1. Settings: annual firm overhead line by line, benefits and payroll taxes %, default billable hours per timekeeper, your target margin on flat fees, scope contingency %, days in the year, default referral fee % and working days per month. Overhead per timekeeper follows and every other sheet reads it.
A6: 2. Timekeepers: one row per lawyer or paralegal with role, annual salary or draw, benefits % and billable hours (defaults from Settings, type your own to override) and bill rate. Loaded salary, overhead share, total annual cost, cost rate, margin per hour, margin % and break-even hours are calculated.
A7: 3. Flat Fee Pricer: one row per matter type or quote with partner, associate and paralegal hours and disbursements. Average cost rates per role come from the Timekeepers sheet; labour cost, cost with scope contingency, total cost, the flat fee at your target margin, effective hourly rate and the gap to the fee you charge today are calculated.
A8: 4. Matter Tracker: one row per matter with fee type, budget hours and fees, actual hours and fees (time at standard rates), agreed fee, billed and collected. Hours and fees variance, realized rate, write-off, recovery % and an over / under budget status are calculated, with totals.
A9: 5. Lock-Up & Contingency: one row per month with unbilled work in progress, accounts receivable and fees billed in the trailing 12 months; WIP days, debtor days, lock-up days and locked-up cash follow. Below, contingency matters: settlement, contingency %, case costs, whether costs come off before the fee and any referral fee; gross fee, net fee to the firm, net to the client and effective hourly rate follow.
A10: 6. Summary: timekeepers, average cost and bill rate, timekeepers with negative margin, flat fees priced below the computed fee and the uplift, matters over budget, write-offs, recovery %, lock-up days and locked-up cash, and net contingency fees.
A12: LEGEND
A13: Blue text = a cell you type into. Black text = a formula, leave it alone. Yellow fill = key inputs.
A15: DEFINITIONS
... A27: Arithmetic only; not legal or financial advice.

Sheet Settings
A1: Settings
A2: Rent and facilities (annual) | B2: 60000 | C2: Example default 60,000 a year. Rent, service charges, utilities, cleaning and repairs.
A3: Support staff (annual) | B3: 90000 | C3: Example default 90,000 a year. Receptionist, secretaries, bookkeeper and practice manager, loaded with their payroll costs.
A4: Software and research (annual) | B4: 12000 | C4: Example default 12,000 a year. Practice management, document management, legal research subscriptions and IT.
A5: Insurance (annual) | B5: 8000 | C5: Example default 8,000 a year. Professional indemnity, office and cyber cover.
A6: Marketing (annual) | B6: 10000 | C6: Example default 10,000 a year. Website, directories, advertising and business development.
A7: Other overhead (annual) | B7: 10000 | C7: Example default 10,000 a year. Practising certificates, training, bank charges, accounting, anything else.
A8: Total annual firm overhead | B8: =SUM(B2:B7) -> 190000 | C8: formula: sum of the six overhead rows above
A9: Overhead allocation method | B9: per timekeeper | C9: Documented, not an input: total overhead is shared equally across every timekeeper listed on the Timekeepers sheet.
A10: Benefits and payroll taxes % | B10: 20 | C10: Default 20. Employer payroll taxes, pension, health cover and other benefits on top of salary or draw; each timekeeper can override it.
A11: Default billable hours per year per timekeeper | B11: 1500 | C11: Default 1,500. Hours recorded and billed to matters, not hours worked; each timekeeper can override it.
A12: Target margin % on flat fees | B12: 35 | C12: Default 35. Your own placeholder target margin on price (profit ÷ fee), not a recommendation or an industry benchmark; each matter can override it.
A13: Scope contingency % | B13: 15 | C13: Default 15. Cushion added to the estimated labour cost of a flat fee for work that runs over; each matter can override it.
A14: Days in year | B14: 365 | C14: Default 365. Used to turn trailing 12-month fees into fees per day for lock-up days.
A15: Default referral fee % | B15: 0 | C15: Default 0. Share of a contingency fee paid to a referring lawyer, where your rules allow it; each matter can override it.
A16: Working days per month | B16: 21 | C16: Default 21. Used to show billable hours per working day on the Timekeepers sheet (12 months a year).
A17: Number of timekeepers | B17: =COUNTA(Timekeepers!$A$5:$A$24) -> 6 | C17: formula: count of names on the Timekeepers sheet
A18: Overhead per timekeeper (annual) | B18: =IFERROR(ROUND(B8/B17,2),0) -> 31666.67 | C18: formula: total annual overhead ÷ number of timekeepers
A19: Total billable hours per year (all timekeepers) | B19: =Timekeepers!$I$25 -> 8500 | C19: formula: billable hours used, summed on the Timekeepers sheet
A20: Overhead per billable hour (firm) | B20: =IFERROR(ROUND(B8/B19,2),0) -> 22.35 | C20: formula: total annual overhead ÷ total billable hours; what overhead adds to each hour billed

Sheet Timekeepers
A1: Timekeepers
A2: One row per timekeeper. Benefits % and billable hours default from Settings; type your own in the 'or type your own' columns to override them.
A4: Name | B4: Role | C4: Annual salary or draw | D4: Default benefits % (Settings) | E4: or type your own benefits % | F4: Benefits % used | G4: Default billable hours (Settings) | H4: or type your own hours | I4: Billable hours used | J4: Bill rate | K4: Loaded salary | L4: Overhead allocation | M4: Total annual cost | N4: Cost rate | O4: Margin per hour | P4: Margin % | Q4: Break-even hours | R4: Billable hours per working day
A5: Partner A | B5: partner | C5: 180000 | D5: =IF(A5="","",Settings!$B$10) -> 20 | F5: =IF(A5="","",IF(E5<>"",E5,D5)) -> 20 | G5: =IF(A5="","",Settings!$B$11) -> 1500 | I5: =IF(A5="","",IF(H5<>"",H5,G5)) -> 1500 | J5: 450 | K5: =IF(A5="","",ROUND(C5*(1+F5/100),2)) -> 216000 | L5: =IF(A5="","",Settings!$B$18) -> 31666.67 | M5: =IF(A5="","",K5+L5) -> 247666.67 | N5: =IF(A5="","",IFERROR(ROUND(M5/I5,2),0)) -> 165.11 | O5: =IF(A5="","",ROUND(J5-N5,2)) -> 284.89 | P5: =IF(A5="","",IFERROR(ROUND(O5/J5*100,2),0)) -> 63.31 | Q5: =IF(A5="","",IFERROR(ROUND(M5/J5,2),0)) -> 550.37 | R5: =IF(A5="","",IFERROR(ROUND(I5/(Settings!$B$16*12),2),0)) -> 5.95
A6: Partner B | B6: partner | C6: 160000 | D6: =IF(A6="","",Settings!$B$10) -> 20 | F6: =IF(A6="","",IF(E6<>"",E6,D6)) -> 20 | G6: =IF(A6="","",Settings!$B$11) -> 1500 | H6: 1300 | I6: =IF(A6="","",IF(H6<>"",H6,G6)) -> 1300 | J6: 400 | K6: =IF(A6="","",ROUND(C6*(1+F6/100),2)) -> 192000 | L6: =IF(A6="","",Settings!$B$18) -> 31666.67 | M6: =IF(A6="","",K6+L6) -> 223666.67 | N6: =IF(A6="","",IFERROR(ROUND(M6/I6,2),0)) -> 172.05 | O6: =IF(A6="","",ROUND(J6-N6,2)) -> 227.95 | P6: =IF(A6="","",IFERROR(ROUND(O6/J6*100,2),0)) -> 56.99 | Q6: =IF(A6="","",IFERROR(ROUND(M6/J6,2),0)) -> 559.17 | R6: =IF(A6="","",IFERROR(ROUND(I6/(Settings!$B$16*12),2),0)) -> 5.16
A7: Associate A | B7: associate | C7: 95000 | D7: =IF(A7="","",Settings!$B$10) -> 20 | F7: =IF(A7="","",IF(E7<>"",E7,D7)) -> 20 | G7: =IF(A7="","",Settings!$B$11) -> 1500 | I7: =IF(A7="","",IF(H7<>"",H7,G7)) -> 1500 | J7: 275 | K7: =IF(A7="","",ROUND(C7*(1+F7/100),2)) -> 114000 | L7: =IF(A7="","",Settings!$B$18) -> 31666.67 | M7: =IF(A7="","",K7+L7) -> 145666.67 | N7: =IF(A7="","",IFERROR(ROUND(M7/I7,2),0)) -> 97.11 | O7: =IF(A7="","",ROUND(J7-N7,2)) -> 177.89 | P7: =IF(A7="","",IFERROR(ROUND(O7/J7*100,2),0)) -> 64.69 | Q7: =IF(A7="","",IFERROR(ROUND(M7/J7,2),0)) -> 529.7 | R7: =IF(A7="","",IFERROR(ROUND(I7/(Settings!$B$16*12),2),0)) -> 5.95
A8: Associate B | B8: associate | C8: 85000 | D8: =IF(A8="","",Settings!$B$10) -> 20 | E8: 25 | F8: =IF(A8="","",IF(E8<>"",E8,D8)) -> 25 | G8: =IF(A8="","",Settings!$B$11) -> 1500 | I8: =IF(A8="","",IF(H8<>"",H8,G8)) -> 1500 | J8: 250 | K8: =IF(A8="","",ROUND(C8*(1+F8/100),2)) -> 106250 | L8: =IF(A8="","",Settings!$B$18) -> 31666.67 | M8: =IF(A8="","",K8+L8) -> 137916.67 | N8: =IF(A8="","",IFERROR(ROUND(M8/I8,2),0)) -> 91.94 | O8: =IF(A8="","",ROUND(J8-N8,2)) -> 158.06 | P8: =IF(A8="","",IFERROR(ROUND(O8/J8*100,2),0)) -> 63.22 | Q8: =IF(A8="","",IFERROR(ROUND(M8/J8,2),0)) -> 551.67 | R8: =IF(A8="","",IFERROR(ROUND(I8/(Settings!$B$16*12),2),0)) -> 5.95
A9: Associate C | B9: associate | C9: 70000 | D9: =IF(A9="","",Settings!$B$10) -> 20 | F9: =IF(A9="","",IF(E9<>"",E9,D9)) -> 20 | G9: =IF(A9="","",Settings!$B$11) -> 1500 | I9: =IF(A9="","",IF(H9<>"",H9,G9)) -> 1500 | J9: 225 | K9: =IF(A9="","",ROUND(C9*(1+F9/100),2)) -> 84000 | L9: =IF(A9="","",Settings!$B$18) -> 31666.67 | M9: =IF(A9="","",K9+L9) -> 115666.67 | N9: =IF(A9="","",IFERROR(ROUND(M9/I9,2),0)) -> 77.11 | O9: =IF(A9="","",ROUND(J9-N9,2)) -> 147.89 | P9: =IF(A9="","",IFERROR(ROUND(O9/J9*100,2),0)) -> 65.73 | Q9: =IF(A9="","",IFERROR(ROUND(M9/J9,2),0)) -> 514.07 | R9: =IF(A9="","",IFERROR(ROUND(I9/(Settings!$B$16*12),2),0)) -> 5.95
A10: Paralegal A | B10: paralegal | C10: 50000 | D10: =IF(A10="","",Settings!$B$10) -> 20 | F10: =IF(A10="","",IF(E10<>"",E10,D10)) -> 20 | G10: =IF(A10="","",Settings!$B$11) -> 1500 | H10: 1200 | I10: =IF(A10="","",IF(H10<>"",H10,G10)) -> 1200 | J10: 150 | K10: =IF(A10="","",ROUND(C10*(1+F10/100),2)) -> 60000 | L10: =IF(A10="","",Settings!$B$18) -> 31666.67 | M10: =IF(A10="","",K10+L10) -> 91666.67 | N10: =IF(A10="","",IFERROR(ROUND(M10/I10,2),0)) -> 76.39 | O10: =IF(A10="","",ROUND(J10-N10,2)) -> 73.61 | P10: =IF(A10="","",IFERROR(ROUND(O10/J10*100,2),0)) -> 49.07 | Q10: =IF(A10="","",IFERROR(ROUND(M10/J10,2),0)) -> 611.11 | R10: =IF(A10="","",IFERROR(ROUND(I10/(Settings!$B$16*12),2),0)) -> 4.76
D11: =IF(A11="","",Settings!$B$10) | F11: =IF(A11="","",IF(E11<>"",E11,D11)) | G11: =IF(A11="","",Settings!$B$11) | I11: =IF(A11="","",IF(H11<>"",H11,G11)) | K11: =IF(A11="","",ROUND(C11*(1+F11/100),2)) | L11: =IF(A11="","",Settings!$B$18) | M11: =IF(A11="","",K11+L11) | N11: =IF(A11="","",IFERROR(ROUND(M11/I11,2),0)) | O11: =IF(A11="","",ROUND(J11-N11,2)) | P11: =IF(A11="","",IFERROR(ROUND(O11/J11*100,2),0)) | Q11: =IF(A11="","",IFERROR(ROUND(M11/J11,2),0)) | R11: =IF(A11="","",IFERROR(ROUND(I11/(Settings!$B$16*12),2),0))
D12: =IF(A12="","",Settings!$B$10) | F12: =IF(A12="","",IF(E12<>"",E12,D12)) | G12: =IF(A12="","",Settings!$B$11) | I12: =IF(A12="","",IF(H12<>"",H12,G12)) | K12: =IF(A12="","",ROUND(C12*(1+F12/100),2)) | L12: =IF(A12="","",Settings!$B$18) | M12: =IF(A12="","",K12+L12) | N12: =IF(A12="","",IFERROR(ROUND(M12/I12,2),0)) | O12: =IF(A12="","",ROUND(J12-N12,2)) | P12: =IF(A12="","",IFERROR(ROUND(O12/J12*100,2),0)) | Q12: =IF(A12="","",IFERROR(ROUND(M12/J12,2),0)) | R12: =IF(A12="","",IFERROR(ROUND(I12/(Settings!$B$16*12),2),0))
D13: =IF(A13="","",Settings!$B$10) | F13: =IF(A13="","",IF(E13<>"",E13,D13)) | G13: =IF(A13="","",Settings!$B$11) | I13: =IF(A13="","",IF(H13<>"",H13,G13)) | K13: =IF(A13="","",ROUND(C13*(1+F13/100),2)) | L13: =IF(A13="","",Settings!$B$18) | M13: =IF(A13="","",K13+L13) | N13: =IF(A13="","",IFERROR(ROUND(M13/I13,2),0)) | O13: =IF(A13="","",ROUND(J13-N13,2)) | P13: =IF(A13="","",IFERROR(ROUND(O13/J13*100,2),0)) | Q13: =IF(A13="","",IFERROR(ROUND(M13/J13,2),0)) | R13: =IF(A13="","",IFERROR(ROUND(I13/(Settings!$B$16*12),2),0))
D14: =IF(A14="","",Settings!$B$10) | F14: =IF(A14="","",IF(E14<>"",E14,D14)) | G14: =IF(A14="","",Settings!$B$11) | I14: =IF(A14="","",IF(H14<>"",H14,G14)) | K14: =IF(A14="","",ROUND(C14*(1+F14/100),2)) | L14: =IF(A14="","",Settings!$B$18) | M14: =IF(A14="","",K14+L14) | N14: =IF(A14="","",IFERROR(ROUND(M14/I14,2),0)) | O14: =IF(A14="","",ROUND(J14-N14,2)) | P14: =IF(A14="","",IFERROR(ROUND(O14/J14*100,2),0)) | Q14: =IF(A14="","",IFERROR(ROUND(M14/J14,2),0)) | R14: =IF(A14="","",IFERROR(ROUND(I14/(Settings!$B$16*12),2),0))
D15: =IF(A15="","",Settings!$B$10) | F15: =IF(A15="","",IF(E15<>"",E15,D15)) | G15: =IF(A15="","",Settings!$B$11) | I15: =IF(A15="","",IF(H15<>"",H15,G15)) | K15: =IF(A15="","",ROUND(C15*(1+F15/100),2)) | L15: =IF(A15="","",Settings!$B$18) | M15: =IF(A15="","",K15+L15) | N15: =IF(A15="","",IFERROR(ROUND(M15/I15,2),0)) | O15: =IF(A15="","",ROUND(J15-N15,2)) | P15: =IF(A15="","",IFERROR(ROUND(O15/J15*100,2),0)) | Q15: =IF(A15="","",IFERROR(ROUND(M15/J15,2),0)) | R15: =IF(A15="","",IFERROR(ROUND(I15/(Settings!$B$16*12),2),0))
D16: =IF(A16="","",Settings!$B$10) | F16: =IF(A16="","",IF(E16<>"",E16,D16)) | G16: =IF(A16="","",Settings!$B$11) | I16: =IF(A16="","",IF(H16<>"",H16,G16)) | K16: =IF(A16="","",ROUND(C16*(1+F16/100),2)) | L16: =IF(A16="","",Settings!$B$18) | M16: =IF(A16="","",K16+L16) | N16: =IF(A16="","",IFERROR(ROUND(M16/I16,2),0)) | O16: =IF(A16="","",ROUND(J16-N16,2)) | P16: =IF(A16="","",IFERROR(ROUND(O16/J16*100,2),0)) | Q16: =IF(A16="","",IFERROR(ROUND(M16/J16,2),0)) | R16: =IF(A16="","",IFERROR(ROUND(I16/(Settings!$B$16*12),2),0))
D17: =IF(A17="","",Settings!$B$10) | F17: =IF(A17="","",IF(E17<>"",E17,D17)) | G17: =IF(A17="","",Settings!$B$11) | I17: =IF(A17="","",IF(H17<>"",H17,G17)) | K17: =IF(A17="","",ROUND(C17*(1+F17/100),2)) | L17: =IF(A17="","",Settings!$B$18) | M17: =IF(A17="","",K17+L17) | N17: =IF(A17="","",IFERROR(ROUND(M17/I17,2),0)) | O17: =IF(A17="","",ROUND(J17-N17,2)) | P17: =IF(A17="","",IFERROR(ROUND(O17/J17*100,2),0)) | Q17: =IF(A17="","",IFERROR(ROUND(M17/J17,2),0)) | R17: =IF(A17="","",IFERROR(ROUND(I17/(Settings!$B$16*12),2),0))
D18: =IF(A18="","",Settings!$B$10) | F18: =IF(A18="","",IF(E18<>"",E18,D18)) | G18: =IF(A18="","",Settings!$B$11) | I18: =IF(A18="","",IF(H18<>"",H18,G18)) | K18: =IF(A18="","",ROUND(C18*(1+F18/100),2)) | L18: =IF(A18="","",Settings!$B$18) | M18: =IF(A18="","",K18+L18) | N18: =IF(A18="","",IFERROR(ROUND(M18/I18,2),0)) | O18: =IF(A18="","",ROUND(J18-N18,2)) | P18: =IF(A18="","",IFERROR(ROUND(O18/J18*100,2),0)) | Q18: =IF(A18="","",IFERROR(ROUND(M18/J18,2),0)) | R18: =IF(A18="","",IFERROR(ROUND(I18/(Settings!$B$16*12),2),0))
D19: =IF(A19="","",Settings!$B$10) | F19: =IF(A19="","",IF(E19<>"",E19,D19)) | G19: =IF(A19="","",Settings!$B$11) | I19: =IF(A19="","",IF(H19<>"",H19,G19)) | K19: =IF(A19="","",ROUND(C19*(1+F19/100),2)) | L19: =IF(A19="","",Settings!$B$18) | M19: =IF(A19="","",K19+L19) | N19: =IF(A19="","",IFERROR(ROUND(M19/I19,2),0)) | O19: =IF(A19="","",ROUND(J19-N19,2)) | P19: =IF(A19="","",IFERROR(ROUND(O19/J19*100,2),0)) | Q19: =IF(A19="","",IFERROR(ROUND(M19/J19,2),0)) | R19: =IF(A19="","",IFERROR(ROUND(I19/(Settings!$B$16*12),2),0))
D20: =IF(A20="","",Settings!$B$10) | F20: =IF(A20="","",IF(E20<>"",E20,D20)) | G20: =IF(A20="","",Settings!$B$11) | I20: =IF(A20="","",IF(H20<>"",H20,G20)) | K20: =IF(A20="","",ROUND(C20*(1+F20/100),2)) | L20: =IF(A20="","",Settings!$B$18) | M20: =IF(A20="","",K20+L20) | N20: =IF(A20="","",IFERROR(ROUND(M20/I20,2),0)) | O20: =IF(A20="","",ROUND(J20-N20,2)) | P20: =IF(A20="","",IFERROR(ROUND(O20/J20*100,2),0)) | Q20: =IF(A20="","",IFERROR(ROUND(M20/J20,2),0)) | R20: =IF(A20="","",IFERROR(ROUND(I20/(Settings!$B$16*12),2),0))
D21: =IF(A21="","",Settings!$B$10) | F21: =IF(A21="","",IF(E21<>"",E21,D21)) | G21: =IF(A21="","",Settings!$B$11) | I21: =IF(A21="","",IF(H21<>"",H21,G21)) | K21: =IF(A21="","",ROUND(C21*(1+F21/100),2)) | L21: =IF(A21="","",Settings!$B$18) | M21: =IF(A21="","",K21+L21) | N21: =IF(A21="","",IFERROR(ROUND(M21/I21,2),0)) | O21: =IF(A21="","",ROUND(J21-N21,2)) | P21: =IF(A21="","",IFERROR(ROUND(O21/J21*100,2),0)) | Q21: =IF(A21="","",IFERROR(ROUND(M21/J21,2),0)) | R21: =IF(A21="","",IFERROR(ROUND(I21/(Settings!$B$16*12),2),0))
D22: =IF(A22="","",Settings!$B$10) | F22: =IF(A22="","",IF(E22<>"",E22,D22)) | G22: =IF(A22="","",Settings!$B$11) | I22: =IF(A22="","",IF(H22<>"",H22,G22)) | K22: =IF(A22="","",ROUND(C22*(1+F22/100),2)) | L22: =IF(A22="","",Settings!$B$18) | M22: =IF(A22="","",K22+L22) | N22: =IF(A22="","",IFERROR(ROUND(M22/I22,2),0)) | O22: =IF(A22="","",ROUND(J22-N22,2)) | P22: =IF(A22="","",IFERROR(ROUND(O22/J22*100,2),0)) | Q22: =IF(A22="","",IFERROR(ROUND(M22/J22,2),0)) | R22: =IF(A22="","",IFERROR(ROUND(I22/(Settings!$B$16*12),2),0))
... D24: =IF(A24="","",Settings!$B$10) | F24: =IF(A24="","",IF(E24<>"",E24,D24)) | G24: =IF(A24="","",Settings!$B$11) | I24: =IF(A24="","",IF(H24<>"",H24,G24)) | K24: =IF(A24="","",ROUND(C24*(1+F24/100),2)) | L24: =IF(A24="","",Settings!$B$18) | M24: =IF(A24="","",K24+L24) | N24: =IF(A24="","",IFERROR(ROUND(M24/I24,2),0)) | O24: =IF(A24="","",ROUND(J24-N24,2)) | P24: =IF(A24="","",IFERROR(ROUND(O24/J24*100,2),0)) | Q24: =IF(A24="","",IFERROR(ROUND(M24/J24,2),0)) | R24: =IF(A24="","",IFERROR(ROUND(I24/(Settings!$B$16*12),2),0))
A25: Total | B25: =COUNTA(A5:A24) -> 6 | C25: =SUM(C5:C24) -> 640000 | I25: =SUM(I5:I24) -> 8500 | K25: =SUM(K5:K24) -> 772250 | L25: =SUM(L5:L24) -> 190000.02 | M25: =SUM(M5:M24) -> 962250.02 | N25: =IFERROR(ROUND(M25/I25,2),0) -> 113.21

Sheet Flat Fee Pricer
A1: Flat Fee Pricer
A2: Partner cost rate | B2: =IFERROR(ROUND(AVERAGEIF(Timekeepers!$B$5:$B$24,"partner",Timekeepers!$N$5:$N$24),2),0) -> 168.58 | C2: Associate cost rate | D2: =IFERROR(ROUND(AVERAGEIF(Timekeepers!$B$5:$B$24,"associate",Timekeepers!$N$5:$N$24),2),0) -> 88.72 | E2: Paralegal cost rate | F2: =IFERROR(ROUND(AVERAGEIF(Timekeepers!$B$5:$B$24,"paralegal",Timekeepers!$N$5:$N$24),2),0) -> 76.39
A3: One row per matter type or quote. Contingency % and margin % default from Settings; type your own to override them. Current fee is what you charge today.
A4: Matter | B4: Matter type | C4: Partner hours | D4: Associate hours | E4: Paralegal hours | F4: Disbursements | G4: Default contingency % (Settings) | H4: or type your own contingency % | I4: Contingency % used | J4: Default margin % (Settings) | K4: or type your own margin % | L4: Margin % used | M4: Labour cost | N4: Cost with contingency | O4: Total cost | P4: Flat fee | Q4: Total hours | R4: Effective hourly rate | S4: Current fee charged | T4: Gap: current − flat fee
A5: Residential purchase | B5: conveyancing | C5: 2 | D5: 6 | E5: 4 | F5: 150 | G5: =IF(A5="","",Settings!$B$13) -> 15 | I5: =IF(A5="","",IF(H5<>"",H5,G5)) -> 15 | J5: =IF(A5="","",Settings!$B$12) -> 35 | L5: =IF(A5="","",IF(K5<>"",K5,J5)) -> 35 | M5: =IF(A5="","",ROUND(C5*$B$2+D5*$D$2+E5*$F$2,2)) -> 1175.04 | N5: =IF(A5="","",ROUND(M5*(1+I5/100),2)) -> 1351.3 | O5: =IF(A5="","",N5+F5) -> 1501.3 | P5: =IF(A5="","",IFERROR(ROUND(O5/(1-L5/100),2),0)) -> 2309.69 | Q5: =IF(A5="","",C5+D5+E5) -> 12 | R5: =IF(A5="","",IFERROR(ROUND(P5/Q5,2),0)) -> 192.47 | S5: 1800 | T5: =IF(OR(A5="",S5=""),"",ROUND(S5-P5,2)) -> -509.69
A6: Simple will | B6: will and estate | C6: 1 | D6: 2 | E6: 3 | F6: 0 | G6: =IF(A6="","",Settings!$B$13) -> 15 | I6: =IF(A6="","",IF(H6<>"",H6,G6)) -> 15 | J6: =IF(A6="","",Settings!$B$12) -> 35 | L6: =IF(A6="","",IF(K6<>"",K6,J6)) -> 35 | M6: =IF(A6="","",ROUND(C6*$B$2+D6*$D$2+E6*$F$2,2)) -> 575.19 | N6: =IF(A6="","",ROUND(M6*(1+I6/100),2)) -> 661.47 | O6: =IF(A6="","",N6+F6) -> 661.47 | P6: =IF(A6="","",IFERROR(ROUND(O6/(1-L6/100),2),0)) -> 1017.65 | Q6: =IF(A6="","",C6+D6+E6) -> 6 | R6: =IF(A6="","",IFERROR(ROUND(P6/Q6,2),0)) -> 169.61 | S6: 1500 | T6: =IF(OR(A6="",S6=""),"",ROUND(S6-P6,2)) -> 482.35
A7: Company incorporation | B7: incorporation | C7: 1 | D7: 4 | E7: 2 | F7: 300 | G7: =IF(A7="","",Settings!$B$13) -> 15 | I7: =IF(A7="","",IF(H7<>"",H7,G7)) -> 15 | J7: =IF(A7="","",Settings!$B$12) -> 35 | L7: =IF(A7="","",IF(K7<>"",K7,J7)) -> 35 | M7: =IF(A7="","",ROUND(C7*$B$2+D7*$D$2+E7*$F$2,2)) -> 676.24 | N7: =IF(A7="","",ROUND(M7*(1+I7/100),2)) -> 777.68 | O7: =IF(A7="","",N7+F7) -> 1077.68 | P7: =IF(A7="","",IFERROR(ROUND(O7/(1-L7/100),2),0)) -> 1657.97 | Q7: =IF(A7="","",C7+D7+E7) -> 7 | R7: =IF(A7="","",IFERROR(ROUND(P7/Q7,2),0)) -> 236.85 | S7: 2200 | T7: =IF(OR(A7="",S7=""),"",ROUND(S7-P7,2)) -> 542.03
A8: Commercial contract review | B8: contract | C8: 3 | D8: 5 | E8: 0 | F8: 0 | G8: =IF(A8="","",Settings!$B$13) -> 15 | I8: =IF(A8="","",IF(H8<>"",H8,G8)) -> 15 | J8: =IF(A8="","",Settings!$B$12) -> 35 | L8: =IF(A8="","",IF(K8<>"",K8,J8)) -> 35 | M8: =IF(A8="","",ROUND(C8*$B$2+D8*$D$2+E8*$F$2,2)) -> 949.34 | N8: =IF(A8="","",ROUND(M8*(1+I8/100),2)) -> 1091.74 | O8: =IF(A8="","",N8+F8) -> 1091.74 | P8: =IF(A8="","",IFERROR(ROUND(O8/(1-L8/100),2),0)) -> 1679.6 | Q8: =IF(A8="","",C8+D8+E8) -> 8 | R8: =IF(A8="","",IFERROR(ROUND(P8/Q8,2),0)) -> 209.95 | S8: 2500 | T8: =IF(OR(A8="",S8=""),"",ROUND(S8-P8,2)) -> 820.4
A9: Work visa application | B9: immigration | C9: 2 | D9: 8 | E9: 6 | F9: 500 | G9: =IF(A9="","",Settings!$B$13) -> 15 | I9: =IF(A9="","",IF(H9<>"",H9,G9)) -> 15 | J9: =IF(A9="","",Settings!$B$12) -> 35 | L9: =IF(A9="","",IF(K9<>"",K9,J9)) -> 35 | M9: =IF(A9="","",ROUND(C9*$B$2+D9*$D$2+E9*$F$2,2)) -> 1505.26 | N9: =IF(A9="","",ROUND(M9*(1+I9/100),2)) -> 1731.05 | O9: =IF(A9="","",N9+F9) -> 2231.05 | P9: =IF(A9="","",IFERROR(ROUND(O9/(1-L9/100),2),0)) -> 3432.38 | Q9: =IF(A9="","",C9+D9+E9) -> 16 | R9: =IF(A9="","",IFERROR(ROUND(P9/Q9,2),0)) -> 214.52 | S9: 4200 | T9: =IF(OR(A9="",S9=""),"",ROUND(S9-P9,2)) -> 767.62
A10: Litigation: pleadings stage | B10: litigation stage | C10: 10 | D10: 25 | E10: 10 | F10: 1200 | G10: =IF(A10="","",Settings!$B$13) -> 15 | H10: 25 | I10: =IF(A10="","",IF(H10<>"",H10,G10)) -> 25 | J10: =IF(A10="","",Settings!$B$12) -> 35 | K10: 30 | L10: =IF(A10="","",IF(K10<>"",K10,J10)) -> 30 | M10: =IF(A10="","",ROUND(C10*$B$2+D10*$D$2+E10*$F$2,2)) -> 4667.7 | N10: =IF(A10="","",ROUND(M10*(1+I10/100),2)) -> 5834.63 | O10: =IF(A10="","",N10+F10) -> 7034.63 | P10: =IF(A10="","",IFERROR(ROUND(O10/(1-L10/100),2),0)) -> 10049.47 | Q10: =IF(A10="","",C10+D10+E10) -> 45 | R10: =IF(A10="","",IFERROR(ROUND(P10/Q10,2),0)) -> 223.32 | S10: 12000 | T10: =IF(OR(A10="",S10=""),"",ROUND(S10-P10,2)) -> 1950.53
G11: =IF(A11="","",Settings!$B$13) | I11: =IF(A11="","",IF(H11<>"",H11,G11)) | J11: =IF(A11="","",Settings!$B$12) | L11: =IF(A11="","",IF(K11<>"",K11,J11)) | M11: =IF(A11="","",ROUND(C11*$B$2+D11*$D$2+E11*$F$2,2)) | N11: =IF(A11="","",ROUND(M11*(1+I11/100),2)) | O11: =IF(A11="","",N11+F11) | P11: =IF(A11="","",IFERROR(ROUND(O11/(1-L11/100),2),0)) | Q11: =IF(A11="","",C11+D11+E11) | R11: =IF(A11="","",IFERROR(ROUND(P11/Q11,2),0)) | T11: =IF(OR(A11="",S11=""),"",ROUND(S11-P11,2))
G12: =IF(A12="","",Settings!$B$13) | I12: =IF(A12="","",IF(H12<>"",H12,G12)) | J12: =IF(A12="","",Settings!$B$12) | L12: =IF(A12="","",IF(K12<>"",K12,J12)) | M12: =IF(A12="","",ROUND(C12*$B$2+D12*$D$2+E12*$F$2,2)) | N12: =IF(A12="","",ROUND(M12*(1+I12/100),2)) | O12: =IF(A12="","",N12+F12) | P12: =IF(A12="","",IFERROR(ROUND(O12/(1-L12/100),2),0)) | Q12: =IF(A12="","",C12+D12+E12) | R12: =IF(A12="","",IFERROR(ROUND(P12/Q12,2),0)) | T12: =IF(OR(A12="",S12=""),"",ROUND(S12-P12,2))
G13: =IF(A13="","",Settings!$B$13) | I13: =IF(A13="","",IF(H13<>"",H13,G13)) | J13: =IF(A13="","",Settings!$B$12) | L13: =IF(A13="","",IF(K13<>"",K13,J13)) | M13: =IF(A13="","",ROUND(C13*$B$2+D13*$D$2+E13*$F$2,2)) | N13: =IF(A13="","",ROUND(M13*(1+I13/100),2)) | O13: =IF(A13="","",N13+F13) | P13: =IF(A13="","",IFERROR(ROUND(O13/(1-L13/100),2),0)) | Q13: =IF(A13="","",C13+D13+E13) | R13: =IF(A13="","",IFERROR(ROUND(P13/Q13,2),0)) | T13: =IF(OR(A13="",S13=""),"",ROUND(S13-P13,2))
G14: =IF(A14="","",Settings!$B$13) | I14: =IF(A14="","",IF(H14<>"",H14,G14)) | J14: =IF(A14="","",Settings!$B$12) | L14: =IF(A14="","",IF(K14<>"",K14,J14)) | M14: =IF(A14="","",ROUND(C14*$B$2+D14*$D$2+E14*$F$2,2)) | N14: =IF(A14="","",ROUND(M14*(1+I14/100),2)) | O14: =IF(A14="","",N14+F14) | P14: =IF(A14="","",IFERROR(ROUND(O14/(1-L14/100),2),0)) | Q14: =IF(A14="","",C14+D14+E14) | R14: =IF(A14="","",IFERROR(ROUND(P14/Q14,2),0)) | T14: =IF(OR(A14="",S14=""),"",ROUND(S14-P14,2))
G15: =IF(A15="","",Settings!$B$13) | I15: =IF(A15="","",IF(H15<>"",H15,G15)) | J15: =IF(A15="","",Settings!$B$12) | L15: =IF(A15="","",IF(K15<>"",K15,J15)) | M15: =IF(A15="","",ROUND(C15*$B$2+D15*$D$2+E15*$F$2,2)) | N15: =IF(A15="","",ROUND(M15*(1+I15/100),2)) | O15: =IF(A15="","",N15+F15) | P15: =IF(A15="","",IFERROR(ROUND(O15/(1-L15/100),2),0)) | Q15: =IF(A15="","",C15+D15+E15) | R15: =IF(A15="","",IFERROR(ROUND(P15/Q15,2),0)) | T15: =IF(OR(A15="",S15=""),"",ROUND(S15-P15,2))
G16: =IF(A16="","",Settings!$B$13) | I16: =IF(A16="","",IF(H16<>"",H16,G16)) | J16: =IF(A16="","",Settings!$B$12) | L16: =IF(A16="","",IF(K16<>"",K16,J16)) | M16: =IF(A16="","",ROUND(C16*$B$2+D16*$D$2+E16*$F$2,2)) | N16: =IF(A16="","",ROUND(M16*(1+I16/100),2)) | O16: =IF(A16="","",N16+F16) | P16: =IF(A16="","",IFERROR(ROUND(O16/(1-L16/100),2),0)) | Q16: =IF(A16="","",C16+D16+E16) | R16: =IF(A16="","",IFERROR(ROUND(P16/Q16,2),0)) | T16: =IF(OR(A16="",S16=""),"",ROUND(S16-P16,2))
G17: =IF(A17="","",Settings!$B$13) | I17: =IF(A17="","",IF(H17<>"",H17,G17)) | J17: =IF(A17="","",Settings!$B$12) | L17: =IF(A17="","",IF(K17<>"",K17,J17)) | M17: =IF(A17="","",ROUND(C17*$B$2+D17*$D$2+E17*$F$2,2)) | N17: =IF(A17="","",ROUND(M17*(1+I17/100),2)) | O17: =IF(A17="","",N17+F17) | P17: =IF(A17="","",IFERROR(ROUND(O17/(1-L17/100),2),0)) | Q17: =IF(A17="","",C17+D17+E17) | R17: =IF(A17="","",IFERROR(ROUND(P17/Q17,2),0)) | T17: =IF(OR(A17="",S17=""),"",ROUND(S17-P17,2))
G18: =IF(A18="","",Settings!$B$13) | I18: =IF(A18="","",IF(H18<>"",H18,G18)) | J18: =IF(A18="","",Settings!$B$12) | L18: =IF(A18="","",IF(K18<>"",K18,J18)) | M18: =IF(A18="","",ROUND(C18*$B$2+D18*$D$2+E18*$F$2,2)) | N18: =IF(A18="","",ROUND(M18*(1+I18/100),2)) | O18: =IF(A18="","",N18+F18) | P18: =IF(A18="","",IFERROR(ROUND(O18/(1-L18/100),2),0)) | Q18: =IF(A18="","",C18+D18+E18) | R18: =IF(A18="","",IFERROR(ROUND(P18/Q18,2),0)) | T18: =IF(OR(A18="",S18=""),"",ROUND(S18-P18,2))
G19: =IF(A19="","",Settings!$B$13) | I19: =IF(A19="","",IF(H19<>"",H19,G19)) | J19: =IF(A19="","",Settings!$B$12) | L19: =IF(A19="","",IF(K19<>"",K19,J19)) | M19: =IF(A19="","",ROUND(C19*$B$2+D19*$D$2+E19*$F$2,2)) | N19: =IF(A19="","",ROUND(M19*(1+I19/100),2)) | O19: =IF(A19="","",N19+F19) | P19: =IF(A19="","",IFERROR(ROUND(O19/(1-L19/100),2),0)) | Q19: =IF(A19="","",C19+D19+E19) | R19: =IF(A19="","",IFERROR(ROUND(P19/Q19,2),0)) | T19: =IF(OR(A19="",S19=""),"",ROUND(S19-P19,2))
G20: =IF(A20="","",Settings!$B$13) | I20: =IF(A20="","",IF(H20<>"",H20,G20)) | J20: =IF(A20="","",Settings!$B$12) | L20: =IF(A20="","",IF(K20<>"",K20,J20)) | M20: =IF(A20="","",ROUND(C20*$B$2+D20*$D$2+E20*$F$2,2)) | N20: =IF(A20="","",ROUND(M20*(1+I20/100),2)) | O20: =IF(A20="","",N20+F20) | P20: =IF(A20="","",IFERROR(ROUND(O20/(1-L20/100),2),0)) | Q20: =IF(A20="","",C20+D20+E20) | R20: =IF(A20="","",IFERROR(ROUND(P20/Q20,2),0)) | T20: =IF(OR(A20="",S20=""),"",ROUND(S20-P20,2))
G21: =IF(A21="","",Settings!$B$13) | I21: =IF(A21="","",IF(H21<>"",H21,G21)) | J21: =IF(A21="","",Settings!$B$12) | L21: =IF(A21="","",IF(K21<>"",K21,J21)) | M21: =IF(A21="","",ROUND(C21*$B$2+D21*$D$2+E21*$F$2,2)) | N21: =IF(A21="","",ROUND(M21*(1+I21/100),2)) | O21: =IF(A21="","",N21+F21) | P21: =IF(A21="","",IFERROR(ROUND(O21/(1-L21/100),2),0)) | Q21: =IF(A21="","",C21+D21+E21) | R21: =IF(A21="","",IFERROR(ROUND(P21/Q21,2),0)) | T21: =IF(OR(A21="",S21=""),"",ROUND(S21-P21,2))
G22: =IF(A22="","",Settings!$B$13) | I22: =IF(A22="","",IF(H22<>"",H22,G22)) | J22: =IF(A22="","",Settings!$B$12) | L22: =IF(A22="","",IF(K22<>"",K22,J22)) | M22: =IF(A22="","",ROUND(C22*$B$2+D22*$D$2+E22*$F$2,2)) | N22: =IF(A22="","",ROUND(M22*(1+I22/100),2)) | O22: =IF(A22="","",N22+F22) | P22: =IF(A22="","",IFERROR(ROUND(O22/(1-L22/100),2),0)) | Q22: =IF(A22="","",C22+D22+E22) | R22: =IF(A22="","",IFERROR(ROUND(P22/Q22,2),0)) | T22: =IF(OR(A22="",S22=""),"",ROUND(S22-P22,2))
... G24: =IF(A24="","",Settings!$B$13) | I24: =IF(A24="","",IF(H24<>"",H24,G24)) | J24: =IF(A24="","",Settings!$B$12) | L24: =IF(A24="","",IF(K24<>"",K24,J24)) | M24: =IF(A24="","",ROUND(C24*$B$2+D24*$D$2+E24*$F$2,2)) | N24: =IF(A24="","",ROUND(M24*(1+I24/100),2)) | O24: =IF(A24="","",N24+F24) | P24: =IF(A24="","",IFERROR(ROUND(O24/(1-L24/100),2),0)) | Q24: =IF(A24="","",C24+D24+E24) | R24: =IF(A24="","",IFERROR(ROUND(P24/Q24,2),0)) | T24: =IF(OR(A24="",S24=""),"",ROUND(S24-P24,2))
A25: Total | C25: =SUM(C5:C24) -> 19 | D25: =SUM(D5:D24) -> 50 | E25: =SUM(E5:E24) -> 25 | F25: =SUM(F5:F24) -> 2150 | M25: =SUM(M5:M24) -> 9548.77 | N25: =SUM(N5:N24) -> 11447.87 | O25: =SUM(O5:O24) -> 13597.87 | P25: =SUM(P5:P24) -> 20146.76 | Q25: =SUM(Q5:Q24) -> 94 | S25: =SUM(S5:S24) -> 24200 | T25: =SUM(T5:T24) -> 4053.24

Sheet Matter Tracker
A1: Matter Tracker
A2: One row per matter. Actual fees = recorded time at standard rates. Agreed fee is the flat or capped fee; leave it empty for hourly matters.
A4: Matter | B4: Client | C4: Fee type | D4: Budget hours | E4: Budget fees | F4: Actual hours | G4: Actual fees | H4: Agreed fee | I4: Billed | J4: Collected | K4: Hours variance | L4: Hours variance % | M4: Fees variance | N4: Fees variance % | O4: Realized rate | P4: Write-off | Q4: Recovery % | R4: Status
A5: Smith residential purchase | B5: J. Smith | C5: flat | D5: 12 | E5: 1800 | F5: 15 | G5: 2600 | H5: 1800 | I5: 1800 | J5: 1800 | K5: =IF(A5="","",ROUND(F5-D5,2)) -> 3 | L5: =IF(A5="","",IFERROR(ROUND(K5/D5*100,2),0)) -> 25 | M5: =IF(A5="","",ROUND(G5-E5,2)) -> 800 | N5: =IF(A5="","",IFERROR(ROUND(M5/E5*100,2),0)) -> 44.44 | O5: =IF(A5="","",IFERROR(ROUND(J5/F5,2),0)) -> 120 | P5: =IF(A5="","",IF(N(H5)>0,MAX(0,ROUND(G5-H5,2)),MAX(0,ROUND(G5-I5,2)))) -> 800 | Q5: =IF(A5="","",IFERROR(ROUND(J5/G5*100,2),0)) -> 69.23 | R5: =IF(A5="","",IF(G5>E5,"Over budget",IF(G5<E5,"Under budget","On budget"))) -> Over budget
A6: Shareholder agreement | B6: Acme Ltd | C6: hourly | D6: 20 | E6: 5000 | F6: 18 | G6: 4600 | I6: 4600 | J6: 4200 | K6: =IF(A6="","",ROUND(F6-D6,2)) -> -2 | L6: =IF(A6="","",IFERROR(ROUND(K6/D6*100,2),0)) -> -10 | M6: =IF(A6="","",ROUND(G6-E6,2)) -> -400 | N6: =IF(A6="","",IFERROR(ROUND(M6/E6*100,2),0)) -> -8 | O6: =IF(A6="","",IFERROR(ROUND(J6/F6,2),0)) -> 233.33 | P6: =IF(A6="","",IF(N(H6)>0,MAX(0,ROUND(G6-H6,2)),MAX(0,ROUND(G6-I6,2)))) -> 0 | Q6: =IF(A6="","",IFERROR(ROUND(J6/G6*100,2),0)) -> 91.3 | R6: =IF(A6="","",IF(G6>E6,"Over budget",IF(G6<E6,"Under budget","On budget"))) -> Under budget
A7: Patel v Northwind | B7: R. Patel | C7: hourly | D7: 60 | E7: 15000 | F7: 72 | G7: 18500 | I7: 17000 | J7: 15000 | K7: =IF(A7="","",ROUND(F7-D7,2)) -> 12 | L7: =IF(A7="","",IFERROR(ROUND(K7/D7*100,2),0)) -> 20 | M7: =IF(A7="","",ROUND(G7-E7,2)) -> 3500 | N7: =IF(A7="","",IFERROR(ROUND(M7/E7*100,2),0)) -> 23.33 | O7: =IF(A7="","",IFERROR(ROUND(J7/F7,2),0)) -> 208.33 | P7: =IF(A7="","",IF(N(H7)>0,MAX(0,ROUND(G7-H7,2)),MAX(0,ROUND(G7-I7,2)))) -> 1500 | Q7: =IF(A7="","",IFERROR(ROUND(J7/G7*100,2),0)) -> 81.08 | R7: =IF(A7="","",IF(G7>E7,"Over budget",IF(G7<E7,"Under budget","On budget"))) -> Over budget
A8: Lee estate plan | B8: M. Lee | C8: flat | D8: 6 | E8: 1500 | F8: 5 | G8: 1250 | H8: 1500 | I8: 1500 | J8: 1500 | K8: =IF(A8="","",ROUND(F8-D8,2)) -> -1 | L8: =IF(A8="","",IFERROR(ROUND(K8/D8*100,2),0)) -> -16.67 | M8: =IF(A8="","",ROUND(G8-E8,2)) -> -250 | N8: =IF(A8="","",IFERROR(ROUND(M8/E8*100,2),0)) -> -16.67 | O8: =IF(A8="","",IFERROR(ROUND(J8/F8,2),0)) -> 300 | P8: =IF(A8="","",IF(N(H8)>0,MAX(0,ROUND(G8-H8,2)),MAX(0,ROUND(G8-I8,2)))) -> 0 | Q8: =IF(A8="","",IFERROR(ROUND(J8/G8*100,2),0)) -> 120 | R8: =IF(A8="","",IF(G8>E8,"Over budget",IF(G8<E8,"Under budget","On budget"))) -> Under budget
A9: Garcia injury claim | B9: L. Garcia | C9: contingency | D9: 80 | E9: 20000 | F9: 95 | G9: 24000 | H9: 33600 | I9: 33600 | J9: 33600 | K9: =IF(A9="","",ROUND(F9-D9,2)) -> 15 | L9: =IF(A9="","",IFERROR(ROUND(K9/D9*100,2),0)) -> 18.75 | M9: =IF(A9="","",ROUND(G9-E9,2)) -> 4000 | N9: =IF(A9="","",IFERROR(ROUND(M9/E9*100,2),0)) -> 20 | O9: =IF(A9="","",IFERROR(ROUND(J9/F9,2),0)) -> 353.68 | P9: =IF(A9="","",IF(N(H9)>0,MAX(0,ROUND(G9-H9,2)),MAX(0,ROUND(G9-I9,2)))) -> 0 | Q9: =IF(A9="","",IFERROR(ROUND(J9/G9*100,2),0)) -> 140 | R9: =IF(A9="","",IF(G9>E9,"Over budget",IF(G9<E9,"Under budget","On budget"))) -> Over budget
A10: Lease review | B10: Brightline Cafe | C10: hourly | D10: 10 | E10: 2500 | F10: 10 | G10: 2500 | I10: 2500 | J10: 2500 | K10: =IF(A10="","",ROUND(F10-D10,2)) -> 0 | L10: =IF(A10="","",IFERROR(ROUND(K10/D10*100,2),0)) -> 0 | M10: =IF(A10="","",ROUND(G10-E10,2)) -> 0 | N10: =IF(A10="","",IFERROR(ROUND(M10/E10*100,2),0)) -> 0 | O10: =IF(A10="","",IFERROR(ROUND(J10/F10,2),0)) -> 250 | P10: =IF(A10="","",IF(N(H10)>0,MAX(0,ROUND(G10-H10,2)),MAX(0,ROUND(G10-I10,2)))) -> 0 | Q10: =IF(A10="","",IFERROR(ROUND(J10/G10*100,2),0)) -> 100 | R10: =IF(A10="","",IF(G10>E10,"Over budget",IF(G10<E10,"Under budget","On budget"))) -> On budget
A11: Okafor work visa | B11: C. Okafor | C11: flat | D11: 14 | E11: 3500 | F11: 16 | G11: 3900 | H11: 3500 | I11: 3500 | J11: 2000 | K11: =IF(A11="","",ROUND(F11-D11,2)) -> 2 | L11: =IF(A11="","",IFERROR(ROUND(K11/D11*100,2),0)) -> 14.29 | M11: =IF(A11="","",ROUND(G11-E11,2)) -> 400 | N11: =IF(A11="","",IFERROR(ROUND(M11/E11*100,2),0)) -> 11.43 | O11: =IF(A11="","",IFERROR(ROUND(J11/F11,2),0)) -> 125 | P11: =IF(A11="","",IF(N(H11)>0,MAX(0,ROUND(G11-H11,2)),MAX(0,ROUND(G11-I11,2)))) -> 400 | Q11: =IF(A11="","",IFERROR(ROUND(J11/G11*100,2),0)) -> 51.28 | R11: =IF(A11="","",IF(G11>E11,"Over budget",IF(G11<E11,"Under budget","On budget"))) -> Over budget
A12: Harbor employment dispute | B12: Harbor Freight Co | C12: hourly | D12: 40 | E12: 10000 | F12: 35 | G12: 8800 | I12: 8000 | J12: 6000 | K12: =IF(A12="","",ROUND(F12-D12,2)) -> -5 | L12: =IF(A12="","",IFERROR(ROUND(K12/D12*100,2),0)) -> -12.5 | M12: =IF(A12="","",ROUND(G12-E12,2)) -> -1200 | N12: =IF(A12="","",IFERROR(ROUND(M12/E12*100,2),0)) -> -12 | O12: =IF(A12="","",IFERROR(ROUND(J12/F12,2),0)) -> 171.43 | P12: =IF(A12="","",IF(N(H12)>0,MAX(0,ROUND(G12-H12,2)),MAX(0,ROUND(G12-I12,2)))) -> 800 | Q12: =IF(A12="","",IFERROR(ROUND(J12/G12*100,2),0)) -> 68.18 | R12: =IF(A12="","",IF(G12>E12,"Over budget",IF(G12<E12,"Under budget","On budget"))) -> Under budget
K13: =IF(A13="","",ROUND(F13-D13,2)) | L13: =IF(A13="","",IFERROR(ROUND(K13/D13*100,2),0)) | M13: =IF(A13="","",ROUND(G13-E13,2)) | N13: =IF(A13="","",IFERROR(ROUND(M13/E13*100,2),0)) | O13: =IF(A13="","",IFERROR(ROUND(J13/F13,2),0)) | P13: =IF(A13="","",IF(N(H13)>0,MAX(0,ROUND(G13-H13,2)),MAX(0,ROUND(G13-I13,2)))) | Q13: =IF(A13="","",IFERROR(ROUND(J13/G13*100,2),0)) | R13: =IF(A13="","",IF(G13>E13,"Over budget",IF(G13<E13,"Under budget","On budget")))
K14: =IF(A14="","",ROUND(F14-D14,2)) | L14: =IF(A14="","",IFERROR(ROUND(K14/D14*100,2),0)) | M14: =IF(A14="","",ROUND(G14-E14,2)) | N14: =IF(A14="","",IFERROR(ROUND(M14/E14*100,2),0)) | O14: =IF(A14="","",IFERROR(ROUND(J14/F14,2),0)) | P14: =IF(A14="","",IF(N(H14)>0,MAX(0,ROUND(G14-H14,2)),MAX(0,ROUND(G14-I14,2)))) | Q14: =IF(A14="","",IFERROR(ROUND(J14/G14*100,2),0)) | R14: =IF(A14="","",IF(G14>E14,"Over budget",IF(G14<E14,"Under budget","On budget")))
K15: =IF(A15="","",ROUND(F15-D15,2)) | L15: =IF(A15="","",IFERROR(ROUND(K15/D15*100,2),0)) | M15: =IF(A15="","",ROUND(G15-E15,2)) | N15: =IF(A15="","",IFERROR(ROUND(M15/E15*100,2),0)) | O15: =IF(A15="","",IFERROR(ROUND(J15/F15,2),0)) | P15: =IF(A15="","",IF(N(H15)>0,MAX(0,ROUND(G15-H15,2)),MAX(0,ROUND(G15-I15,2)))) | Q15: =IF(A15="","",IFERROR(ROUND(J15/G15*100,2),0)) | R15: =IF(A15="","",IF(G15>E15,"Over budget",IF(G15<E15,"Under budget","On budget")))
K16: =IF(A16="","",ROUND(F16-D16,2)) | L16: =IF(A16="","",IFERROR(ROUND(K16/D16*100,2),0)) | M16: =IF(A16="","",ROUND(G16-E16,2)) | N16: =IF(A16="","",IFERROR(ROUND(M16/E16*100,2),0)) | O16: =IF(A16="","",IFERROR(ROUND(J16/F16,2),0)) | P16: =IF(A16="","",IF(N(H16)>0,MAX(0,ROUND(G16-H16,2)),MAX(0,ROUND(G16-I16,2)))) | Q16: =IF(A16="","",IFERROR(ROUND(J16/G16*100,2),0)) | R16: =IF(A16="","",IF(G16>E16,"Over budget",IF(G16<E16,"Under budget","On budget")))
K17: =IF(A17="","",ROUND(F17-D17,2)) | L17: =IF(A17="","",IFERROR(ROUND(K17/D17*100,2),0)) | M17: =IF(A17="","",ROUND(G17-E17,2)) | N17: =IF(A17="","",IFERROR(ROUND(M17/E17*100,2),0)) | O17: =IF(A17="","",IFERROR(ROUND(J17/F17,2),0)) | P17: =IF(A17="","",IF(N(H17)>0,MAX(0,ROUND(G17-H17,2)),MAX(0,ROUND(G17-I17,2)))) | Q17: =IF(A17="","",IFERROR(ROUND(J17/G17*100,2),0)) | R17: =IF(A17="","",IF(G17>E17,"Over budget",IF(G17<E17,"Under budget","On budget")))
K18: =IF(A18="","",ROUND(F18-D18,2)) | L18: =IF(A18="","",IFERROR(ROUND(K18/D18*100,2),0)) | M18: =IF(A18="","",ROUND(G18-E18,2)) | N18: =IF(A18="","",IFERROR(ROUND(M18/E18*100,2),0)) | O18: =IF(A18="","",IFERROR(ROUND(J18/F18,2),0)) | P18: =IF(A18="","",IF(N(H18)>0,MAX(0,ROUND(G18-H18,2)),MAX(0,ROUND(G18-I18,2)))) | Q18: =IF(A18="","",IFERROR(ROUND(J18/G18*100,2),0)) | R18: =IF(A18="","",IF(G18>E18,"Over budget",IF(G18<E18,"Under budget","On budget")))
K19: =IF(A19="","",ROUND(F19-D19,2)) | L19: =IF(A19="","",IFERROR(ROUND(K19/D19*100,2),0)) | M19: =IF(A19="","",ROUND(G19-E19,2)) | N19: =IF(A19="","",IFERROR(ROUND(M19/E19*100,2),0)) | O19: =IF(A19="","",IFERROR(ROUND(J19/F19,2),0)) | P19: =IF(A19="","",IF(N(H19)>0,MAX(0,ROUND(G19-H19,2)),MAX(0,ROUND(G19-I19,2)))) | Q19: =IF(A19="","",IFERROR(ROUND(J19/G19*100,2),0)) | R19: =IF(A19="","",IF(G19>E19,"Over budget",IF(G19<E19,"Under budget","On budget")))
K20: =IF(A20="","",ROUND(F20-D20,2)) | L20: =IF(A20="","",IFERROR(ROUND(K20/D20*100,2),0)) | M20: =IF(A20="","",ROUND(G20-E20,2)) | N20: =IF(A20="","",IFERROR(ROUND(M20/E20*100,2),0)) | O20: =IF(A20="","",IFERROR(ROUND(J20/F20,2),0)) | P20: =IF(A20="","",IF(N(H20)>0,MAX(0,ROUND(G20-H20,2)),MAX(0,ROUND(G20-I20,2)))) | Q20: =IF(A20="","",IFERROR(ROUND(J20/G20*100,2),0)) | R20: =IF(A20="","",IF(G20>E20,"Over budget",IF(G20<E20,"Under budget","On budget")))
K21: =IF(A21="","",ROUND(F21-D21,2)) | L21: =IF(A21="","",IFERROR(ROUND(K21/D21*100,2),0)) | M21: =IF(A21="","",ROUND(G21-E21,2)) | N21: =IF(A21="","",IFERROR(ROUND(M21/E21*100,2),0)) | O21: =IF(A21="","",IFERROR(ROUND(J21/F21,2),0)) | P21: =IF(A21="","",IF(N(H21)>0,MAX(0,ROUND(G21-H21,2)),MAX(0,ROUND(G21-I21,2)))) | Q21: =IF(A21="","",IFERROR(ROUND(J21/G21*100,2),0)) | R21: =IF(A21="","",IF(G21>E21,"Over budget",IF(G21<E21,"Under budget","On budget")))
K22: =IF(A22="","",ROUND(F22-D22,2)) | L22: =IF(A22="","",IFERROR(ROUND(K22/D22*100,2),0)) | M22: =IF(A22="","",ROUND(G22-E22,2)) | N22: =IF(A22="","",IFERROR(ROUND(M22/E22*100,2),0)) | O22: =IF(A22="","",IFERROR(ROUND(J22/F22,2),0)) | P22: =IF(A22="","",IF(N(H22)>0,MAX(0,ROUND(G22-H22,2)),MAX(0,ROUND(G22-I22,2)))) | Q22: =IF(A22="","",IFERROR(ROUND(J22/G22*100,2),0)) | R22: =IF(A22="","",IF(G22>E22,"Over budget",IF(G22<E22,"Under budget","On budget")))
K23: =IF(A23="","",ROUND(F23-D23,2)) | L23: =IF(A23="","",IFERROR(ROUND(K23/D23*100,2),0)) | M23: =IF(A23="","",ROUND(G23-E23,2)) | N23: =IF(A23="","",IFERROR(ROUND(M23/E23*100,2),0)) | O23: =IF(A23="","",IFERROR(ROUND(J23/F23,2),0)) | P23: =IF(A23="","",IF(N(H23)>0,MAX(0,ROUND(G23-H23,2)),MAX(0,ROUND(G23-I23,2)))) | Q23: =IF(A23="","",IFERROR(ROUND(J23/G23*100,2),0)) | R23: =IF(A23="","",IF(G23>E23,"Over budget",IF(G23<E23,"Under budget","On budget")))
K24: =IF(A24="","",ROUND(F24-D24,2)) | L24: =IF(A24="","",IFERROR(ROUND(K24/D24*100,2),0)) | M24: =IF(A24="","",ROUND(G24-E24,2)) | N24: =IF(A24="","",IFERROR(ROUND(M24/E24*100,2),0)) | O24: =IF(A24="","",IFERROR(ROUND(J24/F24,2),0)) | P24: =IF(A24="","",IF(N(H24)>0,MAX(0,ROUND(G24-H24,2)),MAX(0,ROUND(G24-I24,2)))) | Q24: =IF(A24="","",IFERROR(ROUND(J24/G24*100,2),0)) | R24: =IF(A24="","",IF(G24>E24,"Over budget",IF(G24<E24,"Under budget","On budget")))
... K34: =IF(A34="","",ROUND(F34-D34,2)) | L34: =IF(A34="","",IFERROR(ROUND(K34/D34*100,2),0)) | M34: =IF(A34="","",ROUND(G34-E34,2)) | N34: =IF(A34="","",IFERROR(ROUND(M34/E34*100,2),0)) | O34: =IF(A34="","",IFERROR(ROUND(J34/F34,2),0)) | P34: =IF(A34="","",IF(N(H34)>0,MAX(0,ROUND(G34-H34,2)),MAX(0,ROUND(G34-I34,2)))) | Q34: =IF(A34="","",IFERROR(ROUND(J34/G34*100,2),0)) | R34: =IF(A34="","",IF(G34>E34,"Over budget",IF(G34<E34,"Under budget","On budget")))
A35: Total | B35: =COUNTA(A5:A34) -> 8 | D35: =SUM(D5:D34) -> 242 | E35: =SUM(E5:E34) -> 59300 | F35: =SUM(F5:F34) -> 266 | G35: =SUM(G5:G34) -> 66150 | H35: =SUM(H5:H34) -> 40400 | I35: =SUM(I5:I34) -> 72500 | J35: =SUM(J5:J34) -> 66600 | K35: =SUM(K5:K34) -> 24 | L35: =IFERROR(ROUND(K35/D35*100,2),0) -> 9.92 | M35: =SUM(M5:M34) -> 6850 | N35: =IFERROR(ROUND(M35/E35*100,2),0) -> 11.55 | O35: =IFERROR(ROUND(J35/F35,2),0) -> 250.38 | P35: =SUM(P5:P34) -> 3500 | Q35: =IFERROR(ROUND(J35/G35*100,2),0) -> 100.68

Sheet Lock-Up & Contingency
A1: Lock-Up & Contingency
A2: Lock-up: one row per month, filled top down, from your month-end WIP and debtors reports.
A4: Month | B4: Unbilled WIP | C4: Accounts receivable | D4: Fees billed, trailing 12 months | E4: Fees per day | F4: WIP days | G4: Debtor days | H4: Lock-up days | I4: Locked-up cash | J4: Cash per day of lock-up | K4: Change in lock-up days vs previous month
A5: 46023 | B5: 180000 | C5: 220000 | D5: 1800000 | E5: =IF(A5="","",IFERROR(ROUND(D5/Settings!$B$14,2),0)) -> 4931.51 | F5: =IF(A5="","",IFERROR(ROUND(B5/E5,2),0)) -> 36.5 | G5: =IF(A5="","",IFERROR(ROUND(C5/E5,2),0)) -> 44.61 | H5: =IF(A5="","",F5+G5) -> 81.11 | I5: =IF(A5="","",B5+C5) -> 400000 | J5: =IF(A5="","",IFERROR(ROUND(I5/H5,2),0)) -> 4931.57 | K5: =""
A6: 46054 | B6: 175000 | C6: 230000 | D6: 1820000 | E6: =IF(A6="","",IFERROR(ROUND(D6/Settings!$B$14,2),0)) -> 4986.3 | F6: =IF(A6="","",IFERROR(ROUND(B6/E6,2),0)) -> 35.1 | G6: =IF(A6="","",IFERROR(ROUND(C6/E6,2),0)) -> 46.13 | H6: =IF(A6="","",F6+G6) -> 81.23 | I6: =IF(A6="","",B6+C6) -> 405000 | J6: =IF(A6="","",IFERROR(ROUND(I6/H6,2),0)) -> 4985.84 | K6: =IF(OR(A6="",A5=""),"",ROUND(H6-H5,2)) -> 0.12
A7: 46082 | B7: 170000 | C7: 210000 | D7: 1830000 | E7: =IF(A7="","",IFERROR(ROUND(D7/Settings!$B$14,2),0)) -> 5013.7 | F7: =IF(A7="","",IFERROR(ROUND(B7/E7,2),0)) -> 33.91 | G7: =IF(A7="","",IFERROR(ROUND(C7/E7,2),0)) -> 41.89 | H7: =IF(A7="","",F7+G7) -> 75.8 | I7: =IF(A7="","",B7+C7) -> 380000 | J7: =IF(A7="","",IFERROR(ROUND(I7/H7,2),0)) -> 5013.19 | K7: =IF(OR(A7="",A6=""),"",ROUND(H7-H6,2)) -> -5.43
A8: 46113 | B8: 160000 | C8: 205000 | D8: 1850000 | E8: =IF(A8="","",IFERROR(ROUND(D8/Settings!$B$14,2),0)) -> 5068.49 | F8: =IF(A8="","",IFERROR(ROUND(B8/E8,2),0)) -> 31.57 | G8: =IF(A8="","",IFERROR(ROUND(C8/E8,2),0)) -> 40.45 | H8: =IF(A8="","",F8+G8) -> 72.02 | I8: =IF(A8="","",B8+C8) -> 365000 | J8: =IF(A8="","",IFERROR(ROUND(I8/H8,2),0)) -> 5068.04 | K8: =IF(OR(A8="",A7=""),"",ROUND(H8-H7,2)) -> -3.78
A9: 46143 | B9: 165000 | C9: 195000 | D9: 1860000 | E9: =IF(A9="","",IFERROR(ROUND(D9/Settings!$B$14,2),0)) -> 5095.89 | F9: =IF(A9="","",IFERROR(ROUND(B9/E9,2),0)) -> 32.38 | G9: =IF(A9="","",IFERROR(ROUND(C9/E9,2),0)) -> 38.27 | H9: =IF(A9="","",F9+G9) -> 70.65 | I9: =IF(A9="","",B9+C9) -> 360000 | J9: =IF(A9="","",IFERROR(ROUND(I9/H9,2),0)) -> 5095.54 | K9: =IF(OR(A9="",A8=""),"",ROUND(H9-H8,2)) -> -1.37
A10: 46174 | B10: 150000 | C10: 190000 | D10: 1880000 | E10: =IF(A10="","",IFERROR(ROUND(D10/Settings!$B$14,2),0)) -> 5150.68 | F10: =IF(A10="","",IFERROR(ROUND(B10/E10,2),0)) -> 29.12 | G10: =IF(A10="","",IFERROR(ROUND(C10/E10,2),0)) -> 36.89 | H10: =IF(A10="","",F10+G10) -> 66.01 | I10: =IF(A10="","",B10+C10) -> 340000 | J10: =IF(A10="","",IFERROR(ROUND(I10/H10,2),0)) -> 5150.73 | K10: =IF(OR(A10="",A9=""),"",ROUND(H10-H9,2)) -> -4.64
E11: =IF(A11="","",IFERROR(ROUND(D11/Settings!$B$14,2),0)) | F11: =IF(A11="","",IFERROR(ROUND(B11/E11,2),0)) | G11: =IF(A11="","",IFERROR(ROUND(C11/E11,2),0)) | H11: =IF(A11="","",F11+G11) | I11: =IF(A11="","",B11+C11) | J11: =IF(A11="","",IFERROR(ROUND(I11/H11,2),0)) | K11: =IF(OR(A11="",A10=""),"",ROUND(H11-H10,2))
E12: =IF(A12="","",IFERROR(ROUND(D12/Settings!$B$14,2),0)) | F12: =IF(A12="","",IFERROR(ROUND(B12/E12,2),0)) | G12: =IF(A12="","",IFERROR(ROUND(C12/E12,2),0)) | H12: =IF(A12="","",F12+G12) | I12: =IF(A12="","",B12+C12) | J12: =IF(A12="","",IFERROR(ROUND(I12/H12,2),0)) | K12: =IF(OR(A12="",A11=""),"",ROUND(H12-H11,2))
E13: =IF(A13="","",IFERROR(ROUND(D13/Settings!$B$14,2),0)) | F13: =IF(A13="","",IFERROR(ROUND(B13/E13,2),0)) | G13: =IF(A13="","",IFERROR(ROUND(C13/E13,2),0)) | H13: =IF(A13="","",F13+G13) | I13: =IF(A13="","",B13+C13) | J13: =IF(A13="","",IFERROR(ROUND(I13/H13,2),0)) | K13: =IF(OR(A13="",A12=""),"",ROUND(H13-H12,2))
E14: =IF(A14="","",IFERROR(ROUND(D14/Settings!$B$14,2),0)) | F14: =IF(A14="","",IFERROR(ROUND(B14/E14,2),0)) | G14: =IF(A14="","",IFERROR(ROUND(C14/E14,2),0)) | H14: =IF(A14="","",F14+G14) | I14: =IF(A14="","",B14+C14) | J14: =IF(A14="","",IFERROR(ROUND(I14/H14,2),0)) | K14: =IF(OR(A14="",A13=""),"",ROUND(H14-H13,2))
E15: =IF(A15="","",IFERROR(ROUND(D15/Settings!$B$14,2),0)) | F15: =IF(A15="","",IFERROR(ROUND(B15/E15,2),0)) | G15: =IF(A15="","",IFERROR(ROUND(C15/E15,2),0)) | H15: =IF(A15="","",F15+G15) | I15: =IF(A15="","",B15+C15) | J15: =IF(A15="","",IFERROR(ROUND(I15/H15,2),0)) | K15: =IF(OR(A15="",A14=""),"",ROUND(H15-H14,2))
E16: =IF(A16="","",IFERROR(ROUND(D16/Settings!$B$14,2),0)) | F16: =IF(A16="","",IFERROR(ROUND(B16/E16,2),0)) | G16: =IF(A16="","",IFERROR(ROUND(C16/E16,2),0)) | H16: =IF(A16="","",F16+G16) | I16: =IF(A16="","",B16+C16) | J16: =IF(A16="","",IFERROR(ROUND(I16/H16,2),0)) | K16: =IF(OR(A16="",A15=""),"",ROUND(H16-H15,2))
A19: Contingency matters
A20: Referral fee % defaults from Settings; type your own in column G to override it. Whether costs come off before the fee, and any referral fee, depend on your agreement and your rules.
A21: Matter | B21: Settlement amount | C21: Contingency % | D21: Case costs | E21: Costs deducted before fee | F21: Default referral fee % (Settings) | G21: or type your own referral % | H21: Referral fee % used | I21: Hours worked | J21: Fee base | K21: Gross fee | L21: Referral fee | M21: Net fee to firm | N21: Net to client | O21: Effective hourly rate
A22: Garcia injury claim | B22: 120000 | C22: 30 | D22: 8000 | E22: yes | F22: =IF(A22="","",Settings!$B$15) -> 0 | H22: =IF(A22="","",IF(G22<>"",G22,F22)) -> 0 | I22: 95 | J22: =IF(A22="","",IF(E22="yes",B22-D22,B22)) -> 112000 | K22: =IF(A22="","",ROUND(J22*C22/100,2)) -> 33600 | L22: =IF(A22="","",ROUND(K22*H22/100,2)) -> 0 | M22: =IF(A22="","",K22-L22) -> 33600 | N22: =IF(A22="","",ROUND(B22-K22-D22,2)) -> 78400 | O22: =IF(A22="","",IFERROR(ROUND(M22/I22,2),0)) -> 353.68
A23: Nguyen slip and fall | B23: 45000 | C23: 33.33 | D23: 3000 | E23: no | F23: =IF(A23="","",Settings!$B$15) -> 0 | G23: 25 | H23: =IF(A23="","",IF(G23<>"",G23,F23)) -> 25 | I23: 60 | J23: =IF(A23="","",IF(E23="yes",B23-D23,B23)) -> 45000 | K23: =IF(A23="","",ROUND(J23*C23/100,2)) -> 14998.5 | L23: =IF(A23="","",ROUND(K23*H23/100,2)) -> 3749.63 | M23: =IF(A23="","",K23-L23) -> 11248.87 | N23: =IF(A23="","",ROUND(B23-K23-D23,2)) -> 27001.5 | O23: =IF(A23="","",IFERROR(ROUND(M23/I23,2),0)) -> 187.48
A24: Delta product claim | B24: 250000 | C24: 25 | D24: 22000 | E24: yes | F24: =IF(A24="","",Settings!$B$15) -> 0 | H24: =IF(A24="","",IF(G24<>"",G24,F24)) -> 0 | I24: 310 | J24: =IF(A24="","",IF(E24="yes",B24-D24,B24)) -> 228000 | K24: =IF(A24="","",ROUND(J24*C24/100,2)) -> 57000 | L24: =IF(A24="","",ROUND(K24*H24/100,2)) -> 0 | M24: =IF(A24="","",K24-L24) -> 57000 | N24: =IF(A24="","",ROUND(B24-K24-D24,2)) -> 171000 | O24: =IF(A24="","",IFERROR(ROUND(M24/I24,2),0)) -> 183.87
F25: =IF(A25="","",Settings!$B$15) | H25: =IF(A25="","",IF(G25<>"",G25,F25)) | J25: =IF(A25="","",IF(E25="yes",B25-D25,B25)) | K25: =IF(A25="","",ROUND(J25*C25/100,2)) | L25: =IF(A25="","",ROUND(K25*H25/100,2)) | M25: =IF(A25="","",K25-L25) | N25: =IF(A25="","",ROUND(B25-K25-D25,2)) | O25: =IF(A25="","",IFERROR(ROUND(M25/I25,2),0))
F26: =IF(A26="","",Settings!$B$15) | H26: =IF(A26="","",IF(G26<>"",G26,F26)) | J26: =IF(A26="","",IF(E26="yes",B26-D26,B26)) | K26: =IF(A26="","",ROUND(J26*C26/100,2)) | L26: =IF(A26="","",ROUND(K26*H26/100,2)) | M26: =IF(A26="","",K26-L26) | N26: =IF(A26="","",ROUND(B26-K26-D26,2)) | O26: =IF(A26="","",IFERROR(ROUND(M26/I26,2),0))
F27: =IF(A27="","",Settings!$B$15) | H27: =IF(A27="","",IF(G27<>"",G27,F27)) | J27: =IF(A27="","",IF(E27="yes",B27-D27,B27)) | K27: =IF(A27="","",ROUND(J27*C27/100,2)) | L27: =IF(A27="","",ROUND(K27*H27/100,2)) | M27: =IF(A27="","",K27-L27) | N27: =IF(A27="","",ROUND(B27-K27-D27,2)) | O27: =IF(A27="","",IFERROR(ROUND(M27/I27,2),0))
F28: =IF(A28="","",Settings!$B$15) | H28: =IF(A28="","",IF(G28<>"",G28,F28)) | J28: =IF(A28="","",IF(E28="yes",B28-D28,B28)) | K28: =IF(A28="","",ROUND(J28*C28/100,2)) | L28: =IF(A28="","",ROUND(K28*H28/100,2)) | M28: =IF(A28="","",K28-L28) | N28: =IF(A28="","",ROUND(B28-K28-D28,2)) | O28: =IF(A28="","",IFERROR(ROUND(M28/I28,2),0))
F29: =IF(A29="","",Settings!$B$15) | H29: =IF(A29="","",IF(G29<>"",G29,F29)) | J29: =IF(A29="","",IF(E29="yes",B29-D29,B29)) | K29: =IF(A29="","",ROUND(J29*C29/100,2)) | L29: =IF(A29="","",ROUND(K29*H29/100,2)) | M29: =IF(A29="","",K29-L29) | N29: =IF(A29="","",ROUND(B29-K29-D29,2)) | O29: =IF(A29="","",IFERROR(ROUND(M29/I29,2),0))
F30: =IF(A30="","",Settings!$B$15) | H30: =IF(A30="","",IF(G30<>"",G30,F30)) | J30: =IF(A30="","",IF(E30="yes",B30-D30,B30)) | K30: =IF(A30="","",ROUND(J30*C30/100,2)) | L30: =IF(A30="","",ROUND(K30*H30/100,2)) | M30: =IF(A30="","",K30-L30) | N30: =IF(A30="","",ROUND(B30-K30-D30,2)) | O30: =IF(A30="","",IFERROR(ROUND(M30/I30,2),0))
F31: =IF(A31="","",Settings!$B$15) | H31: =IF(A31="","",IF(G31<>"",G31,F31)) | J31: =IF(A31="","",IF(E31="yes",B31-D31,B31)) | K31: =IF(A31="","",ROUND(J31*C31/100,2)) | L31: =IF(A31="","",ROUND(K31*H31/100,2)) | M31: =IF(A31="","",K31-L31) | N31: =IF(A31="","",ROUND(B31-K31-D31,2)) | O31: =IF(A31="","",IFERROR(ROUND(M31/I31,2),0))
A32: Total | B32: =SUM(B22:B31) -> 415000 | D32: =SUM(D22:D31) -> 33000 | I32: =SUM(I22:I31) -> 465 | K32: =SUM(K22:K31) -> 105598.5 | L32: =SUM(L22:L31) -> 3749.63 | M32: =SUM(M22:M31) -> 101848.87 | N32: =SUM(N22:N31) -> 276401.5 | O32: =IFERROR(ROUND(M32/I32,2),0) -> 219.03

Sheet Summary
A1: Summary
A2: Timekeepers | B2: =Settings!$B$17 -> 6 | C2: from Settings
A3: Average cost rate | B3: =IFERROR(ROUND(AVERAGE(Timekeepers!$N$5:$N$24),2),0) -> 113.29 | C3: simple average of the timekeeper cost rates
A4: Average bill rate | B4: =IFERROR(ROUND(AVERAGE(Timekeepers!$J$5:$J$24),2),0) -> 291.67 | C4: simple average of the timekeeper bill rates
A5: Timekeepers with negative margin | B5: =COUNTIF(Timekeepers!$O$5:$O$24,"<0") -> 0 | C5: bill rate below cost rate
A6: Total annual cost of timekeepers | B6: =Timekeepers!M25 -> 962250.02 | C6: loaded salaries + overhead
A7: Flat fee matters priced below the computed fee | B7: =COUNTIF('Flat Fee Pricer'!$T$5:$T$24,"<0") -> 1 | C7: current fee below the flat fee at your target margin
A8: Monthly uplift at the computed fee | B8: =-SUMIF('Flat Fee Pricer'!$T$5:$T$24,"<0",'Flat Fee Pricer'!$T$5:$T$24) -> 509.69 | C8: assumes each under-priced matter is sold once a month
A9: Matters over budget | B9: =COUNTIF('Matter Tracker'!$R$5:$R$34,"Over budget") -> 4 | C9: actual fees above budget fees
A10: Total write-offs | B10: ='Matter Tracker'!P35 -> 3500 | C10: Matter Tracker totals
A11: Overall recovery % | B11: ='Matter Tracker'!Q35 -> 100.68 | C11: collected ÷ actual fees, from the totals
A12: Latest lock-up days | B12: =IFERROR(INDEX('Lock-Up & Contingency'!$H$5:$H$16,MATCH(MAX('Lock-Up & Contingency'!$A$5:$A$16),'Lock-Up & Contingency'!$A$5:$A$16,0)),0) -> 66.01 | C12: the most recent month on Lock-Up & Contingency
A13: Latest locked-up cash | B13: =IFERROR(INDEX('Lock-Up & Contingency'!$I$5:$I$16,MATCH(MAX('Lock-Up & Contingency'!$A$5:$A$16),'Lock-Up & Contingency'!$A$5:$A$16,0)),0) -> 340000 | C13: unbilled WIP + accounts receivable
A14: Change in lock-up days vs first month | B14: =IFERROR(ROUND(B12-'Lock-Up & Contingency'!H5,2),0) -> -15.1 | C14: negative = cash is coming in faster
A15: Total net contingency fees to firm | B15: ='Lock-Up & Contingency'!M32 -> 101848.87 | C15: after referral fees
A16: Average effective hourly rate on contingency matters | B16: ='Lock-Up & Contingency'!O32 -> 219.03 | C16: total net fee ÷ total hours worked
