Workbook

Sheet Start Here
A1: Home Care Agency Pricing Workbook
A2: by Knackdesk · knackdesk.com
A4: HOW TO USE
A5: 1. Settings: default caregiver pay rate, on-costs %, non-billable paid hours %, six monthly overhead lines, your target margin % on the bill rate, weekend uplift %, overnight rate, mileage rate, hours per caregiver per week, your target utilization % and weeks per quote period. Loaded pay rate, labour cost and overhead per billable hour, cost per billable hour and the default bill rate at your target margin follow and every other sheet reads them.
A6: 2. Service Rates: one row per service level (companion, personal care, dementia care, respite, live-in and your own), with pay rate, on-costs % and margin % (defaults from Settings, type your own to override) and the bill rate you charge today. Cost per billable hour, the bill rate at your margin, margin per hour and the gap between what you charge and the computed rate are calculated.
A7: 3. Caregivers: one row per caregiver with status (active, on leave, left), paid hours, billable hours, travel hours and training hours per week, and pay rate (default from Settings, type your own to override). Non-billable hours, utilization %, other non-billable hours, the weekly cost of non-billable time and the gap to your target utilization are calculated, with totals for active caregivers.
A8: 4. Clients & Quotes: one row per client or quote with service level, hours per week, weekend hours, overnight hours, miles per week, weeks (default from Settings, type your own to override) and status (active, pending, ended). The bill rate is looked up from Service Rates; standard, weekend, overnight and mileage charges, the weekly and period total and the effective hourly rate are calculated, with totals for active clients.
A9: 5. Capacity & Turnover: the top block compares the hours your active caregivers can bill at your target utilization with the hours committed to active clients, and shows spare hours, weekly revenue committed and the revenue ceiling. The lower block takes one row per month with caregivers at the start, leavers, hires, recruiting cost, onboarding hours, trainer cost per hour, unfilled hours and margin per billable hour (defaults you can override), and calculates turnover %, turnover cost, cost per leaver and caregivers at the end.
A10: 6. Summary: cost per billable hour, default bill rate, service levels priced below the computed rate, active caregivers and utilization against your target, active clients, hours committed and spare hours, weekly and period revenue committed, year-to-date leavers, turnover % and turnover cost, and the client with the highest weekly total.
A12: LEGEND
A13: Blue text = a cell you type into. Black text = a formula, leave it alone. Yellow fill = key inputs.
A15: DEFINITIONS
... A27: Arithmetic only; not financial or care advice.

Sheet Settings
A1: Settings
A2: Default caregiver pay rate (per hour) | B2: 16 | C2: Example default 16.00 an hour. What you pay a caregiver per hour before on-costs; each service level and caregiver can override it.
A3: On-costs % | B3: 22 | C3: Default 22. Employer payroll taxes, workers' compensation, holiday pay and payroll fees on top of pay; each service level can override it.
A4: Non-billable paid % of billable hours | B4: 10 | C4: Default 10. Paid travel, training, supervision and waiting time, as a % of billable hours.
A5: Overhead: office (monthly) | B5: 1200 | C5: Example default 1,200 a month. Rent, utilities, phones and office supplies.
A6: Overhead: scheduling software (monthly) | B6: 300 | C6: Example default 300 a month. Scheduling, visit verification and care management software.
A7: Overhead: insurance (monthly) | B7: 900 | C7: Example default 900 a month. Liability, bonding and other business insurance.
A8: Overhead: recruiting and training (monthly) | B8: 1000 | C8: Example default 1,000 a month. Job ads, background checks and ongoing training not costed on Capacity & Turnover.
A9: Overhead: management salaries (monthly) | B9: 3500 | C9: Example default 3,500 a month. Owner, care manager, scheduler and office staff pay, loaded.
A10: Overhead: other (monthly) | B10: 700 | C10: Example default 700 a month. Accounting, marketing, licences and everything else.
A11: Total monthly overhead | B11: =SUM(B5:B10) -> 7600 | C11: formula: sum of the six overhead lines above
A12: Target margin % on bill rate (your own) | B12: 25 | C12: Default 25. Your own placeholder, not a recommendation or an industry benchmark; each service level can override it.
A13: Weekend uplift % | B13: 15 | C13: Default 15. Added to the bill rate for weekend hours on Clients & Quotes.
A14: Overnight rate (per overnight hour) | B14: 20 | C14: Example default 20.00 an hour. Flat rate billed per overnight hour on Clients & Quotes; type 0 if you do not offer overnight care.
A15: Mileage rate (per mile) | B15: 0.5 | C15: Default 0.50 a mile. Charged to the client for miles driven on their errands or visits.
A16: Hours per caregiver per week | B16: 32 | C16: Default 32. Planned paid hours per active caregiver, used for capacity on Capacity & Turnover.
A17: Target utilization % (your own) | B17: 85 | C17: Default 85. Your own placeholder, not a recommendation or an industry benchmark; the share of paid hours you plan to bill.
A18: Weeks per period | B18: 4 | C18: Default 4. Weeks in a quote or billing period on Clients & Quotes; each client can override it.
A19: Loaded pay rate | B19: =ROUND(B2*(1+B3/100),2) -> 19.52 | C19: formula: pay rate × (1 + on-costs %)
A20: Labour cost per billable hour | B20: =ROUND(B19*(1+B4/100),2) -> 21.47 | C20: formula: loaded pay rate × (1 + non-billable paid %)
A21: Planned billable hours per month | B21: =ROUND(Caregivers!$D$35*52/12,2) -> 1196 | C21: formula: billable hours per week of active caregivers (Caregivers totals) × 52 ÷ 12
A22: Overhead per billable hour | B22: =IFERROR(ROUND(B11/B21,2),0) -> 6.35 | C22: formula: total monthly overhead ÷ planned billable hours per month
A23: Cost per billable hour | B23: =ROUND(B20+B22,2) -> 27.82 | C23: formula: labour cost per billable hour + overhead per billable hour
A24: Default bill rate at target margin | B24: =IFERROR(ROUND(B23/(1-B12/100),2),0) -> 37.09 | C24: formula: cost per billable hour ÷ (1 − target margin %)

Sheet Service Rates
A1: Service Rates
A2: One row per service level. Pay rate, on-costs % and margin % default from Settings; type your own to override them. Type the bill rate you charge today to see the gap to the computed rate.
A4: Service level | B4: Default pay rate (Settings) | C4: or type your own pay rate | D4: Pay rate used | E4: Default on-costs % (Settings) | F4: or type your own on-costs % | G4: On-costs % used | H4: Default margin % (Settings) | I4: or type your own margin % | J4: Margin % used | K4: Loaded pay rate | L4: Labour cost per billable hour | M4: Overhead per billable hour | N4: Cost per billable hour | O4: Bill rate at margin | P4: Margin per hour | Q4: Current bill rate charged | R4: Gap (current − computed)
A5: Companion | B5: =IF(A5="","",Settings!$B$2) -> 16 | C5: 15 | D5: =IF(A5="","",IF(C5<>"",C5,B5)) -> 15 | E5: =IF(A5="","",Settings!$B$3) -> 22 | G5: =IF(A5="","",IF(F5<>"",F5,E5)) -> 22 | H5: =IF(A5="","",Settings!$B$12) -> 25 | J5: =IF(A5="","",IF(I5<>"",I5,H5)) -> 25 | K5: =IF(A5="","",ROUND(D5*(1+G5/100),2)) -> 18.3 | L5: =IF(A5="","",ROUND(K5*(1+Settings!$B$4/100),2)) -> 20.13 | M5: =IF(A5="","",Settings!$B$22) -> 6.35 | N5: =IF(A5="","",ROUND(L5+M5,2)) -> 26.48 | O5: =IF(A5="","",IFERROR(ROUND(N5/(1-J5/100),2),0)) -> 35.31 | P5: =IF(A5="","",ROUND(O5-N5,2)) -> 8.83 | Q5: 36 | R5: =IF(OR(A5="",Q5=""),"",ROUND(Q5-O5,2)) -> 0.69
A6: Personal care | B6: =IF(A6="","",Settings!$B$2) -> 16 | D6: =IF(A6="","",IF(C6<>"",C6,B6)) -> 16 | E6: =IF(A6="","",Settings!$B$3) -> 22 | G6: =IF(A6="","",IF(F6<>"",F6,E6)) -> 22 | H6: =IF(A6="","",Settings!$B$12) -> 25 | J6: =IF(A6="","",IF(I6<>"",I6,H6)) -> 25 | K6: =IF(A6="","",ROUND(D6*(1+G6/100),2)) -> 19.52 | L6: =IF(A6="","",ROUND(K6*(1+Settings!$B$4/100),2)) -> 21.47 | M6: =IF(A6="","",Settings!$B$22) -> 6.35 | N6: =IF(A6="","",ROUND(L6+M6,2)) -> 27.82 | O6: =IF(A6="","",IFERROR(ROUND(N6/(1-J6/100),2),0)) -> 37.09 | P6: =IF(A6="","",ROUND(O6-N6,2)) -> 9.27 | Q6: 38 | R6: =IF(OR(A6="",Q6=""),"",ROUND(Q6-O6,2)) -> 0.91
A7: Dementia care | B7: =IF(A7="","",Settings!$B$2) -> 16 | C7: 18 | D7: =IF(A7="","",IF(C7<>"",C7,B7)) -> 18 | E7: =IF(A7="","",Settings!$B$3) -> 22 | G7: =IF(A7="","",IF(F7<>"",F7,E7)) -> 22 | H7: =IF(A7="","",Settings!$B$12) -> 25 | I7: 28 | J7: =IF(A7="","",IF(I7<>"",I7,H7)) -> 28 | K7: =IF(A7="","",ROUND(D7*(1+G7/100),2)) -> 21.96 | L7: =IF(A7="","",ROUND(K7*(1+Settings!$B$4/100),2)) -> 24.16 | M7: =IF(A7="","",Settings!$B$22) -> 6.35 | N7: =IF(A7="","",ROUND(L7+M7,2)) -> 30.51 | O7: =IF(A7="","",IFERROR(ROUND(N7/(1-J7/100),2),0)) -> 42.38 | P7: =IF(A7="","",ROUND(O7-N7,2)) -> 11.87 | Q7: 44 | R7: =IF(OR(A7="",Q7=""),"",ROUND(Q7-O7,2)) -> 1.62
A8: Respite | B8: =IF(A8="","",Settings!$B$2) -> 16 | D8: =IF(A8="","",IF(C8<>"",C8,B8)) -> 16 | E8: =IF(A8="","",Settings!$B$3) -> 22 | G8: =IF(A8="","",IF(F8<>"",F8,E8)) -> 22 | H8: =IF(A8="","",Settings!$B$12) -> 25 | J8: =IF(A8="","",IF(I8<>"",I8,H8)) -> 25 | K8: =IF(A8="","",ROUND(D8*(1+G8/100),2)) -> 19.52 | L8: =IF(A8="","",ROUND(K8*(1+Settings!$B$4/100),2)) -> 21.47 | M8: =IF(A8="","",Settings!$B$22) -> 6.35 | N8: =IF(A8="","",ROUND(L8+M8,2)) -> 27.82 | O8: =IF(A8="","",IFERROR(ROUND(N8/(1-J8/100),2),0)) -> 37.09 | P8: =IF(A8="","",ROUND(O8-N8,2)) -> 9.27 | Q8: 34 | R8: =IF(OR(A8="",Q8=""),"",ROUND(Q8-O8,2)) -> -3.09
A9: Live-in | B9: =IF(A9="","",Settings!$B$2) -> 16 | C9: 14 | D9: =IF(A9="","",IF(C9<>"",C9,B9)) -> 14 | E9: =IF(A9="","",Settings!$B$3) -> 22 | G9: =IF(A9="","",IF(F9<>"",F9,E9)) -> 22 | H9: =IF(A9="","",Settings!$B$12) -> 25 | J9: =IF(A9="","",IF(I9<>"",I9,H9)) -> 25 | K9: =IF(A9="","",ROUND(D9*(1+G9/100),2)) -> 17.08 | L9: =IF(A9="","",ROUND(K9*(1+Settings!$B$4/100),2)) -> 18.79 | M9: =IF(A9="","",Settings!$B$22) -> 6.35 | N9: =IF(A9="","",ROUND(L9+M9,2)) -> 25.14 | O9: =IF(A9="","",IFERROR(ROUND(N9/(1-J9/100),2),0)) -> 33.52 | P9: =IF(A9="","",ROUND(O9-N9,2)) -> 8.38 | Q9: 34 | R9: =IF(OR(A9="",Q9=""),"",ROUND(Q9-O9,2)) -> 0.48
A10: Other | B10: =IF(A10="","",Settings!$B$2) -> 16 | D10: =IF(A10="","",IF(C10<>"",C10,B10)) -> 16 | E10: =IF(A10="","",Settings!$B$3) -> 22 | G10: =IF(A10="","",IF(F10<>"",F10,E10)) -> 22 | H10: =IF(A10="","",Settings!$B$12) -> 25 | J10: =IF(A10="","",IF(I10<>"",I10,H10)) -> 25 | K10: =IF(A10="","",ROUND(D10*(1+G10/100),2)) -> 19.52 | L10: =IF(A10="","",ROUND(K10*(1+Settings!$B$4/100),2)) -> 21.47 | M10: =IF(A10="","",Settings!$B$22) -> 6.35 | N10: =IF(A10="","",ROUND(L10+M10,2)) -> 27.82 | O10: =IF(A10="","",IFERROR(ROUND(N10/(1-J10/100),2),0)) -> 37.09 | P10: =IF(A10="","",ROUND(O10-N10,2)) -> 9.27 | R10: =IF(OR(A10="",Q10=""),"",ROUND(Q10-O10,2))
B11: =IF(A11="","",Settings!$B$2) | D11: =IF(A11="","",IF(C11<>"",C11,B11)) | E11: =IF(A11="","",Settings!$B$3) | G11: =IF(A11="","",IF(F11<>"",F11,E11)) | H11: =IF(A11="","",Settings!$B$12) | J11: =IF(A11="","",IF(I11<>"",I11,H11)) | K11: =IF(A11="","",ROUND(D11*(1+G11/100),2)) | L11: =IF(A11="","",ROUND(K11*(1+Settings!$B$4/100),2)) | M11: =IF(A11="","",Settings!$B$22) | N11: =IF(A11="","",ROUND(L11+M11,2)) | O11: =IF(A11="","",IFERROR(ROUND(N11/(1-J11/100),2),0)) | P11: =IF(A11="","",ROUND(O11-N11,2)) | R11: =IF(OR(A11="",Q11=""),"",ROUND(Q11-O11,2))
B12: =IF(A12="","",Settings!$B$2) | D12: =IF(A12="","",IF(C12<>"",C12,B12)) | E12: =IF(A12="","",Settings!$B$3) | G12: =IF(A12="","",IF(F12<>"",F12,E12)) | H12: =IF(A12="","",Settings!$B$12) | J12: =IF(A12="","",IF(I12<>"",I12,H12)) | K12: =IF(A12="","",ROUND(D12*(1+G12/100),2)) | L12: =IF(A12="","",ROUND(K12*(1+Settings!$B$4/100),2)) | M12: =IF(A12="","",Settings!$B$22) | N12: =IF(A12="","",ROUND(L12+M12,2)) | O12: =IF(A12="","",IFERROR(ROUND(N12/(1-J12/100),2),0)) | P12: =IF(A12="","",ROUND(O12-N12,2)) | R12: =IF(OR(A12="",Q12=""),"",ROUND(Q12-O12,2))
B13: =IF(A13="","",Settings!$B$2) | D13: =IF(A13="","",IF(C13<>"",C13,B13)) | E13: =IF(A13="","",Settings!$B$3) | G13: =IF(A13="","",IF(F13<>"",F13,E13)) | H13: =IF(A13="","",Settings!$B$12) | J13: =IF(A13="","",IF(I13<>"",I13,H13)) | K13: =IF(A13="","",ROUND(D13*(1+G13/100),2)) | L13: =IF(A13="","",ROUND(K13*(1+Settings!$B$4/100),2)) | M13: =IF(A13="","",Settings!$B$22) | N13: =IF(A13="","",ROUND(L13+M13,2)) | O13: =IF(A13="","",IFERROR(ROUND(N13/(1-J13/100),2),0)) | P13: =IF(A13="","",ROUND(O13-N13,2)) | R13: =IF(OR(A13="",Q13=""),"",ROUND(Q13-O13,2))
B14: =IF(A14="","",Settings!$B$2) | D14: =IF(A14="","",IF(C14<>"",C14,B14)) | E14: =IF(A14="","",Settings!$B$3) | G14: =IF(A14="","",IF(F14<>"",F14,E14)) | H14: =IF(A14="","",Settings!$B$12) | J14: =IF(A14="","",IF(I14<>"",I14,H14)) | K14: =IF(A14="","",ROUND(D14*(1+G14/100),2)) | L14: =IF(A14="","",ROUND(K14*(1+Settings!$B$4/100),2)) | M14: =IF(A14="","",Settings!$B$22) | N14: =IF(A14="","",ROUND(L14+M14,2)) | O14: =IF(A14="","",IFERROR(ROUND(N14/(1-J14/100),2),0)) | P14: =IF(A14="","",ROUND(O14-N14,2)) | R14: =IF(OR(A14="",Q14=""),"",ROUND(Q14-O14,2))

Sheet Caregivers
A1: Caregivers
A2: One row per caregiver, with typical weekly hours. Pay rate defaults from Settings; type your own to override it. Totals count active caregivers only.
A4: Caregiver | B4: Status | C4: Paid hours per week | D4: Billable hours per week | E4: Travel hours per week | F4: Training hours per week | G4: Default pay rate (Settings) | H4: or type your own pay rate | I4: Pay rate used | J4: Non-billable hours | K4: Utilization % | L4: Other non-billable hours | M4: Non-billable cost per week | N4: vs target utilization (points)
A5: Ana R. | B5: active | C5: 38 | D5: 32 | E5: 3 | F5: 1 | G5: =IF(A5="","",Settings!$B$2) -> 16 | I5: =IF(A5="","",IF(H5<>"",H5,G5)) -> 16 | J5: =IF(A5="","",C5-D5) -> 6 | K5: =IF(A5="","",IFERROR(ROUND(D5/C5*100,2),0)) -> 84.21 | L5: =IF(A5="","",J5-E5-F5) -> 2 | M5: =IF(A5="","",ROUND(J5*I5*(1+Settings!$B$3/100),2)) -> 117.12 | N5: =IF(A5="","",ROUND(K5-Settings!$B$17,2)) -> -0.79
A6: Ben O. | B6: active | C6: 36 | D6: 30 | E6: 4 | F6: 0 | G6: =IF(A6="","",Settings!$B$2) -> 16 | I6: =IF(A6="","",IF(H6<>"",H6,G6)) -> 16 | J6: =IF(A6="","",C6-D6) -> 6 | K6: =IF(A6="","",IFERROR(ROUND(D6/C6*100,2),0)) -> 83.33 | L6: =IF(A6="","",J6-E6-F6) -> 2 | M6: =IF(A6="","",ROUND(J6*I6*(1+Settings!$B$3/100),2)) -> 117.12 | N6: =IF(A6="","",ROUND(K6-Settings!$B$17,2)) -> -1.67
A7: Carla M. | B7: active | C7: 32 | D7: 28 | E7: 2 | F7: 1 | G7: =IF(A7="","",Settings!$B$2) -> 16 | I7: =IF(A7="","",IF(H7<>"",H7,G7)) -> 16 | J7: =IF(A7="","",C7-D7) -> 4 | K7: =IF(A7="","",IFERROR(ROUND(D7/C7*100,2),0)) -> 87.5 | L7: =IF(A7="","",J7-E7-F7) -> 1 | M7: =IF(A7="","",ROUND(J7*I7*(1+Settings!$B$3/100),2)) -> 78.08 | N7: =IF(A7="","",ROUND(K7-Settings!$B$17,2)) -> 2.5
A8: Dev P. | B8: active | C8: 40 | D8: 33 | E8: 5 | F8: 1 | G8: =IF(A8="","",Settings!$B$2) -> 16 | I8: =IF(A8="","",IF(H8<>"",H8,G8)) -> 16 | J8: =IF(A8="","",C8-D8) -> 7 | K8: =IF(A8="","",IFERROR(ROUND(D8/C8*100,2),0)) -> 82.5 | L8: =IF(A8="","",J8-E8-F8) -> 1 | M8: =IF(A8="","",ROUND(J8*I8*(1+Settings!$B$3/100),2)) -> 136.64 | N8: =IF(A8="","",ROUND(K8-Settings!$B$17,2)) -> -2.5
A9: Erin K. | B9: active | C9: 24 | D9: 20 | E9: 2 | F9: 0 | G9: =IF(A9="","",Settings!$B$2) -> 16 | I9: =IF(A9="","",IF(H9<>"",H9,G9)) -> 16 | J9: =IF(A9="","",C9-D9) -> 4 | K9: =IF(A9="","",IFERROR(ROUND(D9/C9*100,2),0)) -> 83.33 | L9: =IF(A9="","",J9-E9-F9) -> 2 | M9: =IF(A9="","",ROUND(J9*I9*(1+Settings!$B$3/100),2)) -> 78.08 | N9: =IF(A9="","",ROUND(K9-Settings!$B$17,2)) -> -1.67
A10: Femi A. | B10: active | C10: 35 | D10: 29 | E10: 3 | F10: 2 | G10: =IF(A10="","",Settings!$B$2) -> 16 | H10: 18 | I10: =IF(A10="","",IF(H10<>"",H10,G10)) -> 18 | J10: =IF(A10="","",C10-D10) -> 6 | K10: =IF(A10="","",IFERROR(ROUND(D10/C10*100,2),0)) -> 82.86 | L10: =IF(A10="","",J10-E10-F10) -> 1 | M10: =IF(A10="","",ROUND(J10*I10*(1+Settings!$B$3/100),2)) -> 131.76 | N10: =IF(A10="","",ROUND(K10-Settings!$B$17,2)) -> -2.14
A11: Grace L. | B11: active | C11: 30 | D11: 24 | E11: 4 | F11: 0 | G11: =IF(A11="","",Settings!$B$2) -> 16 | I11: =IF(A11="","",IF(H11<>"",H11,G11)) -> 16 | J11: =IF(A11="","",C11-D11) -> 6 | K11: =IF(A11="","",IFERROR(ROUND(D11/C11*100,2),0)) -> 80 | L11: =IF(A11="","",J11-E11-F11) -> 2 | M11: =IF(A11="","",ROUND(J11*I11*(1+Settings!$B$3/100),2)) -> 117.12 | N11: =IF(A11="","",ROUND(K11-Settings!$B$17,2)) -> -5
A12: Hugo S. | B12: on leave | C12: 0 | D12: 0 | E12: 0 | F12: 0 | G12: =IF(A12="","",Settings!$B$2) -> 16 | I12: =IF(A12="","",IF(H12<>"",H12,G12)) -> 16 | J12: =IF(A12="","",C12-D12) -> 0 | K12: =IF(A12="","",IFERROR(ROUND(D12/C12*100,2),0)) -> 0 | L12: =IF(A12="","",J12-E12-F12) -> 0 | M12: =IF(A12="","",ROUND(J12*I12*(1+Settings!$B$3/100),2)) -> 0 | N12: =IF(A12="","",ROUND(K12-Settings!$B$17,2)) -> -85
A13: Ines T. | B13: active | C13: 38 | D13: 31 | E13: 4 | F13: 1 | G13: =IF(A13="","",Settings!$B$2) -> 16 | I13: =IF(A13="","",IF(H13<>"",H13,G13)) -> 16 | J13: =IF(A13="","",C13-D13) -> 7 | K13: =IF(A13="","",IFERROR(ROUND(D13/C13*100,2),0)) -> 81.58 | L13: =IF(A13="","",J13-E13-F13) -> 2 | M13: =IF(A13="","",ROUND(J13*I13*(1+Settings!$B$3/100),2)) -> 136.64 | N13: =IF(A13="","",ROUND(K13-Settings!$B$17,2)) -> -3.42
A14: Jamal W. | B14: left | C14: 0 | D14: 0 | E14: 0 | F14: 0 | G14: =IF(A14="","",Settings!$B$2) -> 16 | I14: =IF(A14="","",IF(H14<>"",H14,G14)) -> 16 | J14: =IF(A14="","",C14-D14) -> 0 | K14: =IF(A14="","",IFERROR(ROUND(D14/C14*100,2),0)) -> 0 | L14: =IF(A14="","",J14-E14-F14) -> 0 | M14: =IF(A14="","",ROUND(J14*I14*(1+Settings!$B$3/100),2)) -> 0 | N14: =IF(A14="","",ROUND(K14-Settings!$B$17,2)) -> -85
A15: Kim N. | B15: active | C15: 28 | D15: 22 | E15: 3 | F15: 1 | G15: =IF(A15="","",Settings!$B$2) -> 16 | I15: =IF(A15="","",IF(H15<>"",H15,G15)) -> 16 | J15: =IF(A15="","",C15-D15) -> 6 | K15: =IF(A15="","",IFERROR(ROUND(D15/C15*100,2),0)) -> 78.57 | L15: =IF(A15="","",J15-E15-F15) -> 2 | M15: =IF(A15="","",ROUND(J15*I15*(1+Settings!$B$3/100),2)) -> 117.12 | N15: =IF(A15="","",ROUND(K15-Settings!$B$17,2)) -> -6.43
A16: Luis G. | B16: active | C16: 36 | D16: 27 | E16: 5 | F16: 2 | G16: =IF(A16="","",Settings!$B$2) -> 16 | I16: =IF(A16="","",IF(H16<>"",H16,G16)) -> 16 | J16: =IF(A16="","",C16-D16) -> 9 | K16: =IF(A16="","",IFERROR(ROUND(D16/C16*100,2),0)) -> 75 | L16: =IF(A16="","",J16-E16-F16) -> 2 | M16: =IF(A16="","",ROUND(J16*I16*(1+Settings!$B$3/100),2)) -> 175.68 | N16: =IF(A16="","",ROUND(K16-Settings!$B$17,2)) -> -10
G17: =IF(A17="","",Settings!$B$2) | I17: =IF(A17="","",IF(H17<>"",H17,G17)) | J17: =IF(A17="","",C17-D17) | K17: =IF(A17="","",IFERROR(ROUND(D17/C17*100,2),0)) | L17: =IF(A17="","",J17-E17-F17) | M17: =IF(A17="","",ROUND(J17*I17*(1+Settings!$B$3/100),2)) | N17: =IF(A17="","",ROUND(K17-Settings!$B$17,2))
G18: =IF(A18="","",Settings!$B$2) | I18: =IF(A18="","",IF(H18<>"",H18,G18)) | J18: =IF(A18="","",C18-D18) | K18: =IF(A18="","",IFERROR(ROUND(D18/C18*100,2),0)) | L18: =IF(A18="","",J18-E18-F18) | M18: =IF(A18="","",ROUND(J18*I18*(1+Settings!$B$3/100),2)) | N18: =IF(A18="","",ROUND(K18-Settings!$B$17,2))
G19: =IF(A19="","",Settings!$B$2) | I19: =IF(A19="","",IF(H19<>"",H19,G19)) | J19: =IF(A19="","",C19-D19) | K19: =IF(A19="","",IFERROR(ROUND(D19/C19*100,2),0)) | L19: =IF(A19="","",J19-E19-F19) | M19: =IF(A19="","",ROUND(J19*I19*(1+Settings!$B$3/100),2)) | N19: =IF(A19="","",ROUND(K19-Settings!$B$17,2))
G20: =IF(A20="","",Settings!$B$2) | I20: =IF(A20="","",IF(H20<>"",H20,G20)) | J20: =IF(A20="","",C20-D20) | K20: =IF(A20="","",IFERROR(ROUND(D20/C20*100,2),0)) | L20: =IF(A20="","",J20-E20-F20) | M20: =IF(A20="","",ROUND(J20*I20*(1+Settings!$B$3/100),2)) | N20: =IF(A20="","",ROUND(K20-Settings!$B$17,2))
G21: =IF(A21="","",Settings!$B$2) | I21: =IF(A21="","",IF(H21<>"",H21,G21)) | J21: =IF(A21="","",C21-D21) | K21: =IF(A21="","",IFERROR(ROUND(D21/C21*100,2),0)) | L21: =IF(A21="","",J21-E21-F21) | M21: =IF(A21="","",ROUND(J21*I21*(1+Settings!$B$3/100),2)) | N21: =IF(A21="","",ROUND(K21-Settings!$B$17,2))
G22: =IF(A22="","",Settings!$B$2) | I22: =IF(A22="","",IF(H22<>"",H22,G22)) | J22: =IF(A22="","",C22-D22) | K22: =IF(A22="","",IFERROR(ROUND(D22/C22*100,2),0)) | L22: =IF(A22="","",J22-E22-F22) | M22: =IF(A22="","",ROUND(J22*I22*(1+Settings!$B$3/100),2)) | N22: =IF(A22="","",ROUND(K22-Settings!$B$17,2))
G23: =IF(A23="","",Settings!$B$2) | I23: =IF(A23="","",IF(H23<>"",H23,G23)) | J23: =IF(A23="","",C23-D23) | K23: =IF(A23="","",IFERROR(ROUND(D23/C23*100,2),0)) | L23: =IF(A23="","",J23-E23-F23) | M23: =IF(A23="","",ROUND(J23*I23*(1+Settings!$B$3/100),2)) | N23: =IF(A23="","",ROUND(K23-Settings!$B$17,2))
G24: =IF(A24="","",Settings!$B$2) | I24: =IF(A24="","",IF(H24<>"",H24,G24)) | J24: =IF(A24="","",C24-D24) | K24: =IF(A24="","",IFERROR(ROUND(D24/C24*100,2),0)) | L24: =IF(A24="","",J24-E24-F24) | M24: =IF(A24="","",ROUND(J24*I24*(1+Settings!$B$3/100),2)) | N24: =IF(A24="","",ROUND(K24-Settings!$B$17,2))
G25: =IF(A25="","",Settings!$B$2) | I25: =IF(A25="","",IF(H25<>"",H25,G25)) | J25: =IF(A25="","",C25-D25) | K25: =IF(A25="","",IFERROR(ROUND(D25/C25*100,2),0)) | L25: =IF(A25="","",J25-E25-F25) | M25: =IF(A25="","",ROUND(J25*I25*(1+Settings!$B$3/100),2)) | N25: =IF(A25="","",ROUND(K25-Settings!$B$17,2))
G26: =IF(A26="","",Settings!$B$2) | I26: =IF(A26="","",IF(H26<>"",H26,G26)) | J26: =IF(A26="","",C26-D26) | K26: =IF(A26="","",IFERROR(ROUND(D26/C26*100,2),0)) | L26: =IF(A26="","",J26-E26-F26) | M26: =IF(A26="","",ROUND(J26*I26*(1+Settings!$B$3/100),2)) | N26: =IF(A26="","",ROUND(K26-Settings!$B$17,2))
G27: =IF(A27="","",Settings!$B$2) | I27: =IF(A27="","",IF(H27<>"",H27,G27)) | J27: =IF(A27="","",C27-D27) | K27: =IF(A27="","",IFERROR(ROUND(D27/C27*100,2),0)) | L27: =IF(A27="","",J27-E27-F27) | M27: =IF(A27="","",ROUND(J27*I27*(1+Settings!$B$3/100),2)) | N27: =IF(A27="","",ROUND(K27-Settings!$B$17,2))
G28: =IF(A28="","",Settings!$B$2) | I28: =IF(A28="","",IF(H28<>"",H28,G28)) | J28: =IF(A28="","",C28-D28) | K28: =IF(A28="","",IFERROR(ROUND(D28/C28*100,2),0)) | L28: =IF(A28="","",J28-E28-F28) | M28: =IF(A28="","",ROUND(J28*I28*(1+Settings!$B$3/100),2)) | N28: =IF(A28="","",ROUND(K28-Settings!$B$17,2))
... G34: =IF(A34="","",Settings!$B$2) | I34: =IF(A34="","",IF(H34<>"",H34,G34)) | J34: =IF(A34="","",C34-D34) | K34: =IF(A34="","",IFERROR(ROUND(D34/C34*100,2),0)) | L34: =IF(A34="","",J34-E34-F34) | M34: =IF(A34="","",ROUND(J34*I34*(1+Settings!$B$3/100),2)) | N34: =IF(A34="","",ROUND(K34-Settings!$B$17,2))
A35: Total (active) | B35: =COUNTIF($B$5:$B$34,"active") -> 10 | C35: =SUMIF($B$5:$B$34,"active",C5:C34) -> 337 | D35: =SUMIF($B$5:$B$34,"active",D5:D34) -> 276 | E35: =SUMIF($B$5:$B$34,"active",E5:E34) -> 35 | F35: =SUMIF($B$5:$B$34,"active",F5:F34) -> 9 | J35: =SUMIF($B$5:$B$34,"active",J5:J34) -> 61 | K35: =IFERROR(ROUND(D35/C35*100,2),0) -> 81.9 | L35: =SUMIF($B$5:$B$34,"active",L5:L34) -> 17 | M35: =SUMIF($B$5:$B$34,"active",M5:M34) -> 1205.36 | N35: =ROUND(K35-Settings!$B$17,2) -> -3.1

Sheet Clients & Quotes
A1: Clients & Quotes
A2: One row per client or care plan quote. Weekend and overnight hours are part of hours per week. The bill rate comes from Service Rates for the service level chosen. Weeks default from Settings; type your own to override. Totals count active clients only.
A4: Client | B4: Service level | C4: Hours per week | D4: Weekend hours | E4: Overnight hours | F4: Miles per week | G4: Default weeks (Settings) | H4: or type your own weeks | I4: Weeks used | J4: Status | K4: Bill rate | L4: Standard hours | M4: Standard hours charge | N4: Weekend charge | O4: Overnight charge | P4: Mileage charge | Q4: Weekly total | R4: Period total | S4: Effective hourly rate
A5: Mrs. Alvarez | B5: Personal care | C5: 40 | D5: 8 | E5: 0 | F5: 30 | G5: =IF(A5="","",Settings!$B$18) -> 4 | I5: =IF(A5="","",IF(H5<>"",H5,G5)) -> 4 | J5: active | K5: =IF(A5="","",IFERROR(INDEX('Service Rates'!$O$5:$O$14,MATCH(B5,'Service Rates'!$A$5:$A$14,0)),Settings!$B$24)) -> 37.09 | L5: =IF(A5="","",MAX(0,C5-D5-E5)) -> 32 | M5: =IF(A5="","",ROUND(L5*K5,2)) -> 1186.88 | N5: =IF(A5="","",ROUND(D5*K5*(1+Settings!$B$13/100),2)) -> 341.23 | O5: =IF(A5="","",ROUND(E5*Settings!$B$14,2)) -> 0 | P5: =IF(A5="","",ROUND(F5*Settings!$B$15,2)) -> 15 | Q5: =IF(A5="","",ROUND(M5+N5+O5+P5,2)) -> 1543.11 | R5: =IF(A5="","",ROUND(Q5*I5,2)) -> 6172.44 | S5: =IF(A5="","",IFERROR(ROUND(Q5/C5,2),0)) -> 38.58
A6: Mr. Brennan | B6: Dementia care | C6: 56 | D6: 16 | E6: 0 | F6: 20 | G6: =IF(A6="","",Settings!$B$18) -> 4 | I6: =IF(A6="","",IF(H6<>"",H6,G6)) -> 4 | J6: active | K6: =IF(A6="","",IFERROR(INDEX('Service Rates'!$O$5:$O$14,MATCH(B6,'Service Rates'!$A$5:$A$14,0)),Settings!$B$24)) -> 42.38 | L6: =IF(A6="","",MAX(0,C6-D6-E6)) -> 40 | M6: =IF(A6="","",ROUND(L6*K6,2)) -> 1695.2 | N6: =IF(A6="","",ROUND(D6*K6*(1+Settings!$B$13/100),2)) -> 779.79 | O6: =IF(A6="","",ROUND(E6*Settings!$B$14,2)) -> 0 | P6: =IF(A6="","",ROUND(F6*Settings!$B$15,2)) -> 10 | Q6: =IF(A6="","",ROUND(M6+N6+O6+P6,2)) -> 2484.99 | R6: =IF(A6="","",ROUND(Q6*I6,2)) -> 9939.96 | S6: =IF(A6="","",IFERROR(ROUND(Q6/C6,2),0)) -> 44.37
A7: Mrs. Chen | B7: Companion | C7: 20 | D7: 4 | E7: 0 | F7: 40 | G7: =IF(A7="","",Settings!$B$18) -> 4 | I7: =IF(A7="","",IF(H7<>"",H7,G7)) -> 4 | J7: active | K7: =IF(A7="","",IFERROR(INDEX('Service Rates'!$O$5:$O$14,MATCH(B7,'Service Rates'!$A$5:$A$14,0)),Settings!$B$24)) -> 35.31 | L7: =IF(A7="","",MAX(0,C7-D7-E7)) -> 16 | M7: =IF(A7="","",ROUND(L7*K7,2)) -> 564.96 | N7: =IF(A7="","",ROUND(D7*K7*(1+Settings!$B$13/100),2)) -> 162.43 | O7: =IF(A7="","",ROUND(E7*Settings!$B$14,2)) -> 0 | P7: =IF(A7="","",ROUND(F7*Settings!$B$15,2)) -> 20 | Q7: =IF(A7="","",ROUND(M7+N7+O7+P7,2)) -> 747.39 | R7: =IF(A7="","",ROUND(Q7*I7,2)) -> 2989.56 | S7: =IF(A7="","",IFERROR(ROUND(Q7/C7,2),0)) -> 37.37
A8: Mr. Dlamini | B8: Respite | C8: 12 | D8: 6 | E8: 0 | F8: 10 | G8: =IF(A8="","",Settings!$B$18) -> 4 | H8: 6 | I8: =IF(A8="","",IF(H8<>"",H8,G8)) -> 6 | J8: active | K8: =IF(A8="","",IFERROR(INDEX('Service Rates'!$O$5:$O$14,MATCH(B8,'Service Rates'!$A$5:$A$14,0)),Settings!$B$24)) -> 37.09 | L8: =IF(A8="","",MAX(0,C8-D8-E8)) -> 6 | M8: =IF(A8="","",ROUND(L8*K8,2)) -> 222.54 | N8: =IF(A8="","",ROUND(D8*K8*(1+Settings!$B$13/100),2)) -> 255.92 | O8: =IF(A8="","",ROUND(E8*Settings!$B$14,2)) -> 0 | P8: =IF(A8="","",ROUND(F8*Settings!$B$15,2)) -> 5 | Q8: =IF(A8="","",ROUND(M8+N8+O8+P8,2)) -> 483.46 | R8: =IF(A8="","",ROUND(Q8*I8,2)) -> 2900.76 | S8: =IF(A8="","",IFERROR(ROUND(Q8/C8,2),0)) -> 40.29
A9: Mrs. Evans | B9: Live-in | C9: 84 | D9: 24 | E9: 0 | F9: 0 | G9: =IF(A9="","",Settings!$B$18) -> 4 | I9: =IF(A9="","",IF(H9<>"",H9,G9)) -> 4 | J9: active | K9: =IF(A9="","",IFERROR(INDEX('Service Rates'!$O$5:$O$14,MATCH(B9,'Service Rates'!$A$5:$A$14,0)),Settings!$B$24)) -> 33.52 | L9: =IF(A9="","",MAX(0,C9-D9-E9)) -> 60 | M9: =IF(A9="","",ROUND(L9*K9,2)) -> 2011.2 | N9: =IF(A9="","",ROUND(D9*K9*(1+Settings!$B$13/100),2)) -> 925.15 | O9: =IF(A9="","",ROUND(E9*Settings!$B$14,2)) -> 0 | P9: =IF(A9="","",ROUND(F9*Settings!$B$15,2)) -> 0 | Q9: =IF(A9="","",ROUND(M9+N9+O9+P9,2)) -> 2936.35 | R9: =IF(A9="","",ROUND(Q9*I9,2)) -> 11745.4 | S9: =IF(A9="","",IFERROR(ROUND(Q9/C9,2),0)) -> 34.96
A10: Mr. Fischer | B10: Personal care | C10: 30 | D10: 0 | E10: 8 | F10: 15 | G10: =IF(A10="","",Settings!$B$18) -> 4 | I10: =IF(A10="","",IF(H10<>"",H10,G10)) -> 4 | J10: active | K10: =IF(A10="","",IFERROR(INDEX('Service Rates'!$O$5:$O$14,MATCH(B10,'Service Rates'!$A$5:$A$14,0)),Settings!$B$24)) -> 37.09 | L10: =IF(A10="","",MAX(0,C10-D10-E10)) -> 22 | M10: =IF(A10="","",ROUND(L10*K10,2)) -> 815.98 | N10: =IF(A10="","",ROUND(D10*K10*(1+Settings!$B$13/100),2)) -> 0 | O10: =IF(A10="","",ROUND(E10*Settings!$B$14,2)) -> 160 | P10: =IF(A10="","",ROUND(F10*Settings!$B$15,2)) -> 7.5 | Q10: =IF(A10="","",ROUND(M10+N10+O10+P10,2)) -> 983.48 | R10: =IF(A10="","",ROUND(Q10*I10,2)) -> 3933.92 | S10: =IF(A10="","",IFERROR(ROUND(Q10/C10,2),0)) -> 32.78
A11: Mrs. Gupta | B11: Companion | C11: 15 | D11: 0 | E11: 0 | F11: 20 | G11: =IF(A11="","",Settings!$B$18) -> 4 | I11: =IF(A11="","",IF(H11<>"",H11,G11)) -> 4 | J11: pending | K11: =IF(A11="","",IFERROR(INDEX('Service Rates'!$O$5:$O$14,MATCH(B11,'Service Rates'!$A$5:$A$14,0)),Settings!$B$24)) -> 35.31 | L11: =IF(A11="","",MAX(0,C11-D11-E11)) -> 15 | M11: =IF(A11="","",ROUND(L11*K11,2)) -> 529.65 | N11: =IF(A11="","",ROUND(D11*K11*(1+Settings!$B$13/100),2)) -> 0 | O11: =IF(A11="","",ROUND(E11*Settings!$B$14,2)) -> 0 | P11: =IF(A11="","",ROUND(F11*Settings!$B$15,2)) -> 10 | Q11: =IF(A11="","",ROUND(M11+N11+O11+P11,2)) -> 539.65 | R11: =IF(A11="","",ROUND(Q11*I11,2)) -> 2158.6 | S11: =IF(A11="","",IFERROR(ROUND(Q11/C11,2),0)) -> 35.98
A12: Mr. Harris | B12: Personal care | C12: 25 | D12: 5 | E12: 0 | F12: 25 | G12: =IF(A12="","",Settings!$B$18) -> 4 | I12: =IF(A12="","",IF(H12<>"",H12,G12)) -> 4 | J12: ended | K12: =IF(A12="","",IFERROR(INDEX('Service Rates'!$O$5:$O$14,MATCH(B12,'Service Rates'!$A$5:$A$14,0)),Settings!$B$24)) -> 37.09 | L12: =IF(A12="","",MAX(0,C12-D12-E12)) -> 20 | M12: =IF(A12="","",ROUND(L12*K12,2)) -> 741.8 | N12: =IF(A12="","",ROUND(D12*K12*(1+Settings!$B$13/100),2)) -> 213.27 | O12: =IF(A12="","",ROUND(E12*Settings!$B$14,2)) -> 0 | P12: =IF(A12="","",ROUND(F12*Settings!$B$15,2)) -> 12.5 | Q12: =IF(A12="","",ROUND(M12+N12+O12+P12,2)) -> 967.57 | R12: =IF(A12="","",ROUND(Q12*I12,2)) -> 3870.28 | S12: =IF(A12="","",IFERROR(ROUND(Q12/C12,2),0)) -> 38.7
G13: =IF(A13="","",Settings!$B$18) | I13: =IF(A13="","",IF(H13<>"",H13,G13)) | K13: =IF(A13="","",IFERROR(INDEX('Service Rates'!$O$5:$O$14,MATCH(B13,'Service Rates'!$A$5:$A$14,0)),Settings!$B$24)) | L13: =IF(A13="","",MAX(0,C13-D13-E13)) | M13: =IF(A13="","",ROUND(L13*K13,2)) | N13: =IF(A13="","",ROUND(D13*K13*(1+Settings!$B$13/100),2)) | O13: =IF(A13="","",ROUND(E13*Settings!$B$14,2)) | P13: =IF(A13="","",ROUND(F13*Settings!$B$15,2)) | Q13: =IF(A13="","",ROUND(M13+N13+O13+P13,2)) | R13: =IF(A13="","",ROUND(Q13*I13,2)) | S13: =IF(A13="","",IFERROR(ROUND(Q13/C13,2),0))
G14: =IF(A14="","",Settings!$B$18) | I14: =IF(A14="","",IF(H14<>"",H14,G14)) | K14: =IF(A14="","",IFERROR(INDEX('Service Rates'!$O$5:$O$14,MATCH(B14,'Service Rates'!$A$5:$A$14,0)),Settings!$B$24)) | L14: =IF(A14="","",MAX(0,C14-D14-E14)) | M14: =IF(A14="","",ROUND(L14*K14,2)) | N14: =IF(A14="","",ROUND(D14*K14*(1+Settings!$B$13/100),2)) | O14: =IF(A14="","",ROUND(E14*Settings!$B$14,2)) | P14: =IF(A14="","",ROUND(F14*Settings!$B$15,2)) | Q14: =IF(A14="","",ROUND(M14+N14+O14+P14,2)) | R14: =IF(A14="","",ROUND(Q14*I14,2)) | S14: =IF(A14="","",IFERROR(ROUND(Q14/C14,2),0))
G15: =IF(A15="","",Settings!$B$18) | I15: =IF(A15="","",IF(H15<>"",H15,G15)) | K15: =IF(A15="","",IFERROR(INDEX('Service Rates'!$O$5:$O$14,MATCH(B15,'Service Rates'!$A$5:$A$14,0)),Settings!$B$24)) | L15: =IF(A15="","",MAX(0,C15-D15-E15)) | M15: =IF(A15="","",ROUND(L15*K15,2)) | N15: =IF(A15="","",ROUND(D15*K15*(1+Settings!$B$13/100),2)) | O15: =IF(A15="","",ROUND(E15*Settings!$B$14,2)) | P15: =IF(A15="","",ROUND(F15*Settings!$B$15,2)) | Q15: =IF(A15="","",ROUND(M15+N15+O15+P15,2)) | R15: =IF(A15="","",ROUND(Q15*I15,2)) | S15: =IF(A15="","",IFERROR(ROUND(Q15/C15,2),0))
G16: =IF(A16="","",Settings!$B$18) | I16: =IF(A16="","",IF(H16<>"",H16,G16)) | K16: =IF(A16="","",IFERROR(INDEX('Service Rates'!$O$5:$O$14,MATCH(B16,'Service Rates'!$A$5:$A$14,0)),Settings!$B$24)) | L16: =IF(A16="","",MAX(0,C16-D16-E16)) | M16: =IF(A16="","",ROUND(L16*K16,2)) | N16: =IF(A16="","",ROUND(D16*K16*(1+Settings!$B$13/100),2)) | O16: =IF(A16="","",ROUND(E16*Settings!$B$14,2)) | P16: =IF(A16="","",ROUND(F16*Settings!$B$15,2)) | Q16: =IF(A16="","",ROUND(M16+N16+O16+P16,2)) | R16: =IF(A16="","",ROUND(Q16*I16,2)) | S16: =IF(A16="","",IFERROR(ROUND(Q16/C16,2),0))
G17: =IF(A17="","",Settings!$B$18) | I17: =IF(A17="","",IF(H17<>"",H17,G17)) | K17: =IF(A17="","",IFERROR(INDEX('Service Rates'!$O$5:$O$14,MATCH(B17,'Service Rates'!$A$5:$A$14,0)),Settings!$B$24)) | L17: =IF(A17="","",MAX(0,C17-D17-E17)) | M17: =IF(A17="","",ROUND(L17*K17,2)) | N17: =IF(A17="","",ROUND(D17*K17*(1+Settings!$B$13/100),2)) | O17: =IF(A17="","",ROUND(E17*Settings!$B$14,2)) | P17: =IF(A17="","",ROUND(F17*Settings!$B$15,2)) | Q17: =IF(A17="","",ROUND(M17+N17+O17+P17,2)) | R17: =IF(A17="","",ROUND(Q17*I17,2)) | S17: =IF(A17="","",IFERROR(ROUND(Q17/C17,2),0))
G18: =IF(A18="","",Settings!$B$18) | I18: =IF(A18="","",IF(H18<>"",H18,G18)) | K18: =IF(A18="","",IFERROR(INDEX('Service Rates'!$O$5:$O$14,MATCH(B18,'Service Rates'!$A$5:$A$14,0)),Settings!$B$24)) | L18: =IF(A18="","",MAX(0,C18-D18-E18)) | M18: =IF(A18="","",ROUND(L18*K18,2)) | N18: =IF(A18="","",ROUND(D18*K18*(1+Settings!$B$13/100),2)) | O18: =IF(A18="","",ROUND(E18*Settings!$B$14,2)) | P18: =IF(A18="","",ROUND(F18*Settings!$B$15,2)) | Q18: =IF(A18="","",ROUND(M18+N18+O18+P18,2)) | R18: =IF(A18="","",ROUND(Q18*I18,2)) | S18: =IF(A18="","",IFERROR(ROUND(Q18/C18,2),0))
G19: =IF(A19="","",Settings!$B$18) | I19: =IF(A19="","",IF(H19<>"",H19,G19)) | K19: =IF(A19="","",IFERROR(INDEX('Service Rates'!$O$5:$O$14,MATCH(B19,'Service Rates'!$A$5:$A$14,0)),Settings!$B$24)) | L19: =IF(A19="","",MAX(0,C19-D19-E19)) | M19: =IF(A19="","",ROUND(L19*K19,2)) | N19: =IF(A19="","",ROUND(D19*K19*(1+Settings!$B$13/100),2)) | O19: =IF(A19="","",ROUND(E19*Settings!$B$14,2)) | P19: =IF(A19="","",ROUND(F19*Settings!$B$15,2)) | Q19: =IF(A19="","",ROUND(M19+N19+O19+P19,2)) | R19: =IF(A19="","",ROUND(Q19*I19,2)) | S19: =IF(A19="","",IFERROR(ROUND(Q19/C19,2),0))
G20: =IF(A20="","",Settings!$B$18) | I20: =IF(A20="","",IF(H20<>"",H20,G20)) | K20: =IF(A20="","",IFERROR(INDEX('Service Rates'!$O$5:$O$14,MATCH(B20,'Service Rates'!$A$5:$A$14,0)),Settings!$B$24)) | L20: =IF(A20="","",MAX(0,C20-D20-E20)) | M20: =IF(A20="","",ROUND(L20*K20,2)) | N20: =IF(A20="","",ROUND(D20*K20*(1+Settings!$B$13/100),2)) | O20: =IF(A20="","",ROUND(E20*Settings!$B$14,2)) | P20: =IF(A20="","",ROUND(F20*Settings!$B$15,2)) | Q20: =IF(A20="","",ROUND(M20+N20+O20+P20,2)) | R20: =IF(A20="","",ROUND(Q20*I20,2)) | S20: =IF(A20="","",IFERROR(ROUND(Q20/C20,2),0))
G21: =IF(A21="","",Settings!$B$18) | I21: =IF(A21="","",IF(H21<>"",H21,G21)) | K21: =IF(A21="","",IFERROR(INDEX('Service Rates'!$O$5:$O$14,MATCH(B21,'Service Rates'!$A$5:$A$14,0)),Settings!$B$24)) | L21: =IF(A21="","",MAX(0,C21-D21-E21)) | M21: =IF(A21="","",ROUND(L21*K21,2)) | N21: =IF(A21="","",ROUND(D21*K21*(1+Settings!$B$13/100),2)) | O21: =IF(A21="","",ROUND(E21*Settings!$B$14,2)) | P21: =IF(A21="","",ROUND(F21*Settings!$B$15,2)) | Q21: =IF(A21="","",ROUND(M21+N21+O21+P21,2)) | R21: =IF(A21="","",ROUND(Q21*I21,2)) | S21: =IF(A21="","",IFERROR(ROUND(Q21/C21,2),0))
G22: =IF(A22="","",Settings!$B$18) | I22: =IF(A22="","",IF(H22<>"",H22,G22)) | K22: =IF(A22="","",IFERROR(INDEX('Service Rates'!$O$5:$O$14,MATCH(B22,'Service Rates'!$A$5:$A$14,0)),Settings!$B$24)) | L22: =IF(A22="","",MAX(0,C22-D22-E22)) | M22: =IF(A22="","",ROUND(L22*K22,2)) | N22: =IF(A22="","",ROUND(D22*K22*(1+Settings!$B$13/100),2)) | O22: =IF(A22="","",ROUND(E22*Settings!$B$14,2)) | P22: =IF(A22="","",ROUND(F22*Settings!$B$15,2)) | Q22: =IF(A22="","",ROUND(M22+N22+O22+P22,2)) | R22: =IF(A22="","",ROUND(Q22*I22,2)) | S22: =IF(A22="","",IFERROR(ROUND(Q22/C22,2),0))
G23: =IF(A23="","",Settings!$B$18) | I23: =IF(A23="","",IF(H23<>"",H23,G23)) | K23: =IF(A23="","",IFERROR(INDEX('Service Rates'!$O$5:$O$14,MATCH(B23,'Service Rates'!$A$5:$A$14,0)),Settings!$B$24)) | L23: =IF(A23="","",MAX(0,C23-D23-E23)) | M23: =IF(A23="","",ROUND(L23*K23,2)) | N23: =IF(A23="","",ROUND(D23*K23*(1+Settings!$B$13/100),2)) | O23: =IF(A23="","",ROUND(E23*Settings!$B$14,2)) | P23: =IF(A23="","",ROUND(F23*Settings!$B$15,2)) | Q23: =IF(A23="","",ROUND(M23+N23+O23+P23,2)) | R23: =IF(A23="","",ROUND(Q23*I23,2)) | S23: =IF(A23="","",IFERROR(ROUND(Q23/C23,2),0))
G24: =IF(A24="","",Settings!$B$18) | I24: =IF(A24="","",IF(H24<>"",H24,G24)) | K24: =IF(A24="","",IFERROR(INDEX('Service Rates'!$O$5:$O$14,MATCH(B24,'Service Rates'!$A$5:$A$14,0)),Settings!$B$24)) | L24: =IF(A24="","",MAX(0,C24-D24-E24)) | M24: =IF(A24="","",ROUND(L24*K24,2)) | N24: =IF(A24="","",ROUND(D24*K24*(1+Settings!$B$13/100),2)) | O24: =IF(A24="","",ROUND(E24*Settings!$B$14,2)) | P24: =IF(A24="","",ROUND(F24*Settings!$B$15,2)) | Q24: =IF(A24="","",ROUND(M24+N24+O24+P24,2)) | R24: =IF(A24="","",ROUND(Q24*I24,2)) | S24: =IF(A24="","",IFERROR(ROUND(Q24/C24,2),0))
A25: Total (active) | B25: =COUNTIF($J$5:$J$24,"active") -> 6 | C25: =SUMIF($J$5:$J$24,"active",C5:C24) -> 242 | D25: =SUMIF($J$5:$J$24,"active",D5:D24) -> 58 | E25: =SUMIF($J$5:$J$24,"active",E5:E24) -> 8 | F25: =SUMIF($J$5:$J$24,"active",F5:F24) -> 115 | L25: =SUMIF($J$5:$J$24,"active",L5:L24) -> 176 | M25: =SUMIF($J$5:$J$24,"active",M5:M24) -> 6496.76 | N25: =SUMIF($J$5:$J$24,"active",N5:N24) -> 2464.52 | O25: =SUMIF($J$5:$J$24,"active",O5:O24) -> 160 | P25: =SUMIF($J$5:$J$24,"active",P5:P24) -> 57.5 | Q25: =SUMIF($J$5:$J$24,"active",Q5:Q24) -> 9178.78 | R25: =SUMIF($J$5:$J$24,"active",R5:R24) -> 37682.04 | S25: =IFERROR(ROUND(Q25/C25,2),0) -> 37.93

Sheet Capacity & Turnover
A1: Capacity & Turnover
A2: Top: weekly capacity of active caregivers against hours committed to active clients. Below: one row per month of caregiver turnover, filled top down.
A4: CAPACITY (per week)
A5: Active caregivers | B5: =COUNTIF(Caregivers!$B$5:$B$34,"active") -> 10
A6: Paid capacity per week (hours) | B6: =ROUND(B5*Settings!$B$16,2) -> 320
A7: Billable capacity at target utilization (hours) | B7: =ROUND(B6*Settings!$B$17/100,2) -> 272
A8: Hours committed to active clients | B8: =SUMIF('Clients & Quotes'!$J$5:$J$24,"active",'Clients & Quotes'!$C$5:$C$24) -> 242
A9: Spare hours | B9: =ROUND(B7-B8,2) -> 30
A10: Status | B10: =IF(B9<0,"overcommitted","spare") -> spare
A11: Weekly revenue committed | B11: =SUMIF('Clients & Quotes'!$J$5:$J$24,"active",'Clients & Quotes'!$Q$5:$Q$24) -> 9178.78
A12: Weekly revenue ceiling | B12: =IFERROR(ROUND(B11/B8*B7,2),ROUND(B7*Settings!$B$24,2)) -> 10316.65
A13: Default trainer cost per hour | B13: 30
A15: Month | B15: Caregivers at start | C15: Leavers | D15: Hires | E15: Recruiting cost | F15: Onboarding hours | G15: Default trainer cost per hour | H15: or type your own trainer cost | I15: Trainer cost per hour used | J15: Unfilled hours | K15: Default margin per billable hour (Settings) | L15: or type your own margin per hour | M15: Margin per billable hour used | N15: Turnover % for the month | O15: Cost per leaver | P15: Turnover cost for the month | Q15: Caregivers at end
A16: 46023 | B16: 11 | C16: 1 | D16: 2 | E16: 600 | F16: 32 | G16: =IF(A16="","",$B$13) -> 30 | I16: =IF(A16="","",IF(H16<>"",H16,G16)) -> 30 | J16: 20 | K16: =IF(A16="","",ROUND(Settings!$B$24-Settings!$B$23,2)) -> 9.27 | M16: =IF(A16="","",IF(L16<>"",L16,K16)) -> 9.27 | N16: =IF(A16="","",IFERROR(ROUND(C16/B16*100,2),0)) -> 9.09 | O16: =IF(A16="","",IFERROR(ROUND(P16/C16,2),0)) -> 1745.4 | P16: =IF(A16="","",ROUND(E16+F16*I16+J16*M16,2)) -> 1745.4 | Q16: =IF(A16="","",B16-C16+D16) -> 12
A17: 46054 | B17: 12 | C17: 2 | D17: 1 | E17: 900 | F17: 16 | G17: =IF(A17="","",$B$13) -> 30 | I17: =IF(A17="","",IF(H17<>"",H17,G17)) -> 30 | J17: 40 | K17: =IF(A17="","",ROUND(Settings!$B$24-Settings!$B$23,2)) -> 9.27 | M17: =IF(A17="","",IF(L17<>"",L17,K17)) -> 9.27 | N17: =IF(A17="","",IFERROR(ROUND(C17/B17*100,2),0)) -> 16.67 | O17: =IF(A17="","",IFERROR(ROUND(P17/C17,2),0)) -> 875.4 | P17: =IF(A17="","",ROUND(E17+F17*I17+J17*M17,2)) -> 1750.8 | Q17: =IF(A17="","",B17-C17+D17) -> 11
A18: 46082 | B18: 11 | C18: 1 | D18: 1 | E18: 450 | F18: 16 | G18: =IF(A18="","",$B$13) -> 30 | I18: =IF(A18="","",IF(H18<>"",H18,G18)) -> 30 | J18: 12 | K18: =IF(A18="","",ROUND(Settings!$B$24-Settings!$B$23,2)) -> 9.27 | M18: =IF(A18="","",IF(L18<>"",L18,K18)) -> 9.27 | N18: =IF(A18="","",IFERROR(ROUND(C18/B18*100,2),0)) -> 9.09 | O18: =IF(A18="","",IFERROR(ROUND(P18/C18,2),0)) -> 1041.24 | P18: =IF(A18="","",ROUND(E18+F18*I18+J18*M18,2)) -> 1041.24 | Q18: =IF(A18="","",B18-C18+D18) -> 11
A19: 46113 | B19: 11 | C19: 0 | D19: 1 | E19: 500 | F19: 16 | G19: =IF(A19="","",$B$13) -> 30 | I19: =IF(A19="","",IF(H19<>"",H19,G19)) -> 30 | J19: 0 | K19: =IF(A19="","",ROUND(Settings!$B$24-Settings!$B$23,2)) -> 9.27 | M19: =IF(A19="","",IF(L19<>"",L19,K19)) -> 9.27 | N19: =IF(A19="","",IFERROR(ROUND(C19/B19*100,2),0)) -> 0 | O19: =IF(A19="","",IFERROR(ROUND(P19/C19,2),0)) -> 0 | P19: =IF(A19="","",ROUND(E19+F19*I19+J19*M19,2)) -> 980 | Q19: =IF(A19="","",B19-C19+D19) -> 12
A20: 46143 | B20: 12 | C20: 2 | D20: 1 | E20: 800 | F20: 16 | G20: =IF(A20="","",$B$13) -> 30 | I20: =IF(A20="","",IF(H20<>"",H20,G20)) -> 30 | J20: 30 | K20: =IF(A20="","",ROUND(Settings!$B$24-Settings!$B$23,2)) -> 9.27 | M20: =IF(A20="","",IF(L20<>"",L20,K20)) -> 9.27 | N20: =IF(A20="","",IFERROR(ROUND(C20/B20*100,2),0)) -> 16.67 | O20: =IF(A20="","",IFERROR(ROUND(P20/C20,2),0)) -> 779.05 | P20: =IF(A20="","",ROUND(E20+F20*I20+J20*M20,2)) -> 1558.1 | Q20: =IF(A20="","",B20-C20+D20) -> 11
A21: 46174 | B21: 11 | C21: 1 | D21: 1 | E21: 400 | F21: 16 | G21: =IF(A21="","",$B$13) -> 30 | I21: =IF(A21="","",IF(H21<>"",H21,G21)) -> 30 | J21: 10 | K21: =IF(A21="","",ROUND(Settings!$B$24-Settings!$B$23,2)) -> 9.27 | M21: =IF(A21="","",IF(L21<>"",L21,K21)) -> 9.27 | N21: =IF(A21="","",IFERROR(ROUND(C21/B21*100,2),0)) -> 9.09 | O21: =IF(A21="","",IFERROR(ROUND(P21/C21,2),0)) -> 972.7 | P21: =IF(A21="","",ROUND(E21+F21*I21+J21*M21,2)) -> 972.7 | Q21: =IF(A21="","",B21-C21+D21) -> 11
G22: =IF(A22="","",$B$13) | I22: =IF(A22="","",IF(H22<>"",H22,G22)) | K22: =IF(A22="","",ROUND(Settings!$B$24-Settings!$B$23,2)) | M22: =IF(A22="","",IF(L22<>"",L22,K22)) | N22: =IF(A22="","",IFERROR(ROUND(C22/B22*100,2),0)) | O22: =IF(A22="","",IFERROR(ROUND(P22/C22,2),0)) | P22: =IF(A22="","",ROUND(E22+F22*I22+J22*M22,2)) | Q22: =IF(A22="","",B22-C22+D22)
G23: =IF(A23="","",$B$13) | I23: =IF(A23="","",IF(H23<>"",H23,G23)) | K23: =IF(A23="","",ROUND(Settings!$B$24-Settings!$B$23,2)) | M23: =IF(A23="","",IF(L23<>"",L23,K23)) | N23: =IF(A23="","",IFERROR(ROUND(C23/B23*100,2),0)) | O23: =IF(A23="","",IFERROR(ROUND(P23/C23,2),0)) | P23: =IF(A23="","",ROUND(E23+F23*I23+J23*M23,2)) | Q23: =IF(A23="","",B23-C23+D23)
G24: =IF(A24="","",$B$13) | I24: =IF(A24="","",IF(H24<>"",H24,G24)) | K24: =IF(A24="","",ROUND(Settings!$B$24-Settings!$B$23,2)) | M24: =IF(A24="","",IF(L24<>"",L24,K24)) | N24: =IF(A24="","",IFERROR(ROUND(C24/B24*100,2),0)) | O24: =IF(A24="","",IFERROR(ROUND(P24/C24,2),0)) | P24: =IF(A24="","",ROUND(E24+F24*I24+J24*M24,2)) | Q24: =IF(A24="","",B24-C24+D24)
G25: =IF(A25="","",$B$13) | I25: =IF(A25="","",IF(H25<>"",H25,G25)) | K25: =IF(A25="","",ROUND(Settings!$B$24-Settings!$B$23,2)) | M25: =IF(A25="","",IF(L25<>"",L25,K25)) | N25: =IF(A25="","",IFERROR(ROUND(C25/B25*100,2),0)) | O25: =IF(A25="","",IFERROR(ROUND(P25/C25,2),0)) | P25: =IF(A25="","",ROUND(E25+F25*I25+J25*M25,2)) | Q25: =IF(A25="","",B25-C25+D25)
G26: =IF(A26="","",$B$13) | I26: =IF(A26="","",IF(H26<>"",H26,G26)) | K26: =IF(A26="","",ROUND(Settings!$B$24-Settings!$B$23,2)) | M26: =IF(A26="","",IF(L26<>"",L26,K26)) | N26: =IF(A26="","",IFERROR(ROUND(C26/B26*100,2),0)) | O26: =IF(A26="","",IFERROR(ROUND(P26/C26,2),0)) | P26: =IF(A26="","",ROUND(E26+F26*I26+J26*M26,2)) | Q26: =IF(A26="","",B26-C26+D26)
G27: =IF(A27="","",$B$13) | I27: =IF(A27="","",IF(H27<>"",H27,G27)) | K27: =IF(A27="","",ROUND(Settings!$B$24-Settings!$B$23,2)) | M27: =IF(A27="","",IF(L27<>"",L27,K27)) | N27: =IF(A27="","",IFERROR(ROUND(C27/B27*100,2),0)) | O27: =IF(A27="","",IFERROR(ROUND(P27/C27,2),0)) | P27: =IF(A27="","",ROUND(E27+F27*I27+J27*M27,2)) | Q27: =IF(A27="","",B27-C27+D27)
A28: Total | B28: =IFERROR(ROUND((AVERAGE(B16:B27)+AVERAGE(Q16:Q27))/2,2),0) -> 11.33 | C28: =SUM(C16:C27) -> 7 | D28: =SUM(D16:D27) -> 7 | E28: =SUM(E16:E27) -> 3650 | F28: =SUM(F16:F27) -> 112 | J28: =SUM(J16:J27) -> 112 | N28: =IFERROR(ROUND(C28/B28*100,2),0) -> 61.78 | O28: =IFERROR(ROUND(P28/C28,2),0) -> 1149.75 | P28: =SUM(P16:P27) -> 8048.24

Sheet Summary
A1: Summary
A2: Cost per billable hour | B2: =Settings!$B$23 -> 27.82 | C2: from Settings: labour cost + overhead per billable hour
A3: Default bill rate at target margin | B3: =Settings!$B$24 -> 37.09 | C3: from Settings: cost per billable hour ÷ (1 − target margin %)
A4: Service levels priced below the computed rate | B4: =COUNTIF('Service Rates'!$R$5:$R$14,"<0") -> 1 | C4: Service Rates rows where the current bill rate is below the bill rate at margin
A5: Active caregivers | B5: ='Capacity & Turnover'!B5 -> 10 | C5: Caregivers with status active
A6: Team utilization % | B6: =Caregivers!K35 -> 81.9 | C6: billable ÷ paid hours of active caregivers, from the Caregivers totals
A7: Target utilization % (your own) | B7: =Settings!$B$17 -> 85 | C7: from Settings; your own placeholder, not a benchmark
A8: Utilization vs target (points) | B8: =ROUND(B6-B7,2) -> -3.1 | C8: negative = below your own target
A9: Active clients | B9: =COUNTIF('Clients & Quotes'!$J$5:$J$24,"active") -> 6 | C9: Clients & Quotes with status active
A10: Weekly hours committed | B10: ='Capacity & Turnover'!B8 -> 242 | C10: hours per week for active clients
A11: Spare hours per week | B11: ='Capacity & Turnover'!B9 -> 30 | C11: billable capacity at target utilization − hours committed
A12: Weekly revenue committed | B12: ='Clients & Quotes'!Q25 -> 9178.78 | C12: weekly totals for active clients
A13: Period revenue committed | B13: ='Clients & Quotes'!R25 -> 37682.04 | C13: period totals for active clients
A14: Year-to-date leavers | B14: ='Capacity & Turnover'!C28 -> 7 | C14: Capacity & Turnover totals
A15: Year-to-date turnover % | B15: ='Capacity & Turnover'!N28 -> 61.78 | C15: leavers ÷ average headcount
A16: Year-to-date turnover cost | B16: ='Capacity & Turnover'!P28 -> 8048.24 | C16: recruiting + onboarding + margin lost on unfilled hours
A17: Client with the highest weekly total | B17: =IFERROR(INDEX('Clients & Quotes'!$A$5:$A$24,MATCH(MAX('Clients & Quotes'!$Q$5:$Q$24),'Clients & Quotes'!$Q$5:$Q$24,0)),"") -> Mrs. Evans | C17: largest weekly total on Clients & Quotes, any status
A18: Its weekly total | B18: =IFERROR(MAX('Clients & Quotes'!$Q$5:$Q$24),0) -> 2936.35 | C18: highest weekly total on Clients & Quotes
