Workbook

Sheet Start Here
A1: Insurance Agency Numbers Workbook
A2: by Knackdesk · knackdesk.com
A4: HOW TO USE
A5: 1. Settings: default new-business and renewal commission %, default agent split %, agency fee per policy, your target retention % and target compensation ratio %, producer cost per hour, years for lifetime commission and support staff count. Producers, employees, policies on the book, the book's renewal commission and the book's retention % are calculated from the other sheets.
A6: 2. Book by Line: one row per line of business with policies at the start of the year, policies lost, new policies and average premium; renewal and new-business commission % default from Settings (type your own to override). Policies at the end, retention %, lapse %, net growth %, renewal commission on the retained book, new-business commission, commission lost and retention against your target are calculated, with totals.
A7: 3. Producers: one row per producer with status, policies written, premium written, the commission revenue credited to them, compensation paid and hours on prospecting. Revenue per policy, compensation ratio %, a new-business commission check at the Settings % and the ratio against your target are calculated, with totals and a per-producer average.
A8: 4. Acquisition: one row per month with marketing spend, lead costs, producer hours (default from Producers, type your own to override), policies written and first-year and renewal commission per policy (defaults from Settings and the book's average premium). Total acquisition cost, cost per policy, lifetime commission per policy, value-to-cost ratio and payback policies are calculated.
A9: 5. Commission Splits: one row per policy or client with producer, premium and carrier commission %; agent split % and agency fee default from Settings (type your own to override). Gross commission, agent share, agency share, agent net after fee, the agent's effective % of premium and agency net are calculated, with a per-producer block below.
A10: 6. Summary: policies on the book and retention against your target, renewal commission and commission lost, lines below target, revenue per producer and per employee, compensation ratio, acquisition cost, lifetime commission and value-to-cost, the best line and best producer, and total agent and agency net from splits.
A12: LEGEND
A13: Blue text = a cell you type into. Black text = a formula, leave it alone. Yellow fill = key inputs.
A15: DEFINITIONS
... A27: Arithmetic only; not financial, legal or licensing advice.

Sheet Settings
A1: Settings
A2: Default new-business commission % | B2: 15 | C2: Default 15. Placeholder; use the first-year commission % in your carrier contracts. Each line can override it on Book by Line.
A3: Default renewal commission % | B3: 10 | C3: Default 10. Placeholder; use the renewal commission % in your carrier contracts. Each line can override it on Book by Line.
A4: Default agent split % | B4: 60 | C4: Default 60. Placeholder; the producer's share of the commission in your producer agreements. Each split can override it.
A5: Agency fee per policy | B5: 10 | C5: Default 10. Placeholder; a per-policy fee charged to the producer on Commission Splits. Type 0 if you do not charge one.
A6: Target retention % | B6: 90 | C6: Default 90. Your own placeholder, not a recommendation and not an industry benchmark: the retention you are aiming for.
A7: Target compensation ratio % | B7: 35 | C7: Default 35. Your own placeholder, not a recommendation and not an industry benchmark: producer pay as a % of the commission revenue credited to them.
A8: Producer cost per hour for acquisition time | B8: 45 | C8: Default 45. Placeholder; what an hour of producer prospecting time costs you, used in Acquisition cost.
A9: Years for lifetime commission (1 to 5) | B9: 3 | C9: Default 3. How many years of commission (first year plus renewals) a new policy is valued at on Acquisition; up to 5.
A10: Support staff count | B10: 3 | C10: Default 3. Account managers, CSRs and admin who are not producers; used for revenue per employee.
A11: Producers | B11: =COUNTA(Producers!A5:A16) -> 5 | C11: formula: names on the Producers sheet (including anyone who left during the year)
A12: Total employees | B12: =B11+B10 -> 8 | C12: formula: producers + support staff count
A13: Policies on the book now | B13: ='Book by Line'!L17 -> 1132 | C13: formula: policies at the end of the year, from the Book by Line totals
A14: Book annual renewal commission | B14: ='Book by Line'!P17 -> 164761 | C14: formula: annual renewal commission on the retained book, from the Book by Line totals
A15: Book retention % | B15: ='Book by Line'!M17 -> 91.12 | C15: formula: total retention from the Book by Line totals; Acquisition values renewals at this rate

Sheet Book by Line
A1: Book by Line
A2: One row per line of business. Renewal and new-business commission % default from Settings; type your own to override them. Retention counts only the policies on the book at the start of the year.
A4: Line of business | B4: Policies at start of year | C4: Policies lost | D4: New policies | E4: Average premium | F4: Default renewal commission % (Settings) | G4: or type your own renewal % | H4: Renewal % used | I4: Default new-business commission % (Settings) | J4: or type your own new-business % | K4: New-business % used | L4: Policies at end | M4: Retention % | N4: Lapse % | O4: Net growth % | P4: Annual renewal commission (retained book) | Q4: New-business commission | R4: Commission lost to lapses | S4: Retention vs target (points)
A5: Personal auto | B5: 420 | C5: 46 | D5: 70 | E5: 1400 | F5: =IF(A5="","",Settings!$B$3) -> 10 | H5: =IF(A5="","",IF(G5<>"",G5,F5)) -> 10 | I5: =IF(A5="","",Settings!$B$2) -> 15 | K5: =IF(A5="","",IF(J5<>"",J5,I5)) -> 15 | L5: =IF(A5="","",B5-C5+D5) -> 444 | M5: =IF(A5="","",IFERROR(ROUND((B5-C5)/B5*100,2),0)) -> 89.05 | N5: =IF(A5="","",IFERROR(ROUND(C5/B5*100,2),0)) -> 10.95 | O5: =IF(A5="","",IFERROR(ROUND((L5-B5)/B5*100,2),0)) -> 5.71 | P5: =IF(A5="","",ROUND((B5-C5)*E5*H5/100,2)) -> 52360 | Q5: =IF(A5="","",ROUND(D5*E5*K5/100,2)) -> 14700 | R5: =IF(A5="","",ROUND(C5*E5*H5/100,2)) -> 6440 | S5: =IF(A5="","",ROUND(M5-Settings!$B$6,2)) -> -0.95
A6: Homeowners | B6: 310 | C6: 25 | D6: 40 | E6: 1600 | F6: =IF(A6="","",Settings!$B$3) -> 10 | H6: =IF(A6="","",IF(G6<>"",G6,F6)) -> 10 | I6: =IF(A6="","",Settings!$B$2) -> 15 | K6: =IF(A6="","",IF(J6<>"",J6,I6)) -> 15 | L6: =IF(A6="","",B6-C6+D6) -> 325 | M6: =IF(A6="","",IFERROR(ROUND((B6-C6)/B6*100,2),0)) -> 91.94 | N6: =IF(A6="","",IFERROR(ROUND(C6/B6*100,2),0)) -> 8.06 | O6: =IF(A6="","",IFERROR(ROUND((L6-B6)/B6*100,2),0)) -> 4.84 | P6: =IF(A6="","",ROUND((B6-C6)*E6*H6/100,2)) -> 45600 | Q6: =IF(A6="","",ROUND(D6*E6*K6/100,2)) -> 9600 | R6: =IF(A6="","",ROUND(C6*E6*H6/100,2)) -> 4000 | S6: =IF(A6="","",ROUND(M6-Settings!$B$6,2)) -> 1.94
A7: Commercial | B7: 85 | C7: 6 | D7: 12 | E7: 5200 | F7: =IF(A7="","",Settings!$B$3) -> 10 | G7: 12 | H7: =IF(A7="","",IF(G7<>"",G7,F7)) -> 12 | I7: =IF(A7="","",Settings!$B$2) -> 15 | K7: =IF(A7="","",IF(J7<>"",J7,I7)) -> 15 | L7: =IF(A7="","",B7-C7+D7) -> 91 | M7: =IF(A7="","",IFERROR(ROUND((B7-C7)/B7*100,2),0)) -> 92.94 | N7: =IF(A7="","",IFERROR(ROUND(C7/B7*100,2),0)) -> 7.06 | O7: =IF(A7="","",IFERROR(ROUND((L7-B7)/B7*100,2),0)) -> 7.06 | P7: =IF(A7="","",ROUND((B7-C7)*E7*H7/100,2)) -> 49296 | Q7: =IF(A7="","",ROUND(D7*E7*K7/100,2)) -> 9360 | R7: =IF(A7="","",ROUND(C7*E7*H7/100,2)) -> 3744 | S7: =IF(A7="","",ROUND(M7-Settings!$B$6,2)) -> 2.94
A8: Life | B8: 120 | C8: 5 | D8: 15 | E8: 900 | F8: =IF(A8="","",Settings!$B$3) -> 10 | G8: 2 | H8: =IF(A8="","",IF(G8<>"",G8,F8)) -> 2 | I8: =IF(A8="","",Settings!$B$2) -> 15 | J8: 50 | K8: =IF(A8="","",IF(J8<>"",J8,I8)) -> 50 | L8: =IF(A8="","",B8-C8+D8) -> 130 | M8: =IF(A8="","",IFERROR(ROUND((B8-C8)/B8*100,2),0)) -> 95.83 | N8: =IF(A8="","",IFERROR(ROUND(C8/B8*100,2),0)) -> 4.17 | O8: =IF(A8="","",IFERROR(ROUND((L8-B8)/B8*100,2),0)) -> 8.33 | P8: =IF(A8="","",ROUND((B8-C8)*E8*H8/100,2)) -> 2070 | Q8: =IF(A8="","",ROUND(D8*E8*K8/100,2)) -> 6750 | R8: =IF(A8="","",ROUND(C8*E8*H8/100,2)) -> 90 | S8: =IF(A8="","",ROUND(M8-Settings!$B$6,2)) -> 5.83
A9: Health | B9: 60 | C9: 9 | D9: 10 | E9: 2400 | F9: =IF(A9="","",Settings!$B$3) -> 10 | H9: =IF(A9="","",IF(G9<>"",G9,F9)) -> 10 | I9: =IF(A9="","",Settings!$B$2) -> 15 | K9: =IF(A9="","",IF(J9<>"",J9,I9)) -> 15 | L9: =IF(A9="","",B9-C9+D9) -> 61 | M9: =IF(A9="","",IFERROR(ROUND((B9-C9)/B9*100,2),0)) -> 85 | N9: =IF(A9="","",IFERROR(ROUND(C9/B9*100,2),0)) -> 15 | O9: =IF(A9="","",IFERROR(ROUND((L9-B9)/B9*100,2),0)) -> 1.67 | P9: =IF(A9="","",ROUND((B9-C9)*E9*H9/100,2)) -> 12240 | Q9: =IF(A9="","",ROUND(D9*E9*K9/100,2)) -> 3600 | R9: =IF(A9="","",ROUND(C9*E9*H9/100,2)) -> 2160 | S9: =IF(A9="","",ROUND(M9-Settings!$B$6,2)) -> -5
A10: Umbrella | B10: 75 | C10: 4 | D10: 10 | E10: 450 | F10: =IF(A10="","",Settings!$B$3) -> 10 | H10: =IF(A10="","",IF(G10<>"",G10,F10)) -> 10 | I10: =IF(A10="","",Settings!$B$2) -> 15 | K10: =IF(A10="","",IF(J10<>"",J10,I10)) -> 15 | L10: =IF(A10="","",B10-C10+D10) -> 81 | M10: =IF(A10="","",IFERROR(ROUND((B10-C10)/B10*100,2),0)) -> 94.67 | N10: =IF(A10="","",IFERROR(ROUND(C10/B10*100,2),0)) -> 5.33 | O10: =IF(A10="","",IFERROR(ROUND((L10-B10)/B10*100,2),0)) -> 8 | P10: =IF(A10="","",ROUND((B10-C10)*E10*H10/100,2)) -> 3195 | Q10: =IF(A10="","",ROUND(D10*E10*K10/100,2)) -> 675 | R10: =IF(A10="","",ROUND(C10*E10*H10/100,2)) -> 180 | S10: =IF(A10="","",ROUND(M10-Settings!$B$6,2)) -> 4.67
F11: =IF(A11="","",Settings!$B$3) | H11: =IF(A11="","",IF(G11<>"",G11,F11)) | I11: =IF(A11="","",Settings!$B$2) | K11: =IF(A11="","",IF(J11<>"",J11,I11)) | L11: =IF(A11="","",B11-C11+D11) | M11: =IF(A11="","",IFERROR(ROUND((B11-C11)/B11*100,2),0)) | N11: =IF(A11="","",IFERROR(ROUND(C11/B11*100,2),0)) | O11: =IF(A11="","",IFERROR(ROUND((L11-B11)/B11*100,2),0)) | P11: =IF(A11="","",ROUND((B11-C11)*E11*H11/100,2)) | Q11: =IF(A11="","",ROUND(D11*E11*K11/100,2)) | R11: =IF(A11="","",ROUND(C11*E11*H11/100,2)) | S11: =IF(A11="","",ROUND(M11-Settings!$B$6,2))
F12: =IF(A12="","",Settings!$B$3) | H12: =IF(A12="","",IF(G12<>"",G12,F12)) | I12: =IF(A12="","",Settings!$B$2) | K12: =IF(A12="","",IF(J12<>"",J12,I12)) | L12: =IF(A12="","",B12-C12+D12) | M12: =IF(A12="","",IFERROR(ROUND((B12-C12)/B12*100,2),0)) | N12: =IF(A12="","",IFERROR(ROUND(C12/B12*100,2),0)) | O12: =IF(A12="","",IFERROR(ROUND((L12-B12)/B12*100,2),0)) | P12: =IF(A12="","",ROUND((B12-C12)*E12*H12/100,2)) | Q12: =IF(A12="","",ROUND(D12*E12*K12/100,2)) | R12: =IF(A12="","",ROUND(C12*E12*H12/100,2)) | S12: =IF(A12="","",ROUND(M12-Settings!$B$6,2))
F13: =IF(A13="","",Settings!$B$3) | H13: =IF(A13="","",IF(G13<>"",G13,F13)) | I13: =IF(A13="","",Settings!$B$2) | K13: =IF(A13="","",IF(J13<>"",J13,I13)) | L13: =IF(A13="","",B13-C13+D13) | M13: =IF(A13="","",IFERROR(ROUND((B13-C13)/B13*100,2),0)) | N13: =IF(A13="","",IFERROR(ROUND(C13/B13*100,2),0)) | O13: =IF(A13="","",IFERROR(ROUND((L13-B13)/B13*100,2),0)) | P13: =IF(A13="","",ROUND((B13-C13)*E13*H13/100,2)) | Q13: =IF(A13="","",ROUND(D13*E13*K13/100,2)) | R13: =IF(A13="","",ROUND(C13*E13*H13/100,2)) | S13: =IF(A13="","",ROUND(M13-Settings!$B$6,2))
F14: =IF(A14="","",Settings!$B$3) | H14: =IF(A14="","",IF(G14<>"",G14,F14)) | I14: =IF(A14="","",Settings!$B$2) | K14: =IF(A14="","",IF(J14<>"",J14,I14)) | L14: =IF(A14="","",B14-C14+D14) | M14: =IF(A14="","",IFERROR(ROUND((B14-C14)/B14*100,2),0)) | N14: =IF(A14="","",IFERROR(ROUND(C14/B14*100,2),0)) | O14: =IF(A14="","",IFERROR(ROUND((L14-B14)/B14*100,2),0)) | P14: =IF(A14="","",ROUND((B14-C14)*E14*H14/100,2)) | Q14: =IF(A14="","",ROUND(D14*E14*K14/100,2)) | R14: =IF(A14="","",ROUND(C14*E14*H14/100,2)) | S14: =IF(A14="","",ROUND(M14-Settings!$B$6,2))
F15: =IF(A15="","",Settings!$B$3) | H15: =IF(A15="","",IF(G15<>"",G15,F15)) | I15: =IF(A15="","",Settings!$B$2) | K15: =IF(A15="","",IF(J15<>"",J15,I15)) | L15: =IF(A15="","",B15-C15+D15) | M15: =IF(A15="","",IFERROR(ROUND((B15-C15)/B15*100,2),0)) | N15: =IF(A15="","",IFERROR(ROUND(C15/B15*100,2),0)) | O15: =IF(A15="","",IFERROR(ROUND((L15-B15)/B15*100,2),0)) | P15: =IF(A15="","",ROUND((B15-C15)*E15*H15/100,2)) | Q15: =IF(A15="","",ROUND(D15*E15*K15/100,2)) | R15: =IF(A15="","",ROUND(C15*E15*H15/100,2)) | S15: =IF(A15="","",ROUND(M15-Settings!$B$6,2))
F16: =IF(A16="","",Settings!$B$3) | H16: =IF(A16="","",IF(G16<>"",G16,F16)) | I16: =IF(A16="","",Settings!$B$2) | K16: =IF(A16="","",IF(J16<>"",J16,I16)) | L16: =IF(A16="","",B16-C16+D16) | M16: =IF(A16="","",IFERROR(ROUND((B16-C16)/B16*100,2),0)) | N16: =IF(A16="","",IFERROR(ROUND(C16/B16*100,2),0)) | O16: =IF(A16="","",IFERROR(ROUND((L16-B16)/B16*100,2),0)) | P16: =IF(A16="","",ROUND((B16-C16)*E16*H16/100,2)) | Q16: =IF(A16="","",ROUND(D16*E16*K16/100,2)) | R16: =IF(A16="","",ROUND(C16*E16*H16/100,2)) | S16: =IF(A16="","",ROUND(M16-Settings!$B$6,2))
A17: Total | B17: =SUM(B5:B16) -> 1070 | C17: =SUM(C5:C16) -> 95 | D17: =SUM(D5:D16) -> 157 | E17: =IFERROR(ROUND(SUMPRODUCT(B5:B16,E5:E16)/B17,2),0) -> 1693.22 | L17: =SUM(L5:L16) -> 1132 | M17: =IFERROR(ROUND((B17-C17)/B17*100,2),0) -> 91.12 | N17: =IFERROR(ROUND(C17/B17*100,2),0) -> 8.88 | O17: =IFERROR(ROUND((L17-B17)/B17*100,2),0) -> 5.79 | P17: =SUM(P5:P16) -> 164761 | Q17: =SUM(Q5:Q16) -> 44685 | R17: =SUM(R5:R16) -> 16614 | S17: =ROUND(M17-Settings!$B$6,2) -> 1.12

Sheet Producers
A1: Producers
A2: One row per producer for the year, including anyone who left. Commission revenue credited, compensation paid and hours come from your own records; the check column applies the Settings new-business % to premium written.
A4: Producer | B4: Status | C4: Policies written this year | D4: Premium written | E4: Commission revenue credited | F4: Compensation paid | G4: Hours on prospecting | H4: Revenue per policy | I4: Compensation ratio % | J4: New-business commission at Settings % (check) | K4: Credited − check | L4: Compensation ratio vs target (points)
A5: A. Rivera | B5: active | C5: 140 | D5: 210000 | E5: 34000 | F5: 12000 | G5: 380 | H5: =IF(A5="","",IFERROR(ROUND(E5/C5,2),0)) -> 242.86 | I5: =IF(A5="","",IFERROR(ROUND(F5/E5*100,2),0)) -> 35.29 | J5: =IF(A5="","",ROUND(D5*Settings!$B$2/100,2)) -> 31500 | K5: =IF(A5="","",ROUND(E5-J5,2)) -> 2500 | L5: =IF(A5="","",ROUND(I5-Settings!$B$7,2)) -> 0.29
A6: B. Cole | B6: active | C6: 95 | D6: 160000 | E6: 25500 | F6: 9600 | G6: 300 | H6: =IF(A6="","",IFERROR(ROUND(E6/C6,2),0)) -> 268.42 | I6: =IF(A6="","",IFERROR(ROUND(F6/E6*100,2),0)) -> 37.65 | J6: =IF(A6="","",ROUND(D6*Settings!$B$2/100,2)) -> 24000 | K6: =IF(A6="","",ROUND(E6-J6,2)) -> 1500 | L6: =IF(A6="","",ROUND(I6-Settings!$B$7,2)) -> 2.65
A7: C. Park | B7: active | C7: 120 | D7: 150000 | E7: 23000 | F7: 7800 | G7: 340 | H7: =IF(A7="","",IFERROR(ROUND(E7/C7,2),0)) -> 191.67 | I7: =IF(A7="","",IFERROR(ROUND(F7/E7*100,2),0)) -> 33.91 | J7: =IF(A7="","",ROUND(D7*Settings!$B$2/100,2)) -> 22500 | K7: =IF(A7="","",ROUND(E7-J7,2)) -> 500 | L7: =IF(A7="","",ROUND(I7-Settings!$B$7,2)) -> -1.09
A8: D. Shah | B8: active | C8: 60 | D8: 85000 | E8: 13500 | F8: 5400 | G8: 260 | H8: =IF(A8="","",IFERROR(ROUND(E8/C8,2),0)) -> 225 | I8: =IF(A8="","",IFERROR(ROUND(F8/E8*100,2),0)) -> 40 | J8: =IF(A8="","",ROUND(D8*Settings!$B$2/100,2)) -> 12750 | K8: =IF(A8="","",ROUND(E8-J8,2)) -> 750 | L8: =IF(A8="","",ROUND(I8-Settings!$B$7,2)) -> 5
A9: E. Grant | B9: left | C9: 30 | D9: 40000 | E9: 6200 | F9: 3100 | G9: 120 | H9: =IF(A9="","",IFERROR(ROUND(E9/C9,2),0)) -> 206.67 | I9: =IF(A9="","",IFERROR(ROUND(F9/E9*100,2),0)) -> 50 | J9: =IF(A9="","",ROUND(D9*Settings!$B$2/100,2)) -> 6000 | K9: =IF(A9="","",ROUND(E9-J9,2)) -> 200 | L9: =IF(A9="","",ROUND(I9-Settings!$B$7,2)) -> 15
H10: =IF(A10="","",IFERROR(ROUND(E10/C10,2),0)) | I10: =IF(A10="","",IFERROR(ROUND(F10/E10*100,2),0)) | J10: =IF(A10="","",ROUND(D10*Settings!$B$2/100,2)) | K10: =IF(A10="","",ROUND(E10-J10,2)) | L10: =IF(A10="","",ROUND(I10-Settings!$B$7,2))
H11: =IF(A11="","",IFERROR(ROUND(E11/C11,2),0)) | I11: =IF(A11="","",IFERROR(ROUND(F11/E11*100,2),0)) | J11: =IF(A11="","",ROUND(D11*Settings!$B$2/100,2)) | K11: =IF(A11="","",ROUND(E11-J11,2)) | L11: =IF(A11="","",ROUND(I11-Settings!$B$7,2))
H12: =IF(A12="","",IFERROR(ROUND(E12/C12,2),0)) | I12: =IF(A12="","",IFERROR(ROUND(F12/E12*100,2),0)) | J12: =IF(A12="","",ROUND(D12*Settings!$B$2/100,2)) | K12: =IF(A12="","",ROUND(E12-J12,2)) | L12: =IF(A12="","",ROUND(I12-Settings!$B$7,2))
H13: =IF(A13="","",IFERROR(ROUND(E13/C13,2),0)) | I13: =IF(A13="","",IFERROR(ROUND(F13/E13*100,2),0)) | J13: =IF(A13="","",ROUND(D13*Settings!$B$2/100,2)) | K13: =IF(A13="","",ROUND(E13-J13,2)) | L13: =IF(A13="","",ROUND(I13-Settings!$B$7,2))
H14: =IF(A14="","",IFERROR(ROUND(E14/C14,2),0)) | I14: =IF(A14="","",IFERROR(ROUND(F14/E14*100,2),0)) | J14: =IF(A14="","",ROUND(D14*Settings!$B$2/100,2)) | K14: =IF(A14="","",ROUND(E14-J14,2)) | L14: =IF(A14="","",ROUND(I14-Settings!$B$7,2))
H15: =IF(A15="","",IFERROR(ROUND(E15/C15,2),0)) | I15: =IF(A15="","",IFERROR(ROUND(F15/E15*100,2),0)) | J15: =IF(A15="","",ROUND(D15*Settings!$B$2/100,2)) | K15: =IF(A15="","",ROUND(E15-J15,2)) | L15: =IF(A15="","",ROUND(I15-Settings!$B$7,2))
H16: =IF(A16="","",IFERROR(ROUND(E16/C16,2),0)) | I16: =IF(A16="","",IFERROR(ROUND(F16/E16*100,2),0)) | J16: =IF(A16="","",ROUND(D16*Settings!$B$2/100,2)) | K16: =IF(A16="","",ROUND(E16-J16,2)) | L16: =IF(A16="","",ROUND(I16-Settings!$B$7,2))
A17: Total | B17: =COUNTA(A5:A16) -> 5 | C17: =SUM(C5:C16) -> 445 | D17: =SUM(D5:D16) -> 645000 | E17: =SUM(E5:E16) -> 102200 | F17: =SUM(F5:F16) -> 37900 | G17: =SUM(G5:G16) -> 1400 | H17: =IFERROR(ROUND(E17/C17,2),0) -> 229.66 | I17: =IFERROR(ROUND(F17/E17*100,2),0) -> 37.08 | J17: =SUM(J5:J16) -> 96750 | K17: =SUM(K5:K16) -> 5450 | L17: =ROUND(I17-Settings!$B$7,2) -> 2.08
A18: Per-producer average | C18: =IFERROR(ROUND(C17/$B$17,2),0) -> 89 | D18: =IFERROR(ROUND(D17/$B$17,2),0) -> 129000 | E18: =IFERROR(ROUND(E17/$B$17,2),0) -> 20440 | F18: =IFERROR(ROUND(F17/$B$17,2),0) -> 7580 | G18: =IFERROR(ROUND(G17/$B$17,2),0) -> 280 | J18: =IFERROR(ROUND(J17/$B$17,2),0) -> 19350

Sheet Acquisition
A1: Acquisition
A2: One row per month. Producer hours default from Producers ÷ 12; commission per policy defaults from the Settings % on the book's average premium. Type your own to override them.
A4: Month | B4: Marketing spend | C4: Lead costs | D4: Default producer hours (Producers ÷ 12) | E4: or type your own hours | F4: Producer hours used | G4: Policies written | H4: Default first-year commission per policy | I4: or type your own first-year | J4: First-year commission used | K4: Default renewal commission per policy | L4: or type your own renewal | M4: Renewal commission used | N4: Total acquisition cost | O4: Cost per policy | P4: Lifetime commission per policy | Q4: Value-to-cost ratio | R4: Payback policies
A5: Jan | B5: 800 | C5: 600 | D5: =IF(A5="","",ROUND(Producers!$G$17/12,1)) -> 116.7 | F5: =IF(A5="","",IF(E5<>"",E5,D5)) -> 116.7 | G5: 22 | H5: =IF(A5="","",ROUND(Settings!$B$2/100*'Book by Line'!$E$17,2)) -> 253.98 | J5: =IF(A5="","",IF(I5<>"",I5,H5)) -> 253.98 | K5: =IF(A5="","",ROUND(Settings!$B$3/100*'Book by Line'!$E$17,2)) -> 169.32 | M5: =IF(A5="","",IF(L5<>"",L5,K5)) -> 169.32 | N5: =IF(A5="","",ROUND(B5+C5+F5*Settings!$B$8,2)) -> 6651.5 | O5: =IF(A5="","",IFERROR(ROUND(N5/G5,2),0)) -> 302.34 | P5: =IF(A5="","",ROUND(J5+M5*(IF(Settings!$B$9>=2,'Book by Line'!$M$17/100,0)+IF(Settings!$B$9>=3,POWER('Book by Line'!$M$17/100,2),0)+IF(Settings!$B$9>=4,POWER('Book by Line'!$M$17/100,3),0)+IF(Settings!$B$9>=5,POWER('Book by Line'!$M$17/100,4),0)),2)) -> 548.85 | Q5: =IF(A5="","",IFERROR(ROUND(P5/O5,2),0)) -> 1.82 | R5: =IF(A5="","",IFERROR(ROUND(N5/J5,1),0)) -> 26.2
A6: Feb | B6: 800 | C6: 450 | D6: =IF(A6="","",ROUND(Producers!$G$17/12,1)) -> 116.7 | F6: =IF(A6="","",IF(E6<>"",E6,D6)) -> 116.7 | G6: 18 | H6: =IF(A6="","",ROUND(Settings!$B$2/100*'Book by Line'!$E$17,2)) -> 253.98 | J6: =IF(A6="","",IF(I6<>"",I6,H6)) -> 253.98 | K6: =IF(A6="","",ROUND(Settings!$B$3/100*'Book by Line'!$E$17,2)) -> 169.32 | M6: =IF(A6="","",IF(L6<>"",L6,K6)) -> 169.32 | N6: =IF(A6="","",ROUND(B6+C6+F6*Settings!$B$8,2)) -> 6501.5 | O6: =IF(A6="","",IFERROR(ROUND(N6/G6,2),0)) -> 361.19 | P6: =IF(A6="","",ROUND(J6+M6*(IF(Settings!$B$9>=2,'Book by Line'!$M$17/100,0)+IF(Settings!$B$9>=3,POWER('Book by Line'!$M$17/100,2),0)+IF(Settings!$B$9>=4,POWER('Book by Line'!$M$17/100,3),0)+IF(Settings!$B$9>=5,POWER('Book by Line'!$M$17/100,4),0)),2)) -> 548.85 | Q6: =IF(A6="","",IFERROR(ROUND(P6/O6,2),0)) -> 1.52 | R6: =IF(A6="","",IFERROR(ROUND(N6/J6,1),0)) -> 25.6
A7: Mar | B7: 1200 | C7: 700 | D7: =IF(A7="","",ROUND(Producers!$G$17/12,1)) -> 116.7 | E7: 140 | F7: =IF(A7="","",IF(E7<>"",E7,D7)) -> 140 | G7: 30 | H7: =IF(A7="","",ROUND(Settings!$B$2/100*'Book by Line'!$E$17,2)) -> 253.98 | J7: =IF(A7="","",IF(I7<>"",I7,H7)) -> 253.98 | K7: =IF(A7="","",ROUND(Settings!$B$3/100*'Book by Line'!$E$17,2)) -> 169.32 | M7: =IF(A7="","",IF(L7<>"",L7,K7)) -> 169.32 | N7: =IF(A7="","",ROUND(B7+C7+F7*Settings!$B$8,2)) -> 8200 | O7: =IF(A7="","",IFERROR(ROUND(N7/G7,2),0)) -> 273.33 | P7: =IF(A7="","",ROUND(J7+M7*(IF(Settings!$B$9>=2,'Book by Line'!$M$17/100,0)+IF(Settings!$B$9>=3,POWER('Book by Line'!$M$17/100,2),0)+IF(Settings!$B$9>=4,POWER('Book by Line'!$M$17/100,3),0)+IF(Settings!$B$9>=5,POWER('Book by Line'!$M$17/100,4),0)),2)) -> 548.85 | Q7: =IF(A7="","",IFERROR(ROUND(P7/O7,2),0)) -> 2.01 | R7: =IF(A7="","",IFERROR(ROUND(N7/J7,1),0)) -> 32.3
A8: Apr | B8: 900 | C8: 500 | D8: =IF(A8="","",ROUND(Producers!$G$17/12,1)) -> 116.7 | F8: =IF(A8="","",IF(E8<>"",E8,D8)) -> 116.7 | G8: 21 | H8: =IF(A8="","",ROUND(Settings!$B$2/100*'Book by Line'!$E$17,2)) -> 253.98 | J8: =IF(A8="","",IF(I8<>"",I8,H8)) -> 253.98 | K8: =IF(A8="","",ROUND(Settings!$B$3/100*'Book by Line'!$E$17,2)) -> 169.32 | M8: =IF(A8="","",IF(L8<>"",L8,K8)) -> 169.32 | N8: =IF(A8="","",ROUND(B8+C8+F8*Settings!$B$8,2)) -> 6651.5 | O8: =IF(A8="","",IFERROR(ROUND(N8/G8,2),0)) -> 316.74 | P8: =IF(A8="","",ROUND(J8+M8*(IF(Settings!$B$9>=2,'Book by Line'!$M$17/100,0)+IF(Settings!$B$9>=3,POWER('Book by Line'!$M$17/100,2),0)+IF(Settings!$B$9>=4,POWER('Book by Line'!$M$17/100,3),0)+IF(Settings!$B$9>=5,POWER('Book by Line'!$M$17/100,4),0)),2)) -> 548.85 | Q8: =IF(A8="","",IFERROR(ROUND(P8/O8,2),0)) -> 1.73 | R8: =IF(A8="","",IFERROR(ROUND(N8/J8,1),0)) -> 26.2
A9: May | B9: 900 | C9: 650 | D9: =IF(A9="","",ROUND(Producers!$G$17/12,1)) -> 116.7 | F9: =IF(A9="","",IF(E9<>"",E9,D9)) -> 116.7 | G9: 24 | H9: =IF(A9="","",ROUND(Settings!$B$2/100*'Book by Line'!$E$17,2)) -> 253.98 | I9: 260 | J9: =IF(A9="","",IF(I9<>"",I9,H9)) -> 260 | K9: =IF(A9="","",ROUND(Settings!$B$3/100*'Book by Line'!$E$17,2)) -> 169.32 | M9: =IF(A9="","",IF(L9<>"",L9,K9)) -> 169.32 | N9: =IF(A9="","",ROUND(B9+C9+F9*Settings!$B$8,2)) -> 6801.5 | O9: =IF(A9="","",IFERROR(ROUND(N9/G9,2),0)) -> 283.4 | P9: =IF(A9="","",ROUND(J9+M9*(IF(Settings!$B$9>=2,'Book by Line'!$M$17/100,0)+IF(Settings!$B$9>=3,POWER('Book by Line'!$M$17/100,2),0)+IF(Settings!$B$9>=4,POWER('Book by Line'!$M$17/100,3),0)+IF(Settings!$B$9>=5,POWER('Book by Line'!$M$17/100,4),0)),2)) -> 554.87 | Q9: =IF(A9="","",IFERROR(ROUND(P9/O9,2),0)) -> 1.96 | R9: =IF(A9="","",IFERROR(ROUND(N9/J9,1),0)) -> 26.2
A10: Jun | B10: 600 | C10: 400 | D10: =IF(A10="","",ROUND(Producers!$G$17/12,1)) -> 116.7 | F10: =IF(A10="","",IF(E10<>"",E10,D10)) -> 116.7 | G10: 15 | H10: =IF(A10="","",ROUND(Settings!$B$2/100*'Book by Line'!$E$17,2)) -> 253.98 | J10: =IF(A10="","",IF(I10<>"",I10,H10)) -> 253.98 | K10: =IF(A10="","",ROUND(Settings!$B$3/100*'Book by Line'!$E$17,2)) -> 169.32 | M10: =IF(A10="","",IF(L10<>"",L10,K10)) -> 169.32 | N10: =IF(A10="","",ROUND(B10+C10+F10*Settings!$B$8,2)) -> 6251.5 | O10: =IF(A10="","",IFERROR(ROUND(N10/G10,2),0)) -> 416.77 | P10: =IF(A10="","",ROUND(J10+M10*(IF(Settings!$B$9>=2,'Book by Line'!$M$17/100,0)+IF(Settings!$B$9>=3,POWER('Book by Line'!$M$17/100,2),0)+IF(Settings!$B$9>=4,POWER('Book by Line'!$M$17/100,3),0)+IF(Settings!$B$9>=5,POWER('Book by Line'!$M$17/100,4),0)),2)) -> 548.85 | Q10: =IF(A10="","",IFERROR(ROUND(P10/O10,2),0)) -> 1.32 | R10: =IF(A10="","",IFERROR(ROUND(N10/J10,1),0)) -> 24.6
D11: =IF(A11="","",ROUND(Producers!$G$17/12,1)) | F11: =IF(A11="","",IF(E11<>"",E11,D11)) | H11: =IF(A11="","",ROUND(Settings!$B$2/100*'Book by Line'!$E$17,2)) | J11: =IF(A11="","",IF(I11<>"",I11,H11)) | K11: =IF(A11="","",ROUND(Settings!$B$3/100*'Book by Line'!$E$17,2)) | M11: =IF(A11="","",IF(L11<>"",L11,K11)) | N11: =IF(A11="","",ROUND(B11+C11+F11*Settings!$B$8,2)) | O11: =IF(A11="","",IFERROR(ROUND(N11/G11,2),0)) | P11: =IF(A11="","",ROUND(J11+M11*(IF(Settings!$B$9>=2,'Book by Line'!$M$17/100,0)+IF(Settings!$B$9>=3,POWER('Book by Line'!$M$17/100,2),0)+IF(Settings!$B$9>=4,POWER('Book by Line'!$M$17/100,3),0)+IF(Settings!$B$9>=5,POWER('Book by Line'!$M$17/100,4),0)),2)) | Q11: =IF(A11="","",IFERROR(ROUND(P11/O11,2),0)) | R11: =IF(A11="","",IFERROR(ROUND(N11/J11,1),0))
D12: =IF(A12="","",ROUND(Producers!$G$17/12,1)) | F12: =IF(A12="","",IF(E12<>"",E12,D12)) | H12: =IF(A12="","",ROUND(Settings!$B$2/100*'Book by Line'!$E$17,2)) | J12: =IF(A12="","",IF(I12<>"",I12,H12)) | K12: =IF(A12="","",ROUND(Settings!$B$3/100*'Book by Line'!$E$17,2)) | M12: =IF(A12="","",IF(L12<>"",L12,K12)) | N12: =IF(A12="","",ROUND(B12+C12+F12*Settings!$B$8,2)) | O12: =IF(A12="","",IFERROR(ROUND(N12/G12,2),0)) | P12: =IF(A12="","",ROUND(J12+M12*(IF(Settings!$B$9>=2,'Book by Line'!$M$17/100,0)+IF(Settings!$B$9>=3,POWER('Book by Line'!$M$17/100,2),0)+IF(Settings!$B$9>=4,POWER('Book by Line'!$M$17/100,3),0)+IF(Settings!$B$9>=5,POWER('Book by Line'!$M$17/100,4),0)),2)) | Q12: =IF(A12="","",IFERROR(ROUND(P12/O12,2),0)) | R12: =IF(A12="","",IFERROR(ROUND(N12/J12,1),0))
D13: =IF(A13="","",ROUND(Producers!$G$17/12,1)) | F13: =IF(A13="","",IF(E13<>"",E13,D13)) | H13: =IF(A13="","",ROUND(Settings!$B$2/100*'Book by Line'!$E$17,2)) | J13: =IF(A13="","",IF(I13<>"",I13,H13)) | K13: =IF(A13="","",ROUND(Settings!$B$3/100*'Book by Line'!$E$17,2)) | M13: =IF(A13="","",IF(L13<>"",L13,K13)) | N13: =IF(A13="","",ROUND(B13+C13+F13*Settings!$B$8,2)) | O13: =IF(A13="","",IFERROR(ROUND(N13/G13,2),0)) | P13: =IF(A13="","",ROUND(J13+M13*(IF(Settings!$B$9>=2,'Book by Line'!$M$17/100,0)+IF(Settings!$B$9>=3,POWER('Book by Line'!$M$17/100,2),0)+IF(Settings!$B$9>=4,POWER('Book by Line'!$M$17/100,3),0)+IF(Settings!$B$9>=5,POWER('Book by Line'!$M$17/100,4),0)),2)) | Q13: =IF(A13="","",IFERROR(ROUND(P13/O13,2),0)) | R13: =IF(A13="","",IFERROR(ROUND(N13/J13,1),0))
D14: =IF(A14="","",ROUND(Producers!$G$17/12,1)) | F14: =IF(A14="","",IF(E14<>"",E14,D14)) | H14: =IF(A14="","",ROUND(Settings!$B$2/100*'Book by Line'!$E$17,2)) | J14: =IF(A14="","",IF(I14<>"",I14,H14)) | K14: =IF(A14="","",ROUND(Settings!$B$3/100*'Book by Line'!$E$17,2)) | M14: =IF(A14="","",IF(L14<>"",L14,K14)) | N14: =IF(A14="","",ROUND(B14+C14+F14*Settings!$B$8,2)) | O14: =IF(A14="","",IFERROR(ROUND(N14/G14,2),0)) | P14: =IF(A14="","",ROUND(J14+M14*(IF(Settings!$B$9>=2,'Book by Line'!$M$17/100,0)+IF(Settings!$B$9>=3,POWER('Book by Line'!$M$17/100,2),0)+IF(Settings!$B$9>=4,POWER('Book by Line'!$M$17/100,3),0)+IF(Settings!$B$9>=5,POWER('Book by Line'!$M$17/100,4),0)),2)) | Q14: =IF(A14="","",IFERROR(ROUND(P14/O14,2),0)) | R14: =IF(A14="","",IFERROR(ROUND(N14/J14,1),0))
D15: =IF(A15="","",ROUND(Producers!$G$17/12,1)) | F15: =IF(A15="","",IF(E15<>"",E15,D15)) | H15: =IF(A15="","",ROUND(Settings!$B$2/100*'Book by Line'!$E$17,2)) | J15: =IF(A15="","",IF(I15<>"",I15,H15)) | K15: =IF(A15="","",ROUND(Settings!$B$3/100*'Book by Line'!$E$17,2)) | M15: =IF(A15="","",IF(L15<>"",L15,K15)) | N15: =IF(A15="","",ROUND(B15+C15+F15*Settings!$B$8,2)) | O15: =IF(A15="","",IFERROR(ROUND(N15/G15,2),0)) | P15: =IF(A15="","",ROUND(J15+M15*(IF(Settings!$B$9>=2,'Book by Line'!$M$17/100,0)+IF(Settings!$B$9>=3,POWER('Book by Line'!$M$17/100,2),0)+IF(Settings!$B$9>=4,POWER('Book by Line'!$M$17/100,3),0)+IF(Settings!$B$9>=5,POWER('Book by Line'!$M$17/100,4),0)),2)) | Q15: =IF(A15="","",IFERROR(ROUND(P15/O15,2),0)) | R15: =IF(A15="","",IFERROR(ROUND(N15/J15,1),0))
D16: =IF(A16="","",ROUND(Producers!$G$17/12,1)) | F16: =IF(A16="","",IF(E16<>"",E16,D16)) | H16: =IF(A16="","",ROUND(Settings!$B$2/100*'Book by Line'!$E$17,2)) | J16: =IF(A16="","",IF(I16<>"",I16,H16)) | K16: =IF(A16="","",ROUND(Settings!$B$3/100*'Book by Line'!$E$17,2)) | M16: =IF(A16="","",IF(L16<>"",L16,K16)) | N16: =IF(A16="","",ROUND(B16+C16+F16*Settings!$B$8,2)) | O16: =IF(A16="","",IFERROR(ROUND(N16/G16,2),0)) | P16: =IF(A16="","",ROUND(J16+M16*(IF(Settings!$B$9>=2,'Book by Line'!$M$17/100,0)+IF(Settings!$B$9>=3,POWER('Book by Line'!$M$17/100,2),0)+IF(Settings!$B$9>=4,POWER('Book by Line'!$M$17/100,3),0)+IF(Settings!$B$9>=5,POWER('Book by Line'!$M$17/100,4),0)),2)) | Q16: =IF(A16="","",IFERROR(ROUND(P16/O16,2),0)) | R16: =IF(A16="","",IFERROR(ROUND(N16/J16,1),0))
A17: Total | B17: =SUM(B5:B16) -> 5200 | C17: =SUM(C5:C16) -> 3300 | F17: =SUM(F5:F16) -> 723.5 | G17: =SUM(G5:G16) -> 130 | J17: =IFERROR(ROUND(SUMPRODUCT(G5:G16,J5:J16)/G17,2),0) -> 255.09 | M17: =IFERROR(ROUND(SUMPRODUCT(G5:G16,M5:M16)/G17,2),0) -> 169.32 | N17: =SUM(N5:N16) -> 41057.5 | O17: =IFERROR(ROUND(N17/G17,2),0) -> 315.83 | P17: =ROUND(J17+M17*(IF(Settings!$B$9>=2,'Book by Line'!$M$17/100,0)+IF(Settings!$B$9>=3,POWER('Book by Line'!$M$17/100,2),0)+IF(Settings!$B$9>=4,POWER('Book by Line'!$M$17/100,3),0)+IF(Settings!$B$9>=5,POWER('Book by Line'!$M$17/100,4),0)),2) -> 549.96 | Q17: =IFERROR(ROUND(P17/O17,2),0) -> 1.74 | R17: =IFERROR(ROUND(N17/J17,1),0) -> 161

Sheet Commission Splits
A1: Commission Splits
A2: One row per policy or client. Agent split % and agency fee default from Settings; type your own to override them. The carrier commission % is the one in your carrier contract for this policy.
A4: Policy or client | B4: Producer | C4: Premium | D4: Carrier commission % | E4: Default agent split % (Settings) | F4: or type your own split % | G4: Agent split % used | H4: Default agency fee (Settings) | I4: or type your own fee | J4: Agency fee used | K4: Gross commission | L4: Agent share | M4: Agency share | N4: Agent net after fee | O4: Agent effective % of premium | P4: Agency net
A5: Miller auto | B5: A. Rivera | C5: 1450 | D5: 15 | E5: =IF(A5="","",Settings!$B$4) -> 60 | G5: =IF(A5="","",IF(F5<>"",F5,E5)) -> 60 | H5: =IF(A5="","",Settings!$B$5) -> 10 | J5: =IF(A5="","",IF(I5<>"",I5,H5)) -> 10 | K5: =IF(A5="","",ROUND(C5*D5/100,2)) -> 217.5 | L5: =IF(A5="","",ROUND(K5*G5/100,2)) -> 130.5 | M5: =IF(A5="","",ROUND(K5-L5,2)) -> 87 | N5: =IF(A5="","",ROUND(L5-J5,2)) -> 120.5 | O5: =IF(A5="","",IFERROR(ROUND(N5/C5*100,2),0)) -> 8.31 | P5: =IF(A5="","",ROUND(M5+J5,2)) -> 97
A6: Lopez home | B6: A. Rivera | C6: 1700 | D6: 15 | E6: =IF(A6="","",Settings!$B$4) -> 60 | G6: =IF(A6="","",IF(F6<>"",F6,E6)) -> 60 | H6: =IF(A6="","",Settings!$B$5) -> 10 | J6: =IF(A6="","",IF(I6<>"",I6,H6)) -> 10 | K6: =IF(A6="","",ROUND(C6*D6/100,2)) -> 255 | L6: =IF(A6="","",ROUND(K6*G6/100,2)) -> 153 | M6: =IF(A6="","",ROUND(K6-L6,2)) -> 102 | N6: =IF(A6="","",ROUND(L6-J6,2)) -> 143 | O6: =IF(A6="","",IFERROR(ROUND(N6/C6*100,2),0)) -> 8.41 | P6: =IF(A6="","",ROUND(M6+J6,2)) -> 112
A7: Harbor Cafe BOP | B7: B. Cole | C7: 4800 | D7: 12 | E7: =IF(A7="","",Settings!$B$4) -> 60 | F7: 50 | G7: =IF(A7="","",IF(F7<>"",F7,E7)) -> 50 | H7: =IF(A7="","",Settings!$B$5) -> 10 | J7: =IF(A7="","",IF(I7<>"",I7,H7)) -> 10 | K7: =IF(A7="","",ROUND(C7*D7/100,2)) -> 576 | L7: =IF(A7="","",ROUND(K7*G7/100,2)) -> 288 | M7: =IF(A7="","",ROUND(K7-L7,2)) -> 288 | N7: =IF(A7="","",ROUND(L7-J7,2)) -> 278 | O7: =IF(A7="","",IFERROR(ROUND(N7/C7*100,2),0)) -> 5.79 | P7: =IF(A7="","",ROUND(M7+J7,2)) -> 298
A8: Nguyen life | B8: C. Park | C8: 1100 | D8: 60 | E8: =IF(A8="","",Settings!$B$4) -> 60 | G8: =IF(A8="","",IF(F8<>"",F8,E8)) -> 60 | H8: =IF(A8="","",Settings!$B$5) -> 10 | J8: =IF(A8="","",IF(I8<>"",I8,H8)) -> 10 | K8: =IF(A8="","",ROUND(C8*D8/100,2)) -> 660 | L8: =IF(A8="","",ROUND(K8*G8/100,2)) -> 396 | M8: =IF(A8="","",ROUND(K8-L8,2)) -> 264 | N8: =IF(A8="","",ROUND(L8-J8,2)) -> 386 | O8: =IF(A8="","",IFERROR(ROUND(N8/C8*100,2),0)) -> 35.09 | P8: =IF(A8="","",ROUND(M8+J8,2)) -> 274
A9: Patel auto | B9: C. Park | C9: 1300 | D9: 15 | E9: =IF(A9="","",Settings!$B$4) -> 60 | G9: =IF(A9="","",IF(F9<>"",F9,E9)) -> 60 | H9: =IF(A9="","",Settings!$B$5) -> 10 | J9: =IF(A9="","",IF(I9<>"",I9,H9)) -> 10 | K9: =IF(A9="","",ROUND(C9*D9/100,2)) -> 195 | L9: =IF(A9="","",ROUND(K9*G9/100,2)) -> 117 | M9: =IF(A9="","",ROUND(K9-L9,2)) -> 78 | N9: =IF(A9="","",ROUND(L9-J9,2)) -> 107 | O9: =IF(A9="","",IFERROR(ROUND(N9/C9*100,2),0)) -> 8.23 | P9: =IF(A9="","",ROUND(M9+J9,2)) -> 88
A10: Okafor home | B10: B. Cole | C10: 1550 | D10: 15 | E10: =IF(A10="","",Settings!$B$4) -> 60 | G10: =IF(A10="","",IF(F10<>"",F10,E10)) -> 60 | H10: =IF(A10="","",Settings!$B$5) -> 10 | I10: 0 | J10: =IF(A10="","",IF(I10<>"",I10,H10)) -> 0 | K10: =IF(A10="","",ROUND(C10*D10/100,2)) -> 232.5 | L10: =IF(A10="","",ROUND(K10*G10/100,2)) -> 139.5 | M10: =IF(A10="","",ROUND(K10-L10,2)) -> 93 | N10: =IF(A10="","",ROUND(L10-J10,2)) -> 139.5 | O10: =IF(A10="","",IFERROR(ROUND(N10/C10*100,2),0)) -> 9 | P10: =IF(A10="","",ROUND(M10+J10,2)) -> 93
A11: Summit Builders GL | B11: D. Shah | C11: 7200 | D11: 12 | E11: =IF(A11="","",Settings!$B$4) -> 60 | G11: =IF(A11="","",IF(F11<>"",F11,E11)) -> 60 | H11: =IF(A11="","",Settings!$B$5) -> 10 | J11: =IF(A11="","",IF(I11<>"",I11,H11)) -> 10 | K11: =IF(A11="","",ROUND(C11*D11/100,2)) -> 864 | L11: =IF(A11="","",ROUND(K11*G11/100,2)) -> 518.4 | M11: =IF(A11="","",ROUND(K11-L11,2)) -> 345.6 | N11: =IF(A11="","",ROUND(L11-J11,2)) -> 508.4 | O11: =IF(A11="","",IFERROR(ROUND(N11/C11*100,2),0)) -> 7.06 | P11: =IF(A11="","",ROUND(M11+J11,2)) -> 355.6
A12: Reyes umbrella | B12: D. Shah | C12: 480 | D12: 15 | E12: =IF(A12="","",Settings!$B$4) -> 60 | G12: =IF(A12="","",IF(F12<>"",F12,E12)) -> 60 | H12: =IF(A12="","",Settings!$B$5) -> 10 | J12: =IF(A12="","",IF(I12<>"",I12,H12)) -> 10 | K12: =IF(A12="","",ROUND(C12*D12/100,2)) -> 72 | L12: =IF(A12="","",ROUND(K12*G12/100,2)) -> 43.2 | M12: =IF(A12="","",ROUND(K12-L12,2)) -> 28.8 | N12: =IF(A12="","",ROUND(L12-J12,2)) -> 33.2 | O12: =IF(A12="","",IFERROR(ROUND(N12/C12*100,2),0)) -> 6.92 | P12: =IF(A12="","",ROUND(M12+J12,2)) -> 38.8
A13: Kim health | B13: A. Rivera | C13: 2600 | D13: 8 | E13: =IF(A13="","",Settings!$B$4) -> 60 | G13: =IF(A13="","",IF(F13<>"",F13,E13)) -> 60 | H13: =IF(A13="","",Settings!$B$5) -> 10 | J13: =IF(A13="","",IF(I13<>"",I13,H13)) -> 10 | K13: =IF(A13="","",ROUND(C13*D13/100,2)) -> 208 | L13: =IF(A13="","",ROUND(K13*G13/100,2)) -> 124.8 | M13: =IF(A13="","",ROUND(K13-L13,2)) -> 83.2 | N13: =IF(A13="","",ROUND(L13-J13,2)) -> 114.8 | O13: =IF(A13="","",IFERROR(ROUND(N13/C13*100,2),0)) -> 4.42 | P13: =IF(A13="","",ROUND(M13+J13,2)) -> 93.2
A14: Baker auto | B14: E. Grant | C14: 1250 | D14: 15 | E14: =IF(A14="","",Settings!$B$4) -> 60 | G14: =IF(A14="","",IF(F14<>"",F14,E14)) -> 60 | H14: =IF(A14="","",Settings!$B$5) -> 10 | J14: =IF(A14="","",IF(I14<>"",I14,H14)) -> 10 | K14: =IF(A14="","",ROUND(C14*D14/100,2)) -> 187.5 | L14: =IF(A14="","",ROUND(K14*G14/100,2)) -> 112.5 | M14: =IF(A14="","",ROUND(K14-L14,2)) -> 75 | N14: =IF(A14="","",ROUND(L14-J14,2)) -> 102.5 | O14: =IF(A14="","",IFERROR(ROUND(N14/C14*100,2),0)) -> 8.2 | P14: =IF(A14="","",ROUND(M14+J14,2)) -> 85
E15: =IF(A15="","",Settings!$B$4) | G15: =IF(A15="","",IF(F15<>"",F15,E15)) | H15: =IF(A15="","",Settings!$B$5) | J15: =IF(A15="","",IF(I15<>"",I15,H15)) | K15: =IF(A15="","",ROUND(C15*D15/100,2)) | L15: =IF(A15="","",ROUND(K15*G15/100,2)) | M15: =IF(A15="","",ROUND(K15-L15,2)) | N15: =IF(A15="","",ROUND(L15-J15,2)) | O15: =IF(A15="","",IFERROR(ROUND(N15/C15*100,2),0)) | P15: =IF(A15="","",ROUND(M15+J15,2))
E16: =IF(A16="","",Settings!$B$4) | G16: =IF(A16="","",IF(F16<>"",F16,E16)) | H16: =IF(A16="","",Settings!$B$5) | J16: =IF(A16="","",IF(I16<>"",I16,H16)) | K16: =IF(A16="","",ROUND(C16*D16/100,2)) | L16: =IF(A16="","",ROUND(K16*G16/100,2)) | M16: =IF(A16="","",ROUND(K16-L16,2)) | N16: =IF(A16="","",ROUND(L16-J16,2)) | O16: =IF(A16="","",IFERROR(ROUND(N16/C16*100,2),0)) | P16: =IF(A16="","",ROUND(M16+J16,2))
E17: =IF(A17="","",Settings!$B$4) | G17: =IF(A17="","",IF(F17<>"",F17,E17)) | H17: =IF(A17="","",Settings!$B$5) | J17: =IF(A17="","",IF(I17<>"",I17,H17)) | K17: =IF(A17="","",ROUND(C17*D17/100,2)) | L17: =IF(A17="","",ROUND(K17*G17/100,2)) | M17: =IF(A17="","",ROUND(K17-L17,2)) | N17: =IF(A17="","",ROUND(L17-J17,2)) | O17: =IF(A17="","",IFERROR(ROUND(N17/C17*100,2),0)) | P17: =IF(A17="","",ROUND(M17+J17,2))
E18: =IF(A18="","",Settings!$B$4) | G18: =IF(A18="","",IF(F18<>"",F18,E18)) | H18: =IF(A18="","",Settings!$B$5) | J18: =IF(A18="","",IF(I18<>"",I18,H18)) | K18: =IF(A18="","",ROUND(C18*D18/100,2)) | L18: =IF(A18="","",ROUND(K18*G18/100,2)) | M18: =IF(A18="","",ROUND(K18-L18,2)) | N18: =IF(A18="","",ROUND(L18-J18,2)) | O18: =IF(A18="","",IFERROR(ROUND(N18/C18*100,2),0)) | P18: =IF(A18="","",ROUND(M18+J18,2))
E19: =IF(A19="","",Settings!$B$4) | G19: =IF(A19="","",IF(F19<>"",F19,E19)) | H19: =IF(A19="","",Settings!$B$5) | J19: =IF(A19="","",IF(I19<>"",I19,H19)) | K19: =IF(A19="","",ROUND(C19*D19/100,2)) | L19: =IF(A19="","",ROUND(K19*G19/100,2)) | M19: =IF(A19="","",ROUND(K19-L19,2)) | N19: =IF(A19="","",ROUND(L19-J19,2)) | O19: =IF(A19="","",IFERROR(ROUND(N19/C19*100,2),0)) | P19: =IF(A19="","",ROUND(M19+J19,2))
E20: =IF(A20="","",Settings!$B$4) | G20: =IF(A20="","",IF(F20<>"",F20,E20)) | H20: =IF(A20="","",Settings!$B$5) | J20: =IF(A20="","",IF(I20<>"",I20,H20)) | K20: =IF(A20="","",ROUND(C20*D20/100,2)) | L20: =IF(A20="","",ROUND(K20*G20/100,2)) | M20: =IF(A20="","",ROUND(K20-L20,2)) | N20: =IF(A20="","",ROUND(L20-J20,2)) | O20: =IF(A20="","",IFERROR(ROUND(N20/C20*100,2),0)) | P20: =IF(A20="","",ROUND(M20+J20,2))
E21: =IF(A21="","",Settings!$B$4) | G21: =IF(A21="","",IF(F21<>"",F21,E21)) | H21: =IF(A21="","",Settings!$B$5) | J21: =IF(A21="","",IF(I21<>"",I21,H21)) | K21: =IF(A21="","",ROUND(C21*D21/100,2)) | L21: =IF(A21="","",ROUND(K21*G21/100,2)) | M21: =IF(A21="","",ROUND(K21-L21,2)) | N21: =IF(A21="","",ROUND(L21-J21,2)) | O21: =IF(A21="","",IFERROR(ROUND(N21/C21*100,2),0)) | P21: =IF(A21="","",ROUND(M21+J21,2))
E22: =IF(A22="","",Settings!$B$4) | G22: =IF(A22="","",IF(F22<>"",F22,E22)) | H22: =IF(A22="","",Settings!$B$5) | J22: =IF(A22="","",IF(I22<>"",I22,H22)) | K22: =IF(A22="","",ROUND(C22*D22/100,2)) | L22: =IF(A22="","",ROUND(K22*G22/100,2)) | M22: =IF(A22="","",ROUND(K22-L22,2)) | N22: =IF(A22="","",ROUND(L22-J22,2)) | O22: =IF(A22="","",IFERROR(ROUND(N22/C22*100,2),0)) | P22: =IF(A22="","",ROUND(M22+J22,2))
E23: =IF(A23="","",Settings!$B$4) | G23: =IF(A23="","",IF(F23<>"",F23,E23)) | H23: =IF(A23="","",Settings!$B$5) | J23: =IF(A23="","",IF(I23<>"",I23,H23)) | K23: =IF(A23="","",ROUND(C23*D23/100,2)) | L23: =IF(A23="","",ROUND(K23*G23/100,2)) | M23: =IF(A23="","",ROUND(K23-L23,2)) | N23: =IF(A23="","",ROUND(L23-J23,2)) | O23: =IF(A23="","",IFERROR(ROUND(N23/C23*100,2),0)) | P23: =IF(A23="","",ROUND(M23+J23,2))
E24: =IF(A24="","",Settings!$B$4) | G24: =IF(A24="","",IF(F24<>"",F24,E24)) | H24: =IF(A24="","",Settings!$B$5) | J24: =IF(A24="","",IF(I24<>"",I24,H24)) | K24: =IF(A24="","",ROUND(C24*D24/100,2)) | L24: =IF(A24="","",ROUND(K24*G24/100,2)) | M24: =IF(A24="","",ROUND(K24-L24,2)) | N24: =IF(A24="","",ROUND(L24-J24,2)) | O24: =IF(A24="","",IFERROR(ROUND(N24/C24*100,2),0)) | P24: =IF(A24="","",ROUND(M24+J24,2))
A25: Total | C25: =SUM(C5:C24) -> 23430 | J25: =SUM(J5:J24) -> 90 | K25: =SUM(K5:K24) -> 3467.5 | L25: =SUM(L5:L24) -> 2022.9 | M25: =SUM(M5:M24) -> 1444.6 | N25: =SUM(N5:N24) -> 1932.9 | O25: =IFERROR(ROUND(N25/C25*100,2),0) -> 8.25 | P25: =SUM(P5:P24) -> 1534.6
A26: PER-PRODUCER TOTALS
A27: Producer | B27: Policies | C27: Premium | D27: Gross commission | E27: Agent net after fee | F27: Agency net
A28: A. Rivera | B28: =IF(A28="","",COUNTIF($B$5:$B$24,A28)) -> 3 | C28: =IF(A28="","",SUMIF($B$5:$B$24,A28,$C$5:$C$24)) -> 5750 | D28: =IF(A28="","",SUMIF($B$5:$B$24,A28,$K$5:$K$24)) -> 680.5 | E28: =IF(A28="","",SUMIF($B$5:$B$24,A28,$N$5:$N$24)) -> 378.3 | F28: =IF(A28="","",SUMIF($B$5:$B$24,A28,$P$5:$P$24)) -> 302.2
A29: B. Cole | B29: =IF(A29="","",COUNTIF($B$5:$B$24,A29)) -> 2 | C29: =IF(A29="","",SUMIF($B$5:$B$24,A29,$C$5:$C$24)) -> 6350 | D29: =IF(A29="","",SUMIF($B$5:$B$24,A29,$K$5:$K$24)) -> 808.5 | E29: =IF(A29="","",SUMIF($B$5:$B$24,A29,$N$5:$N$24)) -> 417.5 | F29: =IF(A29="","",SUMIF($B$5:$B$24,A29,$P$5:$P$24)) -> 391
A30: C. Park | B30: =IF(A30="","",COUNTIF($B$5:$B$24,A30)) -> 2 | C30: =IF(A30="","",SUMIF($B$5:$B$24,A30,$C$5:$C$24)) -> 2400 | D30: =IF(A30="","",SUMIF($B$5:$B$24,A30,$K$5:$K$24)) -> 855 | E30: =IF(A30="","",SUMIF($B$5:$B$24,A30,$N$5:$N$24)) -> 493 | F30: =IF(A30="","",SUMIF($B$5:$B$24,A30,$P$5:$P$24)) -> 362
A31: D. Shah | B31: =IF(A31="","",COUNTIF($B$5:$B$24,A31)) -> 2 | C31: =IF(A31="","",SUMIF($B$5:$B$24,A31,$C$5:$C$24)) -> 7680 | D31: =IF(A31="","",SUMIF($B$5:$B$24,A31,$K$5:$K$24)) -> 936 | E31: =IF(A31="","",SUMIF($B$5:$B$24,A31,$N$5:$N$24)) -> 541.6 | F31: =IF(A31="","",SUMIF($B$5:$B$24,A31,$P$5:$P$24)) -> 394.4
A32: E. Grant | B32: =IF(A32="","",COUNTIF($B$5:$B$24,A32)) -> 1 | C32: =IF(A32="","",SUMIF($B$5:$B$24,A32,$C$5:$C$24)) -> 1250 | D32: =IF(A32="","",SUMIF($B$5:$B$24,A32,$K$5:$K$24)) -> 187.5 | E32: =IF(A32="","",SUMIF($B$5:$B$24,A32,$N$5:$N$24)) -> 102.5 | F32: =IF(A32="","",SUMIF($B$5:$B$24,A32,$P$5:$P$24)) -> 85
B33: =IF(A33="","",COUNTIF($B$5:$B$24,A33)) | C33: =IF(A33="","",SUMIF($B$5:$B$24,A33,$C$5:$C$24)) | D33: =IF(A33="","",SUMIF($B$5:$B$24,A33,$K$5:$K$24)) | E33: =IF(A33="","",SUMIF($B$5:$B$24,A33,$N$5:$N$24)) | F33: =IF(A33="","",SUMIF($B$5:$B$24,A33,$P$5:$P$24))

Sheet Summary
A1: Summary
A2: Policies on the book now | B2: =Settings!$B$13 -> 1132 | C2: Book by Line totals: start − lost + new
A3: Retention % | B3: ='Book by Line'!M17 -> 91.12 | C3: Book by Line totals: (start − lost) ÷ start
A4: Target retention % (your own) | B4: =Settings!$B$6 -> 90 | C4: from Settings: your own placeholder, not a benchmark
A5: Retention vs target (points) | B5: =ROUND(B3-B4,2) -> 1.12 | C5: negative = below your own target
A6: Annual renewal commission on the retained book | B6: ='Book by Line'!P17 -> 164761 | C6: retained policies × average premium × renewal %
A7: Commission lost to lapses | B7: ='Book by Line'!R17 -> 16614 | C7: lost policies × average premium × renewal %
A8: Lines below target retention | B8: =COUNTIF('Book by Line'!$S$5:$S$16,"<0") -> 2 | C8: Book by Line rows with retention below your target
A9: Agency commission revenue | B9: =ROUND('Book by Line'!P17+'Book by Line'!Q17,2) -> 209446 | C9: Book by Line: renewal commission + new-business commission
A10: Producers | B10: =Settings!$B$11 -> 5 | C10: names on the Producers sheet
A11: Revenue per producer | B11: =IFERROR(ROUND(B9/B10,2),0) -> 41889.2 | C11: agency commission revenue ÷ producers
A12: Revenue per employee | B12: =IFERROR(ROUND(B9/Settings!$B$12,2),0) -> 26180.75 | C12: agency commission revenue ÷ (producers + support staff)
A13: Compensation ratio % | B13: =Producers!I17 -> 37.08 | C13: Producers totals: compensation paid ÷ commission revenue credited
A14: Compensation ratio vs target (points) | B14: =ROUND(B13-Settings!$B$7,2) -> 2.08 | C14: positive = above your own target
A15: Acquisition cost year to date | B15: =Acquisition!N17 -> 41057.5 | C15: Acquisition totals: marketing + leads + producer time
A16: Cost per policy acquired | B16: =Acquisition!O17 -> 315.83 | C16: Acquisition totals: cost ÷ policies written
A17: Lifetime commission per policy | B17: =Acquisition!P17 -> 549.96 | C17: first-year + renewals over the Settings years at book retention
A18: Value-to-cost ratio | B18: =Acquisition!Q17 -> 1.74 | C18: lifetime commission per policy ÷ cost per policy
A19: Best line by net growth | B19: =IFERROR(INDEX('Book by Line'!$A$5:$A$16,MATCH(MAX('Book by Line'!$O$5:$O$16),'Book by Line'!$O$5:$O$16,0)),"") -> Life | C19: highest net growth % on Book by Line
A20: Its net growth % | B20: =IFERROR(MAX('Book by Line'!$O$5:$O$16),0) -> 8.33 | C20: policies at end vs start
A21: Best producer by commission revenue | B21: =IFERROR(INDEX(Producers!$A$5:$A$16,MATCH(MAX(Producers!$E$5:$E$16),Producers!$E$5:$E$16,0)),"") -> A. Rivera | C21: highest commission revenue credited on Producers
A22: Their commission revenue | B22: =IFERROR(MAX(Producers!$E$5:$E$16),0) -> 34000 | C22: commission revenue credited
A23: Total agent net from splits | B23: ='Commission Splits'!N25 -> 1932.9 | C23: Commission Splits totals: agent share − agency fees
A24: Total agency net from splits | B24: ='Commission Splits'!P25 -> 1534.6 | C24: Commission Splits totals: agency share + agency fees
