Workbook

Sheet Start Here
A1: Salon & Appointment Pricing Workbook
A2: by Knackdesk · knackdesk.com
A4: HOW TO USE
A5: 1. Settings: your monthly overhead line by line, take-home income goal, working weeks, hours, billable share, profit margin, product cost %, average ticket, booth rent, commission split and no-show fee. Every other sheet reads them.
A6: 2. Service Menu: one row per service with category, minutes, product cost, current price and weekly units. Time cost, floor price, suggested price, the gap to your current price and weekly revenue and gross profit are calculated.
A7: 3. Booth vs Commission: compares your monthly take-home renting a booth against working on commission, shows the verdict, the break-even revenue and five revenue scenarios.
A8: 4. Weekly Log: one row per week with appointments booked, no-shows, late cancellations, revenue and costs. No-show rate, lost revenue, fees recovered and net are calculated, with totals and a 4-week trailing average.
A9: 5. Capacity: how many appointments fit in your week from your hours, average service length and buffer time, the revenue ceiling, and your latest logged week against what you expect.
A10: 6. Summary: target hourly rate, services priced below floor, weekly menu revenue and gross profit, best and worst margin services, the booth vs commission verdict, no-show losses and expected appointments.
A12: LEGEND
A13: Blue text = a cell you type into. Black text = a formula, leave it alone. Yellow fill = key inputs.
A15: DEFINITIONS
... A24: Arithmetic only; not financial advice.

Sheet Settings
A1: Settings
A2: Rent or booth fee (monthly) | B2: 1200 | C2: Example default 1,200 a month. Your room, chair or booth cost; leave 0 here if you pay booth rent weekly and set it in row 17 instead.
A3: Products and supplies (monthly) | B3: 300 | C3: Example default 300 a month. Backbar, towels and consumables not charged per service.
A4: Insurance (monthly) | B4: 80 | C4: Example default 80 a month. Liability and equipment cover.
A5: Software and booking (monthly) | B5: 60 | C5: Example default 60 a month. Booking app, card fees subscription, accounting.
A6: Marketing (monthly) | B6: 100 | C6: Example default 100 a month. Ads, listings, printing.
A7: Other overhead (monthly) | B7: 160 | C7: Example default 160 a month. Training, phone, laundry, anything else.
A8: Total monthly overhead | B8: =SUM(B2:B7) -> 1900 | C8: formula: sum of the six overhead rows above
A9: Monthly take-home income goal | B9: 4000 | C9: Example default 4,000 a month. What you want to pay yourself before personal tax.
A10: Working weeks per year | B10: 48 | C10: Default 48: 52 weeks less 4 weeks of holiday, sickness and training.
A11: Hours worked per week | B11: 40 | C11: Default 40. All hours at work, including admin and gaps.
A12: Share of hours that are billable % | B12: 75 | C12: Default 75. The share of your hours spent on paid services; the rest is cleaning, admin, gaps and no-shows.
A13: Profit margin % to add on services | B13: 20 | C13: Default 20. Added on top of the floor price to give the suggested price.
A14: Product cost % of revenue | B14: 10 | C14: Default 10. Used on Booth vs Commission: product you buy yourself when renting a booth.
A15: Average ticket | B15: 65 | C15: Default 65. Average spend per appointment; used for no-show cost and capacity revenue.
A16: Payroll taxes and benefits % | B16: 0 | C16: Default 0. Only if you pay yourself or staff through payroll: added on top of the income goal in the target hourly rate.
A17: Weekly booth rent | B17: 300 | C17: Default 300 a week. Used on Booth vs Commission (× 52 ÷ 12 for a monthly figure).
A18: Commission % you keep (commission salon) | B18: 45 | C18: Default 45. Your share of service revenue when working on commission; the salon keeps the rest and supplies product.
A19: No-show fee | B19: 25 | C19: Default 25. Charged per no-show or late cancellation; used on the Weekly Log.
A20: Billable hours per month | B20: =ROUND(B11*B12/100*B10/12,2) -> 120 | C20: formula: hours per week × billable % × working weeks ÷ 12
A21: Target hourly rate | B21: =IFERROR(ROUND((B8+B9*(1+B16/100))/B20,2),0) -> 49.17 | C21: formula: (total overhead + income goal, plus payroll % if any) ÷ billable hours per month
A22: Overhead per billable hour | B22: =IFERROR(ROUND(B8/B20,2),0) -> 15.83 | C22: formula: total overhead ÷ billable hours per month (the part of the rate that only keeps the doors open)
A23: Target rate per minute | B23: =ROUND(B21/60,4) -> 0.8195 | C23: formula: target hourly rate ÷ 60

Sheet Service Menu
A1: Service Menu
A2: One row per service. Time cost uses the target hourly rate from Settings; suggested price adds your profit margin to the floor price.
A4: Service | B4: Category | C4: Minutes | D4: Product cost per service | E4: Current price | F4: Weekly units | G4: Time cost | H4: Floor price | I4: Suggested price | J4: Gap (current − suggested) | K4: Weekly revenue | L4: Weekly gross profit | M4: Gross profit per minute
A5: Women's cut | B5: hair | C5: 45 | D5: 4 | E5: 55 | F5: 12 | G5: =IF(A5="","",ROUND(Settings!$B$21*C5/60,2)) -> 36.88 | H5: =IF(A5="","",G5+D5) -> 40.88 | I5: =IF(A5="","",ROUND(H5*(1+Settings!$B$13/100),2)) -> 49.06 | J5: =IF(A5="","",E5-I5) -> 5.94 | K5: =IF(A5="","",ROUND(E5*F5,2)) -> 660 | L5: =IF(A5="","",ROUND((E5-D5)*F5,2)) -> 612 | M5: =IF(A5="","",IFERROR(ROUND((E5-D5)/C5,3),"")) -> 1.133
A6: Full colour | B6: colour | C6: 120 | D6: 22 | E6: 140 | F6: 5 | G6: =IF(A6="","",ROUND(Settings!$B$21*C6/60,2)) -> 98.34 | H6: =IF(A6="","",G6+D6) -> 120.34 | I6: =IF(A6="","",ROUND(H6*(1+Settings!$B$13/100),2)) -> 144.41 | J6: =IF(A6="","",E6-I6) -> -4.41 | K6: =IF(A6="","",ROUND(E6*F6,2)) -> 700 | L6: =IF(A6="","",ROUND((E6-D6)*F6,2)) -> 590 | M6: =IF(A6="","",IFERROR(ROUND((E6-D6)/C6,3),"")) -> 0.983
A7: Beard trim | B7: barber | C7: 20 | D7: 1 | E7: 22 | F7: 15 | G7: =IF(A7="","",ROUND(Settings!$B$21*C7/60,2)) -> 16.39 | H7: =IF(A7="","",G7+D7) -> 17.39 | I7: =IF(A7="","",ROUND(H7*(1+Settings!$B$13/100),2)) -> 20.87 | J7: =IF(A7="","",E7-I7) -> 1.13 | K7: =IF(A7="","",ROUND(E7*F7,2)) -> 330 | L7: =IF(A7="","",ROUND((E7-D7)*F7,2)) -> 315 | M7: =IF(A7="","",IFERROR(ROUND((E7-D7)/C7,3),"")) -> 1.05
A8: Personal training session | B8: training | C8: 60 | D8: 0 | E8: 60 | F8: 10 | G8: =IF(A8="","",ROUND(Settings!$B$21*C8/60,2)) -> 49.17 | H8: =IF(A8="","",G8+D8) -> 49.17 | I8: =IF(A8="","",ROUND(H8*(1+Settings!$B$13/100),2)) -> 59 | J8: =IF(A8="","",E8-I8) -> 1 | K8: =IF(A8="","",ROUND(E8*F8,2)) -> 600 | L8: =IF(A8="","",ROUND((E8-D8)*F8,2)) -> 600 | M8: =IF(A8="","",IFERROR(ROUND((E8-D8)/C8,3),"")) -> 1
A9: Men's cut | B9: barber | C9: 30 | D9: 2 | E9: 30 | F9: 6 | G9: =IF(A9="","",ROUND(Settings!$B$21*C9/60,2)) -> 24.59 | H9: =IF(A9="","",G9+D9) -> 26.59 | I9: =IF(A9="","",ROUND(H9*(1+Settings!$B$13/100),2)) -> 31.91 | J9: =IF(A9="","",E9-I9) -> -1.91 | K9: =IF(A9="","",ROUND(E9*F9,2)) -> 180 | L9: =IF(A9="","",ROUND((E9-D9)*F9,2)) -> 168 | M9: =IF(A9="","",IFERROR(ROUND((E9-D9)/C9,3),"")) -> 0.933
A10: Gel manicure | B10: nails | C10: 45 | D10: 5 | E10: 40 | F10: 3 | G10: =IF(A10="","",ROUND(Settings!$B$21*C10/60,2)) -> 36.88 | H10: =IF(A10="","",G10+D10) -> 41.88 | I10: =IF(A10="","",ROUND(H10*(1+Settings!$B$13/100),2)) -> 50.26 | J10: =IF(A10="","",E10-I10) -> -10.26 | K10: =IF(A10="","",ROUND(E10*F10,2)) -> 120 | L10: =IF(A10="","",ROUND((E10-D10)*F10,2)) -> 105 | M10: =IF(A10="","",IFERROR(ROUND((E10-D10)/C10,3),"")) -> 0.778
A11: Express facial | B11: skin | C11: 30 | D11: 6 | E11: 45 | F11: 2 | G11: =IF(A11="","",ROUND(Settings!$B$21*C11/60,2)) -> 24.59 | H11: =IF(A11="","",G11+D11) -> 30.59 | I11: =IF(A11="","",ROUND(H11*(1+Settings!$B$13/100),2)) -> 36.71 | J11: =IF(A11="","",E11-I11) -> 8.29 | K11: =IF(A11="","",ROUND(E11*F11,2)) -> 90 | L11: =IF(A11="","",ROUND((E11-D11)*F11,2)) -> 78 | M11: =IF(A11="","",IFERROR(ROUND((E11-D11)/C11,3),"")) -> 1.3
A12: Deep tissue massage | B12: massage | C12: 60 | D12: 3 | E12: 75 | F12: 2 | G12: =IF(A12="","",ROUND(Settings!$B$21*C12/60,2)) -> 49.17 | H12: =IF(A12="","",G12+D12) -> 52.17 | I12: =IF(A12="","",ROUND(H12*(1+Settings!$B$13/100),2)) -> 62.6 | J12: =IF(A12="","",E12-I12) -> 12.4 | K12: =IF(A12="","",ROUND(E12*F12,2)) -> 150 | L12: =IF(A12="","",ROUND((E12-D12)*F12,2)) -> 144 | M12: =IF(A12="","",IFERROR(ROUND((E12-D12)/C12,3),"")) -> 1.2
G13: =IF(A13="","",ROUND(Settings!$B$21*C13/60,2)) | H13: =IF(A13="","",G13+D13) | I13: =IF(A13="","",ROUND(H13*(1+Settings!$B$13/100),2)) | J13: =IF(A13="","",E13-I13) | K13: =IF(A13="","",ROUND(E13*F13,2)) | L13: =IF(A13="","",ROUND((E13-D13)*F13,2)) | M13: =IF(A13="","",IFERROR(ROUND((E13-D13)/C13,3),""))
G14: =IF(A14="","",ROUND(Settings!$B$21*C14/60,2)) | H14: =IF(A14="","",G14+D14) | I14: =IF(A14="","",ROUND(H14*(1+Settings!$B$13/100),2)) | J14: =IF(A14="","",E14-I14) | K14: =IF(A14="","",ROUND(E14*F14,2)) | L14: =IF(A14="","",ROUND((E14-D14)*F14,2)) | M14: =IF(A14="","",IFERROR(ROUND((E14-D14)/C14,3),""))
G15: =IF(A15="","",ROUND(Settings!$B$21*C15/60,2)) | H15: =IF(A15="","",G15+D15) | I15: =IF(A15="","",ROUND(H15*(1+Settings!$B$13/100),2)) | J15: =IF(A15="","",E15-I15) | K15: =IF(A15="","",ROUND(E15*F15,2)) | L15: =IF(A15="","",ROUND((E15-D15)*F15,2)) | M15: =IF(A15="","",IFERROR(ROUND((E15-D15)/C15,3),""))
G16: =IF(A16="","",ROUND(Settings!$B$21*C16/60,2)) | H16: =IF(A16="","",G16+D16) | I16: =IF(A16="","",ROUND(H16*(1+Settings!$B$13/100),2)) | J16: =IF(A16="","",E16-I16) | K16: =IF(A16="","",ROUND(E16*F16,2)) | L16: =IF(A16="","",ROUND((E16-D16)*F16,2)) | M16: =IF(A16="","",IFERROR(ROUND((E16-D16)/C16,3),""))
G17: =IF(A17="","",ROUND(Settings!$B$21*C17/60,2)) | H17: =IF(A17="","",G17+D17) | I17: =IF(A17="","",ROUND(H17*(1+Settings!$B$13/100),2)) | J17: =IF(A17="","",E17-I17) | K17: =IF(A17="","",ROUND(E17*F17,2)) | L17: =IF(A17="","",ROUND((E17-D17)*F17,2)) | M17: =IF(A17="","",IFERROR(ROUND((E17-D17)/C17,3),""))
G18: =IF(A18="","",ROUND(Settings!$B$21*C18/60,2)) | H18: =IF(A18="","",G18+D18) | I18: =IF(A18="","",ROUND(H18*(1+Settings!$B$13/100),2)) | J18: =IF(A18="","",E18-I18) | K18: =IF(A18="","",ROUND(E18*F18,2)) | L18: =IF(A18="","",ROUND((E18-D18)*F18,2)) | M18: =IF(A18="","",IFERROR(ROUND((E18-D18)/C18,3),""))
G19: =IF(A19="","",ROUND(Settings!$B$21*C19/60,2)) | H19: =IF(A19="","",G19+D19) | I19: =IF(A19="","",ROUND(H19*(1+Settings!$B$13/100),2)) | J19: =IF(A19="","",E19-I19) | K19: =IF(A19="","",ROUND(E19*F19,2)) | L19: =IF(A19="","",ROUND((E19-D19)*F19,2)) | M19: =IF(A19="","",IFERROR(ROUND((E19-D19)/C19,3),""))
G20: =IF(A20="","",ROUND(Settings!$B$21*C20/60,2)) | H20: =IF(A20="","",G20+D20) | I20: =IF(A20="","",ROUND(H20*(1+Settings!$B$13/100),2)) | J20: =IF(A20="","",E20-I20) | K20: =IF(A20="","",ROUND(E20*F20,2)) | L20: =IF(A20="","",ROUND((E20-D20)*F20,2)) | M20: =IF(A20="","",IFERROR(ROUND((E20-D20)/C20,3),""))
G21: =IF(A21="","",ROUND(Settings!$B$21*C21/60,2)) | H21: =IF(A21="","",G21+D21) | I21: =IF(A21="","",ROUND(H21*(1+Settings!$B$13/100),2)) | J21: =IF(A21="","",E21-I21) | K21: =IF(A21="","",ROUND(E21*F21,2)) | L21: =IF(A21="","",ROUND((E21-D21)*F21,2)) | M21: =IF(A21="","",IFERROR(ROUND((E21-D21)/C21,3),""))
G22: =IF(A22="","",ROUND(Settings!$B$21*C22/60,2)) | H22: =IF(A22="","",G22+D22) | I22: =IF(A22="","",ROUND(H22*(1+Settings!$B$13/100),2)) | J22: =IF(A22="","",E22-I22) | K22: =IF(A22="","",ROUND(E22*F22,2)) | L22: =IF(A22="","",ROUND((E22-D22)*F22,2)) | M22: =IF(A22="","",IFERROR(ROUND((E22-D22)/C22,3),""))
G23: =IF(A23="","",ROUND(Settings!$B$21*C23/60,2)) | H23: =IF(A23="","",G23+D23) | I23: =IF(A23="","",ROUND(H23*(1+Settings!$B$13/100),2)) | J23: =IF(A23="","",E23-I23) | K23: =IF(A23="","",ROUND(E23*F23,2)) | L23: =IF(A23="","",ROUND((E23-D23)*F23,2)) | M23: =IF(A23="","",IFERROR(ROUND((E23-D23)/C23,3),""))
G24: =IF(A24="","",ROUND(Settings!$B$21*C24/60,2)) | H24: =IF(A24="","",G24+D24) | I24: =IF(A24="","",ROUND(H24*(1+Settings!$B$13/100),2)) | J24: =IF(A24="","",E24-I24) | K24: =IF(A24="","",ROUND(E24*F24,2)) | L24: =IF(A24="","",ROUND((E24-D24)*F24,2)) | M24: =IF(A24="","",IFERROR(ROUND((E24-D24)/C24,3),""))
... G44: =IF(A44="","",ROUND(Settings!$B$21*C44/60,2)) | H44: =IF(A44="","",G44+D44) | I44: =IF(A44="","",ROUND(H44*(1+Settings!$B$13/100),2)) | J44: =IF(A44="","",E44-I44) | K44: =IF(A44="","",ROUND(E44*F44,2)) | L44: =IF(A44="","",ROUND((E44-D44)*F44,2)) | M44: =IF(A44="","",IFERROR(ROUND((E44-D44)/C44,3),""))
A45: Total | C45: =SUMPRODUCT(C5:C44,F5:F44) -> 2535 | F45: =SUM(F5:F44) -> 55 | K45: =SUM(K5:K44) -> 2830 | L45: =SUM(L5:L44) -> 2612
A46: Minutes column total = weekly minutes booked (minutes × weekly units)

Sheet Booth vs Commission
A1: Booth vs Commission
A2: Renting a booth: you keep revenue less booth rent and product. Commission: you keep your commission share and the salon supplies product.
A4: Monthly revenue from Service Menu | B4: =ROUND('Service Menu'!K45*52/12,2) -> 12263.33 | C4: weekly revenue × 52 ÷ 12
A5: or type your own monthly revenue | C5: optional override; leave empty to use the line above
A6: Monthly revenue used | B6: =IF(B5="",B4,B5) -> 12263.33 | C6: your override if typed, otherwise the Service Menu figure
A7: Weekly booth rent | B7: =Settings!$B$17 -> 300 | C7: from Settings
A8: Booth rent monthly | B8: =ROUND(B7*52/12,2) -> 1300 | C8: weekly rent × 52 ÷ 12
A9: Product cost % of revenue | B9: =Settings!$B$14 -> 10 | C9: from Settings; paid by you when renting a booth
A10: Commission % you keep | B10: =Settings!$B$18 -> 45 | C10: from Settings
A11: Booth rent % of revenue | B11: =IFERROR(ROUND(B8/B6*100,2),"n/a") -> 10.6 | C11: booth rent monthly ÷ monthly revenue
A12: Booth rent take-home (monthly) | B12: =ROUND(B6-B8-B6*B9/100,2) -> 9737 | C12: revenue − booth rent − revenue × product %
A13: Commission take-home (monthly) | B13: =ROUND(B6*B10/100,2) -> 5518.5 | C13: revenue × commission % you keep
A14: Difference (booth − commission) | B14: =B12-B13 -> 4218.5 | C14: positive: booth rent leaves you more
A15: Verdict | B15: =IF(ROUND(B14,2)>0,"Booth rent pays more",IF(ROUND(B14,2)<0,"Commission pays more","Both pay the same")) -> Booth rent pays more
A16: Break-even monthly revenue | B16: =IF(1-B10/100-B9/100<=0,"n/a",IFERROR(ROUND(B8/(1-B10/100-B9/100),2),"n/a")) -> 2888.89 | C16: booth rent monthly ÷ (1 − commission % − product %); above it booth rent pays more
A18: Revenue scenarios
A19: Revenue change % | B19: Monthly revenue | C19: Booth take-home | D19: Commission take-home | E19: Better option
A20: -20 | B20: =ROUND($B$6*(1+A20/100),2) -> 9810.66 | C20: =ROUND(B20-$B$8-B20*$B$9/100,2) -> 7529.59 | D20: =ROUND(B20*$B$10/100,2) -> 4414.8 | E20: =IF(C20>D20,"Booth rent",IF(C20<D20,"Commission","Same")) -> Booth rent
A21: -10 | B21: =ROUND($B$6*(1+A21/100),2) -> 11037 | C21: =ROUND(B21-$B$8-B21*$B$9/100,2) -> 8633.3 | D21: =ROUND(B21*$B$10/100,2) -> 4966.65 | E21: =IF(C21>D21,"Booth rent",IF(C21<D21,"Commission","Same")) -> Booth rent
A22: 0 | B22: =ROUND($B$6*(1+A22/100),2) -> 12263.33 | C22: =ROUND(B22-$B$8-B22*$B$9/100,2) -> 9737 | D22: =ROUND(B22*$B$10/100,2) -> 5518.5 | E22: =IF(C22>D22,"Booth rent",IF(C22<D22,"Commission","Same")) -> Booth rent
A23: 10 | B23: =ROUND($B$6*(1+A23/100),2) -> 13489.66 | C23: =ROUND(B23-$B$8-B23*$B$9/100,2) -> 10840.69 | D23: =ROUND(B23*$B$10/100,2) -> 6070.35 | E23: =IF(C23>D23,"Booth rent",IF(C23<D23,"Commission","Same")) -> Booth rent
A24: 20 | B24: =ROUND($B$6*(1+A24/100),2) -> 14716 | C24: =ROUND(B24-$B$8-B24*$B$9/100,2) -> 11944.4 | D24: =ROUND(B24*$B$10/100,2) -> 6622.2 | E24: =IF(C24>D24,"Booth rent",IF(C24<D24,"Commission","Same")) -> Booth rent

Sheet Weekly Log
A1: Weekly Log
A2: One row per week, filled top down. Lost revenue uses the average ticket and fees recovered use the no-show fee from Settings.
A4: Week start | B4: Appointments booked | C4: No-shows | D4: Late cancellations | E4: Revenue | F4: Product spend | G4: Booth rent or overhead paid | H4: Tips (optional) | I4: Completed appointments | J4: No-show rate % | K4: Lost revenue | L4: Fees recovered | M4: Net | N4: Revenue per completed appointment
A5: 46237 | B5: 32 | C5: 2 | D5: 1 | E5: 1950 | F5: 195 | G5: 300 | H5: 120 | I5: =IF(A5="","",B5-C5-D5) -> 29 | J5: =IF(A5="","",IFERROR(ROUND((C5+D5)/B5*100,2),0)) -> 9.38 | K5: =IF(A5="","",ROUND((C5+D5)*Settings!$B$15,2)) -> 195 | L5: =IF(A5="","",ROUND((C5+D5)*Settings!$B$19,2)) -> 75 | M5: =IF(A5="","",E5-F5-G5) -> 1455 | N5: =IF(A5="","",IFERROR(ROUND(E5/I5,2),"")) -> 67.24
A6: 46244 | B6: 34 | C6: 1 | D6: 2 | E6: 2080 | F6: 205 | G6: 300 | H6: 135 | I6: =IF(A6="","",B6-C6-D6) -> 31 | J6: =IF(A6="","",IFERROR(ROUND((C6+D6)/B6*100,2),0)) -> 8.82 | K6: =IF(A6="","",ROUND((C6+D6)*Settings!$B$15,2)) -> 195 | L6: =IF(A6="","",ROUND((C6+D6)*Settings!$B$19,2)) -> 75 | M6: =IF(A6="","",E6-F6-G6) -> 1575 | N6: =IF(A6="","",IFERROR(ROUND(E6/I6,2),"")) -> 67.1
A7: 46251 | B7: 30 | C7: 3 | D7: 0 | E7: 1840 | F7: 180 | G7: 300 | H7: 110 | I7: =IF(A7="","",B7-C7-D7) -> 27 | J7: =IF(A7="","",IFERROR(ROUND((C7+D7)/B7*100,2),0)) -> 10 | K7: =IF(A7="","",ROUND((C7+D7)*Settings!$B$15,2)) -> 195 | L7: =IF(A7="","",ROUND((C7+D7)*Settings!$B$19,2)) -> 75 | M7: =IF(A7="","",E7-F7-G7) -> 1360 | N7: =IF(A7="","",IFERROR(ROUND(E7/I7,2),"")) -> 68.15
A8: 46258 | B8: 33 | C8: 2 | D8: 2 | E8: 1990 | F8: 198 | G8: 300 | H8: 125 | I8: =IF(A8="","",B8-C8-D8) -> 29 | J8: =IF(A8="","",IFERROR(ROUND((C8+D8)/B8*100,2),0)) -> 12.12 | K8: =IF(A8="","",ROUND((C8+D8)*Settings!$B$15,2)) -> 260 | L8: =IF(A8="","",ROUND((C8+D8)*Settings!$B$19,2)) -> 100 | M8: =IF(A8="","",E8-F8-G8) -> 1492 | N8: =IF(A8="","",IFERROR(ROUND(E8/I8,2),"")) -> 68.62
A9: 46265 | B9: 35 | C9: 1 | D9: 1 | E9: 2210 | F9: 220 | G9: 300 | H9: 150 | I9: =IF(A9="","",B9-C9-D9) -> 33 | J9: =IF(A9="","",IFERROR(ROUND((C9+D9)/B9*100,2),0)) -> 5.71 | K9: =IF(A9="","",ROUND((C9+D9)*Settings!$B$15,2)) -> 130 | L9: =IF(A9="","",ROUND((C9+D9)*Settings!$B$19,2)) -> 50 | M9: =IF(A9="","",E9-F9-G9) -> 1690 | N9: =IF(A9="","",IFERROR(ROUND(E9/I9,2),"")) -> 66.97
A10: 46272 | B10: 31 | C10: 2 | D10: 1 | E10: 1900 | F10: 190 | G10: 300 | H10: 115 | I10: =IF(A10="","",B10-C10-D10) -> 28 | J10: =IF(A10="","",IFERROR(ROUND((C10+D10)/B10*100,2),0)) -> 9.68 | K10: =IF(A10="","",ROUND((C10+D10)*Settings!$B$15,2)) -> 195 | L10: =IF(A10="","",ROUND((C10+D10)*Settings!$B$19,2)) -> 75 | M10: =IF(A10="","",E10-F10-G10) -> 1410 | N10: =IF(A10="","",IFERROR(ROUND(E10/I10,2),"")) -> 67.86
I11: =IF(A11="","",B11-C11-D11) | J11: =IF(A11="","",IFERROR(ROUND((C11+D11)/B11*100,2),0)) | K11: =IF(A11="","",ROUND((C11+D11)*Settings!$B$15,2)) | L11: =IF(A11="","",ROUND((C11+D11)*Settings!$B$19,2)) | M11: =IF(A11="","",E11-F11-G11) | N11: =IF(A11="","",IFERROR(ROUND(E11/I11,2),""))
I12: =IF(A12="","",B12-C12-D12) | J12: =IF(A12="","",IFERROR(ROUND((C12+D12)/B12*100,2),0)) | K12: =IF(A12="","",ROUND((C12+D12)*Settings!$B$15,2)) | L12: =IF(A12="","",ROUND((C12+D12)*Settings!$B$19,2)) | M12: =IF(A12="","",E12-F12-G12) | N12: =IF(A12="","",IFERROR(ROUND(E12/I12,2),""))
I13: =IF(A13="","",B13-C13-D13) | J13: =IF(A13="","",IFERROR(ROUND((C13+D13)/B13*100,2),0)) | K13: =IF(A13="","",ROUND((C13+D13)*Settings!$B$15,2)) | L13: =IF(A13="","",ROUND((C13+D13)*Settings!$B$19,2)) | M13: =IF(A13="","",E13-F13-G13) | N13: =IF(A13="","",IFERROR(ROUND(E13/I13,2),""))
I14: =IF(A14="","",B14-C14-D14) | J14: =IF(A14="","",IFERROR(ROUND((C14+D14)/B14*100,2),0)) | K14: =IF(A14="","",ROUND((C14+D14)*Settings!$B$15,2)) | L14: =IF(A14="","",ROUND((C14+D14)*Settings!$B$19,2)) | M14: =IF(A14="","",E14-F14-G14) | N14: =IF(A14="","",IFERROR(ROUND(E14/I14,2),""))
I15: =IF(A15="","",B15-C15-D15) | J15: =IF(A15="","",IFERROR(ROUND((C15+D15)/B15*100,2),0)) | K15: =IF(A15="","",ROUND((C15+D15)*Settings!$B$15,2)) | L15: =IF(A15="","",ROUND((C15+D15)*Settings!$B$19,2)) | M15: =IF(A15="","",E15-F15-G15) | N15: =IF(A15="","",IFERROR(ROUND(E15/I15,2),""))
I16: =IF(A16="","",B16-C16-D16) | J16: =IF(A16="","",IFERROR(ROUND((C16+D16)/B16*100,2),0)) | K16: =IF(A16="","",ROUND((C16+D16)*Settings!$B$15,2)) | L16: =IF(A16="","",ROUND((C16+D16)*Settings!$B$19,2)) | M16: =IF(A16="","",E16-F16-G16) | N16: =IF(A16="","",IFERROR(ROUND(E16/I16,2),""))
I17: =IF(A17="","",B17-C17-D17) | J17: =IF(A17="","",IFERROR(ROUND((C17+D17)/B17*100,2),0)) | K17: =IF(A17="","",ROUND((C17+D17)*Settings!$B$15,2)) | L17: =IF(A17="","",ROUND((C17+D17)*Settings!$B$19,2)) | M17: =IF(A17="","",E17-F17-G17) | N17: =IF(A17="","",IFERROR(ROUND(E17/I17,2),""))
I18: =IF(A18="","",B18-C18-D18) | J18: =IF(A18="","",IFERROR(ROUND((C18+D18)/B18*100,2),0)) | K18: =IF(A18="","",ROUND((C18+D18)*Settings!$B$15,2)) | L18: =IF(A18="","",ROUND((C18+D18)*Settings!$B$19,2)) | M18: =IF(A18="","",E18-F18-G18) | N18: =IF(A18="","",IFERROR(ROUND(E18/I18,2),""))
I19: =IF(A19="","",B19-C19-D19) | J19: =IF(A19="","",IFERROR(ROUND((C19+D19)/B19*100,2),0)) | K19: =IF(A19="","",ROUND((C19+D19)*Settings!$B$15,2)) | L19: =IF(A19="","",ROUND((C19+D19)*Settings!$B$19,2)) | M19: =IF(A19="","",E19-F19-G19) | N19: =IF(A19="","",IFERROR(ROUND(E19/I19,2),""))
I20: =IF(A20="","",B20-C20-D20) | J20: =IF(A20="","",IFERROR(ROUND((C20+D20)/B20*100,2),0)) | K20: =IF(A20="","",ROUND((C20+D20)*Settings!$B$15,2)) | L20: =IF(A20="","",ROUND((C20+D20)*Settings!$B$19,2)) | M20: =IF(A20="","",E20-F20-G20) | N20: =IF(A20="","",IFERROR(ROUND(E20/I20,2),""))
I21: =IF(A21="","",B21-C21-D21) | J21: =IF(A21="","",IFERROR(ROUND((C21+D21)/B21*100,2),0)) | K21: =IF(A21="","",ROUND((C21+D21)*Settings!$B$15,2)) | L21: =IF(A21="","",ROUND((C21+D21)*Settings!$B$19,2)) | M21: =IF(A21="","",E21-F21-G21) | N21: =IF(A21="","",IFERROR(ROUND(E21/I21,2),""))
I22: =IF(A22="","",B22-C22-D22) | J22: =IF(A22="","",IFERROR(ROUND((C22+D22)/B22*100,2),0)) | K22: =IF(A22="","",ROUND((C22+D22)*Settings!$B$15,2)) | L22: =IF(A22="","",ROUND((C22+D22)*Settings!$B$19,2)) | M22: =IF(A22="","",E22-F22-G22) | N22: =IF(A22="","",IFERROR(ROUND(E22/I22,2),""))
... I56: =IF(A56="","",B56-C56-D56) | J56: =IF(A56="","",IFERROR(ROUND((C56+D56)/B56*100,2),0)) | K56: =IF(A56="","",ROUND((C56+D56)*Settings!$B$15,2)) | L56: =IF(A56="","",ROUND((C56+D56)*Settings!$B$19,2)) | M56: =IF(A56="","",E56-F56-G56) | N56: =IF(A56="","",IFERROR(ROUND(E56/I56,2),""))
A57: Total | B57: =SUM(B5:B56) -> 195 | C57: =SUM(C5:C56) -> 11 | D57: =SUM(D5:D56) -> 7 | E57: =SUM(E5:E56) -> 11970 | F57: =SUM(F5:F56) -> 1188 | G57: =SUM(G5:G56) -> 1800 | H57: =SUM(H5:H56) -> 755 | I57: =SUM(I5:I56) -> 177 | J57: =IFERROR(ROUND((C57+D57)/B57*100,2),0) -> 9.23 | K57: =SUM(K5:K56) -> 1170 | L57: =SUM(L5:L56) -> 450 | M57: =SUM(M5:M56) -> 8982 | N57: =IFERROR(ROUND(E57/I57,2),0) -> 67.63
A58: 4-week average | B58: =IFERROR(ROUND(AVERAGE(INDEX($B$5:$B$56,MAX(1,COUNT($A$5:$A$56)-3)):INDEX($B$5:$B$56,COUNT($A$5:$A$56))),2),0) -> 32.25 | C58: =IFERROR(ROUND(AVERAGE(INDEX($C$5:$C$56,MAX(1,COUNT($A$5:$A$56)-3)):INDEX($C$5:$C$56,COUNT($A$5:$A$56))),2),0) -> 2 | D58: =IFERROR(ROUND(AVERAGE(INDEX($D$5:$D$56,MAX(1,COUNT($A$5:$A$56)-3)):INDEX($D$5:$D$56,COUNT($A$5:$A$56))),2),0) -> 1 | E58: =IFERROR(ROUND(AVERAGE(INDEX($E$5:$E$56,MAX(1,COUNT($A$5:$A$56)-3)):INDEX($E$5:$E$56,COUNT($A$5:$A$56))),2),0) -> 1985 | F58: =IFERROR(ROUND(AVERAGE(INDEX($F$5:$F$56,MAX(1,COUNT($A$5:$A$56)-3)):INDEX($F$5:$F$56,COUNT($A$5:$A$56))),2),0) -> 197 | G58: =IFERROR(ROUND(AVERAGE(INDEX($G$5:$G$56,MAX(1,COUNT($A$5:$A$56)-3)):INDEX($G$5:$G$56,COUNT($A$5:$A$56))),2),0) -> 300 | H58: =IFERROR(ROUND(AVERAGE(INDEX($H$5:$H$56,MAX(1,COUNT($A$5:$A$56)-3)):INDEX($H$5:$H$56,COUNT($A$5:$A$56))),2),0) -> 125 | I58: =IFERROR(ROUND(AVERAGE(INDEX($I$5:$I$56,MAX(1,COUNT($A$5:$A$56)-3)):INDEX($I$5:$I$56,COUNT($A$5:$A$56))),2),0) -> 29.25 | J58: =IFERROR(ROUND((C58+D58)/B58*100,2),0) -> 9.3 | K58: =IFERROR(ROUND(AVERAGE(INDEX($K$5:$K$56,MAX(1,COUNT($A$5:$A$56)-3)):INDEX($K$5:$K$56,COUNT($A$5:$A$56))),2),0) -> 195 | L58: =IFERROR(ROUND(AVERAGE(INDEX($L$5:$L$56,MAX(1,COUNT($A$5:$A$56)-3)):INDEX($L$5:$L$56,COUNT($A$5:$A$56))),2),0) -> 75 | M58: =IFERROR(ROUND(AVERAGE(INDEX($M$5:$M$56,MAX(1,COUNT($A$5:$A$56)-3)):INDEX($M$5:$M$56,COUNT($A$5:$A$56))),2),0) -> 1488 | N58: =IFERROR(ROUND(E58/I58,2),0) -> 67.86

Sheet Capacity
A1: Capacity
A2: How many appointments fit in your week, and what they could earn.
A4: Hours worked per week | B4: =Settings!$B$11 -> 40 | C4: from Settings
A5: Share of hours that are billable % | B5: =Settings!$B$12 -> 75 | C5: from Settings
A6: Average service minutes from Service Menu | B6: =IFERROR(ROUND(SUMPRODUCT('Service Menu'!C5:C44,'Service Menu'!F5:F44)/SUM('Service Menu'!F5:F44),1),0) -> 46.1 | C6: weighted by weekly units
A7: or type your own average service minutes | C7: optional override; leave empty to use the line above
A8: Average service minutes used | B8: =IF(B7="",B6,B7) -> 46.1 | C8: your override if typed, otherwise the Service Menu figure
A9: Buffer minutes between appointments | B9: 10 | C9: default 10: cleaning, reset and payment
A10: Slot minutes | B10: =B8+B9 -> 56.1 | C10: service minutes + buffer
A11: Max appointments per week | B11: =IFERROR(INT(B4*60/B10),0) -> 42 | C11: hours × 60 ÷ slot minutes, rounded down
A12: Expected appointments per week | B12: =ROUND(B11*B5/100,0) -> 32 | C12: max appointments × billable %
A13: Average ticket | B13: =Settings!$B$15 -> 65 | C13: from Settings
A14: Revenue ceiling per week | B14: =ROUND(B11*B13,2) -> 2730 | C14: max appointments × average ticket
A15: Expected revenue per week | B15: =ROUND(B12*B13,2) -> 2080 | C15: expected appointments × average ticket
A17: Booked appointments, latest logged week | B17: =IF(COUNT('Weekly Log'!A5:A56)=0,"n/a",IFERROR(INDEX('Weekly Log'!B5:B56,MATCH(MAX('Weekly Log'!A5:A56),'Weekly Log'!A5:A56,0)),"n/a")) -> 31 | C17: the row with the latest week start date on the Weekly Log
A18: Booked vs expected | B18: =IFERROR(B17-B12,"n/a") -> -1 | C18: positive: busier than expected

Sheet Summary
A1: Summary
A2: Target hourly rate | B2: =Settings!$B$21 -> 49.17 | C2: from Settings
A3: Billable hours per month | B3: =Settings!$B$20 -> 120 | C3: from Settings
A4: Services on the menu | B4: =COUNTA('Service Menu'!A5:A44) -> 8
A5: Services priced below floor | B5: =SUMPRODUCT(('Service Menu'!A5:A44<>"")*('Service Menu'!E5:E44<'Service Menu'!H5:H44)) -> 1 | C5: current price below floor price
A6: Services priced below suggested | B6: =COUNTIF('Service Menu'!J5:J44,"<0") -> 3 | C6: gap column below zero
A7: Weekly revenue from menu | B7: ='Service Menu'!K45 -> 2830
A8: Weekly gross profit from menu | B8: ='Service Menu'!L45 -> 2612 | C8: revenue less product cost
A9: Highest-margin service | B9: =IFERROR(INDEX('Service Menu'!A5:A44,MATCH(MAX('Service Menu'!M5:M44),'Service Menu'!M5:M44,0)),"") -> Express facial | C9: highest gross profit per minute
A10: Lowest-margin service | B10: =IFERROR(INDEX('Service Menu'!A5:A44,MATCH(MIN('Service Menu'!M5:M44),'Service Menu'!M5:M44,0)),"") -> Gel manicure | C10: lowest gross profit per minute: re-price first
A11: Booth vs commission | B11: ='Booth vs Commission'!B15 -> Booth rent pays more
A12: Break-even monthly revenue | B12: ='Booth vs Commission'!B16 -> 2888.89 | C12: above it booth rent pays more
A13: Lost revenue to no-shows (logged weeks) | B13: ='Weekly Log'!K57 -> 1170 | C13: Weekly Log total
A14: No-show fees recovered (logged weeks) | B14: ='Weekly Log'!L57 -> 450 | C14: Weekly Log total
A15: Expected appointments per week | B15: =Capacity!B12 -> 32 | C15: from Capacity
