Workbook

Sheet Start Here
A1: Staffing Agency Margin Workbook
A2: by Knackdesk · knackdesk.com
A4: HOW TO USE
A5: 1. Settings: number of recruiters, average recruiter salary, benefits and payroll taxes %, tools and job boards, office and other overhead, working hours per recruiter, and your default permanent fee %, temp on-costs %, temp markup %, guarantee days, expected fall-off % and rebate %. Desk cost per recruiter, recruiter cost per hour and the reserve % of fee follow and every other sheet reads them.
A6: 2. Perm Placements: one row per permanent placement with date, client, role, annual salary, fee % (default from Settings, type your own to override), split %, recruiter hours, advertising cost, invoiced and collected. Gross fee, split fee, net fee, delivery cost, margin, margin %, net fee per recruiter hour, expected rebate reserve and net fee after reserve are calculated, with totals.
A7: 3. Temp Assignments: one row per temp or contractor with client, worker, pay rate, on-costs % and markup % (defaults from Settings, type your own to override), an optional bill rate you have agreed, hours per week and weeks. Bill rate used, loaded cost per hour, gross margin per hour and %, and weekly and assignment revenue and margin are calculated, with totals.
A8: 4. Desk Performance: one row per month with job orders received and filled, candidates submitted, interviews, total days to fill and temp margin earned. Perm placements and net perm fees for the month are counted from the Perm Placements sheet by date (type your own to override). Gross margin, desk cost for the month, desk profit, fill rate, average days to fill, submittals per fill, interview to fill % and margin per recruiter are calculated.
A9: 5. Rebate Reserve: one row per placement still inside or recently out of its guarantee, with start date, net fee, guarantee days, fall-off % and rebate % (defaults from Settings, type your own to override) and the outcome. Guarantee end date, expected reserve, reserve released, rebate paid and reserve still held are calculated, with totals.
A10: 6. Summary: recruiters, desk cost per recruiter, recruiter cost per hour, year-to-date perm net fees, temp margin, gross margin, desk cost and desk profit, break-even placements per recruiter, placements below your margin % threshold, the thinnest temp assignment, year-to-date fill rate and days to fill, and the reserve position.
A12: LEGEND
A13: Blue text = a cell you type into. Black text = a formula, leave it alone. Yellow fill = key inputs.
A15: DEFINITIONS
... A26: Arithmetic only; not financial advice.

Sheet Settings
A1: Settings
A2: Number of recruiters | B2: 4 | C2: Example default 4. Fee-earning recruiters whose desks carry the agency's cost; owners who bill count too.
A3: Average recruiter salary (annual) | B3: 55000 | C3: Example default 55,000 a year. Base salary plus the commission you expect to pay, averaged across recruiters.
A4: Benefits and payroll taxes % for staff | B4: 20 | C4: Default 20. Employer payroll taxes, pension, health cover and other benefits on top of recruiter salary.
A5: Tools and job boards (annual) | B5: 36000 | C5: Example default 36,000 a year. Applicant tracking system, CRM, job board subscriptions, LinkedIn seats, background checks.
A6: Office and other overhead (annual) | B6: 72000 | C6: Example default 72,000 a year. Rent, admin staff, insurance, accounting, marketing and everything else.
A7: Working hours per recruiter per year | B7: 1800 | C7: Default 1,800. Hours a recruiter is at work in a year, used to cost an hour of desk time.
A8: Default permanent fee % | B8: 20 | C8: Default 20. Fee as a % of the candidate's first-year salary; each placement can override it.
A9: Default on-costs % for temps | B9: 18 | C9: Default 18. Employer taxes, holiday pay, insurance and payroll fees on top of a temp's pay rate; each assignment can override it.
A10: Default temp markup % | B10: 55 | C10: Default 55. Markup on the pay rate to get the bill rate; each assignment can override it or set its own bill rate.
A11: Default guarantee days | B11: 90 | C11: Default 90. Days after the start date during which a fall-off triggers a rebate; each placement can override it.
A12: Expected fall-off % | B12: 8 | C12: Default 8. Share of placements you expect to fall off inside the guarantee; your own placeholder, set it from your history.
A13: Rebate % of fee | B13: 100 | C13: Default 100. Share of the fee refunded or credited on a fall-off (100 = full refund or free replacement).
A14: Default placement fee for the reserve | B14: 12000 | C14: Example default 12,000. A typical net fee, used only to show the reserve per placement below.
A15: Loaded recruiter cost per year (each) | B15: =ROUND(B3*(1+B4/100),2) -> 66000 | C15: formula: average salary × (1 + benefits and payroll taxes %)
A16: Total desk cost per year | B16: =ROUND(B2*B15+B5+B6,2) -> 372000 | C16: formula: recruiters × loaded cost + tools and job boards + office and other overhead
A17: Desk cost per recruiter (annual) | B17: =IFERROR(ROUND(B16/B2,2),0) -> 93000 | C17: formula: total desk cost ÷ number of recruiters
A18: Recruiter cost per hour | B18: =IFERROR(ROUND(B17/B7,2),0) -> 51.67 | C18: formula: desk cost per recruiter ÷ working hours per recruiter per year
A19: Reserve % of fee | B19: =ROUND(B12*B13/100,2) -> 8 | C19: formula: expected fall-off % × rebate % ÷ 100; the share of each net fee to hold back until the guarantee ends
A20: Reserve per placement at the default fee | B20: =ROUND(B14*B19/100,2) -> 960 | C20: formula: default placement fee × reserve % of fee

Sheet Perm Placements
A1: Perm Placements
A2: One row per permanent placement. Fee % defaults from Settings; type your own in 'or type your own fee %' to override it. Delivery cost uses the recruiter cost per hour from Settings.
A4: Date | B4: Client | C4: Role | D4: Annual salary | E4: Default fee % (Settings) | F4: or type your own fee % | G4: Fee % used | H4: Split % | I4: Recruiter hours | J4: Advertising cost | K4: Invoiced | L4: Collected | M4: Gross fee | N4: Split fee | O4: Net fee | P4: Delivery cost | Q4: Margin on placement | R4: Margin % | S4: Net fee per recruiter hour | T4: Expected rebate reserve | U4: Net fee after reserve
A5: 46034 | B5: Northwind Logistics | C5: Warehouse manager | D5: 65000 | E5: =IF(B5="","",Settings!$B$8) -> 20 | G5: =IF(B5="","",IF(F5<>"",F5,E5)) -> 20 | H5: 25 | I5: 40 | J5: 400 | K5: yes | L5: 13000 | M5: =IF(B5="","",ROUND(D5*G5/100,2)) -> 13000 | N5: =IF(B5="","",ROUND(M5*H5/100,2)) -> 3250 | O5: =IF(B5="","",M5-N5) -> 9750 | P5: =IF(B5="","",ROUND(I5*Settings!$B$18+J5,2)) -> 2466.8 | Q5: =IF(B5="","",ROUND(O5-P5,2)) -> 7283.2 | R5: =IF(B5="","",IFERROR(ROUND(Q5/O5*100,2),0)) -> 74.7 | S5: =IF(B5="","",IFERROR(ROUND(O5/I5,2),0)) -> 243.75 | T5: =IF(B5="","",ROUND(O5*Settings!$B$19/100,2)) -> 780 | U5: =IF(B5="","",ROUND(O5-T5,2)) -> 8970
A6: 46048 | B6: Brightline Dental | C6: Practice manager | D6: 48000 | E6: =IF(B6="","",Settings!$B$8) -> 20 | G6: =IF(B6="","",IF(F6<>"",F6,E6)) -> 20 | H6: 0 | I6: 35 | J6: 250 | K6: yes | L6: 9600 | M6: =IF(B6="","",ROUND(D6*G6/100,2)) -> 9600 | N6: =IF(B6="","",ROUND(M6*H6/100,2)) -> 0 | O6: =IF(B6="","",M6-N6) -> 9600 | P6: =IF(B6="","",ROUND(I6*Settings!$B$18+J6,2)) -> 2058.45 | Q6: =IF(B6="","",ROUND(O6-P6,2)) -> 7541.55 | R6: =IF(B6="","",IFERROR(ROUND(Q6/O6*100,2),0)) -> 78.56 | S6: =IF(B6="","",IFERROR(ROUND(O6/I6,2),0)) -> 274.29 | T6: =IF(B6="","",ROUND(O6*Settings!$B$19/100,2)) -> 768 | U6: =IF(B6="","",ROUND(O6-T6,2)) -> 8832
A7: 46062 | B7: Acme Engineering | C7: Senior mechanical engineer | D7: 85000 | E7: =IF(B7="","",Settings!$B$8) -> 20 | F7: 22 | G7: =IF(B7="","",IF(F7<>"",F7,E7)) -> 22 | H7: 0 | I7: 60 | J7: 1200 | K7: yes | L7: 18700 | M7: =IF(B7="","",ROUND(D7*G7/100,2)) -> 18700 | N7: =IF(B7="","",ROUND(M7*H7/100,2)) -> 0 | O7: =IF(B7="","",M7-N7) -> 18700 | P7: =IF(B7="","",ROUND(I7*Settings!$B$18+J7,2)) -> 4300.2 | Q7: =IF(B7="","",ROUND(O7-P7,2)) -> 14399.8 | R7: =IF(B7="","",IFERROR(ROUND(Q7/O7*100,2),0)) -> 77 | S7: =IF(B7="","",IFERROR(ROUND(O7/I7,2),0)) -> 311.67 | T7: =IF(B7="","",ROUND(O7*Settings!$B$19/100,2)) -> 1496 | U7: =IF(B7="","",ROUND(O7-T7,2)) -> 17204
A8: 46084 | B8: Harbor Foods | C8: Finance assistant | D8: 32000 | E8: =IF(B8="","",Settings!$B$8) -> 20 | F8: 15 | G8: =IF(B8="","",IF(F8<>"",F8,E8)) -> 15 | H8: 0 | I8: 45 | J8: 300 | K8: yes | L8: 4800 | M8: =IF(B8="","",ROUND(D8*G8/100,2)) -> 4800 | N8: =IF(B8="","",ROUND(M8*H8/100,2)) -> 0 | O8: =IF(B8="","",M8-N8) -> 4800 | P8: =IF(B8="","",ROUND(I8*Settings!$B$18+J8,2)) -> 2625.15 | Q8: =IF(B8="","",ROUND(O8-P8,2)) -> 2174.85 | R8: =IF(B8="","",IFERROR(ROUND(Q8/O8*100,2),0)) -> 45.31 | S8: =IF(B8="","",IFERROR(ROUND(O8/I8,2),0)) -> 106.67 | T8: =IF(B8="","",ROUND(O8*Settings!$B$19/100,2)) -> 384 | U8: =IF(B8="","",ROUND(O8-T8,2)) -> 4416
A9: 46119 | B9: Delta Software | C9: Product designer | D9: 72000 | E9: =IF(B9="","",Settings!$B$8) -> 20 | G9: =IF(B9="","",IF(F9<>"",F9,E9)) -> 20 | H9: 50 | I9: 30 | J9: 0 | K9: yes | L9: 14400 | M9: =IF(B9="","",ROUND(D9*G9/100,2)) -> 14400 | N9: =IF(B9="","",ROUND(M9*H9/100,2)) -> 7200 | O9: =IF(B9="","",M9-N9) -> 7200 | P9: =IF(B9="","",ROUND(I9*Settings!$B$18+J9,2)) -> 1550.1 | Q9: =IF(B9="","",ROUND(O9-P9,2)) -> 5649.9 | R9: =IF(B9="","",IFERROR(ROUND(Q9/O9*100,2),0)) -> 78.47 | S9: =IF(B9="","",IFERROR(ROUND(O9/I9,2),0)) -> 240 | T9: =IF(B9="","",ROUND(O9*Settings!$B$19/100,2)) -> 576 | U9: =IF(B9="","",ROUND(O9-T9,2)) -> 6624
A10: 46134 | B10: Okafor & Co | C10: Office administrator | D10: 28000 | E10: =IF(B10="","",Settings!$B$8) -> 20 | G10: =IF(B10="","",IF(F10<>"",F10,E10)) -> 20 | H10: 0 | I10: 50 | J10: 500 | K10: yes | L10: 5600 | M10: =IF(B10="","",ROUND(D10*G10/100,2)) -> 5600 | N10: =IF(B10="","",ROUND(M10*H10/100,2)) -> 0 | O10: =IF(B10="","",M10-N10) -> 5600 | P10: =IF(B10="","",ROUND(I10*Settings!$B$18+J10,2)) -> 3083.5 | Q10: =IF(B10="","",ROUND(O10-P10,2)) -> 2516.5 | R10: =IF(B10="","",IFERROR(ROUND(Q10/O10*100,2),0)) -> 44.94 | S10: =IF(B10="","",IFERROR(ROUND(O10/I10,2),0)) -> 112 | T10: =IF(B10="","",ROUND(O10*Settings!$B$19/100,2)) -> 448 | U10: =IF(B10="","",ROUND(O10-T10,2)) -> 5152
A11: 46156 | B11: Northwind Logistics | C11: Transport planner | D11: 52000 | E11: =IF(B11="","",Settings!$B$8) -> 20 | G11: =IF(B11="","",IF(F11<>"",F11,E11)) -> 20 | H11: 0 | I11: 25 | J11: 200 | K11: yes | L11: 0 | M11: =IF(B11="","",ROUND(D11*G11/100,2)) -> 10400 | N11: =IF(B11="","",ROUND(M11*H11/100,2)) -> 0 | O11: =IF(B11="","",M11-N11) -> 10400 | P11: =IF(B11="","",ROUND(I11*Settings!$B$18+J11,2)) -> 1491.75 | Q11: =IF(B11="","",ROUND(O11-P11,2)) -> 8908.25 | R11: =IF(B11="","",IFERROR(ROUND(Q11/O11*100,2),0)) -> 85.66 | S11: =IF(B11="","",IFERROR(ROUND(O11/I11,2),0)) -> 416 | T11: =IF(B11="","",ROUND(O11*Settings!$B$19/100,2)) -> 832 | U11: =IF(B11="","",ROUND(O11-T11,2)) -> 9568
A12: 46175 | B12: Garcia Retail | C12: Store manager | D12: 45000 | E12: =IF(B12="","",Settings!$B$8) -> 20 | G12: =IF(B12="","",IF(F12<>"",F12,E12)) -> 20 | H12: 0 | I12: 30 | J12: 350 | K12: no | L12: 0 | M12: =IF(B12="","",ROUND(D12*G12/100,2)) -> 9000 | N12: =IF(B12="","",ROUND(M12*H12/100,2)) -> 0 | O12: =IF(B12="","",M12-N12) -> 9000 | P12: =IF(B12="","",ROUND(I12*Settings!$B$18+J12,2)) -> 1900.1 | Q12: =IF(B12="","",ROUND(O12-P12,2)) -> 7099.9 | R12: =IF(B12="","",IFERROR(ROUND(Q12/O12*100,2),0)) -> 78.89 | S12: =IF(B12="","",IFERROR(ROUND(O12/I12,2),0)) -> 300 | T12: =IF(B12="","",ROUND(O12*Settings!$B$19/100,2)) -> 720 | U12: =IF(B12="","",ROUND(O12-T12,2)) -> 8280
E13: =IF(B13="","",Settings!$B$8) | G13: =IF(B13="","",IF(F13<>"",F13,E13)) | M13: =IF(B13="","",ROUND(D13*G13/100,2)) | N13: =IF(B13="","",ROUND(M13*H13/100,2)) | O13: =IF(B13="","",M13-N13) | P13: =IF(B13="","",ROUND(I13*Settings!$B$18+J13,2)) | Q13: =IF(B13="","",ROUND(O13-P13,2)) | R13: =IF(B13="","",IFERROR(ROUND(Q13/O13*100,2),0)) | S13: =IF(B13="","",IFERROR(ROUND(O13/I13,2),0)) | T13: =IF(B13="","",ROUND(O13*Settings!$B$19/100,2)) | U13: =IF(B13="","",ROUND(O13-T13,2))
E14: =IF(B14="","",Settings!$B$8) | G14: =IF(B14="","",IF(F14<>"",F14,E14)) | M14: =IF(B14="","",ROUND(D14*G14/100,2)) | N14: =IF(B14="","",ROUND(M14*H14/100,2)) | O14: =IF(B14="","",M14-N14) | P14: =IF(B14="","",ROUND(I14*Settings!$B$18+J14,2)) | Q14: =IF(B14="","",ROUND(O14-P14,2)) | R14: =IF(B14="","",IFERROR(ROUND(Q14/O14*100,2),0)) | S14: =IF(B14="","",IFERROR(ROUND(O14/I14,2),0)) | T14: =IF(B14="","",ROUND(O14*Settings!$B$19/100,2)) | U14: =IF(B14="","",ROUND(O14-T14,2))
E15: =IF(B15="","",Settings!$B$8) | G15: =IF(B15="","",IF(F15<>"",F15,E15)) | M15: =IF(B15="","",ROUND(D15*G15/100,2)) | N15: =IF(B15="","",ROUND(M15*H15/100,2)) | O15: =IF(B15="","",M15-N15) | P15: =IF(B15="","",ROUND(I15*Settings!$B$18+J15,2)) | Q15: =IF(B15="","",ROUND(O15-P15,2)) | R15: =IF(B15="","",IFERROR(ROUND(Q15/O15*100,2),0)) | S15: =IF(B15="","",IFERROR(ROUND(O15/I15,2),0)) | T15: =IF(B15="","",ROUND(O15*Settings!$B$19/100,2)) | U15: =IF(B15="","",ROUND(O15-T15,2))
E16: =IF(B16="","",Settings!$B$8) | G16: =IF(B16="","",IF(F16<>"",F16,E16)) | M16: =IF(B16="","",ROUND(D16*G16/100,2)) | N16: =IF(B16="","",ROUND(M16*H16/100,2)) | O16: =IF(B16="","",M16-N16) | P16: =IF(B16="","",ROUND(I16*Settings!$B$18+J16,2)) | Q16: =IF(B16="","",ROUND(O16-P16,2)) | R16: =IF(B16="","",IFERROR(ROUND(Q16/O16*100,2),0)) | S16: =IF(B16="","",IFERROR(ROUND(O16/I16,2),0)) | T16: =IF(B16="","",ROUND(O16*Settings!$B$19/100,2)) | U16: =IF(B16="","",ROUND(O16-T16,2))
E17: =IF(B17="","",Settings!$B$8) | G17: =IF(B17="","",IF(F17<>"",F17,E17)) | M17: =IF(B17="","",ROUND(D17*G17/100,2)) | N17: =IF(B17="","",ROUND(M17*H17/100,2)) | O17: =IF(B17="","",M17-N17) | P17: =IF(B17="","",ROUND(I17*Settings!$B$18+J17,2)) | Q17: =IF(B17="","",ROUND(O17-P17,2)) | R17: =IF(B17="","",IFERROR(ROUND(Q17/O17*100,2),0)) | S17: =IF(B17="","",IFERROR(ROUND(O17/I17,2),0)) | T17: =IF(B17="","",ROUND(O17*Settings!$B$19/100,2)) | U17: =IF(B17="","",ROUND(O17-T17,2))
E18: =IF(B18="","",Settings!$B$8) | G18: =IF(B18="","",IF(F18<>"",F18,E18)) | M18: =IF(B18="","",ROUND(D18*G18/100,2)) | N18: =IF(B18="","",ROUND(M18*H18/100,2)) | O18: =IF(B18="","",M18-N18) | P18: =IF(B18="","",ROUND(I18*Settings!$B$18+J18,2)) | Q18: =IF(B18="","",ROUND(O18-P18,2)) | R18: =IF(B18="","",IFERROR(ROUND(Q18/O18*100,2),0)) | S18: =IF(B18="","",IFERROR(ROUND(O18/I18,2),0)) | T18: =IF(B18="","",ROUND(O18*Settings!$B$19/100,2)) | U18: =IF(B18="","",ROUND(O18-T18,2))
E19: =IF(B19="","",Settings!$B$8) | G19: =IF(B19="","",IF(F19<>"",F19,E19)) | M19: =IF(B19="","",ROUND(D19*G19/100,2)) | N19: =IF(B19="","",ROUND(M19*H19/100,2)) | O19: =IF(B19="","",M19-N19) | P19: =IF(B19="","",ROUND(I19*Settings!$B$18+J19,2)) | Q19: =IF(B19="","",ROUND(O19-P19,2)) | R19: =IF(B19="","",IFERROR(ROUND(Q19/O19*100,2),0)) | S19: =IF(B19="","",IFERROR(ROUND(O19/I19,2),0)) | T19: =IF(B19="","",ROUND(O19*Settings!$B$19/100,2)) | U19: =IF(B19="","",ROUND(O19-T19,2))
E20: =IF(B20="","",Settings!$B$8) | G20: =IF(B20="","",IF(F20<>"",F20,E20)) | M20: =IF(B20="","",ROUND(D20*G20/100,2)) | N20: =IF(B20="","",ROUND(M20*H20/100,2)) | O20: =IF(B20="","",M20-N20) | P20: =IF(B20="","",ROUND(I20*Settings!$B$18+J20,2)) | Q20: =IF(B20="","",ROUND(O20-P20,2)) | R20: =IF(B20="","",IFERROR(ROUND(Q20/O20*100,2),0)) | S20: =IF(B20="","",IFERROR(ROUND(O20/I20,2),0)) | T20: =IF(B20="","",ROUND(O20*Settings!$B$19/100,2)) | U20: =IF(B20="","",ROUND(O20-T20,2))
E21: =IF(B21="","",Settings!$B$8) | G21: =IF(B21="","",IF(F21<>"",F21,E21)) | M21: =IF(B21="","",ROUND(D21*G21/100,2)) | N21: =IF(B21="","",ROUND(M21*H21/100,2)) | O21: =IF(B21="","",M21-N21) | P21: =IF(B21="","",ROUND(I21*Settings!$B$18+J21,2)) | Q21: =IF(B21="","",ROUND(O21-P21,2)) | R21: =IF(B21="","",IFERROR(ROUND(Q21/O21*100,2),0)) | S21: =IF(B21="","",IFERROR(ROUND(O21/I21,2),0)) | T21: =IF(B21="","",ROUND(O21*Settings!$B$19/100,2)) | U21: =IF(B21="","",ROUND(O21-T21,2))
E22: =IF(B22="","",Settings!$B$8) | G22: =IF(B22="","",IF(F22<>"",F22,E22)) | M22: =IF(B22="","",ROUND(D22*G22/100,2)) | N22: =IF(B22="","",ROUND(M22*H22/100,2)) | O22: =IF(B22="","",M22-N22) | P22: =IF(B22="","",ROUND(I22*Settings!$B$18+J22,2)) | Q22: =IF(B22="","",ROUND(O22-P22,2)) | R22: =IF(B22="","",IFERROR(ROUND(Q22/O22*100,2),0)) | S22: =IF(B22="","",IFERROR(ROUND(O22/I22,2),0)) | T22: =IF(B22="","",ROUND(O22*Settings!$B$19/100,2)) | U22: =IF(B22="","",ROUND(O22-T22,2))
E23: =IF(B23="","",Settings!$B$8) | G23: =IF(B23="","",IF(F23<>"",F23,E23)) | M23: =IF(B23="","",ROUND(D23*G23/100,2)) | N23: =IF(B23="","",ROUND(M23*H23/100,2)) | O23: =IF(B23="","",M23-N23) | P23: =IF(B23="","",ROUND(I23*Settings!$B$18+J23,2)) | Q23: =IF(B23="","",ROUND(O23-P23,2)) | R23: =IF(B23="","",IFERROR(ROUND(Q23/O23*100,2),0)) | S23: =IF(B23="","",IFERROR(ROUND(O23/I23,2),0)) | T23: =IF(B23="","",ROUND(O23*Settings!$B$19/100,2)) | U23: =IF(B23="","",ROUND(O23-T23,2))
E24: =IF(B24="","",Settings!$B$8) | G24: =IF(B24="","",IF(F24<>"",F24,E24)) | M24: =IF(B24="","",ROUND(D24*G24/100,2)) | N24: =IF(B24="","",ROUND(M24*H24/100,2)) | O24: =IF(B24="","",M24-N24) | P24: =IF(B24="","",ROUND(I24*Settings!$B$18+J24,2)) | Q24: =IF(B24="","",ROUND(O24-P24,2)) | R24: =IF(B24="","",IFERROR(ROUND(Q24/O24*100,2),0)) | S24: =IF(B24="","",IFERROR(ROUND(O24/I24,2),0)) | T24: =IF(B24="","",ROUND(O24*Settings!$B$19/100,2)) | U24: =IF(B24="","",ROUND(O24-T24,2))
... E34: =IF(B34="","",Settings!$B$8) | G34: =IF(B34="","",IF(F34<>"",F34,E34)) | M34: =IF(B34="","",ROUND(D34*G34/100,2)) | N34: =IF(B34="","",ROUND(M34*H34/100,2)) | O34: =IF(B34="","",M34-N34) | P34: =IF(B34="","",ROUND(I34*Settings!$B$18+J34,2)) | Q34: =IF(B34="","",ROUND(O34-P34,2)) | R34: =IF(B34="","",IFERROR(ROUND(Q34/O34*100,2),0)) | S34: =IF(B34="","",IFERROR(ROUND(O34/I34,2),0)) | T34: =IF(B34="","",ROUND(O34*Settings!$B$19/100,2)) | U34: =IF(B34="","",ROUND(O34-T34,2))
A35: Total | B35: =COUNTA(B5:B34) -> 8 | D35: =SUM(D5:D34) -> 427000 | I35: =SUM(I5:I34) -> 315 | J35: =SUM(J5:J34) -> 3200 | L35: =SUM(L5:L34) -> 66100 | M35: =SUM(M5:M34) -> 85500 | N35: =SUM(N5:N34) -> 10450 | O35: =SUM(O5:O34) -> 75050 | P35: =SUM(P5:P34) -> 19476.05 | Q35: =SUM(Q5:Q34) -> 55573.95 | R35: =IFERROR(ROUND(Q35/O35*100,2),0) -> 74.05 | S35: =IFERROR(ROUND(O35/I35,2),0) -> 238.25 | T35: =SUM(T5:T34) -> 6004 | U35: =SUM(U5:U34) -> 69046

Sheet Temp Assignments
A1: Temp Assignments
A2: One row per temp or contractor assignment. On-costs % and markup % default from Settings; type your own to override them. Leave 'Bill rate override' empty to bill at pay rate × (1 + markup %).
A4: Client | B4: Worker | C4: Pay rate | D4: Default on-costs % (Settings) | E4: or type your own on-costs % | F4: On-costs % used | G4: Default markup % (Settings) | H4: or type your own markup % | I4: Markup % used | J4: Bill rate override | K4: Hours per week | L4: Weeks | M4: Bill rate used | N4: Loaded cost per hour | O4: Gross margin per hour | P4: Gross margin % | Q4: Bill per week | R4: Margin per week | S4: Margin for assignment | T4: Revenue for assignment
A5: Northwind Logistics | B5: Warehouse operative A | C5: 20 | D5: =IF(A5="","",Settings!$B$9) -> 18 | F5: =IF(A5="","",IF(E5<>"",E5,D5)) -> 18 | G5: =IF(A5="","",Settings!$B$10) -> 55 | I5: =IF(A5="","",IF(H5<>"",H5,G5)) -> 55 | K5: 40 | L5: 12 | M5: =IF(A5="","",IF(N(J5)>0,J5,ROUND(C5*(1+I5/100),2))) -> 31 | N5: =IF(A5="","",ROUND(C5*(1+F5/100),2)) -> 23.6 | O5: =IF(A5="","",ROUND(M5-N5,2)) -> 7.4 | P5: =IF(A5="","",IFERROR(ROUND(O5/M5*100,2),0)) -> 23.87 | Q5: =IF(A5="","",ROUND(M5*K5,2)) -> 1240 | R5: =IF(A5="","",ROUND(O5*K5,2)) -> 296 | S5: =IF(A5="","",ROUND(R5*L5,2)) -> 3552 | T5: =IF(A5="","",ROUND(Q5*L5,2)) -> 14880
A6: Northwind Logistics | B6: Forklift driver B | C6: 22 | D6: =IF(A6="","",Settings!$B$9) -> 18 | F6: =IF(A6="","",IF(E6<>"",E6,D6)) -> 18 | G6: =IF(A6="","",Settings!$B$10) -> 55 | I6: =IF(A6="","",IF(H6<>"",H6,G6)) -> 55 | K6: 40 | L6: 26 | M6: =IF(A6="","",IF(N(J6)>0,J6,ROUND(C6*(1+I6/100),2))) -> 34.1 | N6: =IF(A6="","",ROUND(C6*(1+F6/100),2)) -> 25.96 | O6: =IF(A6="","",ROUND(M6-N6,2)) -> 8.14 | P6: =IF(A6="","",IFERROR(ROUND(O6/M6*100,2),0)) -> 23.87 | Q6: =IF(A6="","",ROUND(M6*K6,2)) -> 1364 | R6: =IF(A6="","",ROUND(O6*K6,2)) -> 325.6 | S6: =IF(A6="","",ROUND(R6*L6,2)) -> 8465.6 | T6: =IF(A6="","",ROUND(Q6*L6,2)) -> 35464
A7: Brightline Dental | B7: Dental receptionist C | C7: 19 | D7: =IF(A7="","",Settings!$B$9) -> 18 | F7: =IF(A7="","",IF(E7<>"",E7,D7)) -> 18 | G7: =IF(A7="","",Settings!$B$10) -> 55 | I7: =IF(A7="","",IF(H7<>"",H7,G7)) -> 55 | K7: 30 | L7: 8 | M7: =IF(A7="","",IF(N(J7)>0,J7,ROUND(C7*(1+I7/100),2))) -> 29.45 | N7: =IF(A7="","",ROUND(C7*(1+F7/100),2)) -> 22.42 | O7: =IF(A7="","",ROUND(M7-N7,2)) -> 7.03 | P7: =IF(A7="","",IFERROR(ROUND(O7/M7*100,2),0)) -> 23.87 | Q7: =IF(A7="","",ROUND(M7*K7,2)) -> 883.5 | R7: =IF(A7="","",ROUND(O7*K7,2)) -> 210.9 | S7: =IF(A7="","",ROUND(R7*L7,2)) -> 1687.2 | T7: =IF(A7="","",ROUND(Q7*L7,2)) -> 7068
A8: Acme Engineering | B8: CAD technician D | C8: 30 | D8: =IF(A8="","",Settings!$B$9) -> 18 | F8: =IF(A8="","",IF(E8<>"",E8,D8)) -> 18 | G8: =IF(A8="","",Settings!$B$10) -> 55 | I8: =IF(A8="","",IF(H8<>"",H8,G8)) -> 55 | J8: 44 | K8: 37.5 | L8: 20 | M8: =IF(A8="","",IF(N(J8)>0,J8,ROUND(C8*(1+I8/100),2))) -> 44 | N8: =IF(A8="","",ROUND(C8*(1+F8/100),2)) -> 35.4 | O8: =IF(A8="","",ROUND(M8-N8,2)) -> 8.6 | P8: =IF(A8="","",IFERROR(ROUND(O8/M8*100,2),0)) -> 19.55 | Q8: =IF(A8="","",ROUND(M8*K8,2)) -> 1650 | R8: =IF(A8="","",ROUND(O8*K8,2)) -> 322.5 | S8: =IF(A8="","",ROUND(R8*L8,2)) -> 6450 | T8: =IF(A8="","",ROUND(Q8*L8,2)) -> 33000
A9: Harbor Foods | B9: Production line E | C9: 18 | D9: =IF(A9="","",Settings!$B$9) -> 18 | F9: =IF(A9="","",IF(E9<>"",E9,D9)) -> 18 | G9: =IF(A9="","",Settings!$B$10) -> 55 | I9: =IF(A9="","",IF(H9<>"",H9,G9)) -> 55 | K9: 40 | L9: 16 | M9: =IF(A9="","",IF(N(J9)>0,J9,ROUND(C9*(1+I9/100),2))) -> 27.9 | N9: =IF(A9="","",ROUND(C9*(1+F9/100),2)) -> 21.24 | O9: =IF(A9="","",ROUND(M9-N9,2)) -> 6.66 | P9: =IF(A9="","",IFERROR(ROUND(O9/M9*100,2),0)) -> 23.87 | Q9: =IF(A9="","",ROUND(M9*K9,2)) -> 1116 | R9: =IF(A9="","",ROUND(O9*K9,2)) -> 266.4 | S9: =IF(A9="","",ROUND(R9*L9,2)) -> 4262.4 | T9: =IF(A9="","",ROUND(Q9*L9,2)) -> 17856
A10: Delta Software | B10: QA contractor F | C10: 45 | D10: =IF(A10="","",Settings!$B$9) -> 18 | E10: 12 | F10: =IF(A10="","",IF(E10<>"",E10,D10)) -> 12 | G10: =IF(A10="","",Settings!$B$10) -> 55 | H10: 40 | I10: =IF(A10="","",IF(H10<>"",H10,G10)) -> 40 | K10: 37.5 | L10: 24 | M10: =IF(A10="","",IF(N(J10)>0,J10,ROUND(C10*(1+I10/100),2))) -> 63 | N10: =IF(A10="","",ROUND(C10*(1+F10/100),2)) -> 50.4 | O10: =IF(A10="","",ROUND(M10-N10,2)) -> 12.6 | P10: =IF(A10="","",IFERROR(ROUND(O10/M10*100,2),0)) -> 20 | Q10: =IF(A10="","",ROUND(M10*K10,2)) -> 2362.5 | R10: =IF(A10="","",ROUND(O10*K10,2)) -> 472.5 | S10: =IF(A10="","",ROUND(R10*L10,2)) -> 11340 | T10: =IF(A10="","",ROUND(Q10*L10,2)) -> 56700
A11: Garcia Retail | B11: Seasonal sales G | C11: 25 | D11: =IF(A11="","",Settings!$B$9) -> 18 | F11: =IF(A11="","",IF(E11<>"",E11,D11)) -> 18 | G11: =IF(A11="","",Settings!$B$10) -> 55 | H11: 25 | I11: =IF(A11="","",IF(H11<>"",H11,G11)) -> 25 | K11: 35 | L11: 10 | M11: =IF(A11="","",IF(N(J11)>0,J11,ROUND(C11*(1+I11/100),2))) -> 31.25 | N11: =IF(A11="","",ROUND(C11*(1+F11/100),2)) -> 29.5 | O11: =IF(A11="","",ROUND(M11-N11,2)) -> 1.75 | P11: =IF(A11="","",IFERROR(ROUND(O11/M11*100,2),0)) -> 5.6 | Q11: =IF(A11="","",ROUND(M11*K11,2)) -> 1093.75 | R11: =IF(A11="","",ROUND(O11*K11,2)) -> 61.25 | S11: =IF(A11="","",ROUND(R11*L11,2)) -> 612.5 | T11: =IF(A11="","",ROUND(Q11*L11,2)) -> 10937.5
A12: Okafor & Co | B12: Payroll clerk H | C12: 24 | D12: =IF(A12="","",Settings!$B$9) -> 18 | F12: =IF(A12="","",IF(E12<>"",E12,D12)) -> 18 | G12: =IF(A12="","",Settings!$B$10) -> 55 | I12: =IF(A12="","",IF(H12<>"",H12,G12)) -> 55 | K12: 37.5 | L12: 6 | M12: =IF(A12="","",IF(N(J12)>0,J12,ROUND(C12*(1+I12/100),2))) -> 37.2 | N12: =IF(A12="","",ROUND(C12*(1+F12/100),2)) -> 28.32 | O12: =IF(A12="","",ROUND(M12-N12,2)) -> 8.88 | P12: =IF(A12="","",IFERROR(ROUND(O12/M12*100,2),0)) -> 23.87 | Q12: =IF(A12="","",ROUND(M12*K12,2)) -> 1395 | R12: =IF(A12="","",ROUND(O12*K12,2)) -> 333 | S12: =IF(A12="","",ROUND(R12*L12,2)) -> 1998 | T12: =IF(A12="","",ROUND(Q12*L12,2)) -> 8370
D13: =IF(A13="","",Settings!$B$9) | F13: =IF(A13="","",IF(E13<>"",E13,D13)) | G13: =IF(A13="","",Settings!$B$10) | I13: =IF(A13="","",IF(H13<>"",H13,G13)) | M13: =IF(A13="","",IF(N(J13)>0,J13,ROUND(C13*(1+I13/100),2))) | N13: =IF(A13="","",ROUND(C13*(1+F13/100),2)) | O13: =IF(A13="","",ROUND(M13-N13,2)) | P13: =IF(A13="","",IFERROR(ROUND(O13/M13*100,2),0)) | Q13: =IF(A13="","",ROUND(M13*K13,2)) | R13: =IF(A13="","",ROUND(O13*K13,2)) | S13: =IF(A13="","",ROUND(R13*L13,2)) | T13: =IF(A13="","",ROUND(Q13*L13,2))
D14: =IF(A14="","",Settings!$B$9) | F14: =IF(A14="","",IF(E14<>"",E14,D14)) | G14: =IF(A14="","",Settings!$B$10) | I14: =IF(A14="","",IF(H14<>"",H14,G14)) | M14: =IF(A14="","",IF(N(J14)>0,J14,ROUND(C14*(1+I14/100),2))) | N14: =IF(A14="","",ROUND(C14*(1+F14/100),2)) | O14: =IF(A14="","",ROUND(M14-N14,2)) | P14: =IF(A14="","",IFERROR(ROUND(O14/M14*100,2),0)) | Q14: =IF(A14="","",ROUND(M14*K14,2)) | R14: =IF(A14="","",ROUND(O14*K14,2)) | S14: =IF(A14="","",ROUND(R14*L14,2)) | T14: =IF(A14="","",ROUND(Q14*L14,2))
D15: =IF(A15="","",Settings!$B$9) | F15: =IF(A15="","",IF(E15<>"",E15,D15)) | G15: =IF(A15="","",Settings!$B$10) | I15: =IF(A15="","",IF(H15<>"",H15,G15)) | M15: =IF(A15="","",IF(N(J15)>0,J15,ROUND(C15*(1+I15/100),2))) | N15: =IF(A15="","",ROUND(C15*(1+F15/100),2)) | O15: =IF(A15="","",ROUND(M15-N15,2)) | P15: =IF(A15="","",IFERROR(ROUND(O15/M15*100,2),0)) | Q15: =IF(A15="","",ROUND(M15*K15,2)) | R15: =IF(A15="","",ROUND(O15*K15,2)) | S15: =IF(A15="","",ROUND(R15*L15,2)) | T15: =IF(A15="","",ROUND(Q15*L15,2))
D16: =IF(A16="","",Settings!$B$9) | F16: =IF(A16="","",IF(E16<>"",E16,D16)) | G16: =IF(A16="","",Settings!$B$10) | I16: =IF(A16="","",IF(H16<>"",H16,G16)) | M16: =IF(A16="","",IF(N(J16)>0,J16,ROUND(C16*(1+I16/100),2))) | N16: =IF(A16="","",ROUND(C16*(1+F16/100),2)) | O16: =IF(A16="","",ROUND(M16-N16,2)) | P16: =IF(A16="","",IFERROR(ROUND(O16/M16*100,2),0)) | Q16: =IF(A16="","",ROUND(M16*K16,2)) | R16: =IF(A16="","",ROUND(O16*K16,2)) | S16: =IF(A16="","",ROUND(R16*L16,2)) | T16: =IF(A16="","",ROUND(Q16*L16,2))
D17: =IF(A17="","",Settings!$B$9) | F17: =IF(A17="","",IF(E17<>"",E17,D17)) | G17: =IF(A17="","",Settings!$B$10) | I17: =IF(A17="","",IF(H17<>"",H17,G17)) | M17: =IF(A17="","",IF(N(J17)>0,J17,ROUND(C17*(1+I17/100),2))) | N17: =IF(A17="","",ROUND(C17*(1+F17/100),2)) | O17: =IF(A17="","",ROUND(M17-N17,2)) | P17: =IF(A17="","",IFERROR(ROUND(O17/M17*100,2),0)) | Q17: =IF(A17="","",ROUND(M17*K17,2)) | R17: =IF(A17="","",ROUND(O17*K17,2)) | S17: =IF(A17="","",ROUND(R17*L17,2)) | T17: =IF(A17="","",ROUND(Q17*L17,2))
D18: =IF(A18="","",Settings!$B$9) | F18: =IF(A18="","",IF(E18<>"",E18,D18)) | G18: =IF(A18="","",Settings!$B$10) | I18: =IF(A18="","",IF(H18<>"",H18,G18)) | M18: =IF(A18="","",IF(N(J18)>0,J18,ROUND(C18*(1+I18/100),2))) | N18: =IF(A18="","",ROUND(C18*(1+F18/100),2)) | O18: =IF(A18="","",ROUND(M18-N18,2)) | P18: =IF(A18="","",IFERROR(ROUND(O18/M18*100,2),0)) | Q18: =IF(A18="","",ROUND(M18*K18,2)) | R18: =IF(A18="","",ROUND(O18*K18,2)) | S18: =IF(A18="","",ROUND(R18*L18,2)) | T18: =IF(A18="","",ROUND(Q18*L18,2))
D19: =IF(A19="","",Settings!$B$9) | F19: =IF(A19="","",IF(E19<>"",E19,D19)) | G19: =IF(A19="","",Settings!$B$10) | I19: =IF(A19="","",IF(H19<>"",H19,G19)) | M19: =IF(A19="","",IF(N(J19)>0,J19,ROUND(C19*(1+I19/100),2))) | N19: =IF(A19="","",ROUND(C19*(1+F19/100),2)) | O19: =IF(A19="","",ROUND(M19-N19,2)) | P19: =IF(A19="","",IFERROR(ROUND(O19/M19*100,2),0)) | Q19: =IF(A19="","",ROUND(M19*K19,2)) | R19: =IF(A19="","",ROUND(O19*K19,2)) | S19: =IF(A19="","",ROUND(R19*L19,2)) | T19: =IF(A19="","",ROUND(Q19*L19,2))
D20: =IF(A20="","",Settings!$B$9) | F20: =IF(A20="","",IF(E20<>"",E20,D20)) | G20: =IF(A20="","",Settings!$B$10) | I20: =IF(A20="","",IF(H20<>"",H20,G20)) | M20: =IF(A20="","",IF(N(J20)>0,J20,ROUND(C20*(1+I20/100),2))) | N20: =IF(A20="","",ROUND(C20*(1+F20/100),2)) | O20: =IF(A20="","",ROUND(M20-N20,2)) | P20: =IF(A20="","",IFERROR(ROUND(O20/M20*100,2),0)) | Q20: =IF(A20="","",ROUND(M20*K20,2)) | R20: =IF(A20="","",ROUND(O20*K20,2)) | S20: =IF(A20="","",ROUND(R20*L20,2)) | T20: =IF(A20="","",ROUND(Q20*L20,2))
D21: =IF(A21="","",Settings!$B$9) | F21: =IF(A21="","",IF(E21<>"",E21,D21)) | G21: =IF(A21="","",Settings!$B$10) | I21: =IF(A21="","",IF(H21<>"",H21,G21)) | M21: =IF(A21="","",IF(N(J21)>0,J21,ROUND(C21*(1+I21/100),2))) | N21: =IF(A21="","",ROUND(C21*(1+F21/100),2)) | O21: =IF(A21="","",ROUND(M21-N21,2)) | P21: =IF(A21="","",IFERROR(ROUND(O21/M21*100,2),0)) | Q21: =IF(A21="","",ROUND(M21*K21,2)) | R21: =IF(A21="","",ROUND(O21*K21,2)) | S21: =IF(A21="","",ROUND(R21*L21,2)) | T21: =IF(A21="","",ROUND(Q21*L21,2))
D22: =IF(A22="","",Settings!$B$9) | F22: =IF(A22="","",IF(E22<>"",E22,D22)) | G22: =IF(A22="","",Settings!$B$10) | I22: =IF(A22="","",IF(H22<>"",H22,G22)) | M22: =IF(A22="","",IF(N(J22)>0,J22,ROUND(C22*(1+I22/100),2))) | N22: =IF(A22="","",ROUND(C22*(1+F22/100),2)) | O22: =IF(A22="","",ROUND(M22-N22,2)) | P22: =IF(A22="","",IFERROR(ROUND(O22/M22*100,2),0)) | Q22: =IF(A22="","",ROUND(M22*K22,2)) | R22: =IF(A22="","",ROUND(O22*K22,2)) | S22: =IF(A22="","",ROUND(R22*L22,2)) | T22: =IF(A22="","",ROUND(Q22*L22,2))
D23: =IF(A23="","",Settings!$B$9) | F23: =IF(A23="","",IF(E23<>"",E23,D23)) | G23: =IF(A23="","",Settings!$B$10) | I23: =IF(A23="","",IF(H23<>"",H23,G23)) | M23: =IF(A23="","",IF(N(J23)>0,J23,ROUND(C23*(1+I23/100),2))) | N23: =IF(A23="","",ROUND(C23*(1+F23/100),2)) | O23: =IF(A23="","",ROUND(M23-N23,2)) | P23: =IF(A23="","",IFERROR(ROUND(O23/M23*100,2),0)) | Q23: =IF(A23="","",ROUND(M23*K23,2)) | R23: =IF(A23="","",ROUND(O23*K23,2)) | S23: =IF(A23="","",ROUND(R23*L23,2)) | T23: =IF(A23="","",ROUND(Q23*L23,2))
D24: =IF(A24="","",Settings!$B$9) | F24: =IF(A24="","",IF(E24<>"",E24,D24)) | G24: =IF(A24="","",Settings!$B$10) | I24: =IF(A24="","",IF(H24<>"",H24,G24)) | M24: =IF(A24="","",IF(N(J24)>0,J24,ROUND(C24*(1+I24/100),2))) | N24: =IF(A24="","",ROUND(C24*(1+F24/100),2)) | O24: =IF(A24="","",ROUND(M24-N24,2)) | P24: =IF(A24="","",IFERROR(ROUND(O24/M24*100,2),0)) | Q24: =IF(A24="","",ROUND(M24*K24,2)) | R24: =IF(A24="","",ROUND(O24*K24,2)) | S24: =IF(A24="","",ROUND(R24*L24,2)) | T24: =IF(A24="","",ROUND(Q24*L24,2))
... D34: =IF(A34="","",Settings!$B$9) | F34: =IF(A34="","",IF(E34<>"",E34,D34)) | G34: =IF(A34="","",Settings!$B$10) | I34: =IF(A34="","",IF(H34<>"",H34,G34)) | M34: =IF(A34="","",IF(N(J34)>0,J34,ROUND(C34*(1+I34/100),2))) | N34: =IF(A34="","",ROUND(C34*(1+F34/100),2)) | O34: =IF(A34="","",ROUND(M34-N34,2)) | P34: =IF(A34="","",IFERROR(ROUND(O34/M34*100,2),0)) | Q34: =IF(A34="","",ROUND(M34*K34,2)) | R34: =IF(A34="","",ROUND(O34*K34,2)) | S34: =IF(A34="","",ROUND(R34*L34,2)) | T34: =IF(A34="","",ROUND(Q34*L34,2))
A35: Total | B35: =COUNTA(A5:A34) -> 8 | P35: =IFERROR(ROUND(R35/Q35*100,2),0) -> 20.61 | Q35: =SUM(Q5:Q34) -> 11104.75 | R35: =SUM(R5:R34) -> 2288.15 | S35: =SUM(S5:S34) -> 38367.7 | T35: =SUM(T5:T34) -> 184275.5

Sheet Desk Performance
A1: Desk Performance
A2: One row per month, filled top down, with the first day of the month in column A. Perm placements and net perm fees are counted from Perm Placements by date; type your own to override them. Temp margin is typed in because assignments have no dates.
A4: Month | B4: Perm placements (from Perm Placements) | C4: or type your own placements | D4: Perm placements used | E4: Net perm fees (from Perm Placements) | F4: or type your own net fees | G4: Net perm fees used | H4: Temp margin earned | I4: Job orders received | J4: Job orders filled | K4: Candidates submitted | L4: Interviews | M4: Total days to fill | N4: Total gross margin | O4: Desk cost for the month | P4: Desk profit | Q4: Fill rate % | R4: Average days to fill | S4: Submittals per fill | T4: Interview to fill % | U4: Margin per recruiter
A5: 46023 | B5: =IF(A5="","",COUNTIFS('Perm Placements'!$A$5:$A$34,">="&A5,'Perm Placements'!$A$5:$A$34,"<"&DATE(YEAR(A5),MONTH(A5)+1,1))) -> 2 | D5: =IF(A5="","",IF(C5<>"",C5,B5)) -> 2 | E5: =IF(A5="","",ROUND(SUMIFS('Perm Placements'!$O$5:$O$34,'Perm Placements'!$A$5:$A$34,">="&A5,'Perm Placements'!$A$5:$A$34,"<"&DATE(YEAR(A5),MONTH(A5)+1,1)),2)) -> 19350 | G5: =IF(A5="","",IF(F5<>"",F5,E5)) -> 19350 | H5: 14000 | I5: 12 | J5: 5 | K5: 30 | L5: 14 | M5: 160 | N5: =IF(A5="","",ROUND(G5+H5,2)) -> 33350 | O5: =IF(A5="","",ROUND(Settings!$B$16/12,2)) -> 31000 | P5: =IF(A5="","",ROUND(N5-O5,2)) -> 2350 | Q5: =IF(A5="","",IFERROR(ROUND(J5/I5*100,2),0)) -> 41.67 | R5: =IF(A5="","",IFERROR(ROUND(M5/J5,2),0)) -> 32 | S5: =IF(A5="","",IFERROR(ROUND(K5/J5,2),0)) -> 6 | T5: =IF(A5="","",IFERROR(ROUND(J5/L5*100,2),0)) -> 35.71 | U5: =IF(A5="","",IFERROR(ROUND(N5/Settings!$B$2,2),0)) -> 8337.5
A6: 46054 | B6: =IF(A6="","",COUNTIFS('Perm Placements'!$A$5:$A$34,">="&A6,'Perm Placements'!$A$5:$A$34,"<"&DATE(YEAR(A6),MONTH(A6)+1,1))) -> 1 | D6: =IF(A6="","",IF(C6<>"",C6,B6)) -> 1 | E6: =IF(A6="","",ROUND(SUMIFS('Perm Placements'!$O$5:$O$34,'Perm Placements'!$A$5:$A$34,">="&A6,'Perm Placements'!$A$5:$A$34,"<"&DATE(YEAR(A6),MONTH(A6)+1,1)),2)) -> 18700 | G6: =IF(A6="","",IF(F6<>"",F6,E6)) -> 18700 | H6: 15500 | I6: 10 | J6: 4 | K6: 26 | L6: 11 | M6: 140 | N6: =IF(A6="","",ROUND(G6+H6,2)) -> 34200 | O6: =IF(A6="","",ROUND(Settings!$B$16/12,2)) -> 31000 | P6: =IF(A6="","",ROUND(N6-O6,2)) -> 3200 | Q6: =IF(A6="","",IFERROR(ROUND(J6/I6*100,2),0)) -> 40 | R6: =IF(A6="","",IFERROR(ROUND(M6/J6,2),0)) -> 35 | S6: =IF(A6="","",IFERROR(ROUND(K6/J6,2),0)) -> 6.5 | T6: =IF(A6="","",IFERROR(ROUND(J6/L6*100,2),0)) -> 36.36 | U6: =IF(A6="","",IFERROR(ROUND(N6/Settings!$B$2,2),0)) -> 8550
A7: 46082 | B7: =IF(A7="","",COUNTIFS('Perm Placements'!$A$5:$A$34,">="&A7,'Perm Placements'!$A$5:$A$34,"<"&DATE(YEAR(A7),MONTH(A7)+1,1))) -> 1 | D7: =IF(A7="","",IF(C7<>"",C7,B7)) -> 1 | E7: =IF(A7="","",ROUND(SUMIFS('Perm Placements'!$O$5:$O$34,'Perm Placements'!$A$5:$A$34,">="&A7,'Perm Placements'!$A$5:$A$34,"<"&DATE(YEAR(A7),MONTH(A7)+1,1)),2)) -> 4800 | G7: =IF(A7="","",IF(F7<>"",F7,E7)) -> 4800 | H7: 16200 | I7: 14 | J7: 6 | K7: 38 | L7: 17 | M7: 198 | N7: =IF(A7="","",ROUND(G7+H7,2)) -> 21000 | O7: =IF(A7="","",ROUND(Settings!$B$16/12,2)) -> 31000 | P7: =IF(A7="","",ROUND(N7-O7,2)) -> -10000 | Q7: =IF(A7="","",IFERROR(ROUND(J7/I7*100,2),0)) -> 42.86 | R7: =IF(A7="","",IFERROR(ROUND(M7/J7,2),0)) -> 33 | S7: =IF(A7="","",IFERROR(ROUND(K7/J7,2),0)) -> 6.33 | T7: =IF(A7="","",IFERROR(ROUND(J7/L7*100,2),0)) -> 35.29 | U7: =IF(A7="","",IFERROR(ROUND(N7/Settings!$B$2,2),0)) -> 5250
A8: 46113 | B8: =IF(A8="","",COUNTIFS('Perm Placements'!$A$5:$A$34,">="&A8,'Perm Placements'!$A$5:$A$34,"<"&DATE(YEAR(A8),MONTH(A8)+1,1))) -> 2 | D8: =IF(A8="","",IF(C8<>"",C8,B8)) -> 2 | E8: =IF(A8="","",ROUND(SUMIFS('Perm Placements'!$O$5:$O$34,'Perm Placements'!$A$5:$A$34,">="&A8,'Perm Placements'!$A$5:$A$34,"<"&DATE(YEAR(A8),MONTH(A8)+1,1)),2)) -> 12800 | G8: =IF(A8="","",IF(F8<>"",F8,E8)) -> 12800 | H8: 15800 | I8: 11 | J8: 6 | K8: 33 | L8: 15 | M8: 174 | N8: =IF(A8="","",ROUND(G8+H8,2)) -> 28600 | O8: =IF(A8="","",ROUND(Settings!$B$16/12,2)) -> 31000 | P8: =IF(A8="","",ROUND(N8-O8,2)) -> -2400 | Q8: =IF(A8="","",IFERROR(ROUND(J8/I8*100,2),0)) -> 54.55 | R8: =IF(A8="","",IFERROR(ROUND(M8/J8,2),0)) -> 29 | S8: =IF(A8="","",IFERROR(ROUND(K8/J8,2),0)) -> 5.5 | T8: =IF(A8="","",IFERROR(ROUND(J8/L8*100,2),0)) -> 40 | U8: =IF(A8="","",IFERROR(ROUND(N8/Settings!$B$2,2),0)) -> 7150
A9: 46143 | B9: =IF(A9="","",COUNTIFS('Perm Placements'!$A$5:$A$34,">="&A9,'Perm Placements'!$A$5:$A$34,"<"&DATE(YEAR(A9),MONTH(A9)+1,1))) -> 1 | D9: =IF(A9="","",IF(C9<>"",C9,B9)) -> 1 | E9: =IF(A9="","",ROUND(SUMIFS('Perm Placements'!$O$5:$O$34,'Perm Placements'!$A$5:$A$34,">="&A9,'Perm Placements'!$A$5:$A$34,"<"&DATE(YEAR(A9),MONTH(A9)+1,1)),2)) -> 10400 | G9: =IF(A9="","",IF(F9<>"",F9,E9)) -> 10400 | H9: 17100 | I9: 13 | J9: 5 | K9: 35 | L9: 13 | M9: 165 | N9: =IF(A9="","",ROUND(G9+H9,2)) -> 27500 | O9: =IF(A9="","",ROUND(Settings!$B$16/12,2)) -> 31000 | P9: =IF(A9="","",ROUND(N9-O9,2)) -> -3500 | Q9: =IF(A9="","",IFERROR(ROUND(J9/I9*100,2),0)) -> 38.46 | R9: =IF(A9="","",IFERROR(ROUND(M9/J9,2),0)) -> 33 | S9: =IF(A9="","",IFERROR(ROUND(K9/J9,2),0)) -> 7 | T9: =IF(A9="","",IFERROR(ROUND(J9/L9*100,2),0)) -> 38.46 | U9: =IF(A9="","",IFERROR(ROUND(N9/Settings!$B$2,2),0)) -> 6875
A10: 46174 | B10: =IF(A10="","",COUNTIFS('Perm Placements'!$A$5:$A$34,">="&A10,'Perm Placements'!$A$5:$A$34,"<"&DATE(YEAR(A10),MONTH(A10)+1,1))) -> 1 | D10: =IF(A10="","",IF(C10<>"",C10,B10)) -> 1 | E10: =IF(A10="","",ROUND(SUMIFS('Perm Placements'!$O$5:$O$34,'Perm Placements'!$A$5:$A$34,">="&A10,'Perm Placements'!$A$5:$A$34,"<"&DATE(YEAR(A10),MONTH(A10)+1,1)),2)) -> 9000 | G10: =IF(A10="","",IF(F10<>"",F10,E10)) -> 9000 | H10: 16400 | I10: 12 | J10: 5 | K10: 29 | L10: 12 | M10: 150 | N10: =IF(A10="","",ROUND(G10+H10,2)) -> 25400 | O10: =IF(A10="","",ROUND(Settings!$B$16/12,2)) -> 31000 | P10: =IF(A10="","",ROUND(N10-O10,2)) -> -5600 | Q10: =IF(A10="","",IFERROR(ROUND(J10/I10*100,2),0)) -> 41.67 | R10: =IF(A10="","",IFERROR(ROUND(M10/J10,2),0)) -> 30 | S10: =IF(A10="","",IFERROR(ROUND(K10/J10,2),0)) -> 5.8 | T10: =IF(A10="","",IFERROR(ROUND(J10/L10*100,2),0)) -> 41.67 | U10: =IF(A10="","",IFERROR(ROUND(N10/Settings!$B$2,2),0)) -> 6350
B11: =IF(A11="","",COUNTIFS('Perm Placements'!$A$5:$A$34,">="&A11,'Perm Placements'!$A$5:$A$34,"<"&DATE(YEAR(A11),MONTH(A11)+1,1))) | D11: =IF(A11="","",IF(C11<>"",C11,B11)) | E11: =IF(A11="","",ROUND(SUMIFS('Perm Placements'!$O$5:$O$34,'Perm Placements'!$A$5:$A$34,">="&A11,'Perm Placements'!$A$5:$A$34,"<"&DATE(YEAR(A11),MONTH(A11)+1,1)),2)) | G11: =IF(A11="","",IF(F11<>"",F11,E11)) | N11: =IF(A11="","",ROUND(G11+H11,2)) | O11: =IF(A11="","",ROUND(Settings!$B$16/12,2)) | P11: =IF(A11="","",ROUND(N11-O11,2)) | Q11: =IF(A11="","",IFERROR(ROUND(J11/I11*100,2),0)) | R11: =IF(A11="","",IFERROR(ROUND(M11/J11,2),0)) | S11: =IF(A11="","",IFERROR(ROUND(K11/J11,2),0)) | T11: =IF(A11="","",IFERROR(ROUND(J11/L11*100,2),0)) | U11: =IF(A11="","",IFERROR(ROUND(N11/Settings!$B$2,2),0))
B12: =IF(A12="","",COUNTIFS('Perm Placements'!$A$5:$A$34,">="&A12,'Perm Placements'!$A$5:$A$34,"<"&DATE(YEAR(A12),MONTH(A12)+1,1))) | D12: =IF(A12="","",IF(C12<>"",C12,B12)) | E12: =IF(A12="","",ROUND(SUMIFS('Perm Placements'!$O$5:$O$34,'Perm Placements'!$A$5:$A$34,">="&A12,'Perm Placements'!$A$5:$A$34,"<"&DATE(YEAR(A12),MONTH(A12)+1,1)),2)) | G12: =IF(A12="","",IF(F12<>"",F12,E12)) | N12: =IF(A12="","",ROUND(G12+H12,2)) | O12: =IF(A12="","",ROUND(Settings!$B$16/12,2)) | P12: =IF(A12="","",ROUND(N12-O12,2)) | Q12: =IF(A12="","",IFERROR(ROUND(J12/I12*100,2),0)) | R12: =IF(A12="","",IFERROR(ROUND(M12/J12,2),0)) | S12: =IF(A12="","",IFERROR(ROUND(K12/J12,2),0)) | T12: =IF(A12="","",IFERROR(ROUND(J12/L12*100,2),0)) | U12: =IF(A12="","",IFERROR(ROUND(N12/Settings!$B$2,2),0))
B13: =IF(A13="","",COUNTIFS('Perm Placements'!$A$5:$A$34,">="&A13,'Perm Placements'!$A$5:$A$34,"<"&DATE(YEAR(A13),MONTH(A13)+1,1))) | D13: =IF(A13="","",IF(C13<>"",C13,B13)) | E13: =IF(A13="","",ROUND(SUMIFS('Perm Placements'!$O$5:$O$34,'Perm Placements'!$A$5:$A$34,">="&A13,'Perm Placements'!$A$5:$A$34,"<"&DATE(YEAR(A13),MONTH(A13)+1,1)),2)) | G13: =IF(A13="","",IF(F13<>"",F13,E13)) | N13: =IF(A13="","",ROUND(G13+H13,2)) | O13: =IF(A13="","",ROUND(Settings!$B$16/12,2)) | P13: =IF(A13="","",ROUND(N13-O13,2)) | Q13: =IF(A13="","",IFERROR(ROUND(J13/I13*100,2),0)) | R13: =IF(A13="","",IFERROR(ROUND(M13/J13,2),0)) | S13: =IF(A13="","",IFERROR(ROUND(K13/J13,2),0)) | T13: =IF(A13="","",IFERROR(ROUND(J13/L13*100,2),0)) | U13: =IF(A13="","",IFERROR(ROUND(N13/Settings!$B$2,2),0))
B14: =IF(A14="","",COUNTIFS('Perm Placements'!$A$5:$A$34,">="&A14,'Perm Placements'!$A$5:$A$34,"<"&DATE(YEAR(A14),MONTH(A14)+1,1))) | D14: =IF(A14="","",IF(C14<>"",C14,B14)) | E14: =IF(A14="","",ROUND(SUMIFS('Perm Placements'!$O$5:$O$34,'Perm Placements'!$A$5:$A$34,">="&A14,'Perm Placements'!$A$5:$A$34,"<"&DATE(YEAR(A14),MONTH(A14)+1,1)),2)) | G14: =IF(A14="","",IF(F14<>"",F14,E14)) | N14: =IF(A14="","",ROUND(G14+H14,2)) | O14: =IF(A14="","",ROUND(Settings!$B$16/12,2)) | P14: =IF(A14="","",ROUND(N14-O14,2)) | Q14: =IF(A14="","",IFERROR(ROUND(J14/I14*100,2),0)) | R14: =IF(A14="","",IFERROR(ROUND(M14/J14,2),0)) | S14: =IF(A14="","",IFERROR(ROUND(K14/J14,2),0)) | T14: =IF(A14="","",IFERROR(ROUND(J14/L14*100,2),0)) | U14: =IF(A14="","",IFERROR(ROUND(N14/Settings!$B$2,2),0))
B15: =IF(A15="","",COUNTIFS('Perm Placements'!$A$5:$A$34,">="&A15,'Perm Placements'!$A$5:$A$34,"<"&DATE(YEAR(A15),MONTH(A15)+1,1))) | D15: =IF(A15="","",IF(C15<>"",C15,B15)) | E15: =IF(A15="","",ROUND(SUMIFS('Perm Placements'!$O$5:$O$34,'Perm Placements'!$A$5:$A$34,">="&A15,'Perm Placements'!$A$5:$A$34,"<"&DATE(YEAR(A15),MONTH(A15)+1,1)),2)) | G15: =IF(A15="","",IF(F15<>"",F15,E15)) | N15: =IF(A15="","",ROUND(G15+H15,2)) | O15: =IF(A15="","",ROUND(Settings!$B$16/12,2)) | P15: =IF(A15="","",ROUND(N15-O15,2)) | Q15: =IF(A15="","",IFERROR(ROUND(J15/I15*100,2),0)) | R15: =IF(A15="","",IFERROR(ROUND(M15/J15,2),0)) | S15: =IF(A15="","",IFERROR(ROUND(K15/J15,2),0)) | T15: =IF(A15="","",IFERROR(ROUND(J15/L15*100,2),0)) | U15: =IF(A15="","",IFERROR(ROUND(N15/Settings!$B$2,2),0))
B16: =IF(A16="","",COUNTIFS('Perm Placements'!$A$5:$A$34,">="&A16,'Perm Placements'!$A$5:$A$34,"<"&DATE(YEAR(A16),MONTH(A16)+1,1))) | D16: =IF(A16="","",IF(C16<>"",C16,B16)) | E16: =IF(A16="","",ROUND(SUMIFS('Perm Placements'!$O$5:$O$34,'Perm Placements'!$A$5:$A$34,">="&A16,'Perm Placements'!$A$5:$A$34,"<"&DATE(YEAR(A16),MONTH(A16)+1,1)),2)) | G16: =IF(A16="","",IF(F16<>"",F16,E16)) | N16: =IF(A16="","",ROUND(G16+H16,2)) | O16: =IF(A16="","",ROUND(Settings!$B$16/12,2)) | P16: =IF(A16="","",ROUND(N16-O16,2)) | Q16: =IF(A16="","",IFERROR(ROUND(J16/I16*100,2),0)) | R16: =IF(A16="","",IFERROR(ROUND(M16/J16,2),0)) | S16: =IF(A16="","",IFERROR(ROUND(K16/J16,2),0)) | T16: =IF(A16="","",IFERROR(ROUND(J16/L16*100,2),0)) | U16: =IF(A16="","",IFERROR(ROUND(N16/Settings!$B$2,2),0))
A17: Total | D17: =SUM(D5:D16) -> 8 | G17: =SUM(G5:G16) -> 75050 | H17: =SUM(H5:H16) -> 95000 | I17: =SUM(I5:I16) -> 72 | J17: =SUM(J5:J16) -> 31 | K17: =SUM(K5:K16) -> 191 | L17: =SUM(L5:L16) -> 82 | M17: =SUM(M5:M16) -> 987 | N17: =SUM(N5:N16) -> 170050 | ... P17: =SUM(P5:P16) -> -15950 | Q17: =IFERROR(ROUND(J17/I17*100,2),0) -> 43.06 | R17: =IFERROR(ROUND(M17/J17,2),0) -> 31.84 | S17: =IFERROR(ROUND(K17/J17,2),0) -> 6.16 | T17: =IFERROR(ROUND(J17/L17*100,2),0) -> 37.8 | U17: =IFERROR(ROUND(N17/Settings!$B$2,2),0) -> 42512.5

Sheet Rebate Reserve
A1: Rebate Reserve
A2: One row per placement under guarantee. Guarantee days, fall-off % and rebate % default from Settings; type your own to override them. Set the outcome when the guarantee ends or the candidate leaves.
A4: Placement | B4: Start date | C4: Net fee | D4: Default guarantee days (Settings) | E4: or type your own days | F4: Guarantee days used | G4: Default fall-off % (Settings) | H4: or type your own fall-off % | I4: Fall-off % used | J4: Default rebate % (Settings) | K4: or type your own rebate % | L4: Rebate % used | M4: Actual outcome | N4: Guarantee end date | O4: Expected reserve | P4: Reserve released | Q4: Rebate paid | R4: Reserve still held
A5: Northwind Logistics: Warehouse manager | B5: 46034 | C5: 9750 | D5: =IF(A5="","",Settings!$B$11) -> 90 | F5: =IF(A5="","",IF(E5<>"",E5,D5)) -> 90 | G5: =IF(A5="","",Settings!$B$12) -> 8 | I5: =IF(A5="","",IF(H5<>"",H5,G5)) -> 8 | J5: =IF(A5="","",Settings!$B$13) -> 100 | L5: =IF(A5="","",IF(K5<>"",K5,J5)) -> 100 | M5: retained | N5: =IF(A5="","",B5+F5) -> 46124 | O5: =IF(A5="","",ROUND(C5*L5*I5/10000,2)) -> 780 | P5: =IF(A5="","",IF(M5="retained",O5,0)) -> 780 | Q5: =IF(A5="","",IF(M5="fell off",ROUND(C5*L5/100,2),0)) -> 0 | R5: =IF(A5="","",IF(M5="in guarantee",O5,0)) -> 0
A6: Brightline Dental: Practice manager | B6: 46048 | C6: 9600 | D6: =IF(A6="","",Settings!$B$11) -> 90 | F6: =IF(A6="","",IF(E6<>"",E6,D6)) -> 90 | G6: =IF(A6="","",Settings!$B$12) -> 8 | I6: =IF(A6="","",IF(H6<>"",H6,G6)) -> 8 | J6: =IF(A6="","",Settings!$B$13) -> 100 | L6: =IF(A6="","",IF(K6<>"",K6,J6)) -> 100 | M6: retained | N6: =IF(A6="","",B6+F6) -> 46138 | O6: =IF(A6="","",ROUND(C6*L6*I6/10000,2)) -> 768 | P6: =IF(A6="","",IF(M6="retained",O6,0)) -> 768 | Q6: =IF(A6="","",IF(M6="fell off",ROUND(C6*L6/100,2),0)) -> 0 | R6: =IF(A6="","",IF(M6="in guarantee",O6,0)) -> 0
A7: Acme Engineering: Senior mechanical engineer | B7: 46062 | C7: 18700 | D7: =IF(A7="","",Settings!$B$11) -> 90 | F7: =IF(A7="","",IF(E7<>"",E7,D7)) -> 90 | G7: =IF(A7="","",Settings!$B$12) -> 8 | I7: =IF(A7="","",IF(H7<>"",H7,G7)) -> 8 | J7: =IF(A7="","",Settings!$B$13) -> 100 | K7: 50 | L7: =IF(A7="","",IF(K7<>"",K7,J7)) -> 50 | M7: fell off | N7: =IF(A7="","",B7+F7) -> 46152 | O7: =IF(A7="","",ROUND(C7*L7*I7/10000,2)) -> 748 | P7: =IF(A7="","",IF(M7="retained",O7,0)) -> 0 | Q7: =IF(A7="","",IF(M7="fell off",ROUND(C7*L7/100,2),0)) -> 9350 | R7: =IF(A7="","",IF(M7="in guarantee",O7,0)) -> 0
A8: Delta Software: Product designer | B8: 46119 | C8: 7200 | D8: =IF(A8="","",Settings!$B$11) -> 90 | F8: =IF(A8="","",IF(E8<>"",E8,D8)) -> 90 | G8: =IF(A8="","",Settings!$B$12) -> 8 | H8: 12 | I8: =IF(A8="","",IF(H8<>"",H8,G8)) -> 12 | J8: =IF(A8="","",Settings!$B$13) -> 100 | L8: =IF(A8="","",IF(K8<>"",K8,J8)) -> 100 | M8: retained | N8: =IF(A8="","",B8+F8) -> 46209 | O8: =IF(A8="","",ROUND(C8*L8*I8/10000,2)) -> 864 | P8: =IF(A8="","",IF(M8="retained",O8,0)) -> 864 | Q8: =IF(A8="","",IF(M8="fell off",ROUND(C8*L8/100,2),0)) -> 0 | R8: =IF(A8="","",IF(M8="in guarantee",O8,0)) -> 0
A9: Northwind Logistics: Transport planner | B9: 46156 | C9: 10400 | D9: =IF(A9="","",Settings!$B$11) -> 90 | E9: 180 | F9: =IF(A9="","",IF(E9<>"",E9,D9)) -> 180 | G9: =IF(A9="","",Settings!$B$12) -> 8 | I9: =IF(A9="","",IF(H9<>"",H9,G9)) -> 8 | J9: =IF(A9="","",Settings!$B$13) -> 100 | L9: =IF(A9="","",IF(K9<>"",K9,J9)) -> 100 | M9: in guarantee | N9: =IF(A9="","",B9+F9) -> 46336 | O9: =IF(A9="","",ROUND(C9*L9*I9/10000,2)) -> 832 | P9: =IF(A9="","",IF(M9="retained",O9,0)) -> 0 | Q9: =IF(A9="","",IF(M9="fell off",ROUND(C9*L9/100,2),0)) -> 0 | R9: =IF(A9="","",IF(M9="in guarantee",O9,0)) -> 832
A10: Garcia Retail: Store manager | B10: 46175 | C10: 9000 | D10: =IF(A10="","",Settings!$B$11) -> 90 | E10: 180 | F10: =IF(A10="","",IF(E10<>"",E10,D10)) -> 180 | G10: =IF(A10="","",Settings!$B$12) -> 8 | I10: =IF(A10="","",IF(H10<>"",H10,G10)) -> 8 | J10: =IF(A10="","",Settings!$B$13) -> 100 | L10: =IF(A10="","",IF(K10<>"",K10,J10)) -> 100 | M10: in guarantee | N10: =IF(A10="","",B10+F10) -> 46355 | O10: =IF(A10="","",ROUND(C10*L10*I10/10000,2)) -> 720 | P10: =IF(A10="","",IF(M10="retained",O10,0)) -> 0 | Q10: =IF(A10="","",IF(M10="fell off",ROUND(C10*L10/100,2),0)) -> 0 | R10: =IF(A10="","",IF(M10="in guarantee",O10,0)) -> 720
D11: =IF(A11="","",Settings!$B$11) | F11: =IF(A11="","",IF(E11<>"",E11,D11)) | G11: =IF(A11="","",Settings!$B$12) | I11: =IF(A11="","",IF(H11<>"",H11,G11)) | J11: =IF(A11="","",Settings!$B$13) | L11: =IF(A11="","",IF(K11<>"",K11,J11)) | N11: =IF(A11="","",B11+F11) | O11: =IF(A11="","",ROUND(C11*L11*I11/10000,2)) | P11: =IF(A11="","",IF(M11="retained",O11,0)) | Q11: =IF(A11="","",IF(M11="fell off",ROUND(C11*L11/100,2),0)) | R11: =IF(A11="","",IF(M11="in guarantee",O11,0))
D12: =IF(A12="","",Settings!$B$11) | F12: =IF(A12="","",IF(E12<>"",E12,D12)) | G12: =IF(A12="","",Settings!$B$12) | I12: =IF(A12="","",IF(H12<>"",H12,G12)) | J12: =IF(A12="","",Settings!$B$13) | L12: =IF(A12="","",IF(K12<>"",K12,J12)) | N12: =IF(A12="","",B12+F12) | O12: =IF(A12="","",ROUND(C12*L12*I12/10000,2)) | P12: =IF(A12="","",IF(M12="retained",O12,0)) | Q12: =IF(A12="","",IF(M12="fell off",ROUND(C12*L12/100,2),0)) | R12: =IF(A12="","",IF(M12="in guarantee",O12,0))
D13: =IF(A13="","",Settings!$B$11) | F13: =IF(A13="","",IF(E13<>"",E13,D13)) | G13: =IF(A13="","",Settings!$B$12) | I13: =IF(A13="","",IF(H13<>"",H13,G13)) | J13: =IF(A13="","",Settings!$B$13) | L13: =IF(A13="","",IF(K13<>"",K13,J13)) | N13: =IF(A13="","",B13+F13) | O13: =IF(A13="","",ROUND(C13*L13*I13/10000,2)) | P13: =IF(A13="","",IF(M13="retained",O13,0)) | Q13: =IF(A13="","",IF(M13="fell off",ROUND(C13*L13/100,2),0)) | R13: =IF(A13="","",IF(M13="in guarantee",O13,0))
D14: =IF(A14="","",Settings!$B$11) | F14: =IF(A14="","",IF(E14<>"",E14,D14)) | G14: =IF(A14="","",Settings!$B$12) | I14: =IF(A14="","",IF(H14<>"",H14,G14)) | J14: =IF(A14="","",Settings!$B$13) | L14: =IF(A14="","",IF(K14<>"",K14,J14)) | N14: =IF(A14="","",B14+F14) | O14: =IF(A14="","",ROUND(C14*L14*I14/10000,2)) | P14: =IF(A14="","",IF(M14="retained",O14,0)) | Q14: =IF(A14="","",IF(M14="fell off",ROUND(C14*L14/100,2),0)) | R14: =IF(A14="","",IF(M14="in guarantee",O14,0))
D15: =IF(A15="","",Settings!$B$11) | F15: =IF(A15="","",IF(E15<>"",E15,D15)) | G15: =IF(A15="","",Settings!$B$12) | I15: =IF(A15="","",IF(H15<>"",H15,G15)) | J15: =IF(A15="","",Settings!$B$13) | L15: =IF(A15="","",IF(K15<>"",K15,J15)) | N15: =IF(A15="","",B15+F15) | O15: =IF(A15="","",ROUND(C15*L15*I15/10000,2)) | P15: =IF(A15="","",IF(M15="retained",O15,0)) | Q15: =IF(A15="","",IF(M15="fell off",ROUND(C15*L15/100,2),0)) | R15: =IF(A15="","",IF(M15="in guarantee",O15,0))
D16: =IF(A16="","",Settings!$B$11) | F16: =IF(A16="","",IF(E16<>"",E16,D16)) | G16: =IF(A16="","",Settings!$B$12) | I16: =IF(A16="","",IF(H16<>"",H16,G16)) | J16: =IF(A16="","",Settings!$B$13) | L16: =IF(A16="","",IF(K16<>"",K16,J16)) | N16: =IF(A16="","",B16+F16) | O16: =IF(A16="","",ROUND(C16*L16*I16/10000,2)) | P16: =IF(A16="","",IF(M16="retained",O16,0)) | Q16: =IF(A16="","",IF(M16="fell off",ROUND(C16*L16/100,2),0)) | R16: =IF(A16="","",IF(M16="in guarantee",O16,0))
D17: =IF(A17="","",Settings!$B$11) | F17: =IF(A17="","",IF(E17<>"",E17,D17)) | G17: =IF(A17="","",Settings!$B$12) | I17: =IF(A17="","",IF(H17<>"",H17,G17)) | J17: =IF(A17="","",Settings!$B$13) | L17: =IF(A17="","",IF(K17<>"",K17,J17)) | N17: =IF(A17="","",B17+F17) | O17: =IF(A17="","",ROUND(C17*L17*I17/10000,2)) | P17: =IF(A17="","",IF(M17="retained",O17,0)) | Q17: =IF(A17="","",IF(M17="fell off",ROUND(C17*L17/100,2),0)) | R17: =IF(A17="","",IF(M17="in guarantee",O17,0))
D18: =IF(A18="","",Settings!$B$11) | F18: =IF(A18="","",IF(E18<>"",E18,D18)) | G18: =IF(A18="","",Settings!$B$12) | I18: =IF(A18="","",IF(H18<>"",H18,G18)) | J18: =IF(A18="","",Settings!$B$13) | L18: =IF(A18="","",IF(K18<>"",K18,J18)) | N18: =IF(A18="","",B18+F18) | O18: =IF(A18="","",ROUND(C18*L18*I18/10000,2)) | P18: =IF(A18="","",IF(M18="retained",O18,0)) | Q18: =IF(A18="","",IF(M18="fell off",ROUND(C18*L18/100,2),0)) | R18: =IF(A18="","",IF(M18="in guarantee",O18,0))
D19: =IF(A19="","",Settings!$B$11) | F19: =IF(A19="","",IF(E19<>"",E19,D19)) | G19: =IF(A19="","",Settings!$B$12) | I19: =IF(A19="","",IF(H19<>"",H19,G19)) | J19: =IF(A19="","",Settings!$B$13) | L19: =IF(A19="","",IF(K19<>"",K19,J19)) | N19: =IF(A19="","",B19+F19) | O19: =IF(A19="","",ROUND(C19*L19*I19/10000,2)) | P19: =IF(A19="","",IF(M19="retained",O19,0)) | Q19: =IF(A19="","",IF(M19="fell off",ROUND(C19*L19/100,2),0)) | R19: =IF(A19="","",IF(M19="in guarantee",O19,0))
D20: =IF(A20="","",Settings!$B$11) | F20: =IF(A20="","",IF(E20<>"",E20,D20)) | G20: =IF(A20="","",Settings!$B$12) | I20: =IF(A20="","",IF(H20<>"",H20,G20)) | J20: =IF(A20="","",Settings!$B$13) | L20: =IF(A20="","",IF(K20<>"",K20,J20)) | N20: =IF(A20="","",B20+F20) | O20: =IF(A20="","",ROUND(C20*L20*I20/10000,2)) | P20: =IF(A20="","",IF(M20="retained",O20,0)) | Q20: =IF(A20="","",IF(M20="fell off",ROUND(C20*L20/100,2),0)) | R20: =IF(A20="","",IF(M20="in guarantee",O20,0))
D21: =IF(A21="","",Settings!$B$11) | F21: =IF(A21="","",IF(E21<>"",E21,D21)) | G21: =IF(A21="","",Settings!$B$12) | I21: =IF(A21="","",IF(H21<>"",H21,G21)) | J21: =IF(A21="","",Settings!$B$13) | L21: =IF(A21="","",IF(K21<>"",K21,J21)) | N21: =IF(A21="","",B21+F21) | O21: =IF(A21="","",ROUND(C21*L21*I21/10000,2)) | P21: =IF(A21="","",IF(M21="retained",O21,0)) | Q21: =IF(A21="","",IF(M21="fell off",ROUND(C21*L21/100,2),0)) | R21: =IF(A21="","",IF(M21="in guarantee",O21,0))
D22: =IF(A22="","",Settings!$B$11) | F22: =IF(A22="","",IF(E22<>"",E22,D22)) | G22: =IF(A22="","",Settings!$B$12) | I22: =IF(A22="","",IF(H22<>"",H22,G22)) | J22: =IF(A22="","",Settings!$B$13) | L22: =IF(A22="","",IF(K22<>"",K22,J22)) | N22: =IF(A22="","",B22+F22) | O22: =IF(A22="","",ROUND(C22*L22*I22/10000,2)) | P22: =IF(A22="","",IF(M22="retained",O22,0)) | Q22: =IF(A22="","",IF(M22="fell off",ROUND(C22*L22/100,2),0)) | R22: =IF(A22="","",IF(M22="in guarantee",O22,0))
... D24: =IF(A24="","",Settings!$B$11) | F24: =IF(A24="","",IF(E24<>"",E24,D24)) | G24: =IF(A24="","",Settings!$B$12) | I24: =IF(A24="","",IF(H24<>"",H24,G24)) | J24: =IF(A24="","",Settings!$B$13) | L24: =IF(A24="","",IF(K24<>"",K24,J24)) | N24: =IF(A24="","",B24+F24) | O24: =IF(A24="","",ROUND(C24*L24*I24/10000,2)) | P24: =IF(A24="","",IF(M24="retained",O24,0)) | Q24: =IF(A24="","",IF(M24="fell off",ROUND(C24*L24/100,2),0)) | R24: =IF(A24="","",IF(M24="in guarantee",O24,0))
A25: Total | C25: =SUM(C5:C24) -> 64650 | O25: =SUM(O5:O24) -> 4712 | P25: =SUM(P5:P24) -> 2412 | Q25: =SUM(Q5:Q24) -> 9350 | R25: =SUM(R5:R24) -> 1552

Sheet Summary
A1: Summary
A2: Recruiters | B2: =Settings!$B$2 -> 4 | C2: from Settings
A3: Desk cost per recruiter (annual) | B3: =Settings!$B$17 -> 93000 | C3: from Settings: loaded salary + equal share of tools and overhead
A4: Recruiter cost per hour | B4: =Settings!$B$18 -> 51.67 | C4: from Settings: desk cost per recruiter ÷ working hours
A5: Year-to-date perm net fees | B5: ='Desk Performance'!G17 -> 75050 | C5: Desk Performance totals
A6: Year-to-date temp margin | B6: ='Desk Performance'!H17 -> 95000 | C6: Desk Performance totals
A7: Year-to-date total gross margin | B7: ='Desk Performance'!N17 -> 170050 | C7: perm net fees + temp margin
A8: Year-to-date desk cost | B8: ='Desk Performance'!O17 -> 186000 | C8: total desk cost ÷ 12 for each month entered
A9: Year-to-date desk profit | B9: ='Desk Performance'!P17 -> -15950 | C9: gross margin − desk cost
A10: Average net fee per perm placement | B10: =IFERROR(ROUND(AVERAGE('Perm Placements'!$O$5:$O$34),2),0) -> 9381.25 | C10: simple average of net fees on Perm Placements
A11: Break-even placements per recruiter (a year) | B11: =IFERROR(ROUND(B3/B10,2),0) -> 9.91 | C11: desk cost per recruiter ÷ average net fee; perm only, before any temp margin
A12: Margin % threshold (your own) | B12: 70 | C12: Default 70. Your own placeholder threshold for flagging thin perm placements, not a recommendation or an industry benchmark.
A13: Perm placements below the margin % threshold | B13: =COUNTIF('Perm Placements'!$R$5:$R$34,"<"&B12) -> 2 | C13: margin % on Perm Placements below the threshold above
A14: Thinnest temp assignment | B14: =IFERROR(INDEX('Temp Assignments'!$B$5:$B$34,MATCH(MIN('Temp Assignments'!$P$5:$P$34),'Temp Assignments'!$P$5:$P$34,0)),"") -> Seasonal sales G | C14: worker with the lowest gross margin % on Temp Assignments
A15: Its gross margin % | B15: =IFERROR(MIN('Temp Assignments'!$P$5:$P$34),0) -> 5.6 | C15: lowest gross margin % on Temp Assignments
A16: Year-to-date fill rate % | B16: ='Desk Performance'!Q17 -> 43.06 | C16: job orders filled ÷ received, from the Desk Performance totals
A17: Year-to-date average days to fill | B17: ='Desk Performance'!R17 -> 31.84 | C17: total days to fill ÷ job orders filled
A18: Reserve still held | B18: ='Rebate Reserve'!R25 -> 1552 | C18: Rebate Reserve: placements still in guarantee
A19: Rebates paid | B19: ='Rebate Reserve'!Q25 -> 9350 | C19: Rebate Reserve: fall-offs
A20: Reserve released | B20: ='Rebate Reserve'!P25 -> 2412 | C20: Rebate Reserve: placements retained past the guarantee
