Workbook

Sheet Start Here
A1: Small Business Finance Dashboard
A2: by Knackdesk · knackdesk.com
A4: HOW TO USE
A5: 1. Settings: the year and the share of pre-tax profit you want to set aside for tax. The percentage is yours to choose; the workbook does not know your tax rate.
A6: 2. Expenses: one row per operating expense category, one column per month. Monthly totals feed the P&L automatically; yearly totals and each category's share are calculated.
A7: 3. Monthly P&L: enter revenue, cost of sales, interest and owner draws for each month as it closes. Gross, operating and pre-tax profit, margins, the tax set-aside, retained profit and the running total are calculated. Operating expenses default to the Expenses sheet total.
A8: 4. Summary: year-to-date totals and margins, average monthly revenue, best and worst months, tax set aside, draws and the largest expense category.
A10: LEGEND
A11: Blue text = a cell you type into. Black text = a formula, leave it alone. Yellow fill = key inputs.
A12: Blue cells that already contain a formula (operating expenses pulled from the Expenses sheet) may be overwritten with your own figure.
A14: DEFINITIONS
A15: Gross profit = revenue − cost of sales. Operating profit = gross profit − operating expenses. Pre-tax profit = operating profit − interest.
... A17: Enter figures excluding VAT or sales tax you collect. Arithmetic only; not tax, accounting or financial advice. Support: hello@knackdesk.com

Sheet Settings
A1: Settings
A2: Year | B2: 2026 | C2: Shown on the P&L and Summary.
A3: Tax set-aside (% of pre-tax profit) | B3: 25 | C3: Last year's tax and contributions ÷ last year's profit is a reasonable starting point.
A4: Business name | B4: Example Studio | C4: Optional label.

Sheet Expenses
A1: Expenses
A2: Operating expenses by category and month, excluding cost of sales (which goes on the P&L). Blank months count as zero.
A4: Category | B4: Jan | C4: Feb | D4: Mar | E4: Apr | F4: May | G4: Jun | H4: Jul | I4: Aug | J4: Sep | K4: Oct | L4: Nov | M4: Dec | N4: Year total | O4: Share %
A5: Rent and utilities | B5: 900 | C5: 900 | D5: 990 | N5: =IF(A5="","",SUM(B5:M5)) -> 2790 | O5: =IF(A5="","",IFERROR(ROUND(N5/$N$21*100,2),"")) -> 14.26
A6: Salaries and contractors | B6: 4200 | C6: 4200 | D6: 4620 | N6: =IF(A6="","",SUM(B6:M6)) -> 13020 | O6: =IF(A6="","",IFERROR(ROUND(N6/$N$21*100,2),"")) -> 66.56
A7: Software and subscriptions | B7: 260 | C7: 260 | D7: 286 | N7: =IF(A7="","",SUM(B7:M7)) -> 806 | O7: =IF(A7="","",IFERROR(ROUND(N7/$N$21*100,2),"")) -> 4.12
A8: Marketing | B8: 500 | C8: 500 | D8: 550 | N8: =IF(A8="","",SUM(B8:M8)) -> 1550 | O8: =IF(A8="","",IFERROR(ROUND(N8/$N$21*100,2),"")) -> 7.92
A9: Insurance | B9: 120 | C9: 120 | D9: 132 | N9: =IF(A9="","",SUM(B9:M9)) -> 372 | O9: =IF(A9="","",IFERROR(ROUND(N9/$N$21*100,2),"")) -> 1.9
A10: Accounting and legal | B10: 150 | C10: 150 | D10: 165 | N10: =IF(A10="","",SUM(B10:M10)) -> 465 | O10: =IF(A10="","",IFERROR(ROUND(N10/$N$21*100,2),"")) -> 2.38
A11: Travel | B11: 80 | C11: 80 | D11: 88 | N11: =IF(A11="","",SUM(B11:M11)) -> 248 | O11: =IF(A11="","",IFERROR(ROUND(N11/$N$21*100,2),"")) -> 1.27
A12: Other | B12: 100 | C12: 100 | D12: 110 | N12: =IF(A12="","",SUM(B12:M12)) -> 310 | O12: =IF(A12="","",IFERROR(ROUND(N12/$N$21*100,2),"")) -> 1.58
N13: =IF(A13="","",SUM(B13:M13)) | O13: =IF(A13="","",IFERROR(ROUND(N13/$N$21*100,2),""))
N14: =IF(A14="","",SUM(B14:M14)) | O14: =IF(A14="","",IFERROR(ROUND(N14/$N$21*100,2),""))
N15: =IF(A15="","",SUM(B15:M15)) | O15: =IF(A15="","",IFERROR(ROUND(N15/$N$21*100,2),""))
N16: =IF(A16="","",SUM(B16:M16)) | O16: =IF(A16="","",IFERROR(ROUND(N16/$N$21*100,2),""))
N17: =IF(A17="","",SUM(B17:M17)) | O17: =IF(A17="","",IFERROR(ROUND(N17/$N$21*100,2),""))
N18: =IF(A18="","",SUM(B18:M18)) | O18: =IF(A18="","",IFERROR(ROUND(N18/$N$21*100,2),""))
N19: =IF(A19="","",SUM(B19:M19)) | O19: =IF(A19="","",IFERROR(ROUND(N19/$N$21*100,2),""))
N20: =IF(A20="","",SUM(B20:M20)) | O20: =IF(A20="","",IFERROR(ROUND(N20/$N$21*100,2),""))
A21: Total per month | B21: =SUM(B5:B20) -> 6310 | C21: =SUM(C5:C20) -> 6310 | D21: =SUM(D5:D20) -> 6941 | E21: =SUM(E5:E20) -> 0 | F21: =SUM(F5:F20) -> 0 | G21: =SUM(G5:G20) -> 0 | H21: =SUM(H5:H20) -> 0 | I21: =SUM(I5:I20) -> 0 | ... N21: =SUM(N5:N20) -> 19561

Sheet Monthly P&L
A1: Monthly P&L | B1: =Settings!$B$4&" · "&Settings!$B$2 -> Example Studio · 2026
A2: Enter revenue, cost of sales, interest and owner draws each month. Operating expenses come from the Expenses sheet. Leave future months' revenue blank.
A4: Month | B4: Revenue | C4: Cost of sales | D4: Gross profit | E4: Gross margin % | F4: Operating expenses | G4: Operating profit | H4: Operating margin % | I4: Interest | J4: Pre-tax profit | K4: Tax set-aside | L4: Profit after set-aside | M4: Margin after set-aside % | N4: Owner draws | O4: Retained in business | P4: Cumulative retained
A5: Jan | B5: 14000 | C5: 3500 | D5: =IF(B5="","",B5-C5) -> 10500 | E5: =IF(B5="","",IFERROR(ROUND(D5/B5*100,2),"")) -> 75 | F5: =IF(B5="","",Expenses!B21) -> 6310 | G5: =IF(B5="","",D5-F5) -> 4190 | H5: =IF(B5="","",IFERROR(ROUND(G5/B5*100,2),"")) -> 29.93 | I5: 50 | J5: =IF(B5="","",G5-I5) -> 4140 | K5: =IF(B5="","",ROUND(MAX(0,J5)*Settings!$B$3/100,2)) -> 1035 | L5: =IF(B5="","",J5-K5) -> 3105 | M5: =IF(B5="","",IFERROR(ROUND(L5/B5*100,2),"")) -> 22.18 | N5: 3000 | O5: =IF(B5="","",L5-N5) -> 105 | P5: =IF(B5="","",O5) -> 105
A6: Feb | B6: 12500 | C6: 3100 | D6: =IF(B6="","",B6-C6) -> 9400 | E6: =IF(B6="","",IFERROR(ROUND(D6/B6*100,2),"")) -> 75.2 | F6: =IF(B6="","",Expenses!C21) -> 6310 | G6: =IF(B6="","",D6-F6) -> 3090 | H6: =IF(B6="","",IFERROR(ROUND(G6/B6*100,2),"")) -> 24.72 | I6: 50 | J6: =IF(B6="","",G6-I6) -> 3040 | K6: =IF(B6="","",ROUND(MAX(0,J6)*Settings!$B$3/100,2)) -> 760 | L6: =IF(B6="","",J6-K6) -> 2280 | M6: =IF(B6="","",IFERROR(ROUND(L6/B6*100,2),"")) -> 18.24 | N6: 3000 | O6: =IF(B6="","",L6-N6) -> -720 | P6: =IF(B6="","",O6+N(P5)) -> -615
A7: Mar | B7: 16800 | C7: 4200 | D7: =IF(B7="","",B7-C7) -> 12600 | E7: =IF(B7="","",IFERROR(ROUND(D7/B7*100,2),"")) -> 75 | F7: =IF(B7="","",Expenses!D21) -> 6941 | G7: =IF(B7="","",D7-F7) -> 5659 | H7: =IF(B7="","",IFERROR(ROUND(G7/B7*100,2),"")) -> 33.68 | I7: 50 | J7: =IF(B7="","",G7-I7) -> 5609 | K7: =IF(B7="","",ROUND(MAX(0,J7)*Settings!$B$3/100,2)) -> 1402.25 | L7: =IF(B7="","",J7-K7) -> 4206.75 | M7: =IF(B7="","",IFERROR(ROUND(L7/B7*100,2),"")) -> 25.04 | N7: 3500 | O7: =IF(B7="","",L7-N7) -> 706.75 | P7: =IF(B7="","",O7+N(P6)) -> 91.75
A8: Apr | D8: =IF(B8="","",B8-C8) | E8: =IF(B8="","",IFERROR(ROUND(D8/B8*100,2),"")) | F8: =IF(B8="","",Expenses!E21) | G8: =IF(B8="","",D8-F8) | H8: =IF(B8="","",IFERROR(ROUND(G8/B8*100,2),"")) | J8: =IF(B8="","",G8-I8) | K8: =IF(B8="","",ROUND(MAX(0,J8)*Settings!$B$3/100,2)) | L8: =IF(B8="","",J8-K8) | M8: =IF(B8="","",IFERROR(ROUND(L8/B8*100,2),"")) | O8: =IF(B8="","",L8-N8) | P8: =IF(B8="","",O8+N(P7))
A9: May | D9: =IF(B9="","",B9-C9) | E9: =IF(B9="","",IFERROR(ROUND(D9/B9*100,2),"")) | F9: =IF(B9="","",Expenses!F21) | G9: =IF(B9="","",D9-F9) | H9: =IF(B9="","",IFERROR(ROUND(G9/B9*100,2),"")) | J9: =IF(B9="","",G9-I9) | K9: =IF(B9="","",ROUND(MAX(0,J9)*Settings!$B$3/100,2)) | L9: =IF(B9="","",J9-K9) | M9: =IF(B9="","",IFERROR(ROUND(L9/B9*100,2),"")) | O9: =IF(B9="","",L9-N9) | P9: =IF(B9="","",O9+N(P8))
A10: Jun | D10: =IF(B10="","",B10-C10) | E10: =IF(B10="","",IFERROR(ROUND(D10/B10*100,2),"")) | F10: =IF(B10="","",Expenses!G21) | G10: =IF(B10="","",D10-F10) | H10: =IF(B10="","",IFERROR(ROUND(G10/B10*100,2),"")) | J10: =IF(B10="","",G10-I10) | K10: =IF(B10="","",ROUND(MAX(0,J10)*Settings!$B$3/100,2)) | L10: =IF(B10="","",J10-K10) | M10: =IF(B10="","",IFERROR(ROUND(L10/B10*100,2),"")) | O10: =IF(B10="","",L10-N10) | P10: =IF(B10="","",O10+N(P9))
A11: Jul | D11: =IF(B11="","",B11-C11) | E11: =IF(B11="","",IFERROR(ROUND(D11/B11*100,2),"")) | F11: =IF(B11="","",Expenses!H21) | G11: =IF(B11="","",D11-F11) | H11: =IF(B11="","",IFERROR(ROUND(G11/B11*100,2),"")) | J11: =IF(B11="","",G11-I11) | K11: =IF(B11="","",ROUND(MAX(0,J11)*Settings!$B$3/100,2)) | L11: =IF(B11="","",J11-K11) | M11: =IF(B11="","",IFERROR(ROUND(L11/B11*100,2),"")) | O11: =IF(B11="","",L11-N11) | P11: =IF(B11="","",O11+N(P10))
A12: Aug | D12: =IF(B12="","",B12-C12) | E12: =IF(B12="","",IFERROR(ROUND(D12/B12*100,2),"")) | F12: =IF(B12="","",Expenses!I21) | G12: =IF(B12="","",D12-F12) | H12: =IF(B12="","",IFERROR(ROUND(G12/B12*100,2),"")) | J12: =IF(B12="","",G12-I12) | K12: =IF(B12="","",ROUND(MAX(0,J12)*Settings!$B$3/100,2)) | L12: =IF(B12="","",J12-K12) | M12: =IF(B12="","",IFERROR(ROUND(L12/B12*100,2),"")) | O12: =IF(B12="","",L12-N12) | P12: =IF(B12="","",O12+N(P11))
A13: Sep | D13: =IF(B13="","",B13-C13) | E13: =IF(B13="","",IFERROR(ROUND(D13/B13*100,2),"")) | F13: =IF(B13="","",Expenses!J21) | G13: =IF(B13="","",D13-F13) | H13: =IF(B13="","",IFERROR(ROUND(G13/B13*100,2),"")) | J13: =IF(B13="","",G13-I13) | K13: =IF(B13="","",ROUND(MAX(0,J13)*Settings!$B$3/100,2)) | L13: =IF(B13="","",J13-K13) | M13: =IF(B13="","",IFERROR(ROUND(L13/B13*100,2),"")) | O13: =IF(B13="","",L13-N13) | P13: =IF(B13="","",O13+N(P12))
A14: Oct | D14: =IF(B14="","",B14-C14) | E14: =IF(B14="","",IFERROR(ROUND(D14/B14*100,2),"")) | F14: =IF(B14="","",Expenses!K21) | G14: =IF(B14="","",D14-F14) | H14: =IF(B14="","",IFERROR(ROUND(G14/B14*100,2),"")) | J14: =IF(B14="","",G14-I14) | K14: =IF(B14="","",ROUND(MAX(0,J14)*Settings!$B$3/100,2)) | L14: =IF(B14="","",J14-K14) | M14: =IF(B14="","",IFERROR(ROUND(L14/B14*100,2),"")) | O14: =IF(B14="","",L14-N14) | P14: =IF(B14="","",O14+N(P13))
A15: Nov | D15: =IF(B15="","",B15-C15) | E15: =IF(B15="","",IFERROR(ROUND(D15/B15*100,2),"")) | F15: =IF(B15="","",Expenses!L21) | G15: =IF(B15="","",D15-F15) | H15: =IF(B15="","",IFERROR(ROUND(G15/B15*100,2),"")) | J15: =IF(B15="","",G15-I15) | K15: =IF(B15="","",ROUND(MAX(0,J15)*Settings!$B$3/100,2)) | L15: =IF(B15="","",J15-K15) | M15: =IF(B15="","",IFERROR(ROUND(L15/B15*100,2),"")) | O15: =IF(B15="","",L15-N15) | P15: =IF(B15="","",O15+N(P14))
A16: Dec | D16: =IF(B16="","",B16-C16) | E16: =IF(B16="","",IFERROR(ROUND(D16/B16*100,2),"")) | F16: =IF(B16="","",Expenses!M21) | G16: =IF(B16="","",D16-F16) | H16: =IF(B16="","",IFERROR(ROUND(G16/B16*100,2),"")) | J16: =IF(B16="","",G16-I16) | K16: =IF(B16="","",ROUND(MAX(0,J16)*Settings!$B$3/100,2)) | L16: =IF(B16="","",J16-K16) | M16: =IF(B16="","",IFERROR(ROUND(L16/B16*100,2),"")) | O16: =IF(B16="","",L16-N16) | P16: =IF(B16="","",O16+N(P15))
A17: Year | B17: =SUM(B5:B16) -> 43300 | C17: =SUM(C5:C16) -> 10800 | D17: =SUM(D5:D16) -> 32500 | E17: =IFERROR(ROUND(D17/B17*100,2),"") -> 75.06 | F17: =SUM(F5:F16) -> 19561 | G17: =SUM(G5:G16) -> 12939 | H17: =IFERROR(ROUND(G17/B17*100,2),"") -> 29.88 | I17: =SUM(I5:I16) -> 150 | J17: =SUM(J5:J16) -> 12789 | K17: =SUM(K5:K16) -> 3197.25 | L17: =SUM(L5:L16) -> 9591.75 | M17: =IFERROR(ROUND(L17/B17*100,2),"") -> 22.15 | N17: =SUM(N5:N16) -> 9500 | O17: =SUM(O5:O16) -> 91.75

Sheet Summary
A1: Summary (year to date)
A2: Revenue | B2: ='Monthly P&L'!B17 -> 43300
A3: Cost of sales | B3: ='Monthly P&L'!C17 -> 10800
A4: Gross profit | B4: ='Monthly P&L'!D17 -> 32500
A5: Gross margin % | B5: ='Monthly P&L'!E17 -> 75.06
A6: Operating expenses | B6: ='Monthly P&L'!F17 -> 19561
A7: Operating profit | B7: ='Monthly P&L'!G17 -> 12939
A8: Operating margin % | B8: ='Monthly P&L'!H17 -> 29.88
A9: Pre-tax profit | B9: ='Monthly P&L'!J17 -> 12789 | C9: after interest
A10: Set aside for tax | B10: ='Monthly P&L'!K17 -> 3197.25 | C10: at the Settings percentage
A11: Owner draws | B11: ='Monthly P&L'!N17 -> 9500
A12: Retained in the business | B12: ='Monthly P&L'!O17 -> 91.75 | C12: pre-tax profit − tax set-aside − draws
A13: Months entered | B13: =COUNT('Monthly P&L'!B5:B16) -> 3
A14: Average monthly revenue | B14: =IFERROR(ROUND(B2/B13,2),"") -> 14433.33
A15: Best month (revenue) | B15: =IFERROR(INDEX('Monthly P&L'!A5:A16,MATCH(MAX('Monthly P&L'!B5:B16),'Monthly P&L'!B5:B16,0)),"") -> Mar
A16: Worst month (revenue) | B16: =IFERROR(INDEX('Monthly P&L'!A5:A16,MATCH(MIN('Monthly P&L'!B5:B16),'Monthly P&L'!B5:B16,0)),"") -> Feb
A17: Largest expense category | B17: =IFERROR(INDEX(Expenses!A5:A20,MATCH(MAX(Expenses!N5:N20),Expenses!N5:N20,0)),"") -> Salaries and contractors
A18: Largest category share of expenses % | B18: =IFERROR(ROUND(MAX(Expenses!N5:N20)/Expenses!N21*100,2),"") -> 66.56
A19: Operating expenses as % of revenue | B19: =IFERROR(ROUND(B6/B2*100,2),"") -> 45.18
