Workbook

Sheet Start Here
A1: Team Cost & Headcount Planner
A2: by Knackdesk · knackdesk.com
A4: HOW TO USE
A5: 1. Settings: your defaults for employer contributions, hours, weeks worked, productive share, working days and PTO. Every other sheet reads them.
A6: 2. Team: one row per person with salary, benefits and overheads. Employer contributions, total annual and monthly cost, cost per productive hour and the cost multiplier are calculated, with team totals in row 41.
A7: 3. Raises: name a person, choose percent or amount and enter the raise. New salary, monthly difference and the yearly cost to the business (raise plus contributions) are calculated.
A8: 4. PTO: one row per person with entitlement, pay frequency and pay periods completed this year, plus carried-over and taken days. Accrual per period, accrued to date, balance and days still to earn are calculated.
A9: 5. Hiring & Turnover: planned hires with their cost in the plan year, and the cost of turnover per leaver and per year using your average cost per employee.
A11: LEGEND
A12: Blue text = a cell you type into. Black text = a formula, leave it alone. Yellow fill = key inputs.
A13: Blue cells that already contain a formula (defaults pulled from Settings or Team) may be overwritten with your own figure.
A15: DEFINITIONS
... A20: Rates for employer contributions and leave rules differ by country and contract; enter your own. Arithmetic only; not legal, tax or HR advice. Support: hello@knackdesk.com

Sheet Settings
A1: Settings
A2: Employer contributions (% of salary) | B2: 12 | C2: Social security, pension, health or unemployment contributions the employer pays on top of gross salary.
A3: Hours per week | B3: 40 | C3: Contracted hours; overridable per person on the Team sheet.
A4: Weeks worked per year | B4: 46 | C4: 52 minus holiday, public holidays and typical sick leave.
A5: Productive share of hours (%) | B5: 80 | C5: Share of contracted hours spent on billable or output work.
A6: Working days per year | B6: 240 | C6: Used for the daily cost in turnover calculations.
A7: Ramp-up productivity for new hires (%) | B7: 50 | C7: Average output during the ramp-up period as a share of full productivity.
A8: Default paid time off per year (days) | B8: 20 | C8: Overridable per person on the PTO sheet.
A9: Default pay frequency | B9: biweekly | C9: weekly, biweekly, semimonthly or monthly.
A10: Plan year | B10: 2026 | C10: Hires starting in this year are prorated by the months remaining.

Sheet Team
A1: Team
A2: One row per person. Contribution rate and hours default to Settings; overwrite them per person if needed.
A4: Name | B4: Role | C4: Start date | D4: Annual salary | E4: Employer contrib. % | F4: Benefits / yr | G4: Overheads / yr | H4: Employer contributions | I4: Total annual cost | J4: Monthly cost | K4: Hours / week | L4: Cost per productive hour | M4: Cost multiple of salary
A5: Ana Example | B5: Designer | C5: 45352 | D5: 50000 | E5: =IF(A5="","",Settings!$B$2) -> 12 | F5: 4000 | G5: 3000 | H5: =IF(A5="","",ROUND(D5*E5/100,2)) -> 6000 | I5: =IF(A5="","",D5+H5+F5+G5) -> 63000 | J5: =IF(A5="","",ROUND(I5/12,2)) -> 5250 | K5: =IF(A5="","",Settings!$B$3) -> 40 | L5: =IF(A5="","",IFERROR(ROUND(I5/(K5*Settings!$B$4*Settings!$B$5/100),2),"")) -> 42.8 | M5: =IF(A5="","",IFERROR(ROUND(I5/D5,2),"")) -> 1.26
A6: Ben Example | B6: Developer | C6: 45915 | D6: 64000 | E6: =IF(A6="","",Settings!$B$2) -> 12 | F6: 4500 | G6: 3200 | H6: =IF(A6="","",ROUND(D6*E6/100,2)) -> 7680 | I6: =IF(A6="","",D6+H6+F6+G6) -> 79380 | J6: =IF(A6="","",ROUND(I6/12,2)) -> 6615 | K6: =IF(A6="","",Settings!$B$3) -> 40 | L6: =IF(A6="","",IFERROR(ROUND(I6/(K6*Settings!$B$4*Settings!$B$5/100),2),"")) -> 53.93 | M6: =IF(A6="","",IFERROR(ROUND(I6/D6,2),"")) -> 1.24
A7: Cara Example | B7: Support | C7: 46032 | D7: 38000 | E7: =IF(A7="","",Settings!$B$2) -> 12 | F7: 3000 | G7: 2000 | H7: =IF(A7="","",ROUND(D7*E7/100,2)) -> 4560 | I7: =IF(A7="","",D7+H7+F7+G7) -> 47560 | J7: =IF(A7="","",ROUND(I7/12,2)) -> 3963.33 | K7: =IF(A7="","",Settings!$B$3) -> 40 | L7: =IF(A7="","",IFERROR(ROUND(I7/(K7*Settings!$B$4*Settings!$B$5/100),2),"")) -> 32.31 | M7: =IF(A7="","",IFERROR(ROUND(I7/D7,2),"")) -> 1.25
E8: =IF(A8="","",Settings!$B$2) | H8: =IF(A8="","",ROUND(D8*E8/100,2)) | I8: =IF(A8="","",D8+H8+F8+G8) | J8: =IF(A8="","",ROUND(I8/12,2)) | K8: =IF(A8="","",Settings!$B$3) | L8: =IF(A8="","",IFERROR(ROUND(I8/(K8*Settings!$B$4*Settings!$B$5/100),2),"")) | M8: =IF(A8="","",IFERROR(ROUND(I8/D8,2),""))
E9: =IF(A9="","",Settings!$B$2) | H9: =IF(A9="","",ROUND(D9*E9/100,2)) | I9: =IF(A9="","",D9+H9+F9+G9) | J9: =IF(A9="","",ROUND(I9/12,2)) | K9: =IF(A9="","",Settings!$B$3) | L9: =IF(A9="","",IFERROR(ROUND(I9/(K9*Settings!$B$4*Settings!$B$5/100),2),"")) | M9: =IF(A9="","",IFERROR(ROUND(I9/D9,2),""))
E10: =IF(A10="","",Settings!$B$2) | H10: =IF(A10="","",ROUND(D10*E10/100,2)) | I10: =IF(A10="","",D10+H10+F10+G10) | J10: =IF(A10="","",ROUND(I10/12,2)) | K10: =IF(A10="","",Settings!$B$3) | L10: =IF(A10="","",IFERROR(ROUND(I10/(K10*Settings!$B$4*Settings!$B$5/100),2),"")) | M10: =IF(A10="","",IFERROR(ROUND(I10/D10,2),""))
E11: =IF(A11="","",Settings!$B$2) | H11: =IF(A11="","",ROUND(D11*E11/100,2)) | I11: =IF(A11="","",D11+H11+F11+G11) | J11: =IF(A11="","",ROUND(I11/12,2)) | K11: =IF(A11="","",Settings!$B$3) | L11: =IF(A11="","",IFERROR(ROUND(I11/(K11*Settings!$B$4*Settings!$B$5/100),2),"")) | M11: =IF(A11="","",IFERROR(ROUND(I11/D11,2),""))
E12: =IF(A12="","",Settings!$B$2) | H12: =IF(A12="","",ROUND(D12*E12/100,2)) | I12: =IF(A12="","",D12+H12+F12+G12) | J12: =IF(A12="","",ROUND(I12/12,2)) | K12: =IF(A12="","",Settings!$B$3) | L12: =IF(A12="","",IFERROR(ROUND(I12/(K12*Settings!$B$4*Settings!$B$5/100),2),"")) | M12: =IF(A12="","",IFERROR(ROUND(I12/D12,2),""))
E13: =IF(A13="","",Settings!$B$2) | H13: =IF(A13="","",ROUND(D13*E13/100,2)) | I13: =IF(A13="","",D13+H13+F13+G13) | J13: =IF(A13="","",ROUND(I13/12,2)) | K13: =IF(A13="","",Settings!$B$3) | L13: =IF(A13="","",IFERROR(ROUND(I13/(K13*Settings!$B$4*Settings!$B$5/100),2),"")) | M13: =IF(A13="","",IFERROR(ROUND(I13/D13,2),""))
E14: =IF(A14="","",Settings!$B$2) | H14: =IF(A14="","",ROUND(D14*E14/100,2)) | I14: =IF(A14="","",D14+H14+F14+G14) | J14: =IF(A14="","",ROUND(I14/12,2)) | K14: =IF(A14="","",Settings!$B$3) | L14: =IF(A14="","",IFERROR(ROUND(I14/(K14*Settings!$B$4*Settings!$B$5/100),2),"")) | M14: =IF(A14="","",IFERROR(ROUND(I14/D14,2),""))
E15: =IF(A15="","",Settings!$B$2) | H15: =IF(A15="","",ROUND(D15*E15/100,2)) | I15: =IF(A15="","",D15+H15+F15+G15) | J15: =IF(A15="","",ROUND(I15/12,2)) | K15: =IF(A15="","",Settings!$B$3) | L15: =IF(A15="","",IFERROR(ROUND(I15/(K15*Settings!$B$4*Settings!$B$5/100),2),"")) | M15: =IF(A15="","",IFERROR(ROUND(I15/D15,2),""))
E16: =IF(A16="","",Settings!$B$2) | H16: =IF(A16="","",ROUND(D16*E16/100,2)) | I16: =IF(A16="","",D16+H16+F16+G16) | J16: =IF(A16="","",ROUND(I16/12,2)) | K16: =IF(A16="","",Settings!$B$3) | L16: =IF(A16="","",IFERROR(ROUND(I16/(K16*Settings!$B$4*Settings!$B$5/100),2),"")) | M16: =IF(A16="","",IFERROR(ROUND(I16/D16,2),""))
E17: =IF(A17="","",Settings!$B$2) | H17: =IF(A17="","",ROUND(D17*E17/100,2)) | I17: =IF(A17="","",D17+H17+F17+G17) | J17: =IF(A17="","",ROUND(I17/12,2)) | K17: =IF(A17="","",Settings!$B$3) | L17: =IF(A17="","",IFERROR(ROUND(I17/(K17*Settings!$B$4*Settings!$B$5/100),2),"")) | M17: =IF(A17="","",IFERROR(ROUND(I17/D17,2),""))
E18: =IF(A18="","",Settings!$B$2) | H18: =IF(A18="","",ROUND(D18*E18/100,2)) | I18: =IF(A18="","",D18+H18+F18+G18) | J18: =IF(A18="","",ROUND(I18/12,2)) | K18: =IF(A18="","",Settings!$B$3) | L18: =IF(A18="","",IFERROR(ROUND(I18/(K18*Settings!$B$4*Settings!$B$5/100),2),"")) | M18: =IF(A18="","",IFERROR(ROUND(I18/D18,2),""))
E19: =IF(A19="","",Settings!$B$2) | H19: =IF(A19="","",ROUND(D19*E19/100,2)) | I19: =IF(A19="","",D19+H19+F19+G19) | J19: =IF(A19="","",ROUND(I19/12,2)) | K19: =IF(A19="","",Settings!$B$3) | L19: =IF(A19="","",IFERROR(ROUND(I19/(K19*Settings!$B$4*Settings!$B$5/100),2),"")) | M19: =IF(A19="","",IFERROR(ROUND(I19/D19,2),""))
... E40: =IF(A40="","",Settings!$B$2) | H40: =IF(A40="","",ROUND(D40*E40/100,2)) | I40: =IF(A40="","",D40+H40+F40+G40) | J40: =IF(A40="","",ROUND(I40/12,2)) | K40: =IF(A40="","",Settings!$B$3) | L40: =IF(A40="","",IFERROR(ROUND(I40/(K40*Settings!$B$4*Settings!$B$5/100),2),"")) | M40: =IF(A40="","",IFERROR(ROUND(I40/D40,2),""))
A41: Team total | B41: Headcount | C41: =COUNTA(A5:A40) -> 3 | D41: =SUM(D5:D40) -> 152000 | F41: =SUM(F5:F40) -> 11500 | G41: =SUM(G5:G40) -> 8200 | H41: =SUM(H5:H40) -> 18240 | I41: =SUM(I5:I40) -> 189940 | J41: =SUM(J5:J40) -> 15828.33
A42: Average annual cost per person | I42: =IFERROR(ROUND(I41/C41,2),0) -> 63313.33

Sheet Raises
A1: Raises
A2: Type a name from the Team sheet; the current salary is looked up. Choose percent or amount and enter the raise.
A4: Employee | B4: Current salary | C4: Raise type | D4: Raise (% or amount) | E4: Raise per year | F4: New salary | G4: Raise % | H4: Monthly difference | I4: Employer contrib. % | J4: Yearly cost to business
A5: Ana Example | B5: =IF(A5="","",IFERROR(INDEX(Team!$D$5:$D$40,MATCH(A5,Team!$A$5:$A$40,0)),"")) -> 50000 | C5: percent | D5: 5 | E5: =IF(A5="","",IF(C5="percent",ROUND(B5*D5/100,2),D5)) -> 2500 | F5: =IF(A5="","",B5+E5) -> 52500 | G5: =IF(A5="","",IFERROR(ROUND(E5/B5*100,2),"")) -> 5 | H5: =IF(A5="","",ROUND(E5/12,2)) -> 208.33 | I5: =IF(A5="","",Settings!$B$2) -> 12 | J5: =IF(A5="","",ROUND(E5*(1+I5/100),2)) -> 2800
A6: Ben Example | B6: =IF(A6="","",IFERROR(INDEX(Team!$D$5:$D$40,MATCH(A6,Team!$A$5:$A$40,0)),"")) -> 64000 | C6: amount | D6: 3000 | E6: =IF(A6="","",IF(C6="percent",ROUND(B6*D6/100,2),D6)) -> 3000 | F6: =IF(A6="","",B6+E6) -> 67000 | G6: =IF(A6="","",IFERROR(ROUND(E6/B6*100,2),"")) -> 4.69 | H6: =IF(A6="","",ROUND(E6/12,2)) -> 250 | I6: =IF(A6="","",Settings!$B$2) -> 12 | J6: =IF(A6="","",ROUND(E6*(1+I6/100),2)) -> 3360
B7: =IF(A7="","",IFERROR(INDEX(Team!$D$5:$D$40,MATCH(A7,Team!$A$5:$A$40,0)),"")) | E7: =IF(A7="","",IF(C7="percent",ROUND(B7*D7/100,2),D7)) | F7: =IF(A7="","",B7+E7) | G7: =IF(A7="","",IFERROR(ROUND(E7/B7*100,2),"")) | H7: =IF(A7="","",ROUND(E7/12,2)) | I7: =IF(A7="","",Settings!$B$2) | J7: =IF(A7="","",ROUND(E7*(1+I7/100),2))
B8: =IF(A8="","",IFERROR(INDEX(Team!$D$5:$D$40,MATCH(A8,Team!$A$5:$A$40,0)),"")) | E8: =IF(A8="","",IF(C8="percent",ROUND(B8*D8/100,2),D8)) | F8: =IF(A8="","",B8+E8) | G8: =IF(A8="","",IFERROR(ROUND(E8/B8*100,2),"")) | H8: =IF(A8="","",ROUND(E8/12,2)) | I8: =IF(A8="","",Settings!$B$2) | J8: =IF(A8="","",ROUND(E8*(1+I8/100),2))
B9: =IF(A9="","",IFERROR(INDEX(Team!$D$5:$D$40,MATCH(A9,Team!$A$5:$A$40,0)),"")) | E9: =IF(A9="","",IF(C9="percent",ROUND(B9*D9/100,2),D9)) | F9: =IF(A9="","",B9+E9) | G9: =IF(A9="","",IFERROR(ROUND(E9/B9*100,2),"")) | H9: =IF(A9="","",ROUND(E9/12,2)) | I9: =IF(A9="","",Settings!$B$2) | J9: =IF(A9="","",ROUND(E9*(1+I9/100),2))
B10: =IF(A10="","",IFERROR(INDEX(Team!$D$5:$D$40,MATCH(A10,Team!$A$5:$A$40,0)),"")) | E10: =IF(A10="","",IF(C10="percent",ROUND(B10*D10/100,2),D10)) | F10: =IF(A10="","",B10+E10) | G10: =IF(A10="","",IFERROR(ROUND(E10/B10*100,2),"")) | H10: =IF(A10="","",ROUND(E10/12,2)) | I10: =IF(A10="","",Settings!$B$2) | J10: =IF(A10="","",ROUND(E10*(1+I10/100),2))
B11: =IF(A11="","",IFERROR(INDEX(Team!$D$5:$D$40,MATCH(A11,Team!$A$5:$A$40,0)),"")) | E11: =IF(A11="","",IF(C11="percent",ROUND(B11*D11/100,2),D11)) | F11: =IF(A11="","",B11+E11) | G11: =IF(A11="","",IFERROR(ROUND(E11/B11*100,2),"")) | H11: =IF(A11="","",ROUND(E11/12,2)) | I11: =IF(A11="","",Settings!$B$2) | J11: =IF(A11="","",ROUND(E11*(1+I11/100),2))
B12: =IF(A12="","",IFERROR(INDEX(Team!$D$5:$D$40,MATCH(A12,Team!$A$5:$A$40,0)),"")) | E12: =IF(A12="","",IF(C12="percent",ROUND(B12*D12/100,2),D12)) | F12: =IF(A12="","",B12+E12) | G12: =IF(A12="","",IFERROR(ROUND(E12/B12*100,2),"")) | H12: =IF(A12="","",ROUND(E12/12,2)) | I12: =IF(A12="","",Settings!$B$2) | J12: =IF(A12="","",ROUND(E12*(1+I12/100),2))
B13: =IF(A13="","",IFERROR(INDEX(Team!$D$5:$D$40,MATCH(A13,Team!$A$5:$A$40,0)),"")) | E13: =IF(A13="","",IF(C13="percent",ROUND(B13*D13/100,2),D13)) | F13: =IF(A13="","",B13+E13) | G13: =IF(A13="","",IFERROR(ROUND(E13/B13*100,2),"")) | H13: =IF(A13="","",ROUND(E13/12,2)) | I13: =IF(A13="","",Settings!$B$2) | J13: =IF(A13="","",ROUND(E13*(1+I13/100),2))
B14: =IF(A14="","",IFERROR(INDEX(Team!$D$5:$D$40,MATCH(A14,Team!$A$5:$A$40,0)),"")) | E14: =IF(A14="","",IF(C14="percent",ROUND(B14*D14/100,2),D14)) | F14: =IF(A14="","",B14+E14) | G14: =IF(A14="","",IFERROR(ROUND(E14/B14*100,2),"")) | H14: =IF(A14="","",ROUND(E14/12,2)) | I14: =IF(A14="","",Settings!$B$2) | J14: =IF(A14="","",ROUND(E14*(1+I14/100),2))
B15: =IF(A15="","",IFERROR(INDEX(Team!$D$5:$D$40,MATCH(A15,Team!$A$5:$A$40,0)),"")) | E15: =IF(A15="","",IF(C15="percent",ROUND(B15*D15/100,2),D15)) | F15: =IF(A15="","",B15+E15) | G15: =IF(A15="","",IFERROR(ROUND(E15/B15*100,2),"")) | H15: =IF(A15="","",ROUND(E15/12,2)) | I15: =IF(A15="","",Settings!$B$2) | J15: =IF(A15="","",ROUND(E15*(1+I15/100),2))
B16: =IF(A16="","",IFERROR(INDEX(Team!$D$5:$D$40,MATCH(A16,Team!$A$5:$A$40,0)),"")) | E16: =IF(A16="","",IF(C16="percent",ROUND(B16*D16/100,2),D16)) | F16: =IF(A16="","",B16+E16) | G16: =IF(A16="","",IFERROR(ROUND(E16/B16*100,2),"")) | H16: =IF(A16="","",ROUND(E16/12,2)) | I16: =IF(A16="","",Settings!$B$2) | J16: =IF(A16="","",ROUND(E16*(1+I16/100),2))
B17: =IF(A17="","",IFERROR(INDEX(Team!$D$5:$D$40,MATCH(A17,Team!$A$5:$A$40,0)),"")) | E17: =IF(A17="","",IF(C17="percent",ROUND(B17*D17/100,2),D17)) | F17: =IF(A17="","",B17+E17) | G17: =IF(A17="","",IFERROR(ROUND(E17/B17*100,2),"")) | H17: =IF(A17="","",ROUND(E17/12,2)) | I17: =IF(A17="","",Settings!$B$2) | J17: =IF(A17="","",ROUND(E17*(1+I17/100),2))
B18: =IF(A18="","",IFERROR(INDEX(Team!$D$5:$D$40,MATCH(A18,Team!$A$5:$A$40,0)),"")) | E18: =IF(A18="","",IF(C18="percent",ROUND(B18*D18/100,2),D18)) | F18: =IF(A18="","",B18+E18) | G18: =IF(A18="","",IFERROR(ROUND(E18/B18*100,2),"")) | H18: =IF(A18="","",ROUND(E18/12,2)) | I18: =IF(A18="","",Settings!$B$2) | J18: =IF(A18="","",ROUND(E18*(1+I18/100),2))
... B20: =IF(A20="","",IFERROR(INDEX(Team!$D$5:$D$40,MATCH(A20,Team!$A$5:$A$40,0)),"")) | E20: =IF(A20="","",IF(C20="percent",ROUND(B20*D20/100,2),D20)) | F20: =IF(A20="","",B20+E20) | G20: =IF(A20="","",IFERROR(ROUND(E20/B20*100,2),"")) | H20: =IF(A20="","",ROUND(E20/12,2)) | I20: =IF(A20="","",Settings!$B$2) | J20: =IF(A20="","",ROUND(E20*(1+I20/100),2))
A21: Total | E21: =SUM(E5:E20) -> 5500 | H21: =SUM(H5:H20) -> 458.33 | J21: =SUM(J5:J20) -> 6160

Sheet PTO
A1: PTO
A2: One row per person. Entitlement and pay frequency default to Settings. Periods elapsed = pay periods already completed this year.
A4: Employee | B4: PTO per year (days) | C4: Pay frequency | D4: Periods per year | E4: Periods elapsed | F4: Accrual per period | G4: Accrued to date | H4: Carried over | I4: Taken | J4: Balance | K4: Still to accrue
A5: Ana Example | B5: =IF(A5="","",Settings!$B$8) -> 20 | C5: =IF(A5="","",Settings!$B$9) -> biweekly | D5: =IF(A5="","",IF(C5="weekly",52,IF(C5="biweekly",26,IF(C5="semimonthly",24,IF(C5="monthly",12,""))))) -> 26 | E5: 13 | F5: =IF(A5="","",IFERROR(ROUND(B5/D5,2),"")) -> 0.77 | G5: =IF(A5="","",IFERROR(ROUND(B5/D5*E5,2),"")) -> 10 | H5: 3 | I5: 5 | J5: =IF(A5="","",IFERROR(ROUND(H5+G5-I5,2),"")) -> 8 | K5: =IF(A5="","",IFERROR(ROUND(B5-G5,2),"")) -> 10
A6: Ben Example | B6: =IF(A6="","",Settings!$B$8) -> 20 | C6: =IF(A6="","",Settings!$B$9) -> biweekly | D6: =IF(A6="","",IF(C6="weekly",52,IF(C6="biweekly",26,IF(C6="semimonthly",24,IF(C6="monthly",12,""))))) -> 26 | E6: 13 | F6: =IF(A6="","",IFERROR(ROUND(B6/D6,2),"")) -> 0.77 | G6: =IF(A6="","",IFERROR(ROUND(B6/D6*E6,2),"")) -> 10 | H6: 0 | I6: 2 | J6: =IF(A6="","",IFERROR(ROUND(H6+G6-I6,2),"")) -> 8 | K6: =IF(A6="","",IFERROR(ROUND(B6-G6,2),"")) -> 10
A7: Cara Example | B7: =IF(A7="","",Settings!$B$8) -> 20 | C7: =IF(A7="","",Settings!$B$9) -> biweekly | D7: =IF(A7="","",IF(C7="weekly",52,IF(C7="biweekly",26,IF(C7="semimonthly",24,IF(C7="monthly",12,""))))) -> 26 | E7: 13 | F7: =IF(A7="","",IFERROR(ROUND(B7/D7,2),"")) -> 0.77 | G7: =IF(A7="","",IFERROR(ROUND(B7/D7*E7,2),"")) -> 10 | H7: 0 | I7: 0 | J7: =IF(A7="","",IFERROR(ROUND(H7+G7-I7,2),"")) -> 10 | K7: =IF(A7="","",IFERROR(ROUND(B7-G7,2),"")) -> 10
B8: =IF(A8="","",Settings!$B$8) | C8: =IF(A8="","",Settings!$B$9) | D8: =IF(A8="","",IF(C8="weekly",52,IF(C8="biweekly",26,IF(C8="semimonthly",24,IF(C8="monthly",12,""))))) | F8: =IF(A8="","",IFERROR(ROUND(B8/D8,2),"")) | G8: =IF(A8="","",IFERROR(ROUND(B8/D8*E8,2),"")) | J8: =IF(A8="","",IFERROR(ROUND(H8+G8-I8,2),"")) | K8: =IF(A8="","",IFERROR(ROUND(B8-G8,2),""))
B9: =IF(A9="","",Settings!$B$8) | C9: =IF(A9="","",Settings!$B$9) | D9: =IF(A9="","",IF(C9="weekly",52,IF(C9="biweekly",26,IF(C9="semimonthly",24,IF(C9="monthly",12,""))))) | F9: =IF(A9="","",IFERROR(ROUND(B9/D9,2),"")) | G9: =IF(A9="","",IFERROR(ROUND(B9/D9*E9,2),"")) | J9: =IF(A9="","",IFERROR(ROUND(H9+G9-I9,2),"")) | K9: =IF(A9="","",IFERROR(ROUND(B9-G9,2),""))
B10: =IF(A10="","",Settings!$B$8) | C10: =IF(A10="","",Settings!$B$9) | D10: =IF(A10="","",IF(C10="weekly",52,IF(C10="biweekly",26,IF(C10="semimonthly",24,IF(C10="monthly",12,""))))) | F10: =IF(A10="","",IFERROR(ROUND(B10/D10,2),"")) | G10: =IF(A10="","",IFERROR(ROUND(B10/D10*E10,2),"")) | J10: =IF(A10="","",IFERROR(ROUND(H10+G10-I10,2),"")) | K10: =IF(A10="","",IFERROR(ROUND(B10-G10,2),""))
B11: =IF(A11="","",Settings!$B$8) | C11: =IF(A11="","",Settings!$B$9) | D11: =IF(A11="","",IF(C11="weekly",52,IF(C11="biweekly",26,IF(C11="semimonthly",24,IF(C11="monthly",12,""))))) | F11: =IF(A11="","",IFERROR(ROUND(B11/D11,2),"")) | G11: =IF(A11="","",IFERROR(ROUND(B11/D11*E11,2),"")) | J11: =IF(A11="","",IFERROR(ROUND(H11+G11-I11,2),"")) | K11: =IF(A11="","",IFERROR(ROUND(B11-G11,2),""))
B12: =IF(A12="","",Settings!$B$8) | C12: =IF(A12="","",Settings!$B$9) | D12: =IF(A12="","",IF(C12="weekly",52,IF(C12="biweekly",26,IF(C12="semimonthly",24,IF(C12="monthly",12,""))))) | F12: =IF(A12="","",IFERROR(ROUND(B12/D12,2),"")) | G12: =IF(A12="","",IFERROR(ROUND(B12/D12*E12,2),"")) | J12: =IF(A12="","",IFERROR(ROUND(H12+G12-I12,2),"")) | K12: =IF(A12="","",IFERROR(ROUND(B12-G12,2),""))
B13: =IF(A13="","",Settings!$B$8) | C13: =IF(A13="","",Settings!$B$9) | D13: =IF(A13="","",IF(C13="weekly",52,IF(C13="biweekly",26,IF(C13="semimonthly",24,IF(C13="monthly",12,""))))) | F13: =IF(A13="","",IFERROR(ROUND(B13/D13,2),"")) | G13: =IF(A13="","",IFERROR(ROUND(B13/D13*E13,2),"")) | J13: =IF(A13="","",IFERROR(ROUND(H13+G13-I13,2),"")) | K13: =IF(A13="","",IFERROR(ROUND(B13-G13,2),""))
B14: =IF(A14="","",Settings!$B$8) | C14: =IF(A14="","",Settings!$B$9) | D14: =IF(A14="","",IF(C14="weekly",52,IF(C14="biweekly",26,IF(C14="semimonthly",24,IF(C14="monthly",12,""))))) | F14: =IF(A14="","",IFERROR(ROUND(B14/D14,2),"")) | G14: =IF(A14="","",IFERROR(ROUND(B14/D14*E14,2),"")) | J14: =IF(A14="","",IFERROR(ROUND(H14+G14-I14,2),"")) | K14: =IF(A14="","",IFERROR(ROUND(B14-G14,2),""))
B15: =IF(A15="","",Settings!$B$8) | C15: =IF(A15="","",Settings!$B$9) | D15: =IF(A15="","",IF(C15="weekly",52,IF(C15="biweekly",26,IF(C15="semimonthly",24,IF(C15="monthly",12,""))))) | F15: =IF(A15="","",IFERROR(ROUND(B15/D15,2),"")) | G15: =IF(A15="","",IFERROR(ROUND(B15/D15*E15,2),"")) | J15: =IF(A15="","",IFERROR(ROUND(H15+G15-I15,2),"")) | K15: =IF(A15="","",IFERROR(ROUND(B15-G15,2),""))
B16: =IF(A16="","",Settings!$B$8) | C16: =IF(A16="","",Settings!$B$9) | D16: =IF(A16="","",IF(C16="weekly",52,IF(C16="biweekly",26,IF(C16="semimonthly",24,IF(C16="monthly",12,""))))) | F16: =IF(A16="","",IFERROR(ROUND(B16/D16,2),"")) | G16: =IF(A16="","",IFERROR(ROUND(B16/D16*E16,2),"")) | J16: =IF(A16="","",IFERROR(ROUND(H16+G16-I16,2),"")) | K16: =IF(A16="","",IFERROR(ROUND(B16-G16,2),""))
B17: =IF(A17="","",Settings!$B$8) | C17: =IF(A17="","",Settings!$B$9) | D17: =IF(A17="","",IF(C17="weekly",52,IF(C17="biweekly",26,IF(C17="semimonthly",24,IF(C17="monthly",12,""))))) | F17: =IF(A17="","",IFERROR(ROUND(B17/D17,2),"")) | G17: =IF(A17="","",IFERROR(ROUND(B17/D17*E17,2),"")) | J17: =IF(A17="","",IFERROR(ROUND(H17+G17-I17,2),"")) | K17: =IF(A17="","",IFERROR(ROUND(B17-G17,2),""))
B18: =IF(A18="","",Settings!$B$8) | C18: =IF(A18="","",Settings!$B$9) | D18: =IF(A18="","",IF(C18="weekly",52,IF(C18="biweekly",26,IF(C18="semimonthly",24,IF(C18="monthly",12,""))))) | F18: =IF(A18="","",IFERROR(ROUND(B18/D18,2),"")) | G18: =IF(A18="","",IFERROR(ROUND(B18/D18*E18,2),"")) | J18: =IF(A18="","",IFERROR(ROUND(H18+G18-I18,2),"")) | K18: =IF(A18="","",IFERROR(ROUND(B18-G18,2),""))
B19: =IF(A19="","",Settings!$B$8) | C19: =IF(A19="","",Settings!$B$9) | D19: =IF(A19="","",IF(C19="weekly",52,IF(C19="biweekly",26,IF(C19="semimonthly",24,IF(C19="monthly",12,""))))) | F19: =IF(A19="","",IFERROR(ROUND(B19/D19,2),"")) | G19: =IF(A19="","",IFERROR(ROUND(B19/D19*E19,2),"")) | J19: =IF(A19="","",IFERROR(ROUND(H19+G19-I19,2),"")) | K19: =IF(A19="","",IFERROR(ROUND(B19-G19,2),""))
... B40: =IF(A40="","",Settings!$B$8) | C40: =IF(A40="","",Settings!$B$9) | D40: =IF(A40="","",IF(C40="weekly",52,IF(C40="biweekly",26,IF(C40="semimonthly",24,IF(C40="monthly",12,""))))) | F40: =IF(A40="","",IFERROR(ROUND(B40/D40,2),"")) | G40: =IF(A40="","",IFERROR(ROUND(B40/D40*E40,2),"")) | J40: =IF(A40="","",IFERROR(ROUND(H40+G40-I40,2),"")) | K40: =IF(A40="","",IFERROR(ROUND(B40-G40,2),""))

Sheet Hiring & Turnover
A1: Hiring & Turnover
A2: Planned hires are prorated by the months left in the plan year (Settings). The turnover block uses your average cost per person from the Team sheet.
A4: Role | B4: Start month | C4: Annual salary | D4: Employer contrib. % | E4: Benefits + overheads / yr | F4: Total annual cost | G4: Months in plan year | H4: Cost in plan year
A5: Account manager | B5: 46266 | C5: 55000 | D5: =IF(A5="","",Settings!$B$2) -> 12 | E5: 7000 | F5: =IF(A5="","",ROUND(C5*(1+D5/100)+E5,2)) -> 68600 | G5: =IF(OR(A5="",B5=""),"",IF(YEAR(B5)<Settings!$B$10,12,IF(YEAR(B5)>Settings!$B$10,0,13-MONTH(B5)))) -> 4 | H5: =IF(A5="","",IFERROR(ROUND(F5*G5/12,2),"")) -> 22866.67
A6: Junior developer | B6: 46327 | C6: 42000 | D6: =IF(A6="","",Settings!$B$2) -> 12 | E6: 6000 | F6: =IF(A6="","",ROUND(C6*(1+D6/100)+E6,2)) -> 53040 | G6: =IF(OR(A6="",B6=""),"",IF(YEAR(B6)<Settings!$B$10,12,IF(YEAR(B6)>Settings!$B$10,0,13-MONTH(B6)))) -> 2 | H6: =IF(A6="","",IFERROR(ROUND(F6*G6/12,2),"")) -> 8840
D7: =IF(A7="","",Settings!$B$2) | F7: =IF(A7="","",ROUND(C7*(1+D7/100)+E7,2)) | G7: =IF(OR(A7="",B7=""),"",IF(YEAR(B7)<Settings!$B$10,12,IF(YEAR(B7)>Settings!$B$10,0,13-MONTH(B7)))) | H7: =IF(A7="","",IFERROR(ROUND(F7*G7/12,2),""))
D8: =IF(A8="","",Settings!$B$2) | F8: =IF(A8="","",ROUND(C8*(1+D8/100)+E8,2)) | G8: =IF(OR(A8="",B8=""),"",IF(YEAR(B8)<Settings!$B$10,12,IF(YEAR(B8)>Settings!$B$10,0,13-MONTH(B8)))) | H8: =IF(A8="","",IFERROR(ROUND(F8*G8/12,2),""))
D9: =IF(A9="","",Settings!$B$2) | F9: =IF(A9="","",ROUND(C9*(1+D9/100)+E9,2)) | G9: =IF(OR(A9="",B9=""),"",IF(YEAR(B9)<Settings!$B$10,12,IF(YEAR(B9)>Settings!$B$10,0,13-MONTH(B9)))) | H9: =IF(A9="","",IFERROR(ROUND(F9*G9/12,2),""))
D10: =IF(A10="","",Settings!$B$2) | F10: =IF(A10="","",ROUND(C10*(1+D10/100)+E10,2)) | G10: =IF(OR(A10="",B10=""),"",IF(YEAR(B10)<Settings!$B$10,12,IF(YEAR(B10)>Settings!$B$10,0,13-MONTH(B10)))) | H10: =IF(A10="","",IFERROR(ROUND(F10*G10/12,2),""))
D11: =IF(A11="","",Settings!$B$2) | F11: =IF(A11="","",ROUND(C11*(1+D11/100)+E11,2)) | G11: =IF(OR(A11="",B11=""),"",IF(YEAR(B11)<Settings!$B$10,12,IF(YEAR(B11)>Settings!$B$10,0,13-MONTH(B11)))) | H11: =IF(A11="","",IFERROR(ROUND(F11*G11/12,2),""))
D12: =IF(A12="","",Settings!$B$2) | F12: =IF(A12="","",ROUND(C12*(1+D12/100)+E12,2)) | G12: =IF(OR(A12="",B12=""),"",IF(YEAR(B12)<Settings!$B$10,12,IF(YEAR(B12)>Settings!$B$10,0,13-MONTH(B12)))) | H12: =IF(A12="","",IFERROR(ROUND(F12*G12/12,2),""))
D13: =IF(A13="","",Settings!$B$2) | F13: =IF(A13="","",ROUND(C13*(1+D13/100)+E13,2)) | G13: =IF(OR(A13="",B13=""),"",IF(YEAR(B13)<Settings!$B$10,12,IF(YEAR(B13)>Settings!$B$10,0,13-MONTH(B13)))) | H13: =IF(A13="","",IFERROR(ROUND(F13*G13/12,2),""))
D14: =IF(A14="","",Settings!$B$2) | F14: =IF(A14="","",ROUND(C14*(1+D14/100)+E14,2)) | G14: =IF(OR(A14="",B14=""),"",IF(YEAR(B14)<Settings!$B$10,12,IF(YEAR(B14)>Settings!$B$10,0,13-MONTH(B14)))) | H14: =IF(A14="","",IFERROR(ROUND(F14*G14/12,2),""))
D15: =IF(A15="","",Settings!$B$2) | F15: =IF(A15="","",ROUND(C15*(1+D15/100)+E15,2)) | G15: =IF(OR(A15="",B15=""),"",IF(YEAR(B15)<Settings!$B$10,12,IF(YEAR(B15)>Settings!$B$10,0,13-MONTH(B15)))) | H15: =IF(A15="","",IFERROR(ROUND(F15*G15/12,2),""))
D16: =IF(A16="","",Settings!$B$2) | F16: =IF(A16="","",ROUND(C16*(1+D16/100)+E16,2)) | G16: =IF(OR(A16="",B16=""),"",IF(YEAR(B16)<Settings!$B$10,12,IF(YEAR(B16)>Settings!$B$10,0,13-MONTH(B16)))) | H16: =IF(A16="","",IFERROR(ROUND(F16*G16/12,2),""))
A17: Total planned hires | F17: =SUM(F5:F16) -> 121640 | H17: =SUM(H5:H16) -> 31706.67
A20: Turnover cost
A21: Average annual cost per employee | B21: =Team!I42 -> 63313.33 | C21: Defaults to the Team sheet average; overwrite for a specific role.
A22: Working days per year | B22: =Settings!$B$6 -> 240
A23: Recruiting and hiring cost per leaver | B23: 5000 | C23: Ads, agency fees, interview time.
A24: Days the role stays vacant | B24: 30
A25: Onboarding cost per hire | B25: 2000 | C25: Training, equipment, admin.
A26: Ramp-up period (days) | B26: 60
A27: Productivity during ramp-up (%) | B27: =Settings!$B$7 -> 50
A28: Headcount | B28: =Team!C41 -> 3
A29: Annual turnover rate (%) | B29: 15 | C29: Leavers in a year ÷ average headcount.
A30: Cost per leaver | B30: =ROUND(B23+B21/B22*B24+B25+B21/B22*B26*(1-B27/100),2) -> 22828.33 | C30: recruiting + vacancy + onboarding + ramp-up
A31: Expected leavers per year | B31: =ROUND(B28*B29/100,2) -> 0.45 | C31: headcount × turnover rate
A32: Turnover cost per year | B32: =ROUND(B30*B31,2) -> 10272.75 | C32: per leaver × leavers
A33: Cost per leaver as % of annual cost | B33: =IFERROR(ROUND(B30/B21*100,2),"") -> 36.06
A34: Daily cost of the role | B34: =IFERROR(ROUND(B21/B22,2),"") -> 263.81 | C34: annual cost ÷ working days
