Workbook

Sheet Start Here
A1: Landlord Rent & Expense Tracker
A2: by Knackdesk · knackdesk.com
A4: HOW TO USE
A5: 1. Properties: one row per unit. Give each a short code (A, B, C...) and enter rent, tenant, lease dates, deposit held and purchase price.
A6: 2. Rent Log: one row per rent period per property. Enter the property code, due date, amount due, amount paid and paid date. Days late, outstanding and status are calculated.
A7: 3. Expenses: one row per cost, with the property code and a category.
A8: 4. Summary: rent due, collected, outstanding, expenses, net income and gross and net yield per property and for the whole portfolio.
A10: LEGEND
A11: Blue text = a cell you type into. Black text = a formula, leave it alone. Yellow fill = key inputs.
A12: Each table has one example row to overwrite. Property codes must match between sheets exactly.
A14: NOTES
A15: Days late count from the due date to today for unpaid rows, or to the paid date for paid rows. 'Today' recalculates when the file opens.
... A18: Support: hello@knackdesk.com

Sheet Properties
A1: Properties
A2: Today (auto) | B2: =TODAY() -> 46296
A4: Code | B4: Address | C4: Tenant | D4: Monthly rent | E4: Lease start | F4: Lease end | G4: Deposit held | H4: Purchase price | I4: Notes
A5: A | B5: 12 Example Street, Flat 2 | C5: J. Example | D5: 1200 | E5: 46096 | F5: 46461 | G5: 1200 | H5: 200000

Sheet Rent Log
A1: Rent Log
A2: Outstanding total | B2: =SUM(H5:H304) -> 1200 | C2: Rows overdue | D2: =COUNTIF(I5:I304,"Overdue") -> 0
A4: Property code | B4: Period (month) | C4: Due date | D4: Amount due | E4: Amount paid | F4: Paid date | G4: Days late | H4: Outstanding | I4: Status | J4: Note
A5: A | B5: 46265 | C5: 46265 | D5: 1200 | E5: 1200 | F5: 46267 | G5: =IF(C5="",0,IF(E5>=D5,MAX(0,IF(F5="",0,F5-C5)),MAX(0,Properties!$B$2-C5))) -> 2 | H5: =IF(C5="",0,MAX(0,D5-E5)) -> 0 | I5: =IF(C5="","",IF(H5<=0,"Paid",IF(G5>0,"Overdue","Due"))) -> Paid
A6: A | B6: 46296 | C6: 46296 | D6: 1200 | E6: 0 | G6: =IF(C6="",0,IF(E6>=D6,MAX(0,IF(F6="",0,F6-C6)),MAX(0,Properties!$B$2-C6))) -> 0 | H6: =IF(C6="",0,MAX(0,D6-E6)) -> 1200 | I6: =IF(C6="","",IF(H6<=0,"Paid",IF(G6>0,"Overdue","Due"))) -> Due
G7: =IF(C7="",0,IF(E7>=D7,MAX(0,IF(F7="",0,F7-C7)),MAX(0,Properties!$B$2-C7))) -> 0 | H7: =IF(C7="",0,MAX(0,D7-E7)) -> 0 | I7: =IF(C7="","",IF(H7<=0,"Paid",IF(G7>0,"Overdue","Due")))
G8: =IF(C8="",0,IF(E8>=D8,MAX(0,IF(F8="",0,F8-C8)),MAX(0,Properties!$B$2-C8))) -> 0 | H8: =IF(C8="",0,MAX(0,D8-E8)) -> 0 | I8: =IF(C8="","",IF(H8<=0,"Paid",IF(G8>0,"Overdue","Due")))
G9: =IF(C9="",0,IF(E9>=D9,MAX(0,IF(F9="",0,F9-C9)),MAX(0,Properties!$B$2-C9))) -> 0 | H9: =IF(C9="",0,MAX(0,D9-E9)) -> 0 | I9: =IF(C9="","",IF(H9<=0,"Paid",IF(G9>0,"Overdue","Due")))
G10: =IF(C10="",0,IF(E10>=D10,MAX(0,IF(F10="",0,F10-C10)),MAX(0,Properties!$B$2-C10))) -> 0 | H10: =IF(C10="",0,MAX(0,D10-E10)) -> 0 | I10: =IF(C10="","",IF(H10<=0,"Paid",IF(G10>0,"Overdue","Due")))
G11: =IF(C11="",0,IF(E11>=D11,MAX(0,IF(F11="",0,F11-C11)),MAX(0,Properties!$B$2-C11))) -> 0 | H11: =IF(C11="",0,MAX(0,D11-E11)) -> 0 | I11: =IF(C11="","",IF(H11<=0,"Paid",IF(G11>0,"Overdue","Due")))
G12: =IF(C12="",0,IF(E12>=D12,MAX(0,IF(F12="",0,F12-C12)),MAX(0,Properties!$B$2-C12))) -> 0 | H12: =IF(C12="",0,MAX(0,D12-E12)) -> 0 | I12: =IF(C12="","",IF(H12<=0,"Paid",IF(G12>0,"Overdue","Due")))
G13: =IF(C13="",0,IF(E13>=D13,MAX(0,IF(F13="",0,F13-C13)),MAX(0,Properties!$B$2-C13))) -> 0 | H13: =IF(C13="",0,MAX(0,D13-E13)) -> 0 | I13: =IF(C13="","",IF(H13<=0,"Paid",IF(G13>0,"Overdue","Due")))
G14: =IF(C14="",0,IF(E14>=D14,MAX(0,IF(F14="",0,F14-C14)),MAX(0,Properties!$B$2-C14))) -> 0 | H14: =IF(C14="",0,MAX(0,D14-E14)) -> 0 | I14: =IF(C14="","",IF(H14<=0,"Paid",IF(G14>0,"Overdue","Due")))
G15: =IF(C15="",0,IF(E15>=D15,MAX(0,IF(F15="",0,F15-C15)),MAX(0,Properties!$B$2-C15))) -> 0 | H15: =IF(C15="",0,MAX(0,D15-E15)) -> 0 | I15: =IF(C15="","",IF(H15<=0,"Paid",IF(G15>0,"Overdue","Due")))
G16: =IF(C16="",0,IF(E16>=D16,MAX(0,IF(F16="",0,F16-C16)),MAX(0,Properties!$B$2-C16))) -> 0 | H16: =IF(C16="",0,MAX(0,D16-E16)) -> 0 | I16: =IF(C16="","",IF(H16<=0,"Paid",IF(G16>0,"Overdue","Due")))
G17: =IF(C17="",0,IF(E17>=D17,MAX(0,IF(F17="",0,F17-C17)),MAX(0,Properties!$B$2-C17))) -> 0 | H17: =IF(C17="",0,MAX(0,D17-E17)) -> 0 | I17: =IF(C17="","",IF(H17<=0,"Paid",IF(G17>0,"Overdue","Due")))
G18: =IF(C18="",0,IF(E18>=D18,MAX(0,IF(F18="",0,F18-C18)),MAX(0,Properties!$B$2-C18))) -> 0 | H18: =IF(C18="",0,MAX(0,D18-E18)) -> 0 | I18: =IF(C18="","",IF(H18<=0,"Paid",IF(G18>0,"Overdue","Due")))
... G304: =IF(C304="",0,IF(E304>=D304,MAX(0,IF(F304="",0,F304-C304)),MAX(0,Properties!$B$2-C304))) -> 0 | H304: =IF(C304="",0,MAX(0,D304-E304)) -> 0 | I304: =IF(C304="","",IF(H304<=0,"Paid",IF(G304>0,"Overdue","Due")))

Sheet Expenses
A1: Expenses
A2: Total | B2: =SUM(E5:E304) -> 95
A4: Date | B4: Property code | C4: Category | D4: Description | E4: Amount | F4: Year
A5: 46284 | B5: A | C5: Repairs | D5: Example: boiler service | E5: 95 | F5: =IF(A5="","",YEAR(A5)) -> 2026
F6: =IF(A6="","",YEAR(A6))
F7: =IF(A7="","",YEAR(A7))
F8: =IF(A8="","",YEAR(A8))
F9: =IF(A9="","",YEAR(A9))
F10: =IF(A10="","",YEAR(A10))
F11: =IF(A11="","",YEAR(A11))
F12: =IF(A12="","",YEAR(A12))
F13: =IF(A13="","",YEAR(A13))
F14: =IF(A14="","",YEAR(A14))
F15: =IF(A15="","",YEAR(A15))
F16: =IF(A16="","",YEAR(A16))
F17: =IF(A17="","",YEAR(A17))
... F304: =IF(A304="","",YEAR(A304))

Sheet Summary
A1: Summary
A2: Year | B2: 2026
A4: Code | B4: Address | C4: Rent due (year) | D4: Rent collected (year) | E4: Outstanding | F4: Expenses (year) | G4: Net income (year) | H4: Gross yield | I4: Net yield
A5: =IF(Properties!A5="","",Properties!A5) -> A | B5: =IF(Properties!A5="","",Properties!B5) -> 12 Example Street, Flat 2 | C5: =IF(A5="","",SUMIFS('Rent Log'!$D$5:$D$304,'Rent Log'!$A$5:$A$304,A5,'Rent Log'!$C$5:$C$304,">="&DATE($B$2,1,1),'Rent Log'!$C$5:$C$304,"<"&DATE($B$2+1,1,1))) -> 2400 | D5: =IF(A5="","",SUMIFS('Rent Log'!$E$5:$E$304,'Rent Log'!$A$5:$A$304,A5,'Rent Log'!$C$5:$C$304,">="&DATE($B$2,1,1),'Rent Log'!$C$5:$C$304,"<"&DATE($B$2+1,1,1))) -> 1200 | E5: =IF(A5="","",SUMIFS('Rent Log'!$H$5:$H$304,'Rent Log'!$A$5:$A$304,A5)) -> 1200 | F5: =IF(A5="","",SUMIFS(Expenses!$E$5:$E$304,Expenses!$B$5:$B$304,A5,Expenses!$F$5:$F$304,$B$2)) -> 95 | G5: =IF(A5="","",C5-F5) -> 2305 | H5: =IF(OR(A5="",Properties!H5=0,Properties!H5=""),"",ROUND(Properties!D5*12/Properties!H5*100,2)) -> 7.2 | I5: =IF(OR(A5="",Properties!H5=0,Properties!H5=""),"",ROUND((Properties!D5*12-F5)/Properties!H5*100,2)) -> 7.15
A6: =IF(Properties!A6="","",Properties!A6) | B6: =IF(Properties!A6="","",Properties!B6) | C6: =IF(A6="","",SUMIFS('Rent Log'!$D$5:$D$304,'Rent Log'!$A$5:$A$304,A6,'Rent Log'!$C$5:$C$304,">="&DATE($B$2,1,1),'Rent Log'!$C$5:$C$304,"<"&DATE($B$2+1,1,1))) | D6: =IF(A6="","",SUMIFS('Rent Log'!$E$5:$E$304,'Rent Log'!$A$5:$A$304,A6,'Rent Log'!$C$5:$C$304,">="&DATE($B$2,1,1),'Rent Log'!$C$5:$C$304,"<"&DATE($B$2+1,1,1))) | E6: =IF(A6="","",SUMIFS('Rent Log'!$H$5:$H$304,'Rent Log'!$A$5:$A$304,A6)) | F6: =IF(A6="","",SUMIFS(Expenses!$E$5:$E$304,Expenses!$B$5:$B$304,A6,Expenses!$F$5:$F$304,$B$2)) | G6: =IF(A6="","",C6-F6) | H6: =IF(OR(A6="",Properties!H6=0,Properties!H6=""),"",ROUND(Properties!D6*12/Properties!H6*100,2)) | I6: =IF(OR(A6="",Properties!H6=0,Properties!H6=""),"",ROUND((Properties!D6*12-F6)/Properties!H6*100,2))
A7: =IF(Properties!A7="","",Properties!A7) | B7: =IF(Properties!A7="","",Properties!B7) | C7: =IF(A7="","",SUMIFS('Rent Log'!$D$5:$D$304,'Rent Log'!$A$5:$A$304,A7,'Rent Log'!$C$5:$C$304,">="&DATE($B$2,1,1),'Rent Log'!$C$5:$C$304,"<"&DATE($B$2+1,1,1))) | D7: =IF(A7="","",SUMIFS('Rent Log'!$E$5:$E$304,'Rent Log'!$A$5:$A$304,A7,'Rent Log'!$C$5:$C$304,">="&DATE($B$2,1,1),'Rent Log'!$C$5:$C$304,"<"&DATE($B$2+1,1,1))) | E7: =IF(A7="","",SUMIFS('Rent Log'!$H$5:$H$304,'Rent Log'!$A$5:$A$304,A7)) | F7: =IF(A7="","",SUMIFS(Expenses!$E$5:$E$304,Expenses!$B$5:$B$304,A7,Expenses!$F$5:$F$304,$B$2)) | G7: =IF(A7="","",C7-F7) | H7: =IF(OR(A7="",Properties!H7=0,Properties!H7=""),"",ROUND(Properties!D7*12/Properties!H7*100,2)) | I7: =IF(OR(A7="",Properties!H7=0,Properties!H7=""),"",ROUND((Properties!D7*12-F7)/Properties!H7*100,2))
A8: =IF(Properties!A8="","",Properties!A8) | B8: =IF(Properties!A8="","",Properties!B8) | C8: =IF(A8="","",SUMIFS('Rent Log'!$D$5:$D$304,'Rent Log'!$A$5:$A$304,A8,'Rent Log'!$C$5:$C$304,">="&DATE($B$2,1,1),'Rent Log'!$C$5:$C$304,"<"&DATE($B$2+1,1,1))) | D8: =IF(A8="","",SUMIFS('Rent Log'!$E$5:$E$304,'Rent Log'!$A$5:$A$304,A8,'Rent Log'!$C$5:$C$304,">="&DATE($B$2,1,1),'Rent Log'!$C$5:$C$304,"<"&DATE($B$2+1,1,1))) | E8: =IF(A8="","",SUMIFS('Rent Log'!$H$5:$H$304,'Rent Log'!$A$5:$A$304,A8)) | F8: =IF(A8="","",SUMIFS(Expenses!$E$5:$E$304,Expenses!$B$5:$B$304,A8,Expenses!$F$5:$F$304,$B$2)) | G8: =IF(A8="","",C8-F8) | H8: =IF(OR(A8="",Properties!H8=0,Properties!H8=""),"",ROUND(Properties!D8*12/Properties!H8*100,2)) | I8: =IF(OR(A8="",Properties!H8=0,Properties!H8=""),"",ROUND((Properties!D8*12-F8)/Properties!H8*100,2))
A9: =IF(Properties!A9="","",Properties!A9) | B9: =IF(Properties!A9="","",Properties!B9) | C9: =IF(A9="","",SUMIFS('Rent Log'!$D$5:$D$304,'Rent Log'!$A$5:$A$304,A9,'Rent Log'!$C$5:$C$304,">="&DATE($B$2,1,1),'Rent Log'!$C$5:$C$304,"<"&DATE($B$2+1,1,1))) | D9: =IF(A9="","",SUMIFS('Rent Log'!$E$5:$E$304,'Rent Log'!$A$5:$A$304,A9,'Rent Log'!$C$5:$C$304,">="&DATE($B$2,1,1),'Rent Log'!$C$5:$C$304,"<"&DATE($B$2+1,1,1))) | E9: =IF(A9="","",SUMIFS('Rent Log'!$H$5:$H$304,'Rent Log'!$A$5:$A$304,A9)) | F9: =IF(A9="","",SUMIFS(Expenses!$E$5:$E$304,Expenses!$B$5:$B$304,A9,Expenses!$F$5:$F$304,$B$2)) | G9: =IF(A9="","",C9-F9) | H9: =IF(OR(A9="",Properties!H9=0,Properties!H9=""),"",ROUND(Properties!D9*12/Properties!H9*100,2)) | I9: =IF(OR(A9="",Properties!H9=0,Properties!H9=""),"",ROUND((Properties!D9*12-F9)/Properties!H9*100,2))
A10: =IF(Properties!A10="","",Properties!A10) | B10: =IF(Properties!A10="","",Properties!B10) | C10: =IF(A10="","",SUMIFS('Rent Log'!$D$5:$D$304,'Rent Log'!$A$5:$A$304,A10,'Rent Log'!$C$5:$C$304,">="&DATE($B$2,1,1),'Rent Log'!$C$5:$C$304,"<"&DATE($B$2+1,1,1))) | D10: =IF(A10="","",SUMIFS('Rent Log'!$E$5:$E$304,'Rent Log'!$A$5:$A$304,A10,'Rent Log'!$C$5:$C$304,">="&DATE($B$2,1,1),'Rent Log'!$C$5:$C$304,"<"&DATE($B$2+1,1,1))) | E10: =IF(A10="","",SUMIFS('Rent Log'!$H$5:$H$304,'Rent Log'!$A$5:$A$304,A10)) | F10: =IF(A10="","",SUMIFS(Expenses!$E$5:$E$304,Expenses!$B$5:$B$304,A10,Expenses!$F$5:$F$304,$B$2)) | G10: =IF(A10="","",C10-F10) | H10: =IF(OR(A10="",Properties!H10=0,Properties!H10=""),"",ROUND(Properties!D10*12/Properties!H10*100,2)) | I10: =IF(OR(A10="",Properties!H10=0,Properties!H10=""),"",ROUND((Properties!D10*12-F10)/Properties!H10*100,2))
A11: =IF(Properties!A11="","",Properties!A11) | B11: =IF(Properties!A11="","",Properties!B11) | C11: =IF(A11="","",SUMIFS('Rent Log'!$D$5:$D$304,'Rent Log'!$A$5:$A$304,A11,'Rent Log'!$C$5:$C$304,">="&DATE($B$2,1,1),'Rent Log'!$C$5:$C$304,"<"&DATE($B$2+1,1,1))) | D11: =IF(A11="","",SUMIFS('Rent Log'!$E$5:$E$304,'Rent Log'!$A$5:$A$304,A11,'Rent Log'!$C$5:$C$304,">="&DATE($B$2,1,1),'Rent Log'!$C$5:$C$304,"<"&DATE($B$2+1,1,1))) | E11: =IF(A11="","",SUMIFS('Rent Log'!$H$5:$H$304,'Rent Log'!$A$5:$A$304,A11)) | F11: =IF(A11="","",SUMIFS(Expenses!$E$5:$E$304,Expenses!$B$5:$B$304,A11,Expenses!$F$5:$F$304,$B$2)) | G11: =IF(A11="","",C11-F11) | H11: =IF(OR(A11="",Properties!H11=0,Properties!H11=""),"",ROUND(Properties!D11*12/Properties!H11*100,2)) | I11: =IF(OR(A11="",Properties!H11=0,Properties!H11=""),"",ROUND((Properties!D11*12-F11)/Properties!H11*100,2))
A12: =IF(Properties!A12="","",Properties!A12) | B12: =IF(Properties!A12="","",Properties!B12) | C12: =IF(A12="","",SUMIFS('Rent Log'!$D$5:$D$304,'Rent Log'!$A$5:$A$304,A12,'Rent Log'!$C$5:$C$304,">="&DATE($B$2,1,1),'Rent Log'!$C$5:$C$304,"<"&DATE($B$2+1,1,1))) | D12: =IF(A12="","",SUMIFS('Rent Log'!$E$5:$E$304,'Rent Log'!$A$5:$A$304,A12,'Rent Log'!$C$5:$C$304,">="&DATE($B$2,1,1),'Rent Log'!$C$5:$C$304,"<"&DATE($B$2+1,1,1))) | E12: =IF(A12="","",SUMIFS('Rent Log'!$H$5:$H$304,'Rent Log'!$A$5:$A$304,A12)) | F12: =IF(A12="","",SUMIFS(Expenses!$E$5:$E$304,Expenses!$B$5:$B$304,A12,Expenses!$F$5:$F$304,$B$2)) | G12: =IF(A12="","",C12-F12) | H12: =IF(OR(A12="",Properties!H12=0,Properties!H12=""),"",ROUND(Properties!D12*12/Properties!H12*100,2)) | I12: =IF(OR(A12="",Properties!H12=0,Properties!H12=""),"",ROUND((Properties!D12*12-F12)/Properties!H12*100,2))
A13: =IF(Properties!A13="","",Properties!A13) | B13: =IF(Properties!A13="","",Properties!B13) | C13: =IF(A13="","",SUMIFS('Rent Log'!$D$5:$D$304,'Rent Log'!$A$5:$A$304,A13,'Rent Log'!$C$5:$C$304,">="&DATE($B$2,1,1),'Rent Log'!$C$5:$C$304,"<"&DATE($B$2+1,1,1))) | D13: =IF(A13="","",SUMIFS('Rent Log'!$E$5:$E$304,'Rent Log'!$A$5:$A$304,A13,'Rent Log'!$C$5:$C$304,">="&DATE($B$2,1,1),'Rent Log'!$C$5:$C$304,"<"&DATE($B$2+1,1,1))) | E13: =IF(A13="","",SUMIFS('Rent Log'!$H$5:$H$304,'Rent Log'!$A$5:$A$304,A13)) | F13: =IF(A13="","",SUMIFS(Expenses!$E$5:$E$304,Expenses!$B$5:$B$304,A13,Expenses!$F$5:$F$304,$B$2)) | G13: =IF(A13="","",C13-F13) | H13: =IF(OR(A13="",Properties!H13=0,Properties!H13=""),"",ROUND(Properties!D13*12/Properties!H13*100,2)) | I13: =IF(OR(A13="",Properties!H13=0,Properties!H13=""),"",ROUND((Properties!D13*12-F13)/Properties!H13*100,2))
A14: =IF(Properties!A14="","",Properties!A14) | B14: =IF(Properties!A14="","",Properties!B14) | C14: =IF(A14="","",SUMIFS('Rent Log'!$D$5:$D$304,'Rent Log'!$A$5:$A$304,A14,'Rent Log'!$C$5:$C$304,">="&DATE($B$2,1,1),'Rent Log'!$C$5:$C$304,"<"&DATE($B$2+1,1,1))) | D14: =IF(A14="","",SUMIFS('Rent Log'!$E$5:$E$304,'Rent Log'!$A$5:$A$304,A14,'Rent Log'!$C$5:$C$304,">="&DATE($B$2,1,1),'Rent Log'!$C$5:$C$304,"<"&DATE($B$2+1,1,1))) | E14: =IF(A14="","",SUMIFS('Rent Log'!$H$5:$H$304,'Rent Log'!$A$5:$A$304,A14)) | F14: =IF(A14="","",SUMIFS(Expenses!$E$5:$E$304,Expenses!$B$5:$B$304,A14,Expenses!$F$5:$F$304,$B$2)) | G14: =IF(A14="","",C14-F14) | H14: =IF(OR(A14="",Properties!H14=0,Properties!H14=""),"",ROUND(Properties!D14*12/Properties!H14*100,2)) | I14: =IF(OR(A14="",Properties!H14=0,Properties!H14=""),"",ROUND((Properties!D14*12-F14)/Properties!H14*100,2))
A16: Portfolio | C16: =SUM(C5:C14) -> 2400 | D16: =SUM(D5:D14) -> 1200 | E16: =SUM(E5:E14) -> 1200 | F16: =SUM(F5:F14) -> 95 | G16: =SUM(G5:G14) -> 2305 | H16: =IFERROR(ROUND(SUMPRODUCT(Properties!D5:D14)*12/SUM(Properties!H5:H14)*100,2),"") -> 7.2 | I16: =IFERROR(ROUND((SUMPRODUCT(Properties!D5:D14)*12-F16)/SUM(Properties!H5:H14)*100,2),"") -> 7.15
A18: Gross yield = annual rent due ÷ purchase price. Net yield deducts the expenses logged for the chosen year. Yields are blank until a purchase price is entered.
