Workbook

Sheet Start Here
A1: Agency Quote & Project Profit Tracker
A2: by Knackdesk · knackdesk.com
A4: HOW TO USE
A5: 1. Settings: productive hours per day and your default contingency and discount for quotes.
A6: 2. Rate Card: one row per role with the bill rate and the internal cost per hour (salary, contributions and overhead divided by productive hours). Margin and markup per role are calculated.
A7: 3. Quote: name the client and project, then list tasks with a role (pick from the list) and hours. Bill rate and cost rate are looked up from the Rate Card; labour, expenses, contingency and discount roll up into the quote total, blended rate, expected profit and margin. Copy the sheet for each new quote.
A8: 4. Projects: one row per project with price, estimated and actual hours, cost per hour, expenses, invoiced and paid. Profit, margin, effective hourly rate, hours overrun and outstanding balance are calculated.
A9: 5. Summary: totals and averages across every project row.
A11: LEGEND
A12: Blue text = a cell you type into. Black text = a formula, leave it alone. Yellow fill = key inputs.
A13: Blue cells that already contain a formula (defaults pulled from Settings) may be overwritten with your own figure.
A15: DEFINITIONS
... A19: Arithmetic only; not financial or legal advice. Support: hello@knackdesk.com

Sheet Settings
A1: Settings
A2: Productive hours per working day | B2: 8 | C2: Used to convert quoted hours into working days.
A3: Default contingency on quotes (%) | B3: 15 | C3: Allowance for scope the estimate missed; 10 to 20 is common.
A4: Default discount on quotes (%) | B4: 0 | C4: Applied after contingency; leave at 0 unless agreed.

Sheet Rate Card
A1: Rate Card
A2: One row per role. Cost per hour = salary + contributions + overhead ÷ productive hours (the Employee Cost Calculator on knackdesk.com gives this figure).
A4: Role | B4: Bill rate / hour | C4: Cost / hour | D4: Margin % | E4: Markup (bill ÷ cost)
A5: Lead / strategist | B5: 150 | C5: 70 | D5: =IF(A5="","",IFERROR(ROUND((B5-C5)/B5*100,2),"")) -> 53.33 | E5: =IF(A5="","",IFERROR(ROUND(B5/C5,2),"")) -> 2.14
A6: Designer | B6: 80 | C6: 40 | D6: =IF(A6="","",IFERROR(ROUND((B6-C6)/B6*100,2),"")) -> 50 | E6: =IF(A6="","",IFERROR(ROUND(B6/C6,2),"")) -> 2
A7: Developer | B7: 95 | C7: 50 | D7: =IF(A7="","",IFERROR(ROUND((B7-C7)/B7*100,2),"")) -> 47.37 | E7: =IF(A7="","",IFERROR(ROUND(B7/C7,2),"")) -> 1.9
A8: Project manager | B8: 85 | C8: 45 | D8: =IF(A8="","",IFERROR(ROUND((B8-C8)/B8*100,2),"")) -> 47.06 | E8: =IF(A8="","",IFERROR(ROUND(B8/C8,2),"")) -> 1.89
D9: =IF(A9="","",IFERROR(ROUND((B9-C9)/B9*100,2),"")) | E9: =IF(A9="","",IFERROR(ROUND(B9/C9,2),""))
D10: =IF(A10="","",IFERROR(ROUND((B10-C10)/B10*100,2),"")) | E10: =IF(A10="","",IFERROR(ROUND(B10/C10,2),""))
D11: =IF(A11="","",IFERROR(ROUND((B11-C11)/B11*100,2),"")) | E11: =IF(A11="","",IFERROR(ROUND(B11/C11,2),""))
D12: =IF(A12="","",IFERROR(ROUND((B12-C12)/B12*100,2),"")) | E12: =IF(A12="","",IFERROR(ROUND(B12/C12,2),""))
D13: =IF(A13="","",IFERROR(ROUND((B13-C13)/B13*100,2),"")) | E13: =IF(A13="","",IFERROR(ROUND(B13/C13,2),""))
D14: =IF(A14="","",IFERROR(ROUND((B14-C14)/B14*100,2),"")) | E14: =IF(A14="","",IFERROR(ROUND(B14/C14,2),""))

Sheet Quote
A1: Quote
A2: Client | B2: Example Ltd
A3: Project | B3: Website redesign
A5: Task | B5: Role | C5: Hours | D5: Bill rate | E5: Amount | F5: Cost rate | G5: Internal cost
A6: Discovery and strategy | B6: Lead / strategist | C6: 10 | D6: =IF(B6="","",IFERROR(INDEX('Rate Card'!$B$5:$B$14,MATCH(B6,'Rate Card'!$A$5:$A$14,0)),"")) -> 150 | E6: =IF(B6="","",IFERROR(ROUND(C6*D6,2),"")) -> 1500 | F6: =IF(B6="","",IFERROR(INDEX('Rate Card'!$C$5:$C$14,MATCH(B6,'Rate Card'!$A$5:$A$14,0)),"")) -> 70 | G6: =IF(B6="","",IFERROR(ROUND(C6*F6,2),"")) -> 700
A7: Design | B7: Designer | C7: 30 | D7: =IF(B7="","",IFERROR(INDEX('Rate Card'!$B$5:$B$14,MATCH(B7,'Rate Card'!$A$5:$A$14,0)),"")) -> 80 | E7: =IF(B7="","",IFERROR(ROUND(C7*D7,2),"")) -> 2400 | F7: =IF(B7="","",IFERROR(INDEX('Rate Card'!$C$5:$C$14,MATCH(B7,'Rate Card'!$A$5:$A$14,0)),"")) -> 40 | G7: =IF(B7="","",IFERROR(ROUND(C7*F7,2),"")) -> 1200
A8: Build | B8: Developer | C8: 40 | D8: =IF(B8="","",IFERROR(INDEX('Rate Card'!$B$5:$B$14,MATCH(B8,'Rate Card'!$A$5:$A$14,0)),"")) -> 95 | E8: =IF(B8="","",IFERROR(ROUND(C8*D8,2),"")) -> 3800 | F8: =IF(B8="","",IFERROR(INDEX('Rate Card'!$C$5:$C$14,MATCH(B8,'Rate Card'!$A$5:$A$14,0)),"")) -> 50 | G8: =IF(B8="","",IFERROR(ROUND(C8*F8,2),"")) -> 2000
A9: Project management | B9: Project manager | C9: 12 | D9: =IF(B9="","",IFERROR(INDEX('Rate Card'!$B$5:$B$14,MATCH(B9,'Rate Card'!$A$5:$A$14,0)),"")) -> 85 | E9: =IF(B9="","",IFERROR(ROUND(C9*D9,2),"")) -> 1020 | F9: =IF(B9="","",IFERROR(INDEX('Rate Card'!$C$5:$C$14,MATCH(B9,'Rate Card'!$A$5:$A$14,0)),"")) -> 45 | G9: =IF(B9="","",IFERROR(ROUND(C9*F9,2),"")) -> 540
D10: =IF(B10="","",IFERROR(INDEX('Rate Card'!$B$5:$B$14,MATCH(B10,'Rate Card'!$A$5:$A$14,0)),"")) | E10: =IF(B10="","",IFERROR(ROUND(C10*D10,2),"")) | F10: =IF(B10="","",IFERROR(INDEX('Rate Card'!$C$5:$C$14,MATCH(B10,'Rate Card'!$A$5:$A$14,0)),"")) | G10: =IF(B10="","",IFERROR(ROUND(C10*F10,2),""))
D11: =IF(B11="","",IFERROR(INDEX('Rate Card'!$B$5:$B$14,MATCH(B11,'Rate Card'!$A$5:$A$14,0)),"")) | E11: =IF(B11="","",IFERROR(ROUND(C11*D11,2),"")) | F11: =IF(B11="","",IFERROR(INDEX('Rate Card'!$C$5:$C$14,MATCH(B11,'Rate Card'!$A$5:$A$14,0)),"")) | G11: =IF(B11="","",IFERROR(ROUND(C11*F11,2),""))
D12: =IF(B12="","",IFERROR(INDEX('Rate Card'!$B$5:$B$14,MATCH(B12,'Rate Card'!$A$5:$A$14,0)),"")) | E12: =IF(B12="","",IFERROR(ROUND(C12*D12,2),"")) | F12: =IF(B12="","",IFERROR(INDEX('Rate Card'!$C$5:$C$14,MATCH(B12,'Rate Card'!$A$5:$A$14,0)),"")) | G12: =IF(B12="","",IFERROR(ROUND(C12*F12,2),""))
D13: =IF(B13="","",IFERROR(INDEX('Rate Card'!$B$5:$B$14,MATCH(B13,'Rate Card'!$A$5:$A$14,0)),"")) | E13: =IF(B13="","",IFERROR(ROUND(C13*D13,2),"")) | F13: =IF(B13="","",IFERROR(INDEX('Rate Card'!$C$5:$C$14,MATCH(B13,'Rate Card'!$A$5:$A$14,0)),"")) | G13: =IF(B13="","",IFERROR(ROUND(C13*F13,2),""))
D14: =IF(B14="","",IFERROR(INDEX('Rate Card'!$B$5:$B$14,MATCH(B14,'Rate Card'!$A$5:$A$14,0)),"")) | E14: =IF(B14="","",IFERROR(ROUND(C14*D14,2),"")) | F14: =IF(B14="","",IFERROR(INDEX('Rate Card'!$C$5:$C$14,MATCH(B14,'Rate Card'!$A$5:$A$14,0)),"")) | G14: =IF(B14="","",IFERROR(ROUND(C14*F14,2),""))
D15: =IF(B15="","",IFERROR(INDEX('Rate Card'!$B$5:$B$14,MATCH(B15,'Rate Card'!$A$5:$A$14,0)),"")) | E15: =IF(B15="","",IFERROR(ROUND(C15*D15,2),"")) | F15: =IF(B15="","",IFERROR(INDEX('Rate Card'!$C$5:$C$14,MATCH(B15,'Rate Card'!$A$5:$A$14,0)),"")) | G15: =IF(B15="","",IFERROR(ROUND(C15*F15,2),""))
D16: =IF(B16="","",IFERROR(INDEX('Rate Card'!$B$5:$B$14,MATCH(B16,'Rate Card'!$A$5:$A$14,0)),"")) | E16: =IF(B16="","",IFERROR(ROUND(C16*D16,2),"")) | F16: =IF(B16="","",IFERROR(INDEX('Rate Card'!$C$5:$C$14,MATCH(B16,'Rate Card'!$A$5:$A$14,0)),"")) | G16: =IF(B16="","",IFERROR(ROUND(C16*F16,2),""))
D17: =IF(B17="","",IFERROR(INDEX('Rate Card'!$B$5:$B$14,MATCH(B17,'Rate Card'!$A$5:$A$14,0)),"")) | E17: =IF(B17="","",IFERROR(ROUND(C17*D17,2),"")) | F17: =IF(B17="","",IFERROR(INDEX('Rate Card'!$C$5:$C$14,MATCH(B17,'Rate Card'!$A$5:$A$14,0)),"")) | G17: =IF(B17="","",IFERROR(ROUND(C17*F17,2),""))
D18: =IF(B18="","",IFERROR(INDEX('Rate Card'!$B$5:$B$14,MATCH(B18,'Rate Card'!$A$5:$A$14,0)),"")) | E18: =IF(B18="","",IFERROR(ROUND(C18*D18,2),"")) | F18: =IF(B18="","",IFERROR(INDEX('Rate Card'!$C$5:$C$14,MATCH(B18,'Rate Card'!$A$5:$A$14,0)),"")) | G18: =IF(B18="","",IFERROR(ROUND(C18*F18,2),""))
D19: =IF(B19="","",IFERROR(INDEX('Rate Card'!$B$5:$B$14,MATCH(B19,'Rate Card'!$A$5:$A$14,0)),"")) | E19: =IF(B19="","",IFERROR(ROUND(C19*D19,2),"")) | F19: =IF(B19="","",IFERROR(INDEX('Rate Card'!$C$5:$C$14,MATCH(B19,'Rate Card'!$A$5:$A$14,0)),"")) | G19: =IF(B19="","",IFERROR(ROUND(C19*F19,2),""))
D20: =IF(B20="","",IFERROR(INDEX('Rate Card'!$B$5:$B$14,MATCH(B20,'Rate Card'!$A$5:$A$14,0)),"")) | E20: =IF(B20="","",IFERROR(ROUND(C20*D20,2),"")) | F20: =IF(B20="","",IFERROR(INDEX('Rate Card'!$C$5:$C$14,MATCH(B20,'Rate Card'!$A$5:$A$14,0)),"")) | G20: =IF(B20="","",IFERROR(ROUND(C20*F20,2),""))
D21: =IF(B21="","",IFERROR(INDEX('Rate Card'!$B$5:$B$14,MATCH(B21,'Rate Card'!$A$5:$A$14,0)),"")) | E21: =IF(B21="","",IFERROR(ROUND(C21*D21,2),"")) | F21: =IF(B21="","",IFERROR(INDEX('Rate Card'!$C$5:$C$14,MATCH(B21,'Rate Card'!$A$5:$A$14,0)),"")) | G21: =IF(B21="","",IFERROR(ROUND(C21*F21,2),""))
... D25: =IF(B25="","",IFERROR(INDEX('Rate Card'!$B$5:$B$14,MATCH(B25,'Rate Card'!$A$5:$A$14,0)),"")) | E25: =IF(B25="","",IFERROR(ROUND(C25*D25,2),"")) | F25: =IF(B25="","",IFERROR(INDEX('Rate Card'!$C$5:$C$14,MATCH(B25,'Rate Card'!$A$5:$A$14,0)),"")) | G25: =IF(B25="","",IFERROR(ROUND(C25*F25,2),""))
A26: Totals | C26: =SUM(C6:C25) -> 92 | E26: =SUM(E6:E25) -> 8720 | G26: =SUM(G6:G25) -> 4440
A28: Expenses passed through | B28: 500
A29: Contingency (%) | B29: =Settings!$B$3 -> 15
A30: Discount (%) | B30: =Settings!$B$4 -> 0
A32: Labour at bill rates | B32: =E26 -> 8720
A33: Expenses | B33: =B28 -> 500
A34: Subtotal | B34: =B32+B33 -> 9220
A35: Contingency | B35: =ROUND(B34*B29/100,2) -> 1383
A36: Before discount | B36: =B34+B35 -> 10603
A37: Discount | B37: =ROUND(B36*B30/100,2) -> 0
A38: QUOTE TOTAL | B38: =B36-B37 -> 10603
A39: Blended hourly rate | B39: =IFERROR(ROUND(E26/C26,2),"") -> 94.78
A40: Expected internal cost | B40: =G26+B33 -> 4940
A41: Expected profit | B41: =B38-B40 -> 5663
A42: Expected margin % | B42: =IFERROR(ROUND(B41/B38*100,2),"") -> 53.41
A43: Working days of effort | B43: =IFERROR(ROUND(C26/Settings!$B$2,1),"") -> 11.5

Sheet Projects
A1: Projects
A2: One row per project. Enter actual hours as they are logged; profit and overrun update. Cost per hour = blended internal cost of the people on the job.
A4: Client | B4: Project | C4: Status | D4: Price | E4: Estimated hours | F4: Actual hours | G4: Cost / hour | H4: Expenses | I4: Labour cost | J4: Total cost | K4: Profit | L4: Margin % | M4: Effective rate / hour | N4: Hours overrun % | O4: Invoiced | P4: Paid | Q4: Outstanding
A5: Example Ltd | B5: Website redesign | C5: done | D5: 10000 | E5: 92 | F5: 80 | G5: 55 | H5: 500 | I5: =IF(A5="","",ROUND(F5*G5,2)) -> 4400 | J5: =IF(A5="","",I5+H5) -> 4900 | K5: =IF(A5="","",D5-J5) -> 5100 | L5: =IF(A5="","",IFERROR(ROUND(K5/D5*100,2),"")) -> 51 | M5: =IF(A5="","",IFERROR(ROUND(D5/F5,2),"")) -> 125 | N5: =IF(A5="","",IFERROR(ROUND((F5-E5)/E5*100,2),"")) -> -13.04 | O5: 10000 | P5: 10000 | Q5: =IF(A5="","",O5-P5) -> 0
A6: Sample Co | B6: Brand identity | C6: done | D6: 6500 | E6: 60 | F6: 74 | G6: 48 | H6: 200 | I6: =IF(A6="","",ROUND(F6*G6,2)) -> 3552 | J6: =IF(A6="","",I6+H6) -> 3752 | K6: =IF(A6="","",D6-J6) -> 2748 | L6: =IF(A6="","",IFERROR(ROUND(K6/D6*100,2),"")) -> 42.28 | M6: =IF(A6="","",IFERROR(ROUND(D6/F6,2),"")) -> 87.84 | N6: =IF(A6="","",IFERROR(ROUND((F6-E6)/E6*100,2),"")) -> 23.33 | O6: 6500 | P6: 3250 | Q6: =IF(A6="","",O6-P6) -> 3250
A7: Demo Inc | B7: Monthly retainer (Sep) | C7: active | D7: 4000 | E7: 40 | F7: 22 | G7: 50 | H7: 0 | I7: =IF(A7="","",ROUND(F7*G7,2)) -> 1100 | J7: =IF(A7="","",I7+H7) -> 1100 | K7: =IF(A7="","",D7-J7) -> 2900 | L7: =IF(A7="","",IFERROR(ROUND(K7/D7*100,2),"")) -> 72.5 | M7: =IF(A7="","",IFERROR(ROUND(D7/F7,2),"")) -> 181.82 | N7: =IF(A7="","",IFERROR(ROUND((F7-E7)/E7*100,2),"")) -> -45 | O7: 4000 | P7: 0 | Q7: =IF(A7="","",O7-P7) -> 4000
I8: =IF(A8="","",ROUND(F8*G8,2)) | J8: =IF(A8="","",I8+H8) | K8: =IF(A8="","",D8-J8) | L8: =IF(A8="","",IFERROR(ROUND(K8/D8*100,2),"")) | M8: =IF(A8="","",IFERROR(ROUND(D8/F8,2),"")) | N8: =IF(A8="","",IFERROR(ROUND((F8-E8)/E8*100,2),"")) | Q8: =IF(A8="","",O8-P8)
I9: =IF(A9="","",ROUND(F9*G9,2)) | J9: =IF(A9="","",I9+H9) | K9: =IF(A9="","",D9-J9) | L9: =IF(A9="","",IFERROR(ROUND(K9/D9*100,2),"")) | M9: =IF(A9="","",IFERROR(ROUND(D9/F9,2),"")) | N9: =IF(A9="","",IFERROR(ROUND((F9-E9)/E9*100,2),"")) | Q9: =IF(A9="","",O9-P9)
I10: =IF(A10="","",ROUND(F10*G10,2)) | J10: =IF(A10="","",I10+H10) | K10: =IF(A10="","",D10-J10) | L10: =IF(A10="","",IFERROR(ROUND(K10/D10*100,2),"")) | M10: =IF(A10="","",IFERROR(ROUND(D10/F10,2),"")) | N10: =IF(A10="","",IFERROR(ROUND((F10-E10)/E10*100,2),"")) | Q10: =IF(A10="","",O10-P10)
I11: =IF(A11="","",ROUND(F11*G11,2)) | J11: =IF(A11="","",I11+H11) | K11: =IF(A11="","",D11-J11) | L11: =IF(A11="","",IFERROR(ROUND(K11/D11*100,2),"")) | M11: =IF(A11="","",IFERROR(ROUND(D11/F11,2),"")) | N11: =IF(A11="","",IFERROR(ROUND((F11-E11)/E11*100,2),"")) | Q11: =IF(A11="","",O11-P11)
I12: =IF(A12="","",ROUND(F12*G12,2)) | J12: =IF(A12="","",I12+H12) | K12: =IF(A12="","",D12-J12) | L12: =IF(A12="","",IFERROR(ROUND(K12/D12*100,2),"")) | M12: =IF(A12="","",IFERROR(ROUND(D12/F12,2),"")) | N12: =IF(A12="","",IFERROR(ROUND((F12-E12)/E12*100,2),"")) | Q12: =IF(A12="","",O12-P12)
I13: =IF(A13="","",ROUND(F13*G13,2)) | J13: =IF(A13="","",I13+H13) | K13: =IF(A13="","",D13-J13) | L13: =IF(A13="","",IFERROR(ROUND(K13/D13*100,2),"")) | M13: =IF(A13="","",IFERROR(ROUND(D13/F13,2),"")) | N13: =IF(A13="","",IFERROR(ROUND((F13-E13)/E13*100,2),"")) | Q13: =IF(A13="","",O13-P13)
I14: =IF(A14="","",ROUND(F14*G14,2)) | J14: =IF(A14="","",I14+H14) | K14: =IF(A14="","",D14-J14) | L14: =IF(A14="","",IFERROR(ROUND(K14/D14*100,2),"")) | M14: =IF(A14="","",IFERROR(ROUND(D14/F14,2),"")) | N14: =IF(A14="","",IFERROR(ROUND((F14-E14)/E14*100,2),"")) | Q14: =IF(A14="","",O14-P14)
I15: =IF(A15="","",ROUND(F15*G15,2)) | J15: =IF(A15="","",I15+H15) | K15: =IF(A15="","",D15-J15) | L15: =IF(A15="","",IFERROR(ROUND(K15/D15*100,2),"")) | M15: =IF(A15="","",IFERROR(ROUND(D15/F15,2),"")) | N15: =IF(A15="","",IFERROR(ROUND((F15-E15)/E15*100,2),"")) | Q15: =IF(A15="","",O15-P15)
I16: =IF(A16="","",ROUND(F16*G16,2)) | J16: =IF(A16="","",I16+H16) | K16: =IF(A16="","",D16-J16) | L16: =IF(A16="","",IFERROR(ROUND(K16/D16*100,2),"")) | M16: =IF(A16="","",IFERROR(ROUND(D16/F16,2),"")) | N16: =IF(A16="","",IFERROR(ROUND((F16-E16)/E16*100,2),"")) | Q16: =IF(A16="","",O16-P16)
I17: =IF(A17="","",ROUND(F17*G17,2)) | J17: =IF(A17="","",I17+H17) | K17: =IF(A17="","",D17-J17) | L17: =IF(A17="","",IFERROR(ROUND(K17/D17*100,2),"")) | M17: =IF(A17="","",IFERROR(ROUND(D17/F17,2),"")) | N17: =IF(A17="","",IFERROR(ROUND((F17-E17)/E17*100,2),"")) | Q17: =IF(A17="","",O17-P17)
I18: =IF(A18="","",ROUND(F18*G18,2)) | J18: =IF(A18="","",I18+H18) | K18: =IF(A18="","",D18-J18) | L18: =IF(A18="","",IFERROR(ROUND(K18/D18*100,2),"")) | M18: =IF(A18="","",IFERROR(ROUND(D18/F18,2),"")) | N18: =IF(A18="","",IFERROR(ROUND((F18-E18)/E18*100,2),"")) | Q18: =IF(A18="","",O18-P18)
I19: =IF(A19="","",ROUND(F19*G19,2)) | J19: =IF(A19="","",I19+H19) | K19: =IF(A19="","",D19-J19) | L19: =IF(A19="","",IFERROR(ROUND(K19/D19*100,2),"")) | M19: =IF(A19="","",IFERROR(ROUND(D19/F19,2),"")) | N19: =IF(A19="","",IFERROR(ROUND((F19-E19)/E19*100,2),"")) | Q19: =IF(A19="","",O19-P19)
... I40: =IF(A40="","",ROUND(F40*G40,2)) | J40: =IF(A40="","",I40+H40) | K40: =IF(A40="","",D40-J40) | L40: =IF(A40="","",IFERROR(ROUND(K40/D40*100,2),"")) | M40: =IF(A40="","",IFERROR(ROUND(D40/F40,2),"")) | N40: =IF(A40="","",IFERROR(ROUND((F40-E40)/E40*100,2),"")) | Q40: =IF(A40="","",O40-P40)
A41: Totals | D41: =SUM(D5:D40) -> 20500 | F41: =SUM(F5:F40) -> 176 | H41: =SUM(H5:H40) -> 700 | I41: =SUM(I5:I40) -> 9052 | J41: =SUM(J5:J40) -> 9752 | K41: =SUM(K5:K40) -> 10748 | L41: =IFERROR(ROUND(K41/D41*100,2),"") -> 52.43 | O41: =SUM(O5:O40) -> 20500 | P41: =SUM(P5:P40) -> 13250 | Q41: =SUM(Q5:Q40) -> 7250

Sheet Summary
A1: Summary
A2: Projects tracked | B2: =COUNTA(Projects!A5:A40) -> 3
A3: Revenue (sum of prices) | B3: =Projects!D41 -> 20500
A4: Total cost | B4: =Projects!J41 -> 9752 | C4: labour at cost rates plus expenses
A5: Profit | B5: =Projects!K41 -> 10748
A6: Overall margin % | B6: =IFERROR(ROUND(B5/B3*100,2),"") -> 52.43 | C6: profit ÷ revenue
A7: Hours worked | B7: =Projects!F41 -> 176
A8: Average effective rate per hour | B8: =IFERROR(ROUND(B3/B7,2),"") -> 116.48 | C8: revenue ÷ hours
A9: Invoiced | B9: =Projects!O41 -> 20500
A10: Paid | B10: =Projects!P41 -> 13250
A11: Outstanding | B11: =Projects!Q41 -> 7250
A12: Projects that overran their estimate | B12: =COUNTIF(Projects!N5:N40,">0") -> 1
A13: Average hours overrun % | B13: =IFERROR(ROUND(AVERAGE(Projects!N5:N40),2),"") -> -11.57 | C13: across projects with hours entered
