Workbook

Sheet Start Here
A1: Freelancer Finance Kit
A2: by Knackdesk · knackdesk.com
A4: HOW TO USE
A5: 1. Settings: fill in the yellow cells once (your business name, default payment terms, late fee rate, hours and income goal).
A6: 2. Invoices: add one row per invoice. Due date, days overdue, late fee and status are calculated for you.
A7: 3. Rate Calculator: reads Settings and shows the hourly and day rate you need. Change Settings to explore.
A8: 4. Payment Schedule: enter a project total, deposit %, number of milestones and dates to get a payment plan.
A9: 5. Expenses: log costs with a date and category.
A10: 6. Summary: pick a start month and see invoiced, paid, expenses and net by month and quarter.
A12: LEGEND
A13: Blue text = a cell you type into. Black text = a formula, leave it alone. Yellow fill = key inputs to set first.
A14: Each table has one example row showing the expected format. Overwrite it with your own data.
... A20: Support: hello@knackdesk.com

Sheet Settings
A1: Settings
A2: Business name | B2: Your Studio | C2: Shown nowhere else; for your reference.
A3: Currency label | B3: USD | C3: Text only; the kit does not convert currencies.
A4: Default payment terms (days) | B4: 30 | C4: Used when an invoice row leaves Terms blank. Net 30 = 30.
A5: Late fee (% per month) | B5: 1.5 | C5: Prorated by day. Use the rate in your contract; check local caps.
A6: Hours in a billable day | B6: 8
A7: Weeks off per year | B7: 6 | C7: Holiday, sick days, public holidays, gaps between projects.
A8: Hours worked per week | B8: 40
A9: Billable share of hours (%) | B9: 60 | C9: Most solo freelancers bill 50-70% of their hours.
A10: Target income per year | B10: 60000 | C10: What you want to keep after business expenses.
A11: Business expenses per year | B11: 6000 | C11: Software, insurance, equipment, accountant, training.
A12: Tax rate to gross up for (%) | B12: 0 | C12: Leave 0 if the target income is pre-tax.
A13: Today (auto) | B13: =TODAY() -> 46295 | C13: Recalculates each time the file opens; drives days overdue.

Sheet Invoices
A1: Invoices
A2: Outstanding | B2: =SUMIFS(D5:D104,J5:J104,"Open")+SUMIFS(D5:D104,J5:J104,"Overdue") -> 1500 | C2: Overdue | D2: =SUMIFS(D5:D104,J5:J104,"Overdue") -> 1500 | E2: Late fees accrued | F2: =SUM(I5:I104) -> 11.25 | G2: Paid to date | H2: =SUMIFS(D5:D104,J5:J104,"Paid") -> 0
A4: Invoice # | B4: Client | C4: Issue date | D4: Amount | E4: Terms (days) | F4: Due date | G4: Paid date | H4: Days overdue | I4: Late fee | J4: Status | K4: Total due
A5: INV-001 | B5: Example Client Ltd | C5: 46250 | D5: 1500 | E5: 30 | F5: =IF(C5="","",C5+IF(E5="",Settings!$B$4,E5)) -> 46280 | H5: =IF(OR(C5="",G5<>""),0,MAX(0,Settings!$B$13-F5)) -> 15 | I5: =IF(H5>0,ROUND(D5*Settings!$B$5/100*H5/30,2),0) -> 11.25 | J5: =IF(C5="","",IF(G5<>"","Paid",IF(H5>0,"Overdue","Open"))) -> Overdue | K5: =IF(C5="","",D5+I5) -> 1511.25
F6: =IF(C6="","",C6+IF(E6="",Settings!$B$4,E6)) | H6: =IF(OR(C6="",G6<>""),0,MAX(0,Settings!$B$13-F6)) -> 0 | I6: =IF(H6>0,ROUND(D6*Settings!$B$5/100*H6/30,2),0) -> 0 | J6: =IF(C6="","",IF(G6<>"","Paid",IF(H6>0,"Overdue","Open"))) | K6: =IF(C6="","",D6+I6)
F7: =IF(C7="","",C7+IF(E7="",Settings!$B$4,E7)) | H7: =IF(OR(C7="",G7<>""),0,MAX(0,Settings!$B$13-F7)) -> 0 | I7: =IF(H7>0,ROUND(D7*Settings!$B$5/100*H7/30,2),0) -> 0 | J7: =IF(C7="","",IF(G7<>"","Paid",IF(H7>0,"Overdue","Open"))) | K7: =IF(C7="","",D7+I7)
F8: =IF(C8="","",C8+IF(E8="",Settings!$B$4,E8)) | H8: =IF(OR(C8="",G8<>""),0,MAX(0,Settings!$B$13-F8)) -> 0 | I8: =IF(H8>0,ROUND(D8*Settings!$B$5/100*H8/30,2),0) -> 0 | J8: =IF(C8="","",IF(G8<>"","Paid",IF(H8>0,"Overdue","Open"))) | K8: =IF(C8="","",D8+I8)
F9: =IF(C9="","",C9+IF(E9="",Settings!$B$4,E9)) | H9: =IF(OR(C9="",G9<>""),0,MAX(0,Settings!$B$13-F9)) -> 0 | I9: =IF(H9>0,ROUND(D9*Settings!$B$5/100*H9/30,2),0) -> 0 | J9: =IF(C9="","",IF(G9<>"","Paid",IF(H9>0,"Overdue","Open"))) | K9: =IF(C9="","",D9+I9)
F10: =IF(C10="","",C10+IF(E10="",Settings!$B$4,E10)) | H10: =IF(OR(C10="",G10<>""),0,MAX(0,Settings!$B$13-F10)) -> 0 | I10: =IF(H10>0,ROUND(D10*Settings!$B$5/100*H10/30,2),0) -> 0 | J10: =IF(C10="","",IF(G10<>"","Paid",IF(H10>0,"Overdue","Open"))) | K10: =IF(C10="","",D10+I10)
F11: =IF(C11="","",C11+IF(E11="",Settings!$B$4,E11)) | H11: =IF(OR(C11="",G11<>""),0,MAX(0,Settings!$B$13-F11)) -> 0 | I11: =IF(H11>0,ROUND(D11*Settings!$B$5/100*H11/30,2),0) -> 0 | J11: =IF(C11="","",IF(G11<>"","Paid",IF(H11>0,"Overdue","Open"))) | K11: =IF(C11="","",D11+I11)
F12: =IF(C12="","",C12+IF(E12="",Settings!$B$4,E12)) | H12: =IF(OR(C12="",G12<>""),0,MAX(0,Settings!$B$13-F12)) -> 0 | I12: =IF(H12>0,ROUND(D12*Settings!$B$5/100*H12/30,2),0) -> 0 | J12: =IF(C12="","",IF(G12<>"","Paid",IF(H12>0,"Overdue","Open"))) | K12: =IF(C12="","",D12+I12)
F13: =IF(C13="","",C13+IF(E13="",Settings!$B$4,E13)) | H13: =IF(OR(C13="",G13<>""),0,MAX(0,Settings!$B$13-F13)) -> 0 | I13: =IF(H13>0,ROUND(D13*Settings!$B$5/100*H13/30,2),0) -> 0 | J13: =IF(C13="","",IF(G13<>"","Paid",IF(H13>0,"Overdue","Open"))) | K13: =IF(C13="","",D13+I13)
F14: =IF(C14="","",C14+IF(E14="",Settings!$B$4,E14)) | H14: =IF(OR(C14="",G14<>""),0,MAX(0,Settings!$B$13-F14)) -> 0 | I14: =IF(H14>0,ROUND(D14*Settings!$B$5/100*H14/30,2),0) -> 0 | J14: =IF(C14="","",IF(G14<>"","Paid",IF(H14>0,"Overdue","Open"))) | K14: =IF(C14="","",D14+I14)
F15: =IF(C15="","",C15+IF(E15="",Settings!$B$4,E15)) | H15: =IF(OR(C15="",G15<>""),0,MAX(0,Settings!$B$13-F15)) -> 0 | I15: =IF(H15>0,ROUND(D15*Settings!$B$5/100*H15/30,2),0) -> 0 | J15: =IF(C15="","",IF(G15<>"","Paid",IF(H15>0,"Overdue","Open"))) | K15: =IF(C15="","",D15+I15)
F16: =IF(C16="","",C16+IF(E16="",Settings!$B$4,E16)) | H16: =IF(OR(C16="",G16<>""),0,MAX(0,Settings!$B$13-F16)) -> 0 | I16: =IF(H16>0,ROUND(D16*Settings!$B$5/100*H16/30,2),0) -> 0 | J16: =IF(C16="","",IF(G16<>"","Paid",IF(H16>0,"Overdue","Open"))) | K16: =IF(C16="","",D16+I16)
F17: =IF(C17="","",C17+IF(E17="",Settings!$B$4,E17)) | H17: =IF(OR(C17="",G17<>""),0,MAX(0,Settings!$B$13-F17)) -> 0 | I17: =IF(H17>0,ROUND(D17*Settings!$B$5/100*H17/30,2),0) -> 0 | J17: =IF(C17="","",IF(G17<>"","Paid",IF(H17>0,"Overdue","Open"))) | K17: =IF(C17="","",D17+I17)
... F104: =IF(C104="","",C104+IF(E104="",Settings!$B$4,E104)) | H104: =IF(OR(C104="",G104<>""),0,MAX(0,Settings!$B$13-F104)) -> 0 | I104: =IF(H104>0,ROUND(D104*Settings!$B$5/100*H104/30,2),0) -> 0 | J104: =IF(C104="","",IF(G104<>"","Paid",IF(H104>0,"Overdue","Open"))) | K104: =IF(C104="","",D104+I104)

Sheet Rate Calculator
A1: Rate Calculator
A2: All inputs live on the Settings sheet.
A4: Working weeks | B4: =52-Settings!B7 -> 46 | C4: 52 minus weeks off
A5: Hours available | B5: =B4*Settings!B8 -> 1840 | C5: working weeks × hours per week
A6: Billable hours | B6: =ROUND(B5*Settings!B9/100,2) -> 1104 | C6: hours available × billable share
A7: Revenue needed | B7: =Settings!B11+Settings!B10/(1-Settings!B12/100) -> 66000 | C7: expenses + income grossed up for tax
A8: Hourly rate needed | B8: =IFERROR(ROUND(B7/B6,2),"check inputs") -> 59.78 | C8: revenue needed ÷ billable hours
A9: Day rate needed | B9: =IFERROR(ROUND(B8*Settings!B6,2),"check inputs") -> 478.24 | C9: hourly × hours in a billable day

Sheet Payment Schedule
A1: Payment Schedule
A2: Project total | B2: 5000
A3: Deposit (%) | B3: 30
A4: Number of milestones (1-6) | B4: 2
A5: Start date | B5: 46295
A6: Project length (weeks) | B6: 8
A8: Payment | B8: Due date | C8: Amount | D8: Note
A9: Deposit | B9: =$B$5 -> 46295 | C9: =ROUND($B$2*$B$3/100,2) -> 1500 | D9: Due before work starts.
A10: =IF(1>$B$4,"","Milestone 1") -> Milestone 1 | B10: =IF(1>$B$4,"",$B$5+ROUND($B$6*7*1/$B$4,0)) -> 46323 | C10: =IF(1>$B$4,"",IF(1<$B$4,ROUNDDOWN(($B$2-$C$9)/$B$4,2),$B$2-$C$9)) -> 1750 | D10: =IF(1>$B$4,"","Invoice when the milestone deliverable is presented.") -> Invoice when the milestone deliverable is presented.
A11: =IF(2>$B$4,"","Milestone 2") -> Milestone 2 | B11: =IF(2>$B$4,"",$B$5+ROUND($B$6*7*2/$B$4,0)) -> 46351 | C11: =IF(2>$B$4,"",IF(2<$B$4,ROUNDDOWN(($B$2-$C$9)/$B$4,2),($B$2-$C$9)-SUM($C$10:C10))) -> 1750 | D11: =IF(2>$B$4,"","Invoice when the milestone deliverable is presented.") -> Invoice when the milestone deliverable is presented.
A12: =IF(3>$B$4,"","Milestone 3") | B12: =IF(3>$B$4,"",$B$5+ROUND($B$6*7*3/$B$4,0)) | C12: =IF(3>$B$4,"",IF(3<$B$4,ROUNDDOWN(($B$2-$C$9)/$B$4,2),($B$2-$C$9)-SUM($C$10:C11))) | D12: =IF(3>$B$4,"","Invoice when the milestone deliverable is presented.")
A13: =IF(4>$B$4,"","Milestone 4") | B13: =IF(4>$B$4,"",$B$5+ROUND($B$6*7*4/$B$4,0)) | C13: =IF(4>$B$4,"",IF(4<$B$4,ROUNDDOWN(($B$2-$C$9)/$B$4,2),($B$2-$C$9)-SUM($C$10:C12))) | D13: =IF(4>$B$4,"","Invoice when the milestone deliverable is presented.")
A14: =IF(5>$B$4,"","Milestone 5") | B14: =IF(5>$B$4,"",$B$5+ROUND($B$6*7*5/$B$4,0)) | C14: =IF(5>$B$4,"",IF(5<$B$4,ROUNDDOWN(($B$2-$C$9)/$B$4,2),($B$2-$C$9)-SUM($C$10:C13))) | D14: =IF(5>$B$4,"","Invoice when the milestone deliverable is presented.")
A15: =IF(6>$B$4,"","Milestone 6") | B15: =IF(6>$B$4,"",$B$5+ROUND($B$6*7*6/$B$4,0)) | C15: =IF(6>$B$4,"",IF(6<$B$4,ROUNDDOWN(($B$2-$C$9)/$B$4,2),($B$2-$C$9)-SUM($C$10:C14))) | D15: =IF(6>$B$4,"","Invoice when the milestone deliverable is presented.")
A16: Total | C16: =SUM(C9:C15) -> 5000 | D16: Should equal the project total. The last milestone absorbs cent rounding.

Sheet Expenses
A1: Expenses
A2: Total | B2: =SUM(D5:D204) -> 24
A4: Date | B4: Category | C4: Description | D4: Amount | E4: Month
A5: 46285 | B5: Software | C5: Example: design tool subscription | D5: 24 | E5: =IF(A5="","",TEXT(A5,"yyyy-mm")) -> 2026-09
E6: =IF(A6="","",TEXT(A6,"yyyy-mm"))
E7: =IF(A7="","",TEXT(A7,"yyyy-mm"))
E8: =IF(A8="","",TEXT(A8,"yyyy-mm"))
E9: =IF(A9="","",TEXT(A9,"yyyy-mm"))
E10: =IF(A10="","",TEXT(A10,"yyyy-mm"))
E11: =IF(A11="","",TEXT(A11,"yyyy-mm"))
E12: =IF(A12="","",TEXT(A12,"yyyy-mm"))
E13: =IF(A13="","",TEXT(A13,"yyyy-mm"))
E14: =IF(A14="","",TEXT(A14,"yyyy-mm"))
E15: =IF(A15="","",TEXT(A15,"yyyy-mm"))
E16: =IF(A16="","",TEXT(A16,"yyyy-mm"))
E17: =IF(A17="","",TEXT(A17,"yyyy-mm"))
... E204: =IF(A204="","",TEXT(A204,"yyyy-mm"))

Sheet Summary
A1: Summary
A2: Start month | B2: 46266
G4: Quarter | H4: Net
A5: =EDATE($B$2,0) -> 46266 | B5: =SUMIFS(Invoices!$D$5:$D$104,Invoices!$C$5:$C$104,">="&A5,Invoices!$C$5:$C$104,"<"&EDATE(A5,1)) -> 0 | C5: =SUMIFS(Invoices!$D$5:$D$104,Invoices!$G$5:$G$104,">="&A5,Invoices!$G$5:$G$104,"<"&EDATE(A5,1)) -> 0 | D5: =SUMIFS(Expenses!$D$5:$D$204,Expenses!$A$5:$A$204,">="&A5,Expenses!$A$5:$A$204,"<"&EDATE(A5,1)) -> 24 | E5: =C5-D5 -> -24 | G5: ="Q"&1 -> Q1 | H5: =SUM(E5:E7) -> -24
A6: =EDATE($B$2,1) -> 46296 | B6: =SUMIFS(Invoices!$D$5:$D$104,Invoices!$C$5:$C$104,">="&A6,Invoices!$C$5:$C$104,"<"&EDATE(A6,1)) -> 0 | C6: =SUMIFS(Invoices!$D$5:$D$104,Invoices!$G$5:$G$104,">="&A6,Invoices!$G$5:$G$104,"<"&EDATE(A6,1)) -> 0 | D6: =SUMIFS(Expenses!$D$5:$D$204,Expenses!$A$5:$A$204,">="&A6,Expenses!$A$5:$A$204,"<"&EDATE(A6,1)) -> 0 | E6: =C6-D6 -> 0 | G6: ="Q"&2 -> Q2 | H6: =SUM(E8:E10) -> 0
A7: =EDATE($B$2,2) -> 46327 | B7: =SUMIFS(Invoices!$D$5:$D$104,Invoices!$C$5:$C$104,">="&A7,Invoices!$C$5:$C$104,"<"&EDATE(A7,1)) -> 0 | C7: =SUMIFS(Invoices!$D$5:$D$104,Invoices!$G$5:$G$104,">="&A7,Invoices!$G$5:$G$104,"<"&EDATE(A7,1)) -> 0 | D7: =SUMIFS(Expenses!$D$5:$D$204,Expenses!$A$5:$A$204,">="&A7,Expenses!$A$5:$A$204,"<"&EDATE(A7,1)) -> 0 | E7: =C7-D7 -> 0 | G7: ="Q"&3 -> Q3 | H7: =SUM(E11:E13) -> 0
A8: =EDATE($B$2,3) -> 46357 | B8: =SUMIFS(Invoices!$D$5:$D$104,Invoices!$C$5:$C$104,">="&A8,Invoices!$C$5:$C$104,"<"&EDATE(A8,1)) -> 0 | C8: =SUMIFS(Invoices!$D$5:$D$104,Invoices!$G$5:$G$104,">="&A8,Invoices!$G$5:$G$104,"<"&EDATE(A8,1)) -> 0 | D8: =SUMIFS(Expenses!$D$5:$D$204,Expenses!$A$5:$A$204,">="&A8,Expenses!$A$5:$A$204,"<"&EDATE(A8,1)) -> 0 | E8: =C8-D8 -> 0 | G8: ="Q"&4 -> Q4 | H8: =SUM(E14:E16) -> 0
A9: =EDATE($B$2,4) -> 46388 | B9: =SUMIFS(Invoices!$D$5:$D$104,Invoices!$C$5:$C$104,">="&A9,Invoices!$C$5:$C$104,"<"&EDATE(A9,1)) -> 0 | C9: =SUMIFS(Invoices!$D$5:$D$104,Invoices!$G$5:$G$104,">="&A9,Invoices!$G$5:$G$104,"<"&EDATE(A9,1)) -> 0 | D9: =SUMIFS(Expenses!$D$5:$D$204,Expenses!$A$5:$A$204,">="&A9,Expenses!$A$5:$A$204,"<"&EDATE(A9,1)) -> 0 | E9: =C9-D9 -> 0
A10: =EDATE($B$2,5) -> 46419 | B10: =SUMIFS(Invoices!$D$5:$D$104,Invoices!$C$5:$C$104,">="&A10,Invoices!$C$5:$C$104,"<"&EDATE(A10,1)) -> 0 | C10: =SUMIFS(Invoices!$D$5:$D$104,Invoices!$G$5:$G$104,">="&A10,Invoices!$G$5:$G$104,"<"&EDATE(A10,1)) -> 0 | D10: =SUMIFS(Expenses!$D$5:$D$204,Expenses!$A$5:$A$204,">="&A10,Expenses!$A$5:$A$204,"<"&EDATE(A10,1)) -> 0 | E10: =C10-D10 -> 0 | G10: Outstanding now | H10: =Invoices!B2 -> 1500
A11: =EDATE($B$2,6) -> 46447 | B11: =SUMIFS(Invoices!$D$5:$D$104,Invoices!$C$5:$C$104,">="&A11,Invoices!$C$5:$C$104,"<"&EDATE(A11,1)) -> 0 | C11: =SUMIFS(Invoices!$D$5:$D$104,Invoices!$G$5:$G$104,">="&A11,Invoices!$G$5:$G$104,"<"&EDATE(A11,1)) -> 0 | D11: =SUMIFS(Expenses!$D$5:$D$204,Expenses!$A$5:$A$204,">="&A11,Expenses!$A$5:$A$204,"<"&EDATE(A11,1)) -> 0 | E11: =C11-D11 -> 0 | G11: Overdue now | H11: =Invoices!D2 -> 1500
A12: =EDATE($B$2,7) -> 46478 | B12: =SUMIFS(Invoices!$D$5:$D$104,Invoices!$C$5:$C$104,">="&A12,Invoices!$C$5:$C$104,"<"&EDATE(A12,1)) -> 0 | C12: =SUMIFS(Invoices!$D$5:$D$104,Invoices!$G$5:$G$104,">="&A12,Invoices!$G$5:$G$104,"<"&EDATE(A12,1)) -> 0 | D12: =SUMIFS(Expenses!$D$5:$D$204,Expenses!$A$5:$A$204,">="&A12,Expenses!$A$5:$A$204,"<"&EDATE(A12,1)) -> 0 | E12: =C12-D12 -> 0
A13: =EDATE($B$2,8) -> 46508 | B13: =SUMIFS(Invoices!$D$5:$D$104,Invoices!$C$5:$C$104,">="&A13,Invoices!$C$5:$C$104,"<"&EDATE(A13,1)) -> 0 | C13: =SUMIFS(Invoices!$D$5:$D$104,Invoices!$G$5:$G$104,">="&A13,Invoices!$G$5:$G$104,"<"&EDATE(A13,1)) -> 0 | D13: =SUMIFS(Expenses!$D$5:$D$204,Expenses!$A$5:$A$204,">="&A13,Expenses!$A$5:$A$204,"<"&EDATE(A13,1)) -> 0 | E13: =C13-D13 -> 0
A14: =EDATE($B$2,9) -> 46539 | B14: =SUMIFS(Invoices!$D$5:$D$104,Invoices!$C$5:$C$104,">="&A14,Invoices!$C$5:$C$104,"<"&EDATE(A14,1)) -> 0 | C14: =SUMIFS(Invoices!$D$5:$D$104,Invoices!$G$5:$G$104,">="&A14,Invoices!$G$5:$G$104,"<"&EDATE(A14,1)) -> 0 | D14: =SUMIFS(Expenses!$D$5:$D$204,Expenses!$A$5:$A$204,">="&A14,Expenses!$A$5:$A$204,"<"&EDATE(A14,1)) -> 0 | E14: =C14-D14 -> 0
A15: =EDATE($B$2,10) -> 46569 | B15: =SUMIFS(Invoices!$D$5:$D$104,Invoices!$C$5:$C$104,">="&A15,Invoices!$C$5:$C$104,"<"&EDATE(A15,1)) -> 0 | C15: =SUMIFS(Invoices!$D$5:$D$104,Invoices!$G$5:$G$104,">="&A15,Invoices!$G$5:$G$104,"<"&EDATE(A15,1)) -> 0 | D15: =SUMIFS(Expenses!$D$5:$D$204,Expenses!$A$5:$A$204,">="&A15,Expenses!$A$5:$A$204,"<"&EDATE(A15,1)) -> 0 | E15: =C15-D15 -> 0
A16: =EDATE($B$2,11) -> 46600 | B16: =SUMIFS(Invoices!$D$5:$D$104,Invoices!$C$5:$C$104,">="&A16,Invoices!$C$5:$C$104,"<"&EDATE(A16,1)) -> 0 | C16: =SUMIFS(Invoices!$D$5:$D$104,Invoices!$G$5:$G$104,">="&A16,Invoices!$G$5:$G$104,"<"&EDATE(A16,1)) -> 0 | D16: =SUMIFS(Expenses!$D$5:$D$204,Expenses!$A$5:$A$204,">="&A16,Expenses!$A$5:$A$204,"<"&EDATE(A16,1)) -> 0 | E16: =C16-D16 -> 0
A17: 12 months | B17: =SUM(B5:B16) -> 0 | C17: =SUM(C5:C16) -> 0 | D17: =SUM(D5:D16) -> 24 | E17: =SUM(E5:E16) -> -24
