Workbook

Sheet Start Here
A1: Interior Design Pricing Workbook
A2: by Knackdesk · knackdesk.com
A4: HOW TO USE
A5: 1. Settings: your annual income goal, six annual overhead lines, billable hours per year, default contingency %, percentage fee %, procurement markup %, trade discount %, hours per site visit, minimum project fee and complexity uplift %. The hourly rate you need follows; type your own rate to override it, and every other sheet prices at the rate used.
A6: 2. Fee Builder: one row per project or quote with client, concept, development and documentation hours, site visits, hours per visit, contingency % and percentage fee % (defaults from Settings, type your own to override) and the project budget. Total hours, base fee, contingency, design fee, fee as % of budget, the percentage fee, the difference, which pays more, the percentage fee's implied hourly rate and a minimum fee flag are calculated.
A7: 3. Procurement: one row per item you specify and sell, with project, supplier, retail price, trade discount % and markup % (defaults from Settings, type your own to override), an optional client price, freight and handling and quantity. Your cost, the client price used, line cost, revenue, gross profit, margin % and the client's saving against retail are calculated, with totals.
A8: 4. Room Fees: one row per room with the hours it takes, complexity uplift % and rate (defaults from Settings, type your own to override); hours with uplift and the room fee follow. The block below totals each project's room fees, adds site visit hours, applies your minimum project fee and shows the fee per room.
A9: 5. Budget Plan: one row per project with the total budget and the share for your design fee (default from Settings), furniture, construction and contingency. Amounts, allocated %, the amount left and a status (over-allocated, unallocated or fully allocated) are calculated.
A10: 6. Summary: hourly rate needed and used, projects quoted, design fees quoted, projects where a percentage fee pays more, projects at the minimum, procurement revenue, gross profit and margin %, items priced above retail, the highest-fee project and budgets over-allocated.
A12: LEGEND
A13: Blue text = a cell you type into. Black text = a formula, leave it alone. Yellow fill = key inputs.
A15: DEFINITIONS
... A26: Arithmetic only; not financial advice.

Sheet Settings
A1: Settings
A2: Annual income goal (your own) | B2: 60000 | C2: Example default 60,000 a year. Your own placeholder, not a recommendation: what you want to pay yourself before tax.
A3: Overhead: studio or office (annual) | B3: 6000 | C3: Example default 6,000 a year. Rent, utilities and a share of home-office costs.
A4: Overhead: software and subscriptions (annual) | B4: 1800 | C4: Example default 1,800 a year. CAD, rendering, project management and accounting software.
A5: Overhead: insurance (annual) | B5: 1500 | C5: Example default 1,500 a year. Professional indemnity and liability insurance.
A6: Overhead: marketing and portfolio (annual) | B6: 2400 | C6: Example default 2,400 a year. Website, photography, directories and print.
A7: Overhead: samples and travel (annual) | B7: 1800 | C7: Example default 1,800 a year. Samples, showroom visits and unbilled travel.
A8: Overhead: other (annual) | B8: 1500 | C8: Example default 1,500 a year. Accounting, memberships, training and everything else.
A9: Total annual overhead | B9: =SUM(B3:B8) -> 15000 | C9: formula: sum of the six overhead lines above
A10: Billable hours per year | B10: 1100 | C10: Example default 1,100. Hours you can bill in a year after admin, marketing, holidays and quiet weeks; your own placeholder.
A11: Default contingency % | B11: 10 | C11: Default 10. Added to the base fee on Fee Builder for revisions; each project can override it.
A12: Default percentage fee % | B12: 15 | C12: Default 15. Your own placeholder, not a recommendation: the % of project budget you would charge as a percentage fee.
A13: Default markup on procurement % | B13: 25 | C13: Default 25. Your own placeholder, not a recommendation: added to your cost on Procurement; each item can override it.
A14: Default trade discount % | B14: 30 | C14: Default 30. Placeholder; use what your suppliers actually give you. Each item can override it.
A15: Default hours per site visit | B15: 2 | C15: Default 2. Including travel; each project can override it on Fee Builder.
A16: Minimum project fee | B16: 2500 | C16: Example default 2,500. Your own placeholder: the smallest fee you take a project on for.
A17: Default complexity uplift % | B17: 10 | C17: Default 10. Extra hours for a room's complexity on Room Fees; each room can override it.
A18: Hourly rate needed | B18: =IFERROR(ROUND((B2+B9)/B10,2),0) -> 68.18 | C18: formula: (annual income goal + total annual overhead) ÷ billable hours per year
A19: or type your own rate | C19: Leave blank to price at the hourly rate needed; type a rate to price every sheet at your own rate instead.
A20: Rate used for pricing | B20: =IF(B19<>"",B19,B18) -> 68.18 | C20: formula: your own rate if typed, otherwise the hourly rate needed
A21: Total to cover per year | B21: =B2+B9 -> 75000 | C21: formula: annual income goal + total annual overhead
A22: Overhead per billable hour | B22: =IFERROR(ROUND(B9/B10,2),0) -> 13.64 | C22: formula: total annual overhead ÷ billable hours per year (the part of the rate that pays overhead)
A23: Minimum project fee in hours | B23: =IFERROR(ROUND(B16/B20,2),0) -> 36.67 | C23: formula: minimum project fee ÷ rate used: the hours of work your minimum fee pays for

Sheet Fee Builder
A1: Fee Builder
A2: One row per project or quote. Hours per visit, contingency % and percentage fee % default from Settings; type your own to override them. The fee is priced at the rate used on Settings.
A4: Project | B4: Client | C4: Concept hours | D4: Development hours | E4: Documentation hours | F4: Site visits | G4: Default hours per visit (Settings) | H4: or type your own hours per visit | I4: Hours per visit used | J4: Default contingency % (Settings) | K4: or type your own contingency % | L4: Contingency % used | M4: Project budget | N4: Default percentage fee % (Settings) | O4: or type your own percentage fee % | P4: Percentage fee % used | Q4: Total hours | R4: Base fee | S4: Contingency amount | T4: Design fee | U4: Fee as % of budget | V4: Percentage fee amount | W4: Difference (percentage − design fee) | X4: Which pays more | Y4: Implied hourly rate of percentage fee | Z4: Minimum fee check
A5: Hart residence | B5: J. Hart | C5: 20 | D5: 30 | E5: 25 | F5: 6 | G5: =IF(A5="","",Settings!$B$15) -> 2 | I5: =IF(A5="","",IF(H5<>"",H5,G5)) -> 2 | J5: =IF(A5="","",Settings!$B$11) -> 10 | L5: =IF(A5="","",IF(K5<>"",K5,J5)) -> 10 | M5: 120000 | N5: =IF(A5="","",Settings!$B$12) -> 15 | P5: =IF(A5="","",IF(O5<>"",O5,N5)) -> 15 | Q5: =IF(A5="","",C5+D5+E5+F5*I5) -> 87 | R5: =IF(A5="","",ROUND(Q5*Settings!$B$20,2)) -> 5931.66 | S5: =IF(A5="","",ROUND(R5*L5/100,2)) -> 593.17 | T5: =IF(A5="","",ROUND(R5+S5,2)) -> 6524.83 | U5: =IF(A5="","",IFERROR(ROUND(T5/M5*100,2),0)) -> 5.44 | V5: =IF(A5="","",ROUND(M5*P5/100,2)) -> 18000 | W5: =IF(A5="","",ROUND(V5-T5,2)) -> 11475.17 | X5: =IF(A5="","",IF(V5>T5,"percentage fee",IF(V5<T5,"hourly fee","same"))) -> percentage fee | Y5: =IF(A5="","",IFERROR(ROUND(V5/Q5,2),0)) -> 206.9 | Z5: =IF(A5="","",IF(T5<Settings!$B$16,"minimum applies",""))
A6: Lake Street loft | B6: M. Okafor | C6: 14 | D6: 18 | E6: 12 | F6: 4 | G6: =IF(A6="","",Settings!$B$15) -> 2 | H6: 3 | I6: =IF(A6="","",IF(H6<>"",H6,G6)) -> 3 | J6: =IF(A6="","",Settings!$B$11) -> 10 | L6: =IF(A6="","",IF(K6<>"",K6,J6)) -> 10 | M6: 60000 | N6: =IF(A6="","",Settings!$B$12) -> 15 | P6: =IF(A6="","",IF(O6<>"",O6,N6)) -> 15 | Q6: =IF(A6="","",C6+D6+E6+F6*I6) -> 56 | R6: =IF(A6="","",ROUND(Q6*Settings!$B$20,2)) -> 3818.08 | S6: =IF(A6="","",ROUND(R6*L6/100,2)) -> 381.81 | T6: =IF(A6="","",ROUND(R6+S6,2)) -> 4199.89 | U6: =IF(A6="","",IFERROR(ROUND(T6/M6*100,2),0)) -> 7 | V6: =IF(A6="","",ROUND(M6*P6/100,2)) -> 9000 | W6: =IF(A6="","",ROUND(V6-T6,2)) -> 4800.11 | X6: =IF(A6="","",IF(V6>T6,"percentage fee",IF(V6<T6,"hourly fee","same"))) -> percentage fee | Y6: =IF(A6="","",IFERROR(ROUND(V6/Q6,2),0)) -> 160.71 | Z6: =IF(A6="","",IF(T6<Settings!$B$16,"minimum applies",""))
A7: Corner cafe | B7: Bean & Co. | C7: 10 | D7: 16 | E7: 14 | F7: 3 | G7: =IF(A7="","",Settings!$B$15) -> 2 | I7: =IF(A7="","",IF(H7<>"",H7,G7)) -> 2 | J7: =IF(A7="","",Settings!$B$11) -> 10 | K7: 15 | L7: =IF(A7="","",IF(K7<>"",K7,J7)) -> 15 | M7: 45000 | N7: =IF(A7="","",Settings!$B$12) -> 15 | O7: 12 | P7: =IF(A7="","",IF(O7<>"",O7,N7)) -> 12 | Q7: =IF(A7="","",C7+D7+E7+F7*I7) -> 46 | R7: =IF(A7="","",ROUND(Q7*Settings!$B$20,2)) -> 3136.28 | S7: =IF(A7="","",ROUND(R7*L7/100,2)) -> 470.44 | T7: =IF(A7="","",ROUND(R7+S7,2)) -> 3606.72 | U7: =IF(A7="","",IFERROR(ROUND(T7/M7*100,2),0)) -> 8.01 | V7: =IF(A7="","",ROUND(M7*P7/100,2)) -> 5400 | W7: =IF(A7="","",ROUND(V7-T7,2)) -> 1793.28 | X7: =IF(A7="","",IF(V7>T7,"percentage fee",IF(V7<T7,"hourly fee","same"))) -> percentage fee | Y7: =IF(A7="","",IFERROR(ROUND(V7/Q7,2),0)) -> 117.39 | Z7: =IF(A7="","",IF(T7<Settings!$B$16,"minimum applies",""))
A8: Powder room refresh | B8: S. Lind | C8: 4 | D8: 6 | E8: 3 | F8: 1 | G8: =IF(A8="","",Settings!$B$15) -> 2 | I8: =IF(A8="","",IF(H8<>"",H8,G8)) -> 2 | J8: =IF(A8="","",Settings!$B$11) -> 10 | L8: =IF(A8="","",IF(K8<>"",K8,J8)) -> 10 | M8: 6000 | N8: =IF(A8="","",Settings!$B$12) -> 15 | P8: =IF(A8="","",IF(O8<>"",O8,N8)) -> 15 | Q8: =IF(A8="","",C8+D8+E8+F8*I8) -> 15 | R8: =IF(A8="","",ROUND(Q8*Settings!$B$20,2)) -> 1022.7 | S8: =IF(A8="","",ROUND(R8*L8/100,2)) -> 102.27 | T8: =IF(A8="","",ROUND(R8+S8,2)) -> 1124.97 | U8: =IF(A8="","",IFERROR(ROUND(T8/M8*100,2),0)) -> 18.75 | V8: =IF(A8="","",ROUND(M8*P8/100,2)) -> 900 | W8: =IF(A8="","",ROUND(V8-T8,2)) -> -224.97 | X8: =IF(A8="","",IF(V8>T8,"percentage fee",IF(V8<T8,"hourly fee","same"))) -> hourly fee | Y8: =IF(A8="","",IFERROR(ROUND(V8/Q8,2),0)) -> 60 | Z8: =IF(A8="","",IF(T8<Settings!$B$16,"minimum applies","")) -> minimum applies
A9: Mill house | B9: R. & T. Vance | C9: 30 | D9: 45 | E9: 40 | F9: 10 | G9: =IF(A9="","",Settings!$B$15) -> 2 | I9: =IF(A9="","",IF(H9<>"",H9,G9)) -> 2 | J9: =IF(A9="","",Settings!$B$11) -> 10 | L9: =IF(A9="","",IF(K9<>"",K9,J9)) -> 10 | M9: 250000 | N9: =IF(A9="","",Settings!$B$12) -> 15 | P9: =IF(A9="","",IF(O9<>"",O9,N9)) -> 15 | Q9: =IF(A9="","",C9+D9+E9+F9*I9) -> 135 | R9: =IF(A9="","",ROUND(Q9*Settings!$B$20,2)) -> 9204.3 | S9: =IF(A9="","",ROUND(R9*L9/100,2)) -> 920.43 | T9: =IF(A9="","",ROUND(R9+S9,2)) -> 10124.73 | U9: =IF(A9="","",IFERROR(ROUND(T9/M9*100,2),0)) -> 4.05 | V9: =IF(A9="","",ROUND(M9*P9/100,2)) -> 37500 | W9: =IF(A9="","",ROUND(V9-T9,2)) -> 27375.27 | X9: =IF(A9="","",IF(V9>T9,"percentage fee",IF(V9<T9,"hourly fee","same"))) -> percentage fee | Y9: =IF(A9="","",IFERROR(ROUND(V9/Q9,2),0)) -> 277.78 | Z9: =IF(A9="","",IF(T9<Settings!$B$16,"minimum applies",""))
A10: Office reception | B10: Northgate Ltd | C10: 12 | D10: 15 | E10: 10 | F10: 3 | G10: =IF(A10="","",Settings!$B$15) -> 2 | I10: =IF(A10="","",IF(H10<>"",H10,G10)) -> 2 | J10: =IF(A10="","",Settings!$B$11) -> 10 | L10: =IF(A10="","",IF(K10<>"",K10,J10)) -> 10 | M10: 30000 | N10: =IF(A10="","",Settings!$B$12) -> 15 | P10: =IF(A10="","",IF(O10<>"",O10,N10)) -> 15 | Q10: =IF(A10="","",C10+D10+E10+F10*I10) -> 43 | R10: =IF(A10="","",ROUND(Q10*Settings!$B$20,2)) -> 2931.74 | S10: =IF(A10="","",ROUND(R10*L10/100,2)) -> 293.17 | T10: =IF(A10="","",ROUND(R10+S10,2)) -> 3224.91 | U10: =IF(A10="","",IFERROR(ROUND(T10/M10*100,2),0)) -> 10.75 | V10: =IF(A10="","",ROUND(M10*P10/100,2)) -> 4500 | W10: =IF(A10="","",ROUND(V10-T10,2)) -> 1275.09 | X10: =IF(A10="","",IF(V10>T10,"percentage fee",IF(V10<T10,"hourly fee","same"))) -> percentage fee | Y10: =IF(A10="","",IFERROR(ROUND(V10/Q10,2),0)) -> 104.65 | Z10: =IF(A10="","",IF(T10<Settings!$B$16,"minimum applies",""))
G11: =IF(A11="","",Settings!$B$15) | I11: =IF(A11="","",IF(H11<>"",H11,G11)) | J11: =IF(A11="","",Settings!$B$11) | L11: =IF(A11="","",IF(K11<>"",K11,J11)) | N11: =IF(A11="","",Settings!$B$12) | P11: =IF(A11="","",IF(O11<>"",O11,N11)) | Q11: =IF(A11="","",C11+D11+E11+F11*I11) | R11: =IF(A11="","",ROUND(Q11*Settings!$B$20,2)) | S11: =IF(A11="","",ROUND(R11*L11/100,2)) | T11: =IF(A11="","",ROUND(R11+S11,2)) | U11: =IF(A11="","",IFERROR(ROUND(T11/M11*100,2),0)) | V11: =IF(A11="","",ROUND(M11*P11/100,2)) | W11: =IF(A11="","",ROUND(V11-T11,2)) | X11: =IF(A11="","",IF(V11>T11,"percentage fee",IF(V11<T11,"hourly fee","same"))) | Y11: =IF(A11="","",IFERROR(ROUND(V11/Q11,2),0)) | Z11: =IF(A11="","",IF(T11<Settings!$B$16,"minimum applies",""))
G12: =IF(A12="","",Settings!$B$15) | I12: =IF(A12="","",IF(H12<>"",H12,G12)) | J12: =IF(A12="","",Settings!$B$11) | L12: =IF(A12="","",IF(K12<>"",K12,J12)) | N12: =IF(A12="","",Settings!$B$12) | P12: =IF(A12="","",IF(O12<>"",O12,N12)) | Q12: =IF(A12="","",C12+D12+E12+F12*I12) | R12: =IF(A12="","",ROUND(Q12*Settings!$B$20,2)) | S12: =IF(A12="","",ROUND(R12*L12/100,2)) | T12: =IF(A12="","",ROUND(R12+S12,2)) | U12: =IF(A12="","",IFERROR(ROUND(T12/M12*100,2),0)) | V12: =IF(A12="","",ROUND(M12*P12/100,2)) | W12: =IF(A12="","",ROUND(V12-T12,2)) | X12: =IF(A12="","",IF(V12>T12,"percentage fee",IF(V12<T12,"hourly fee","same"))) | Y12: =IF(A12="","",IFERROR(ROUND(V12/Q12,2),0)) | Z12: =IF(A12="","",IF(T12<Settings!$B$16,"minimum applies",""))
G13: =IF(A13="","",Settings!$B$15) | I13: =IF(A13="","",IF(H13<>"",H13,G13)) | J13: =IF(A13="","",Settings!$B$11) | L13: =IF(A13="","",IF(K13<>"",K13,J13)) | N13: =IF(A13="","",Settings!$B$12) | P13: =IF(A13="","",IF(O13<>"",O13,N13)) | Q13: =IF(A13="","",C13+D13+E13+F13*I13) | R13: =IF(A13="","",ROUND(Q13*Settings!$B$20,2)) | S13: =IF(A13="","",ROUND(R13*L13/100,2)) | T13: =IF(A13="","",ROUND(R13+S13,2)) | U13: =IF(A13="","",IFERROR(ROUND(T13/M13*100,2),0)) | V13: =IF(A13="","",ROUND(M13*P13/100,2)) | W13: =IF(A13="","",ROUND(V13-T13,2)) | X13: =IF(A13="","",IF(V13>T13,"percentage fee",IF(V13<T13,"hourly fee","same"))) | Y13: =IF(A13="","",IFERROR(ROUND(V13/Q13,2),0)) | Z13: =IF(A13="","",IF(T13<Settings!$B$16,"minimum applies",""))
G14: =IF(A14="","",Settings!$B$15) | I14: =IF(A14="","",IF(H14<>"",H14,G14)) | J14: =IF(A14="","",Settings!$B$11) | L14: =IF(A14="","",IF(K14<>"",K14,J14)) | N14: =IF(A14="","",Settings!$B$12) | P14: =IF(A14="","",IF(O14<>"",O14,N14)) | Q14: =IF(A14="","",C14+D14+E14+F14*I14) | R14: =IF(A14="","",ROUND(Q14*Settings!$B$20,2)) | S14: =IF(A14="","",ROUND(R14*L14/100,2)) | T14: =IF(A14="","",ROUND(R14+S14,2)) | U14: =IF(A14="","",IFERROR(ROUND(T14/M14*100,2),0)) | V14: =IF(A14="","",ROUND(M14*P14/100,2)) | W14: =IF(A14="","",ROUND(V14-T14,2)) | X14: =IF(A14="","",IF(V14>T14,"percentage fee",IF(V14<T14,"hourly fee","same"))) | Y14: =IF(A14="","",IFERROR(ROUND(V14/Q14,2),0)) | Z14: =IF(A14="","",IF(T14<Settings!$B$16,"minimum applies",""))
G15: =IF(A15="","",Settings!$B$15) | I15: =IF(A15="","",IF(H15<>"",H15,G15)) | J15: =IF(A15="","",Settings!$B$11) | L15: =IF(A15="","",IF(K15<>"",K15,J15)) | N15: =IF(A15="","",Settings!$B$12) | P15: =IF(A15="","",IF(O15<>"",O15,N15)) | Q15: =IF(A15="","",C15+D15+E15+F15*I15) | R15: =IF(A15="","",ROUND(Q15*Settings!$B$20,2)) | S15: =IF(A15="","",ROUND(R15*L15/100,2)) | T15: =IF(A15="","",ROUND(R15+S15,2)) | U15: =IF(A15="","",IFERROR(ROUND(T15/M15*100,2),0)) | V15: =IF(A15="","",ROUND(M15*P15/100,2)) | W15: =IF(A15="","",ROUND(V15-T15,2)) | X15: =IF(A15="","",IF(V15>T15,"percentage fee",IF(V15<T15,"hourly fee","same"))) | Y15: =IF(A15="","",IFERROR(ROUND(V15/Q15,2),0)) | Z15: =IF(A15="","",IF(T15<Settings!$B$16,"minimum applies",""))
G16: =IF(A16="","",Settings!$B$15) | I16: =IF(A16="","",IF(H16<>"",H16,G16)) | J16: =IF(A16="","",Settings!$B$11) | L16: =IF(A16="","",IF(K16<>"",K16,J16)) | N16: =IF(A16="","",Settings!$B$12) | P16: =IF(A16="","",IF(O16<>"",O16,N16)) | Q16: =IF(A16="","",C16+D16+E16+F16*I16) | R16: =IF(A16="","",ROUND(Q16*Settings!$B$20,2)) | S16: =IF(A16="","",ROUND(R16*L16/100,2)) | T16: =IF(A16="","",ROUND(R16+S16,2)) | U16: =IF(A16="","",IFERROR(ROUND(T16/M16*100,2),0)) | V16: =IF(A16="","",ROUND(M16*P16/100,2)) | W16: =IF(A16="","",ROUND(V16-T16,2)) | X16: =IF(A16="","",IF(V16>T16,"percentage fee",IF(V16<T16,"hourly fee","same"))) | Y16: =IF(A16="","",IFERROR(ROUND(V16/Q16,2),0)) | Z16: =IF(A16="","",IF(T16<Settings!$B$16,"minimum applies",""))
G17: =IF(A17="","",Settings!$B$15) | I17: =IF(A17="","",IF(H17<>"",H17,G17)) | J17: =IF(A17="","",Settings!$B$11) | L17: =IF(A17="","",IF(K17<>"",K17,J17)) | N17: =IF(A17="","",Settings!$B$12) | P17: =IF(A17="","",IF(O17<>"",O17,N17)) | Q17: =IF(A17="","",C17+D17+E17+F17*I17) | R17: =IF(A17="","",ROUND(Q17*Settings!$B$20,2)) | S17: =IF(A17="","",ROUND(R17*L17/100,2)) | T17: =IF(A17="","",ROUND(R17+S17,2)) | U17: =IF(A17="","",IFERROR(ROUND(T17/M17*100,2),0)) | V17: =IF(A17="","",ROUND(M17*P17/100,2)) | W17: =IF(A17="","",ROUND(V17-T17,2)) | X17: =IF(A17="","",IF(V17>T17,"percentage fee",IF(V17<T17,"hourly fee","same"))) | Y17: =IF(A17="","",IFERROR(ROUND(V17/Q17,2),0)) | Z17: =IF(A17="","",IF(T17<Settings!$B$16,"minimum applies",""))
G18: =IF(A18="","",Settings!$B$15) | I18: =IF(A18="","",IF(H18<>"",H18,G18)) | J18: =IF(A18="","",Settings!$B$11) | L18: =IF(A18="","",IF(K18<>"",K18,J18)) | N18: =IF(A18="","",Settings!$B$12) | P18: =IF(A18="","",IF(O18<>"",O18,N18)) | Q18: =IF(A18="","",C18+D18+E18+F18*I18) | R18: =IF(A18="","",ROUND(Q18*Settings!$B$20,2)) | S18: =IF(A18="","",ROUND(R18*L18/100,2)) | T18: =IF(A18="","",ROUND(R18+S18,2)) | U18: =IF(A18="","",IFERROR(ROUND(T18/M18*100,2),0)) | V18: =IF(A18="","",ROUND(M18*P18/100,2)) | W18: =IF(A18="","",ROUND(V18-T18,2)) | X18: =IF(A18="","",IF(V18>T18,"percentage fee",IF(V18<T18,"hourly fee","same"))) | Y18: =IF(A18="","",IFERROR(ROUND(V18/Q18,2),0)) | Z18: =IF(A18="","",IF(T18<Settings!$B$16,"minimum applies",""))
G19: =IF(A19="","",Settings!$B$15) | I19: =IF(A19="","",IF(H19<>"",H19,G19)) | J19: =IF(A19="","",Settings!$B$11) | L19: =IF(A19="","",IF(K19<>"",K19,J19)) | N19: =IF(A19="","",Settings!$B$12) | P19: =IF(A19="","",IF(O19<>"",O19,N19)) | Q19: =IF(A19="","",C19+D19+E19+F19*I19) | R19: =IF(A19="","",ROUND(Q19*Settings!$B$20,2)) | S19: =IF(A19="","",ROUND(R19*L19/100,2)) | T19: =IF(A19="","",ROUND(R19+S19,2)) | U19: =IF(A19="","",IFERROR(ROUND(T19/M19*100,2),0)) | V19: =IF(A19="","",ROUND(M19*P19/100,2)) | W19: =IF(A19="","",ROUND(V19-T19,2)) | X19: =IF(A19="","",IF(V19>T19,"percentage fee",IF(V19<T19,"hourly fee","same"))) | Y19: =IF(A19="","",IFERROR(ROUND(V19/Q19,2),0)) | Z19: =IF(A19="","",IF(T19<Settings!$B$16,"minimum applies",""))
G20: =IF(A20="","",Settings!$B$15) | I20: =IF(A20="","",IF(H20<>"",H20,G20)) | J20: =IF(A20="","",Settings!$B$11) | L20: =IF(A20="","",IF(K20<>"",K20,J20)) | N20: =IF(A20="","",Settings!$B$12) | P20: =IF(A20="","",IF(O20<>"",O20,N20)) | Q20: =IF(A20="","",C20+D20+E20+F20*I20) | R20: =IF(A20="","",ROUND(Q20*Settings!$B$20,2)) | S20: =IF(A20="","",ROUND(R20*L20/100,2)) | T20: =IF(A20="","",ROUND(R20+S20,2)) | U20: =IF(A20="","",IFERROR(ROUND(T20/M20*100,2),0)) | V20: =IF(A20="","",ROUND(M20*P20/100,2)) | W20: =IF(A20="","",ROUND(V20-T20,2)) | X20: =IF(A20="","",IF(V20>T20,"percentage fee",IF(V20<T20,"hourly fee","same"))) | Y20: =IF(A20="","",IFERROR(ROUND(V20/Q20,2),0)) | Z20: =IF(A20="","",IF(T20<Settings!$B$16,"minimum applies",""))
G21: =IF(A21="","",Settings!$B$15) | I21: =IF(A21="","",IF(H21<>"",H21,G21)) | J21: =IF(A21="","",Settings!$B$11) | L21: =IF(A21="","",IF(K21<>"",K21,J21)) | N21: =IF(A21="","",Settings!$B$12) | P21: =IF(A21="","",IF(O21<>"",O21,N21)) | Q21: =IF(A21="","",C21+D21+E21+F21*I21) | R21: =IF(A21="","",ROUND(Q21*Settings!$B$20,2)) | S21: =IF(A21="","",ROUND(R21*L21/100,2)) | T21: =IF(A21="","",ROUND(R21+S21,2)) | U21: =IF(A21="","",IFERROR(ROUND(T21/M21*100,2),0)) | V21: =IF(A21="","",ROUND(M21*P21/100,2)) | W21: =IF(A21="","",ROUND(V21-T21,2)) | X21: =IF(A21="","",IF(V21>T21,"percentage fee",IF(V21<T21,"hourly fee","same"))) | Y21: =IF(A21="","",IFERROR(ROUND(V21/Q21,2),0)) | Z21: =IF(A21="","",IF(T21<Settings!$B$16,"minimum applies",""))
G22: =IF(A22="","",Settings!$B$15) | I22: =IF(A22="","",IF(H22<>"",H22,G22)) | J22: =IF(A22="","",Settings!$B$11) | L22: =IF(A22="","",IF(K22<>"",K22,J22)) | N22: =IF(A22="","",Settings!$B$12) | P22: =IF(A22="","",IF(O22<>"",O22,N22)) | Q22: =IF(A22="","",C22+D22+E22+F22*I22) | R22: =IF(A22="","",ROUND(Q22*Settings!$B$20,2)) | S22: =IF(A22="","",ROUND(R22*L22/100,2)) | T22: =IF(A22="","",ROUND(R22+S22,2)) | U22: =IF(A22="","",IFERROR(ROUND(T22/M22*100,2),0)) | V22: =IF(A22="","",ROUND(M22*P22/100,2)) | W22: =IF(A22="","",ROUND(V22-T22,2)) | X22: =IF(A22="","",IF(V22>T22,"percentage fee",IF(V22<T22,"hourly fee","same"))) | Y22: =IF(A22="","",IFERROR(ROUND(V22/Q22,2),0)) | Z22: =IF(A22="","",IF(T22<Settings!$B$16,"minimum applies",""))
... G24: =IF(A24="","",Settings!$B$15) | I24: =IF(A24="","",IF(H24<>"",H24,G24)) | J24: =IF(A24="","",Settings!$B$11) | L24: =IF(A24="","",IF(K24<>"",K24,J24)) | N24: =IF(A24="","",Settings!$B$12) | P24: =IF(A24="","",IF(O24<>"",O24,N24)) | Q24: =IF(A24="","",C24+D24+E24+F24*I24) | R24: =IF(A24="","",ROUND(Q24*Settings!$B$20,2)) | S24: =IF(A24="","",ROUND(R24*L24/100,2)) | T24: =IF(A24="","",ROUND(R24+S24,2)) | U24: =IF(A24="","",IFERROR(ROUND(T24/M24*100,2),0)) | V24: =IF(A24="","",ROUND(M24*P24/100,2)) | W24: =IF(A24="","",ROUND(V24-T24,2)) | X24: =IF(A24="","",IF(V24>T24,"percentage fee",IF(V24<T24,"hourly fee","same"))) | Y24: =IF(A24="","",IFERROR(ROUND(V24/Q24,2),0)) | Z24: =IF(A24="","",IF(T24<Settings!$B$16,"minimum applies",""))
A25: Total | B25: =COUNTA(A5:A24) -> 6 | C25: =SUM(C5:C24) -> 90 | D25: =SUM(D5:D24) -> 130 | E25: =SUM(E5:E24) -> 104 | F25: =SUM(F5:F24) -> 27 | M25: =SUM(M5:M24) -> 511000 | Q25: =SUM(Q5:Q24) -> 382 | R25: =SUM(R5:R24) -> 26044.76 | S25: =SUM(S5:S24) -> 2761.29 | T25: =SUM(T5:T24) -> 28806.05 | U25: =IFERROR(ROUND(T25/M25*100,2),0) -> 5.64 | V25: =SUM(V5:V24) -> 75300 | W25: =SUM(W5:W24) -> 46493.95 | Y25: =IFERROR(ROUND(V25/Q25,2),0) -> 197.12

Sheet Procurement
A1: Procurement
A2: One row per item you buy for a client. Trade discount % and markup % default from Settings; type your own to override them, or type a client price to set it directly. Freight and handling is for the whole line and is passed to the client at cost.
A4: Project | B4: Item | C4: Supplier | D4: Retail price (per unit) | E4: Default trade discount % (Settings) | F4: or type your own trade discount % | G4: Trade discount % used | H4: Default markup % (Settings) | I4: or type your own markup % | J4: Markup % used | K4: or type your own client price (per unit) | L4: Freight and handling (line) | M4: Quantity | N4: Your cost per unit | O4: Client price used (per unit) | P4: Line cost | Q4: Line revenue | R4: Gross profit | S4: Margin % | T4: Client saving vs retail
A5: Hart residence | B5: Sofa | C5: Supplier A | D5: 3200 | E5: =IF(A5="","",Settings!$B$14) -> 30 | G5: =IF(A5="","",IF(F5<>"",F5,E5)) -> 30 | H5: =IF(A5="","",Settings!$B$13) -> 25 | J5: =IF(A5="","",IF(I5<>"",I5,H5)) -> 25 | L5: 150 | M5: 1 | N5: =IF(A5="","",ROUND(D5*(1-G5/100),2)) -> 2240 | O5: =IF(A5="","",IF(K5<>"",K5,ROUND(N5*(1+J5/100),2))) -> 2800 | P5: =IF(A5="","",ROUND(N5*M5+L5,2)) -> 2390 | Q5: =IF(A5="","",ROUND(O5*M5+L5,2)) -> 2950 | R5: =IF(A5="","",ROUND(Q5-P5,2)) -> 560 | S5: =IF(A5="","",IFERROR(ROUND(R5/Q5*100,2),0)) -> 18.98 | T5: =IF(A5="","",ROUND((D5-O5)*M5,2)) -> 400
A6: Hart residence | B6: Dining chairs | C6: Supplier B | D6: 420 | E6: =IF(A6="","",Settings!$B$14) -> 30 | G6: =IF(A6="","",IF(F6<>"",F6,E6)) -> 30 | H6: =IF(A6="","",Settings!$B$13) -> 25 | J6: =IF(A6="","",IF(I6<>"",I6,H6)) -> 25 | L6: 80 | M6: 6 | N6: =IF(A6="","",ROUND(D6*(1-G6/100),2)) -> 294 | O6: =IF(A6="","",IF(K6<>"",K6,ROUND(N6*(1+J6/100),2))) -> 367.5 | P6: =IF(A6="","",ROUND(N6*M6+L6,2)) -> 1844 | Q6: =IF(A6="","",ROUND(O6*M6+L6,2)) -> 2285 | R6: =IF(A6="","",ROUND(Q6-P6,2)) -> 441 | S6: =IF(A6="","",IFERROR(ROUND(R6/Q6*100,2),0)) -> 19.3 | T6: =IF(A6="","",ROUND((D6-O6)*M6,2)) -> 315
A7: Hart residence | B7: Pendant lights | C7: Supplier C | D7: 380 | E7: =IF(A7="","",Settings!$B$14) -> 30 | G7: =IF(A7="","",IF(F7<>"",F7,E7)) -> 30 | H7: =IF(A7="","",Settings!$B$13) -> 25 | J7: =IF(A7="","",IF(I7<>"",I7,H7)) -> 25 | L7: 40 | M7: 3 | N7: =IF(A7="","",ROUND(D7*(1-G7/100),2)) -> 266 | O7: =IF(A7="","",IF(K7<>"",K7,ROUND(N7*(1+J7/100),2))) -> 332.5 | P7: =IF(A7="","",ROUND(N7*M7+L7,2)) -> 838 | Q7: =IF(A7="","",ROUND(O7*M7+L7,2)) -> 1037.5 | R7: =IF(A7="","",ROUND(Q7-P7,2)) -> 199.5 | S7: =IF(A7="","",IFERROR(ROUND(R7/Q7*100,2),0)) -> 19.23 | T7: =IF(A7="","",ROUND((D7-O7)*M7,2)) -> 142.5
A8: Hart residence | B8: Rug | C8: Supplier A | D8: 1800 | E8: =IF(A8="","",Settings!$B$14) -> 30 | G8: =IF(A8="","",IF(F8<>"",F8,E8)) -> 30 | H8: =IF(A8="","",Settings!$B$13) -> 25 | I8: 20 | J8: =IF(A8="","",IF(I8<>"",I8,H8)) -> 20 | L8: 60 | M8: 1 | N8: =IF(A8="","",ROUND(D8*(1-G8/100),2)) -> 1260 | O8: =IF(A8="","",IF(K8<>"",K8,ROUND(N8*(1+J8/100),2))) -> 1512 | P8: =IF(A8="","",ROUND(N8*M8+L8,2)) -> 1320 | Q8: =IF(A8="","",ROUND(O8*M8+L8,2)) -> 1572 | R8: =IF(A8="","",ROUND(Q8-P8,2)) -> 252 | S8: =IF(A8="","",IFERROR(ROUND(R8/Q8*100,2),0)) -> 16.03 | T8: =IF(A8="","",ROUND((D8-O8)*M8,2)) -> 288
A9: Lake Street loft | B9: Bed frame | C9: Supplier D | D9: 2100 | E9: =IF(A9="","",Settings!$B$14) -> 30 | G9: =IF(A9="","",IF(F9<>"",F9,E9)) -> 30 | H9: =IF(A9="","",Settings!$B$13) -> 25 | J9: =IF(A9="","",IF(I9<>"",I9,H9)) -> 25 | L9: 120 | M9: 1 | N9: =IF(A9="","",ROUND(D9*(1-G9/100),2)) -> 1470 | O9: =IF(A9="","",IF(K9<>"",K9,ROUND(N9*(1+J9/100),2))) -> 1837.5 | P9: =IF(A9="","",ROUND(N9*M9+L9,2)) -> 1590 | Q9: =IF(A9="","",ROUND(O9*M9+L9,2)) -> 1957.5 | R9: =IF(A9="","",ROUND(Q9-P9,2)) -> 367.5 | S9: =IF(A9="","",IFERROR(ROUND(R9/Q9*100,2),0)) -> 18.77 | T9: =IF(A9="","",ROUND((D9-O9)*M9,2)) -> 262.5
A10: Lake Street loft | B10: Bedside tables | C10: Supplier D | D10: 450 | E10: =IF(A10="","",Settings!$B$14) -> 30 | G10: =IF(A10="","",IF(F10<>"",F10,E10)) -> 30 | H10: =IF(A10="","",Settings!$B$13) -> 25 | J10: =IF(A10="","",IF(I10<>"",I10,H10)) -> 25 | L10: 30 | M10: 2 | N10: =IF(A10="","",ROUND(D10*(1-G10/100),2)) -> 315 | O10: =IF(A10="","",IF(K10<>"",K10,ROUND(N10*(1+J10/100),2))) -> 393.75 | P10: =IF(A10="","",ROUND(N10*M10+L10,2)) -> 660 | Q10: =IF(A10="","",ROUND(O10*M10+L10,2)) -> 817.5 | R10: =IF(A10="","",ROUND(Q10-P10,2)) -> 157.5 | S10: =IF(A10="","",IFERROR(ROUND(R10/Q10*100,2),0)) -> 19.27 | T10: =IF(A10="","",ROUND((D10-O10)*M10,2)) -> 112.5
A11: Lake Street loft | B11: Curtains (made to measure) | C11: Workroom E | D11: 1600 | E11: =IF(A11="","",Settings!$B$14) -> 30 | F11: 10 | G11: =IF(A11="","",IF(F11<>"",F11,E11)) -> 10 | H11: =IF(A11="","",Settings!$B$13) -> 25 | J11: =IF(A11="","",IF(I11<>"",I11,H11)) -> 25 | L11: 0 | M11: 1 | N11: =IF(A11="","",ROUND(D11*(1-G11/100),2)) -> 1440 | O11: =IF(A11="","",IF(K11<>"",K11,ROUND(N11*(1+J11/100),2))) -> 1800 | P11: =IF(A11="","",ROUND(N11*M11+L11,2)) -> 1440 | Q11: =IF(A11="","",ROUND(O11*M11+L11,2)) -> 1800 | R11: =IF(A11="","",ROUND(Q11-P11,2)) -> 360 | S11: =IF(A11="","",IFERROR(ROUND(R11/Q11*100,2),0)) -> 20 | T11: =IF(A11="","",ROUND((D11-O11)*M11,2)) -> -200
A12: Corner cafe | B12: Cafe chairs | C12: Supplier F | D12: 160 | E12: =IF(A12="","",Settings!$B$14) -> 30 | G12: =IF(A12="","",IF(F12<>"",F12,E12)) -> 30 | H12: =IF(A12="","",Settings!$B$13) -> 25 | J12: =IF(A12="","",IF(I12<>"",I12,H12)) -> 25 | L12: 200 | M12: 24 | N12: =IF(A12="","",ROUND(D12*(1-G12/100),2)) -> 112 | O12: =IF(A12="","",IF(K12<>"",K12,ROUND(N12*(1+J12/100),2))) -> 140 | P12: =IF(A12="","",ROUND(N12*M12+L12,2)) -> 2888 | Q12: =IF(A12="","",ROUND(O12*M12+L12,2)) -> 3560 | R12: =IF(A12="","",ROUND(Q12-P12,2)) -> 672 | S12: =IF(A12="","",IFERROR(ROUND(R12/Q12*100,2),0)) -> 18.88 | T12: =IF(A12="","",ROUND((D12-O12)*M12,2)) -> 480
A13: Corner cafe | B13: Bar stools | C13: Supplier F | D13: 240 | E13: =IF(A13="","",Settings!$B$14) -> 30 | G13: =IF(A13="","",IF(F13<>"",F13,E13)) -> 30 | H13: =IF(A13="","",Settings!$B$13) -> 25 | J13: =IF(A13="","",IF(I13<>"",I13,H13)) -> 25 | L13: 90 | M13: 8 | N13: =IF(A13="","",ROUND(D13*(1-G13/100),2)) -> 168 | O13: =IF(A13="","",IF(K13<>"",K13,ROUND(N13*(1+J13/100),2))) -> 210 | P13: =IF(A13="","",ROUND(N13*M13+L13,2)) -> 1434 | Q13: =IF(A13="","",ROUND(O13*M13+L13,2)) -> 1770 | R13: =IF(A13="","",ROUND(Q13-P13,2)) -> 336 | S13: =IF(A13="","",IFERROR(ROUND(R13/Q13*100,2),0)) -> 18.98 | T13: =IF(A13="","",ROUND((D13-O13)*M13,2)) -> 240
A14: Corner cafe | B14: Wall lights | C14: Supplier C | D14: 210 | E14: =IF(A14="","",Settings!$B$14) -> 30 | G14: =IF(A14="","",IF(F14<>"",F14,E14)) -> 30 | H14: =IF(A14="","",Settings!$B$13) -> 25 | J14: =IF(A14="","",IF(I14<>"",I14,H14)) -> 25 | K14: 175 | L14: 25 | M14: 6 | N14: =IF(A14="","",ROUND(D14*(1-G14/100),2)) -> 147 | O14: =IF(A14="","",IF(K14<>"",K14,ROUND(N14*(1+J14/100),2))) -> 175 | P14: =IF(A14="","",ROUND(N14*M14+L14,2)) -> 907 | Q14: =IF(A14="","",ROUND(O14*M14+L14,2)) -> 1075 | R14: =IF(A14="","",ROUND(Q14-P14,2)) -> 168 | S14: =IF(A14="","",IFERROR(ROUND(R14/Q14*100,2),0)) -> 15.63 | T14: =IF(A14="","",ROUND((D14-O14)*M14,2)) -> 210
E15: =IF(A15="","",Settings!$B$14) | G15: =IF(A15="","",IF(F15<>"",F15,E15)) | H15: =IF(A15="","",Settings!$B$13) | J15: =IF(A15="","",IF(I15<>"",I15,H15)) | N15: =IF(A15="","",ROUND(D15*(1-G15/100),2)) | O15: =IF(A15="","",IF(K15<>"",K15,ROUND(N15*(1+J15/100),2))) | P15: =IF(A15="","",ROUND(N15*M15+L15,2)) | Q15: =IF(A15="","",ROUND(O15*M15+L15,2)) | R15: =IF(A15="","",ROUND(Q15-P15,2)) | S15: =IF(A15="","",IFERROR(ROUND(R15/Q15*100,2),0)) | T15: =IF(A15="","",ROUND((D15-O15)*M15,2))
E16: =IF(A16="","",Settings!$B$14) | G16: =IF(A16="","",IF(F16<>"",F16,E16)) | H16: =IF(A16="","",Settings!$B$13) | J16: =IF(A16="","",IF(I16<>"",I16,H16)) | N16: =IF(A16="","",ROUND(D16*(1-G16/100),2)) | O16: =IF(A16="","",IF(K16<>"",K16,ROUND(N16*(1+J16/100),2))) | P16: =IF(A16="","",ROUND(N16*M16+L16,2)) | Q16: =IF(A16="","",ROUND(O16*M16+L16,2)) | R16: =IF(A16="","",ROUND(Q16-P16,2)) | S16: =IF(A16="","",IFERROR(ROUND(R16/Q16*100,2),0)) | T16: =IF(A16="","",ROUND((D16-O16)*M16,2))
E17: =IF(A17="","",Settings!$B$14) | G17: =IF(A17="","",IF(F17<>"",F17,E17)) | H17: =IF(A17="","",Settings!$B$13) | J17: =IF(A17="","",IF(I17<>"",I17,H17)) | N17: =IF(A17="","",ROUND(D17*(1-G17/100),2)) | O17: =IF(A17="","",IF(K17<>"",K17,ROUND(N17*(1+J17/100),2))) | P17: =IF(A17="","",ROUND(N17*M17+L17,2)) | Q17: =IF(A17="","",ROUND(O17*M17+L17,2)) | R17: =IF(A17="","",ROUND(Q17-P17,2)) | S17: =IF(A17="","",IFERROR(ROUND(R17/Q17*100,2),0)) | T17: =IF(A17="","",ROUND((D17-O17)*M17,2))
E18: =IF(A18="","",Settings!$B$14) | G18: =IF(A18="","",IF(F18<>"",F18,E18)) | H18: =IF(A18="","",Settings!$B$13) | J18: =IF(A18="","",IF(I18<>"",I18,H18)) | N18: =IF(A18="","",ROUND(D18*(1-G18/100),2)) | O18: =IF(A18="","",IF(K18<>"",K18,ROUND(N18*(1+J18/100),2))) | P18: =IF(A18="","",ROUND(N18*M18+L18,2)) | Q18: =IF(A18="","",ROUND(O18*M18+L18,2)) | R18: =IF(A18="","",ROUND(Q18-P18,2)) | S18: =IF(A18="","",IFERROR(ROUND(R18/Q18*100,2),0)) | T18: =IF(A18="","",ROUND((D18-O18)*M18,2))
E19: =IF(A19="","",Settings!$B$14) | G19: =IF(A19="","",IF(F19<>"",F19,E19)) | H19: =IF(A19="","",Settings!$B$13) | J19: =IF(A19="","",IF(I19<>"",I19,H19)) | N19: =IF(A19="","",ROUND(D19*(1-G19/100),2)) | O19: =IF(A19="","",IF(K19<>"",K19,ROUND(N19*(1+J19/100),2))) | P19: =IF(A19="","",ROUND(N19*M19+L19,2)) | Q19: =IF(A19="","",ROUND(O19*M19+L19,2)) | R19: =IF(A19="","",ROUND(Q19-P19,2)) | S19: =IF(A19="","",IFERROR(ROUND(R19/Q19*100,2),0)) | T19: =IF(A19="","",ROUND((D19-O19)*M19,2))
E20: =IF(A20="","",Settings!$B$14) | G20: =IF(A20="","",IF(F20<>"",F20,E20)) | H20: =IF(A20="","",Settings!$B$13) | J20: =IF(A20="","",IF(I20<>"",I20,H20)) | N20: =IF(A20="","",ROUND(D20*(1-G20/100),2)) | O20: =IF(A20="","",IF(K20<>"",K20,ROUND(N20*(1+J20/100),2))) | P20: =IF(A20="","",ROUND(N20*M20+L20,2)) | Q20: =IF(A20="","",ROUND(O20*M20+L20,2)) | R20: =IF(A20="","",ROUND(Q20-P20,2)) | S20: =IF(A20="","",IFERROR(ROUND(R20/Q20*100,2),0)) | T20: =IF(A20="","",ROUND((D20-O20)*M20,2))
E21: =IF(A21="","",Settings!$B$14) | G21: =IF(A21="","",IF(F21<>"",F21,E21)) | H21: =IF(A21="","",Settings!$B$13) | J21: =IF(A21="","",IF(I21<>"",I21,H21)) | N21: =IF(A21="","",ROUND(D21*(1-G21/100),2)) | O21: =IF(A21="","",IF(K21<>"",K21,ROUND(N21*(1+J21/100),2))) | P21: =IF(A21="","",ROUND(N21*M21+L21,2)) | Q21: =IF(A21="","",ROUND(O21*M21+L21,2)) | R21: =IF(A21="","",ROUND(Q21-P21,2)) | S21: =IF(A21="","",IFERROR(ROUND(R21/Q21*100,2),0)) | T21: =IF(A21="","",ROUND((D21-O21)*M21,2))
E22: =IF(A22="","",Settings!$B$14) | G22: =IF(A22="","",IF(F22<>"",F22,E22)) | H22: =IF(A22="","",Settings!$B$13) | J22: =IF(A22="","",IF(I22<>"",I22,H22)) | N22: =IF(A22="","",ROUND(D22*(1-G22/100),2)) | O22: =IF(A22="","",IF(K22<>"",K22,ROUND(N22*(1+J22/100),2))) | P22: =IF(A22="","",ROUND(N22*M22+L22,2)) | Q22: =IF(A22="","",ROUND(O22*M22+L22,2)) | R22: =IF(A22="","",ROUND(Q22-P22,2)) | S22: =IF(A22="","",IFERROR(ROUND(R22/Q22*100,2),0)) | T22: =IF(A22="","",ROUND((D22-O22)*M22,2))
E23: =IF(A23="","",Settings!$B$14) | G23: =IF(A23="","",IF(F23<>"",F23,E23)) | H23: =IF(A23="","",Settings!$B$13) | J23: =IF(A23="","",IF(I23<>"",I23,H23)) | N23: =IF(A23="","",ROUND(D23*(1-G23/100),2)) | O23: =IF(A23="","",IF(K23<>"",K23,ROUND(N23*(1+J23/100),2))) | P23: =IF(A23="","",ROUND(N23*M23+L23,2)) | Q23: =IF(A23="","",ROUND(O23*M23+L23,2)) | R23: =IF(A23="","",ROUND(Q23-P23,2)) | S23: =IF(A23="","",IFERROR(ROUND(R23/Q23*100,2),0)) | T23: =IF(A23="","",ROUND((D23-O23)*M23,2))
E24: =IF(A24="","",Settings!$B$14) | G24: =IF(A24="","",IF(F24<>"",F24,E24)) | H24: =IF(A24="","",Settings!$B$13) | J24: =IF(A24="","",IF(I24<>"",I24,H24)) | N24: =IF(A24="","",ROUND(D24*(1-G24/100),2)) | O24: =IF(A24="","",IF(K24<>"",K24,ROUND(N24*(1+J24/100),2))) | P24: =IF(A24="","",ROUND(N24*M24+L24,2)) | Q24: =IF(A24="","",ROUND(O24*M24+L24,2)) | R24: =IF(A24="","",ROUND(Q24-P24,2)) | S24: =IF(A24="","",IFERROR(ROUND(R24/Q24*100,2),0)) | T24: =IF(A24="","",ROUND((D24-O24)*M24,2))
E25: =IF(A25="","",Settings!$B$14) | G25: =IF(A25="","",IF(F25<>"",F25,E25)) | H25: =IF(A25="","",Settings!$B$13) | J25: =IF(A25="","",IF(I25<>"",I25,H25)) | N25: =IF(A25="","",ROUND(D25*(1-G25/100),2)) | O25: =IF(A25="","",IF(K25<>"",K25,ROUND(N25*(1+J25/100),2))) | P25: =IF(A25="","",ROUND(N25*M25+L25,2)) | Q25: =IF(A25="","",ROUND(O25*M25+L25,2)) | R25: =IF(A25="","",ROUND(Q25-P25,2)) | S25: =IF(A25="","",IFERROR(ROUND(R25/Q25*100,2),0)) | T25: =IF(A25="","",ROUND((D25-O25)*M25,2))
E26: =IF(A26="","",Settings!$B$14) | G26: =IF(A26="","",IF(F26<>"",F26,E26)) | H26: =IF(A26="","",Settings!$B$13) | J26: =IF(A26="","",IF(I26<>"",I26,H26)) | N26: =IF(A26="","",ROUND(D26*(1-G26/100),2)) | O26: =IF(A26="","",IF(K26<>"",K26,ROUND(N26*(1+J26/100),2))) | P26: =IF(A26="","",ROUND(N26*M26+L26,2)) | Q26: =IF(A26="","",ROUND(O26*M26+L26,2)) | R26: =IF(A26="","",ROUND(Q26-P26,2)) | S26: =IF(A26="","",IFERROR(ROUND(R26/Q26*100,2),0)) | T26: =IF(A26="","",ROUND((D26-O26)*M26,2))
... E34: =IF(A34="","",Settings!$B$14) | G34: =IF(A34="","",IF(F34<>"",F34,E34)) | H34: =IF(A34="","",Settings!$B$13) | J34: =IF(A34="","",IF(I34<>"",I34,H34)) | N34: =IF(A34="","",ROUND(D34*(1-G34/100),2)) | O34: =IF(A34="","",IF(K34<>"",K34,ROUND(N34*(1+J34/100),2))) | P34: =IF(A34="","",ROUND(N34*M34+L34,2)) | Q34: =IF(A34="","",ROUND(O34*M34+L34,2)) | R34: =IF(A34="","",ROUND(Q34-P34,2)) | S34: =IF(A34="","",IFERROR(ROUND(R34/Q34*100,2),0)) | T34: =IF(A34="","",ROUND((D34-O34)*M34,2))
A35: Total | B35: =COUNTA(B5:B34) -> 10 | L35: =SUM(L5:L34) -> 795 | M35: =SUM(M5:M34) -> 53 | P35: =SUM(P5:P34) -> 15311 | Q35: =SUM(Q5:Q34) -> 18824.5 | R35: =SUM(R5:R34) -> 3513.5 | S35: =IFERROR(ROUND(R35/Q35*100,2),0) -> 18.66 | T35: =SUM(T5:T34) -> 2250.5

Sheet Room Fees
A1: Room Fees
A2: One row per room. Complexity uplift % and rate default from Settings; type your own to override them. The block below totals each project and applies your minimum project fee.
A4: Project | B4: Room | C4: Hours for the room | D4: Default complexity uplift % (Settings) | E4: or type your own uplift % | F4: Uplift % used | G4: Default rate (Settings) | H4: or type your own rate | I4: Rate used | J4: Hours with uplift | K4: Room fee
A5: Hart residence | B5: Living room | C5: 18 | D5: =IF(A5="","",Settings!$B$17) -> 10 | F5: =IF(A5="","",IF(E5<>"",E5,D5)) -> 10 | G5: =IF(A5="","",Settings!$B$20) -> 68.18 | I5: =IF(A5="","",IF(H5<>"",H5,G5)) -> 68.18 | J5: =IF(A5="","",ROUND(C5*(1+F5/100),2)) -> 19.8 | K5: =IF(A5="","",ROUND(J5*I5,2)) -> 1349.96
A6: Hart residence | B6: Kitchen | C6: 24 | D6: =IF(A6="","",Settings!$B$17) -> 10 | E6: 20 | F6: =IF(A6="","",IF(E6<>"",E6,D6)) -> 20 | G6: =IF(A6="","",Settings!$B$20) -> 68.18 | I6: =IF(A6="","",IF(H6<>"",H6,G6)) -> 68.18 | J6: =IF(A6="","",ROUND(C6*(1+F6/100),2)) -> 28.8 | K6: =IF(A6="","",ROUND(J6*I6,2)) -> 1963.58
A7: Hart residence | B7: Primary bedroom | C7: 14 | D7: =IF(A7="","",Settings!$B$17) -> 10 | F7: =IF(A7="","",IF(E7<>"",E7,D7)) -> 10 | G7: =IF(A7="","",Settings!$B$20) -> 68.18 | I7: =IF(A7="","",IF(H7<>"",H7,G7)) -> 68.18 | J7: =IF(A7="","",ROUND(C7*(1+F7/100),2)) -> 15.4 | K7: =IF(A7="","",ROUND(J7*I7,2)) -> 1049.97
A8: Lake Street loft | B8: Open-plan living | C8: 20 | D8: =IF(A8="","",Settings!$B$17) -> 10 | F8: =IF(A8="","",IF(E8<>"",E8,D8)) -> 10 | G8: =IF(A8="","",Settings!$B$20) -> 68.18 | I8: =IF(A8="","",IF(H8<>"",H8,G8)) -> 68.18 | J8: =IF(A8="","",ROUND(C8*(1+F8/100),2)) -> 22 | K8: =IF(A8="","",ROUND(J8*I8,2)) -> 1499.96
A9: Lake Street loft | B9: Bedroom | C9: 10 | D9: =IF(A9="","",Settings!$B$17) -> 10 | F9: =IF(A9="","",IF(E9<>"",E9,D9)) -> 10 | G9: =IF(A9="","",Settings!$B$20) -> 68.18 | I9: =IF(A9="","",IF(H9<>"",H9,G9)) -> 68.18 | J9: =IF(A9="","",ROUND(C9*(1+F9/100),2)) -> 11 | K9: =IF(A9="","",ROUND(J9*I9,2)) -> 749.98
A10: Lake Street loft | B10: Bathroom | C10: 12 | D10: =IF(A10="","",Settings!$B$17) -> 10 | F10: =IF(A10="","",IF(E10<>"",E10,D10)) -> 10 | G10: =IF(A10="","",Settings!$B$20) -> 68.18 | H10: 80 | I10: =IF(A10="","",IF(H10<>"",H10,G10)) -> 80 | J10: =IF(A10="","",ROUND(C10*(1+F10/100),2)) -> 13.2 | K10: =IF(A10="","",ROUND(J10*I10,2)) -> 1056
A11: Corner cafe | B11: Dining area | C11: 22 | D11: =IF(A11="","",Settings!$B$17) -> 10 | F11: =IF(A11="","",IF(E11<>"",E11,D11)) -> 10 | G11: =IF(A11="","",Settings!$B$20) -> 68.18 | I11: =IF(A11="","",IF(H11<>"",H11,G11)) -> 68.18 | J11: =IF(A11="","",ROUND(C11*(1+F11/100),2)) -> 24.2 | K11: =IF(A11="","",ROUND(J11*I11,2)) -> 1649.96
A12: Corner cafe | B12: Restroom | C12: 6 | D12: =IF(A12="","",Settings!$B$17) -> 10 | F12: =IF(A12="","",IF(E12<>"",E12,D12)) -> 10 | G12: =IF(A12="","",Settings!$B$20) -> 68.18 | I12: =IF(A12="","",IF(H12<>"",H12,G12)) -> 68.18 | J12: =IF(A12="","",ROUND(C12*(1+F12/100),2)) -> 6.6 | K12: =IF(A12="","",ROUND(J12*I12,2)) -> 449.99
D13: =IF(A13="","",Settings!$B$17) | F13: =IF(A13="","",IF(E13<>"",E13,D13)) | G13: =IF(A13="","",Settings!$B$20) | I13: =IF(A13="","",IF(H13<>"",H13,G13)) | J13: =IF(A13="","",ROUND(C13*(1+F13/100),2)) | K13: =IF(A13="","",ROUND(J13*I13,2))
D14: =IF(A14="","",Settings!$B$17) | F14: =IF(A14="","",IF(E14<>"",E14,D14)) | G14: =IF(A14="","",Settings!$B$20) | I14: =IF(A14="","",IF(H14<>"",H14,G14)) | J14: =IF(A14="","",ROUND(C14*(1+F14/100),2)) | K14: =IF(A14="","",ROUND(J14*I14,2))
D15: =IF(A15="","",Settings!$B$17) | F15: =IF(A15="","",IF(E15<>"",E15,D15)) | G15: =IF(A15="","",Settings!$B$20) | I15: =IF(A15="","",IF(H15<>"",H15,G15)) | J15: =IF(A15="","",ROUND(C15*(1+F15/100),2)) | K15: =IF(A15="","",ROUND(J15*I15,2))
D16: =IF(A16="","",Settings!$B$17) | F16: =IF(A16="","",IF(E16<>"",E16,D16)) | G16: =IF(A16="","",Settings!$B$20) | I16: =IF(A16="","",IF(H16<>"",H16,G16)) | J16: =IF(A16="","",ROUND(C16*(1+F16/100),2)) | K16: =IF(A16="","",ROUND(J16*I16,2))
A17: Total | B17: =COUNTA(B5:B16) -> 8 | C17: =SUM(C5:C16) -> 126 | J17: =SUM(J5:J16) -> 141 | K17: =SUM(K5:K16) -> 9769.4
A18: PER-PROJECT FLAT FEE
A19: Project | B19: Rooms | C19: Room fees | D19: Site visit hours | E19: Site visit fee | F19: Fee before minimum | G19: Project fee (at least the minimum) | H19: Minimum check | I19: Fee per room
A20: Hart residence | B20: =IF(A20="","",COUNTIF($A$5:$A$16,A20)) -> 3 | C20: =IF(A20="","",SUMIF($A$5:$A$16,A20,$K$5:$K$16)) -> 4363.51 | D20: 8 | E20: =IF(A20="","",ROUND(D20*Settings!$B$20,2)) -> 545.44 | F20: =IF(A20="","",ROUND(C20+E20,2)) -> 4908.95 | G20: =IF(A20="","",MAX(F20,Settings!$B$16)) -> 4908.95 | H20: =IF(A20="","",IF(F20<Settings!$B$16,"minimum applies","")) | I20: =IF(A20="","",IFERROR(ROUND(G20/B20,2),0)) -> 1636.32
A21: Lake Street loft | B21: =IF(A21="","",COUNTIF($A$5:$A$16,A21)) -> 3 | C21: =IF(A21="","",SUMIF($A$5:$A$16,A21,$K$5:$K$16)) -> 3305.94 | D21: 6 | E21: =IF(A21="","",ROUND(D21*Settings!$B$20,2)) -> 409.08 | F21: =IF(A21="","",ROUND(C21+E21,2)) -> 3715.02 | G21: =IF(A21="","",MAX(F21,Settings!$B$16)) -> 3715.02 | H21: =IF(A21="","",IF(F21<Settings!$B$16,"minimum applies","")) | I21: =IF(A21="","",IFERROR(ROUND(G21/B21,2),0)) -> 1238.34
A22: Corner cafe | B22: =IF(A22="","",COUNTIF($A$5:$A$16,A22)) -> 2 | C22: =IF(A22="","",SUMIF($A$5:$A$16,A22,$K$5:$K$16)) -> 2099.95 | D22: 4 | E22: =IF(A22="","",ROUND(D22*Settings!$B$20,2)) -> 272.72 | F22: =IF(A22="","",ROUND(C22+E22,2)) -> 2372.67 | G22: =IF(A22="","",MAX(F22,Settings!$B$16)) -> 2500 | H22: =IF(A22="","",IF(F22<Settings!$B$16,"minimum applies","")) -> minimum applies | I22: =IF(A22="","",IFERROR(ROUND(G22/B22,2),0)) -> 1250
B23: =IF(A23="","",COUNTIF($A$5:$A$16,A23)) | C23: =IF(A23="","",SUMIF($A$5:$A$16,A23,$K$5:$K$16)) | E23: =IF(A23="","",ROUND(D23*Settings!$B$20,2)) | F23: =IF(A23="","",ROUND(C23+E23,2)) | G23: =IF(A23="","",MAX(F23,Settings!$B$16)) | H23: =IF(A23="","",IF(F23<Settings!$B$16,"minimum applies","")) | I23: =IF(A23="","",IFERROR(ROUND(G23/B23,2),0))
B24: =IF(A24="","",COUNTIF($A$5:$A$16,A24)) | C24: =IF(A24="","",SUMIF($A$5:$A$16,A24,$K$5:$K$16)) | E24: =IF(A24="","",ROUND(D24*Settings!$B$20,2)) | F24: =IF(A24="","",ROUND(C24+E24,2)) | G24: =IF(A24="","",MAX(F24,Settings!$B$16)) | H24: =IF(A24="","",IF(F24<Settings!$B$16,"minimum applies","")) | I24: =IF(A24="","",IFERROR(ROUND(G24/B24,2),0))
B25: =IF(A25="","",COUNTIF($A$5:$A$16,A25)) | C25: =IF(A25="","",SUMIF($A$5:$A$16,A25,$K$5:$K$16)) | E25: =IF(A25="","",ROUND(D25*Settings!$B$20,2)) | F25: =IF(A25="","",ROUND(C25+E25,2)) | G25: =IF(A25="","",MAX(F25,Settings!$B$16)) | H25: =IF(A25="","",IF(F25<Settings!$B$16,"minimum applies","")) | I25: =IF(A25="","",IFERROR(ROUND(G25/B25,2),0))

Sheet Budget Plan
A1: Budget Plan
A2: One row per project. The design fee % defaults from the percentage fee % on Settings; type your own to override it. Type the furniture, construction and contingency shares as % of the total budget.
A4: Project | B4: Total budget | C4: Default design fee % (Settings) | D4: or type your own design fee % | E4: Design fee % used | F4: Furniture % | G4: Construction % | H4: Contingency % | I4: Design fee amount | J4: Furniture amount | K4: Construction amount | L4: Contingency amount | M4: Allocated % | N4: Allocated amount | O4: Remaining | P4: Status
A5: Hart residence | B5: 120000 | C5: =IF(A5="","",Settings!$B$12) -> 15 | E5: =IF(A5="","",IF(D5<>"",D5,C5)) -> 15 | F5: 40 | G5: 30 | H5: 10 | I5: =IF(A5="","",ROUND(B5*E5/100,2)) -> 18000 | J5: =IF(A5="","",ROUND(B5*F5/100,2)) -> 48000 | K5: =IF(A5="","",ROUND(B5*G5/100,2)) -> 36000 | L5: =IF(A5="","",ROUND(B5*H5/100,2)) -> 12000 | M5: =IF(A5="","",E5+F5+G5+H5) -> 95 | N5: =IF(A5="","",ROUND(I5+J5+K5+L5,2)) -> 114000 | O5: =IF(A5="","",ROUND(B5-N5,2)) -> 6000 | P5: =IF(A5="","",IF(O5<0,"over-allocated",IF(O5>0,"unallocated","fully allocated"))) -> unallocated
A6: Lake Street loft | B6: 60000 | C6: =IF(A6="","",Settings!$B$12) -> 15 | E6: =IF(A6="","",IF(D6<>"",D6,C6)) -> 15 | F6: 45 | G6: 30 | H6: 10 | I6: =IF(A6="","",ROUND(B6*E6/100,2)) -> 9000 | J6: =IF(A6="","",ROUND(B6*F6/100,2)) -> 27000 | K6: =IF(A6="","",ROUND(B6*G6/100,2)) -> 18000 | L6: =IF(A6="","",ROUND(B6*H6/100,2)) -> 6000 | M6: =IF(A6="","",E6+F6+G6+H6) -> 100 | N6: =IF(A6="","",ROUND(I6+J6+K6+L6,2)) -> 60000 | O6: =IF(A6="","",ROUND(B6-N6,2)) -> 0 | P6: =IF(A6="","",IF(O6<0,"over-allocated",IF(O6>0,"unallocated","fully allocated"))) -> fully allocated
A7: Corner cafe | B7: 45000 | C7: =IF(A7="","",Settings!$B$12) -> 15 | D7: 12 | E7: =IF(A7="","",IF(D7<>"",D7,C7)) -> 12 | F7: 35 | G7: 50 | H7: 10 | I7: =IF(A7="","",ROUND(B7*E7/100,2)) -> 5400 | J7: =IF(A7="","",ROUND(B7*F7/100,2)) -> 15750 | K7: =IF(A7="","",ROUND(B7*G7/100,2)) -> 22500 | L7: =IF(A7="","",ROUND(B7*H7/100,2)) -> 4500 | M7: =IF(A7="","",E7+F7+G7+H7) -> 107 | N7: =IF(A7="","",ROUND(I7+J7+K7+L7,2)) -> 48150 | O7: =IF(A7="","",ROUND(B7-N7,2)) -> -3150 | P7: =IF(A7="","",IF(O7<0,"over-allocated",IF(O7>0,"unallocated","fully allocated"))) -> over-allocated
A8: Mill house | B8: 250000 | C8: =IF(A8="","",Settings!$B$12) -> 15 | E8: =IF(A8="","",IF(D8<>"",D8,C8)) -> 15 | F8: 30 | G8: 40 | H8: 10 | I8: =IF(A8="","",ROUND(B8*E8/100,2)) -> 37500 | J8: =IF(A8="","",ROUND(B8*F8/100,2)) -> 75000 | K8: =IF(A8="","",ROUND(B8*G8/100,2)) -> 100000 | L8: =IF(A8="","",ROUND(B8*H8/100,2)) -> 25000 | M8: =IF(A8="","",E8+F8+G8+H8) -> 95 | N8: =IF(A8="","",ROUND(I8+J8+K8+L8,2)) -> 237500 | O8: =IF(A8="","",ROUND(B8-N8,2)) -> 12500 | P8: =IF(A8="","",IF(O8<0,"over-allocated",IF(O8>0,"unallocated","fully allocated"))) -> unallocated
C9: =IF(A9="","",Settings!$B$12) | E9: =IF(A9="","",IF(D9<>"",D9,C9)) | I9: =IF(A9="","",ROUND(B9*E9/100,2)) | J9: =IF(A9="","",ROUND(B9*F9/100,2)) | K9: =IF(A9="","",ROUND(B9*G9/100,2)) | L9: =IF(A9="","",ROUND(B9*H9/100,2)) | M9: =IF(A9="","",E9+F9+G9+H9) | N9: =IF(A9="","",ROUND(I9+J9+K9+L9,2)) | O9: =IF(A9="","",ROUND(B9-N9,2)) | P9: =IF(A9="","",IF(O9<0,"over-allocated",IF(O9>0,"unallocated","fully allocated")))
C10: =IF(A10="","",Settings!$B$12) | E10: =IF(A10="","",IF(D10<>"",D10,C10)) | I10: =IF(A10="","",ROUND(B10*E10/100,2)) | J10: =IF(A10="","",ROUND(B10*F10/100,2)) | K10: =IF(A10="","",ROUND(B10*G10/100,2)) | L10: =IF(A10="","",ROUND(B10*H10/100,2)) | M10: =IF(A10="","",E10+F10+G10+H10) | N10: =IF(A10="","",ROUND(I10+J10+K10+L10,2)) | O10: =IF(A10="","",ROUND(B10-N10,2)) | P10: =IF(A10="","",IF(O10<0,"over-allocated",IF(O10>0,"unallocated","fully allocated")))
A11: Total | B11: =SUM(B5:B10) -> 475000 | I11: =SUM(I5:I10) -> 69900 | J11: =SUM(J5:J10) -> 165750 | K11: =SUM(K5:K10) -> 176500 | L11: =SUM(L5:L10) -> 47500 | M11: =IFERROR(ROUND(N11/B11*100,2),0) -> 96.77 | N11: =SUM(N5:N10) -> 459650 | O11: =SUM(O5:O10) -> 15350

Sheet Summary
A1: Summary
A2: Hourly rate needed | B2: =Settings!$B$18 -> 68.18 | C2: from Settings: (income goal + overhead) ÷ billable hours
A3: Rate used for pricing | B3: =Settings!$B$20 -> 68.18 | C3: from Settings: your own rate if typed, otherwise the rate needed
A4: Projects quoted | B4: =COUNTA('Fee Builder'!$A$5:$A$24) -> 6 | C4: rows with a project name on Fee Builder
A5: Total design fees quoted | B5: ='Fee Builder'!T25 -> 28806.05 | C5: Fee Builder totals
A6: Projects where the percentage fee pays more | B6: =COUNTIF('Fee Builder'!$X$5:$X$24,"percentage fee") -> 5 | C6: budget × percentage fee % is above the hourly design fee
A7: Projects at the minimum fee | B7: =COUNTIF('Fee Builder'!$Z$5:$Z$24,"minimum applies") -> 1 | C7: design fee below the minimum project fee on Settings
A8: Procurement revenue | B8: =Procurement!Q35 -> 18824.5 | C8: Procurement totals, freight included at cost
A9: Procurement gross profit | B9: =Procurement!R35 -> 3513.5 | C9: line revenue − line cost
A10: Procurement margin % | B10: =Procurement!S35 -> 18.66 | C10: gross profit ÷ revenue, from the totals
A11: Items priced above retail | B11: =COUNTIF(Procurement!$T$5:$T$34,"<0") -> 1 | C11: items where the client saving vs retail is negative
A12: Highest-fee project | B12: =IFERROR(INDEX('Fee Builder'!$A$5:$A$24,MATCH(MAX('Fee Builder'!$T$5:$T$24),'Fee Builder'!$T$5:$T$24,0)),"") -> Mill house | C12: largest design fee on Fee Builder
A13: Its design fee | B13: =IFERROR(MAX('Fee Builder'!$T$5:$T$24),0) -> 10124.73 | C13: highest design fee on Fee Builder
A14: Budgets over-allocated | B14: =COUNTIF('Budget Plan'!$P$5:$P$10,"over-allocated") -> 1 | C14: Budget Plan rows where the shares add up to more than the budget
