Workbook

Sheet Start Here
A1: Bookkeeping Practice Pricing Workbook
A2: by Knackdesk · knackdesk.com
A4: HOW TO USE
A5: 1. Settings: your monthly overhead line by line, owner income goal, staff cost, working weeks, hours, billable share, standard hourly rate, scope buffer, commitment discount, per-transaction rate and per-account fee. Every other sheet reads them.
A6: 2. Package Builder: one row per client with entity type, transactions, bank and card accounts, add-ons, hours, base fee and what you charge today. The suggested package fee, hourly-equivalent fee, recommended fee, the gap, effective hourly rate and annual fee are calculated.
A7: 3. Catch-Up Quotes: one row per catch-up or clean-up job with months behind, hours per month, rate, setup fee and discount. Total hours, labour cost, discount, quote total and the per-month figure are calculated.
A8: 4. Capacity: how many clients your billable hours can hold after admin time, hours used, spare hours, open client slots and revenue at capacity, read from the Package Builder unless you type your own figures.
A9: 5. Realization Log: one row per month with hours worked, standard rate, amount billed and amount collected. Standard fees, billing, collection and overall realization, write-offs, uncollected and effective rate are calculated, with totals.
A10: 6. Summary: cost-recovery rate against the rate you price with, clients priced below recommended, revenue now and at recommended fees, highest and lowest effective hourly rate clients, open slots and year-to-date realization.
A12: LEGEND
A13: Blue text = a cell you type into. Black text = a formula, leave it alone. Yellow fill = key inputs.
A15: DEFINITIONS
... A25: Arithmetic only; not financial advice.

Sheet Settings
A1: Settings
A2: Software and subscriptions (monthly) | B2: 250 | C2: Example default 250 a month. Ledger software seats, receipt capture, practice management, e-signature.
A3: Insurance (monthly) | B3: 90 | C3: Example default 90 a month. Professional indemnity and cyber cover.
A4: Office or coworking (monthly) | B4: 300 | C4: Example default 300 a month. Rent, desk or a share of home office costs.
A5: Marketing (monthly) | B5: 100 | C5: Example default 100 a month. Website, listings, directory fees, ads.
A6: Professional fees and CPE (monthly) | B6: 60 | C6: Example default 60 a month. Memberships, licences, continuing education spread over 12 months.
A7: Other overhead (monthly) | B7: 100 | C7: Example default 100 a month. Phone, internet, bank charges, anything else.
A8: Total monthly overhead | B8: =SUM(B2:B7) -> 900 | C8: formula: sum of the six overhead rows above
A9: Monthly owner income goal | B9: 4500 | C9: Example default 4,500 a month. What you want to pay yourself before personal tax.
A10: Staff cost per month | B10: 0 | C10: Default 0. Wages, contractor and payroll costs for anyone else working on client files.
A11: Working weeks per year | B11: 48 | C11: Default 48: 52 weeks less 4 weeks of holiday, sickness and training.
A12: Hours worked per week | B12: 40 | C12: Default 40. All hours at work, including admin, sales and learning.
A13: Share of hours that are billable % | B13: 70 | C13: Default 70. The share of your hours spent on client work; the rest is admin, sales and learning.
A14: Standard hourly rate | B14: 90 | C14: Default 90. The hourly rate you price with; set it at or above the cost-recovery rate in row 20.
A15: Scope buffer % for fixed fees | B15: 15 | C15: Default 15. Added to hours × rate when turning hours into a fixed fee, to cover scope creep and messy months.
A16: Commitment discount % | B16: 5 | C16: Default 5. Taken off the hourly-equivalent fee for clients who commit to a monthly package.
A17: Per-transaction rate | B17: 1.5 | C17: Default 1.50 per transaction a month. Used in the package fee on the Package Builder.
A18: Per-bank-account fee | B18: 25 | C18: Default 25 per bank or card account a month. Covers reconciling each account.
A19: Billable hours per month | B19: =ROUND(B12*B13/100*B11/12,2) -> 112 | C19: formula: hours per week × billable % × working weeks ÷ 12
A20: Cost-recovery hourly rate | B20: =IFERROR(ROUND((B8+B9+B10)/B19,2),0) -> 48.21 | C20: formula: (total overhead + income goal + staff cost) ÷ billable hours per month; the least each billable hour must earn
A21: Rate used for pricing | B21: =B14 -> 90 | C21: formula: the standard hourly rate in row 14; set that at or above the cost-recovery rate above
A22: Rate per minute | B22: =ROUND(B21/60,4) -> 1.5 | C22: formula: rate used for pricing ÷ 60

Sheet Package Builder
A1: Package Builder
A2: One row per client. Charges use the per-transaction rate, per-account fee, rate, scope buffer and commitment discount from Settings; the recommended fee is the higher of the package fee and the hourly-equivalent fee.
A4: Client | B4: Entity type | C4: Transactions per month | D4: Bank and card accounts | E4: Add-ons monthly | F4: Estimated hours per month | G4: Base fee | H4: Current fee charged | I4: Transaction charge | J4: Account charge | K4: Suggested monthly fee | L4: Hourly-equivalent fee | M4: Recommended fee | N4: Gap (current − recommended) | O4: Effective hourly rate at current fee | P4: Annual at current fee
A5: Riverside Cafe | B5: company | C5: 180 | D5: 3 | E5: 50 | F5: 7 | G5: 250 | H5: 550 | I5: =IF(A5="","",ROUND(C5*Settings!$B$17,2)) -> 270 | J5: =IF(A5="","",ROUND(D5*Settings!$B$18,2)) -> 75 | K5: =IF(A5="","",G5+I5+J5+E5) -> 645 | L5: =IF(A5="","",ROUND(F5*Settings!$B$21*(1+Settings!$B$15/100)*(1-Settings!$B$16/100),2)) -> 688.28 | M5: =IF(A5="","",MAX(K5,L5)) -> 688.28 | N5: =IF(A5="","",H5-M5) -> -138.28 | O5: =IF(A5="","",IFERROR(ROUND(H5/F5,2),0)) -> 78.57 | P5: =IF(A5="","",ROUND(H5*12,2)) -> 6600
A6: Okafor Consulting | B6: sole trader | C6: 40 | D6: 1 | E6: 0 | F6: 2.5 | G6: 150 | H6: 220 | I6: =IF(A6="","",ROUND(C6*Settings!$B$17,2)) -> 60 | J6: =IF(A6="","",ROUND(D6*Settings!$B$18,2)) -> 25 | K6: =IF(A6="","",G6+I6+J6+E6) -> 235 | L6: =IF(A6="","",ROUND(F6*Settings!$B$21*(1+Settings!$B$15/100)*(1-Settings!$B$16/100),2)) -> 245.81 | M6: =IF(A6="","",MAX(K6,L6)) -> 245.81 | N6: =IF(A6="","",H6-M6) -> -25.81 | O6: =IF(A6="","",IFERROR(ROUND(H6/F6,2),0)) -> 88 | P6: =IF(A6="","",ROUND(H6*12,2)) -> 2640
A7: Lindqvist Dental Partners | B7: partnership | C7: 260 | D7: 4 | E7: 120 | F7: 9 | G7: 300 | H7: 950 | I7: =IF(A7="","",ROUND(C7*Settings!$B$17,2)) -> 390 | J7: =IF(A7="","",ROUND(D7*Settings!$B$18,2)) -> 100 | K7: =IF(A7="","",G7+I7+J7+E7) -> 910 | L7: =IF(A7="","",ROUND(F7*Settings!$B$21*(1+Settings!$B$15/100)*(1-Settings!$B$16/100),2)) -> 884.93 | M7: =IF(A7="","",MAX(K7,L7)) -> 910 | N7: =IF(A7="","",H7-M7) -> 40 | O7: =IF(A7="","",IFERROR(ROUND(H7/F7,2),0)) -> 105.56 | P7: =IF(A7="","",ROUND(H7*12,2)) -> 11400
A8: Hope Street Food Bank | B8: nonprofit | C8: 90 | D8: 2 | E8: 40 | F8: 4 | G8: 200 | H8: 380 | I8: =IF(A8="","",ROUND(C8*Settings!$B$17,2)) -> 135 | J8: =IF(A8="","",ROUND(D8*Settings!$B$18,2)) -> 50 | K8: =IF(A8="","",G8+I8+J8+E8) -> 425 | L8: =IF(A8="","",ROUND(F8*Settings!$B$21*(1+Settings!$B$15/100)*(1-Settings!$B$16/100),2)) -> 393.3 | M8: =IF(A8="","",MAX(K8,L8)) -> 425 | N8: =IF(A8="","",H8-M8) -> -45 | O8: =IF(A8="","",IFERROR(ROUND(H8/F8,2),0)) -> 95 | P8: =IF(A8="","",ROUND(H8*12,2)) -> 4560
A9: Nguyen Builders Ltd | B9: company | C9: 320 | D9: 5 | E9: 150 | F9: 12 | G9: 350 | H9: 600 | I9: =IF(A9="","",ROUND(C9*Settings!$B$17,2)) -> 480 | J9: =IF(A9="","",ROUND(D9*Settings!$B$18,2)) -> 125 | K9: =IF(A9="","",G9+I9+J9+E9) -> 1105 | L9: =IF(A9="","",ROUND(F9*Settings!$B$21*(1+Settings!$B$15/100)*(1-Settings!$B$16/100),2)) -> 1179.9 | M9: =IF(A9="","",MAX(K9,L9)) -> 1179.9 | N9: =IF(A9="","",H9-M9) -> -579.9 | O9: =IF(A9="","",IFERROR(ROUND(H9/F9,2),0)) -> 50 | P9: =IF(A9="","",ROUND(H9*12,2)) -> 7200
A10: Patel Design Studio | B10: sole trader | C10: 60 | D10: 2 | E10: 0 | F10: 3 | G10: 150 | H10: 340 | I10: =IF(A10="","",ROUND(C10*Settings!$B$17,2)) -> 90 | J10: =IF(A10="","",ROUND(D10*Settings!$B$18,2)) -> 50 | K10: =IF(A10="","",G10+I10+J10+E10) -> 290 | L10: =IF(A10="","",ROUND(F10*Settings!$B$21*(1+Settings!$B$15/100)*(1-Settings!$B$16/100),2)) -> 294.98 | M10: =IF(A10="","",MAX(K10,L10)) -> 294.98 | N10: =IF(A10="","",H10-M10) -> 45.02 | O10: =IF(A10="","",IFERROR(ROUND(H10/F10,2),0)) -> 113.33 | P10: =IF(A10="","",ROUND(H10*12,2)) -> 4080
A11: Green & Co Landscaping | B11: partnership | C11: 120 | D11: 2 | E11: 30 | F11: 5 | G11: 250 | H11: 520 | I11: =IF(A11="","",ROUND(C11*Settings!$B$17,2)) -> 180 | J11: =IF(A11="","",ROUND(D11*Settings!$B$18,2)) -> 50 | K11: =IF(A11="","",G11+I11+J11+E11) -> 510 | L11: =IF(A11="","",ROUND(F11*Settings!$B$21*(1+Settings!$B$15/100)*(1-Settings!$B$16/100),2)) -> 491.63 | M11: =IF(A11="","",MAX(K11,L11)) -> 510 | N11: =IF(A11="","",H11-M11) -> 10 | O11: =IF(A11="","",IFERROR(ROUND(H11/F11,2),0)) -> 104 | P11: =IF(A11="","",ROUND(H11*12,2)) -> 6240
A12: Mason Family Trust | B12: other | C12: 25 | D12: 2 | E12: 0 | F12: 1.5 | G12: 150 | H12: 260 | I12: =IF(A12="","",ROUND(C12*Settings!$B$17,2)) -> 37.5 | J12: =IF(A12="","",ROUND(D12*Settings!$B$18,2)) -> 50 | K12: =IF(A12="","",G12+I12+J12+E12) -> 237.5 | L12: =IF(A12="","",ROUND(F12*Settings!$B$21*(1+Settings!$B$15/100)*(1-Settings!$B$16/100),2)) -> 147.49 | M12: =IF(A12="","",MAX(K12,L12)) -> 237.5 | N12: =IF(A12="","",H12-M12) -> 22.5 | O12: =IF(A12="","",IFERROR(ROUND(H12/F12,2),0)) -> 173.33 | P12: =IF(A12="","",ROUND(H12*12,2)) -> 3120
I13: =IF(A13="","",ROUND(C13*Settings!$B$17,2)) | J13: =IF(A13="","",ROUND(D13*Settings!$B$18,2)) | K13: =IF(A13="","",G13+I13+J13+E13) | L13: =IF(A13="","",ROUND(F13*Settings!$B$21*(1+Settings!$B$15/100)*(1-Settings!$B$16/100),2)) | M13: =IF(A13="","",MAX(K13,L13)) | N13: =IF(A13="","",H13-M13) | O13: =IF(A13="","",IFERROR(ROUND(H13/F13,2),0)) | P13: =IF(A13="","",ROUND(H13*12,2))
I14: =IF(A14="","",ROUND(C14*Settings!$B$17,2)) | J14: =IF(A14="","",ROUND(D14*Settings!$B$18,2)) | K14: =IF(A14="","",G14+I14+J14+E14) | L14: =IF(A14="","",ROUND(F14*Settings!$B$21*(1+Settings!$B$15/100)*(1-Settings!$B$16/100),2)) | M14: =IF(A14="","",MAX(K14,L14)) | N14: =IF(A14="","",H14-M14) | O14: =IF(A14="","",IFERROR(ROUND(H14/F14,2),0)) | P14: =IF(A14="","",ROUND(H14*12,2))
I15: =IF(A15="","",ROUND(C15*Settings!$B$17,2)) | J15: =IF(A15="","",ROUND(D15*Settings!$B$18,2)) | K15: =IF(A15="","",G15+I15+J15+E15) | L15: =IF(A15="","",ROUND(F15*Settings!$B$21*(1+Settings!$B$15/100)*(1-Settings!$B$16/100),2)) | M15: =IF(A15="","",MAX(K15,L15)) | N15: =IF(A15="","",H15-M15) | O15: =IF(A15="","",IFERROR(ROUND(H15/F15,2),0)) | P15: =IF(A15="","",ROUND(H15*12,2))
I16: =IF(A16="","",ROUND(C16*Settings!$B$17,2)) | J16: =IF(A16="","",ROUND(D16*Settings!$B$18,2)) | K16: =IF(A16="","",G16+I16+J16+E16) | L16: =IF(A16="","",ROUND(F16*Settings!$B$21*(1+Settings!$B$15/100)*(1-Settings!$B$16/100),2)) | M16: =IF(A16="","",MAX(K16,L16)) | N16: =IF(A16="","",H16-M16) | O16: =IF(A16="","",IFERROR(ROUND(H16/F16,2),0)) | P16: =IF(A16="","",ROUND(H16*12,2))
I17: =IF(A17="","",ROUND(C17*Settings!$B$17,2)) | J17: =IF(A17="","",ROUND(D17*Settings!$B$18,2)) | K17: =IF(A17="","",G17+I17+J17+E17) | L17: =IF(A17="","",ROUND(F17*Settings!$B$21*(1+Settings!$B$15/100)*(1-Settings!$B$16/100),2)) | M17: =IF(A17="","",MAX(K17,L17)) | N17: =IF(A17="","",H17-M17) | O17: =IF(A17="","",IFERROR(ROUND(H17/F17,2),0)) | P17: =IF(A17="","",ROUND(H17*12,2))
I18: =IF(A18="","",ROUND(C18*Settings!$B$17,2)) | J18: =IF(A18="","",ROUND(D18*Settings!$B$18,2)) | K18: =IF(A18="","",G18+I18+J18+E18) | L18: =IF(A18="","",ROUND(F18*Settings!$B$21*(1+Settings!$B$15/100)*(1-Settings!$B$16/100),2)) | M18: =IF(A18="","",MAX(K18,L18)) | N18: =IF(A18="","",H18-M18) | O18: =IF(A18="","",IFERROR(ROUND(H18/F18,2),0)) | P18: =IF(A18="","",ROUND(H18*12,2))
I19: =IF(A19="","",ROUND(C19*Settings!$B$17,2)) | J19: =IF(A19="","",ROUND(D19*Settings!$B$18,2)) | K19: =IF(A19="","",G19+I19+J19+E19) | L19: =IF(A19="","",ROUND(F19*Settings!$B$21*(1+Settings!$B$15/100)*(1-Settings!$B$16/100),2)) | M19: =IF(A19="","",MAX(K19,L19)) | N19: =IF(A19="","",H19-M19) | O19: =IF(A19="","",IFERROR(ROUND(H19/F19,2),0)) | P19: =IF(A19="","",ROUND(H19*12,2))
I20: =IF(A20="","",ROUND(C20*Settings!$B$17,2)) | J20: =IF(A20="","",ROUND(D20*Settings!$B$18,2)) | K20: =IF(A20="","",G20+I20+J20+E20) | L20: =IF(A20="","",ROUND(F20*Settings!$B$21*(1+Settings!$B$15/100)*(1-Settings!$B$16/100),2)) | M20: =IF(A20="","",MAX(K20,L20)) | N20: =IF(A20="","",H20-M20) | O20: =IF(A20="","",IFERROR(ROUND(H20/F20,2),0)) | P20: =IF(A20="","",ROUND(H20*12,2))
I21: =IF(A21="","",ROUND(C21*Settings!$B$17,2)) | J21: =IF(A21="","",ROUND(D21*Settings!$B$18,2)) | K21: =IF(A21="","",G21+I21+J21+E21) | L21: =IF(A21="","",ROUND(F21*Settings!$B$21*(1+Settings!$B$15/100)*(1-Settings!$B$16/100),2)) | M21: =IF(A21="","",MAX(K21,L21)) | N21: =IF(A21="","",H21-M21) | O21: =IF(A21="","",IFERROR(ROUND(H21/F21,2),0)) | P21: =IF(A21="","",ROUND(H21*12,2))
I22: =IF(A22="","",ROUND(C22*Settings!$B$17,2)) | J22: =IF(A22="","",ROUND(D22*Settings!$B$18,2)) | K22: =IF(A22="","",G22+I22+J22+E22) | L22: =IF(A22="","",ROUND(F22*Settings!$B$21*(1+Settings!$B$15/100)*(1-Settings!$B$16/100),2)) | M22: =IF(A22="","",MAX(K22,L22)) | N22: =IF(A22="","",H22-M22) | O22: =IF(A22="","",IFERROR(ROUND(H22/F22,2),0)) | P22: =IF(A22="","",ROUND(H22*12,2))
I23: =IF(A23="","",ROUND(C23*Settings!$B$17,2)) | J23: =IF(A23="","",ROUND(D23*Settings!$B$18,2)) | K23: =IF(A23="","",G23+I23+J23+E23) | L23: =IF(A23="","",ROUND(F23*Settings!$B$21*(1+Settings!$B$15/100)*(1-Settings!$B$16/100),2)) | M23: =IF(A23="","",MAX(K23,L23)) | N23: =IF(A23="","",H23-M23) | O23: =IF(A23="","",IFERROR(ROUND(H23/F23,2),0)) | P23: =IF(A23="","",ROUND(H23*12,2))
I24: =IF(A24="","",ROUND(C24*Settings!$B$17,2)) | J24: =IF(A24="","",ROUND(D24*Settings!$B$18,2)) | K24: =IF(A24="","",G24+I24+J24+E24) | L24: =IF(A24="","",ROUND(F24*Settings!$B$21*(1+Settings!$B$15/100)*(1-Settings!$B$16/100),2)) | M24: =IF(A24="","",MAX(K24,L24)) | N24: =IF(A24="","",H24-M24) | O24: =IF(A24="","",IFERROR(ROUND(H24/F24,2),0)) | P24: =IF(A24="","",ROUND(H24*12,2))
... I34: =IF(A34="","",ROUND(C34*Settings!$B$17,2)) | J34: =IF(A34="","",ROUND(D34*Settings!$B$18,2)) | K34: =IF(A34="","",G34+I34+J34+E34) | L34: =IF(A34="","",ROUND(F34*Settings!$B$21*(1+Settings!$B$15/100)*(1-Settings!$B$16/100),2)) | M34: =IF(A34="","",MAX(K34,L34)) | N34: =IF(A34="","",H34-M34) | O34: =IF(A34="","",IFERROR(ROUND(H34/F34,2),0)) | P34: =IF(A34="","",ROUND(H34*12,2))
A35: Total | B35: =COUNTA(A5:A34) -> 8 | F35: =SUM(F5:F34) -> 44 | H35: =SUM(H5:H34) -> 3820 | K35: =SUM(K5:K34) -> 4357.5 | L35: =SUM(L5:L34) -> 4326.32 | M35: =SUM(M5:M34) -> 4491.47 | N35: =H35-M35 -> -671.47 | O35: =IFERROR(ROUND(H35/F35,2),0) -> 86.82 | P35: =SUM(P5:P34) -> 45840
A36: Total row: monthly revenue at current fees (column H), annual (column P), total hours (column F) and client count (column B).

Sheet Catch-Up Quotes
A1: Catch-Up Quotes
A2: One row per catch-up or clean-up job. The default rate comes from Settings; type your own rate in column E to override it for that quote.
A4: Client | B4: Months behind | C4: Hours per month | D4: Default rate (Settings) | E4: or type your own rate | F4: Rate used | G4: Setup fee | H4: Discount % | I4: Total hours | J4: Labour cost | K4: Subtotal | L4: Discount | M4: Quote total | N4: Per month caught up
A5: Harbour Bakery | B5: 6 | C5: 5 | D5: =IF(A5="","",Settings!$B$21) -> 90 | F5: =IF(A5="","",IF(E5<>"",E5,D5)) -> 90 | G5: 150 | H5: 10 | I5: =IF(A5="","",ROUND(B5*C5,2)) -> 30 | J5: =IF(A5="","",ROUND(I5*F5,2)) -> 2700 | K5: =IF(A5="","",J5+G5) -> 2850 | L5: =IF(A5="","",ROUND(K5*H5/100,2)) -> 285 | M5: =IF(A5="","",K5-L5) -> 2565 | N5: =IF(A5="","",IFERROR(ROUND(M5/B5,2),0)) -> 427.5
A6: Kowalski Plumbing | B6: 12 | C6: 3.5 | D6: =IF(A6="","",Settings!$B$21) -> 90 | E6: 80 | F6: =IF(A6="","",IF(E6<>"",E6,D6)) -> 80 | G6: 200 | H6: 0 | I6: =IF(A6="","",ROUND(B6*C6,2)) -> 42 | J6: =IF(A6="","",ROUND(I6*F6,2)) -> 3360 | K6: =IF(A6="","",J6+G6) -> 3560 | L6: =IF(A6="","",ROUND(K6*H6/100,2)) -> 0 | M6: =IF(A6="","",K6-L6) -> 3560 | N6: =IF(A6="","",IFERROR(ROUND(M6/B6,2),0)) -> 296.67
A7: Sunrise Yoga Studio | B7: 3 | C7: 4 | D7: =IF(A7="","",Settings!$B$21) -> 90 | F7: =IF(A7="","",IF(E7<>"",E7,D7)) -> 90 | G7: 100 | H7: 5 | I7: =IF(A7="","",ROUND(B7*C7,2)) -> 12 | J7: =IF(A7="","",ROUND(I7*F7,2)) -> 1080 | K7: =IF(A7="","",J7+G7) -> 1180 | L7: =IF(A7="","",ROUND(K7*H7/100,2)) -> 59 | M7: =IF(A7="","",K7-L7) -> 1121 | N7: =IF(A7="","",IFERROR(ROUND(M7/B7,2),0)) -> 373.67
A8: Ellis Property Group | B8: 9 | C8: 8 | D8: =IF(A8="","",Settings!$B$21) -> 90 | E8: 85 | F8: =IF(A8="","",IF(E8<>"",E8,D8)) -> 85 | G8: 250 | H8: 10 | I8: =IF(A8="","",ROUND(B8*C8,2)) -> 72 | J8: =IF(A8="","",ROUND(I8*F8,2)) -> 6120 | K8: =IF(A8="","",J8+G8) -> 6370 | L8: =IF(A8="","",ROUND(K8*H8/100,2)) -> 637 | M8: =IF(A8="","",K8-L8) -> 5733 | N8: =IF(A8="","",IFERROR(ROUND(M8/B8,2),0)) -> 637
D9: =IF(A9="","",Settings!$B$21) | F9: =IF(A9="","",IF(E9<>"",E9,D9)) | I9: =IF(A9="","",ROUND(B9*C9,2)) | J9: =IF(A9="","",ROUND(I9*F9,2)) | K9: =IF(A9="","",J9+G9) | L9: =IF(A9="","",ROUND(K9*H9/100,2)) | M9: =IF(A9="","",K9-L9) | N9: =IF(A9="","",IFERROR(ROUND(M9/B9,2),0))
D10: =IF(A10="","",Settings!$B$21) | F10: =IF(A10="","",IF(E10<>"",E10,D10)) | I10: =IF(A10="","",ROUND(B10*C10,2)) | J10: =IF(A10="","",ROUND(I10*F10,2)) | K10: =IF(A10="","",J10+G10) | L10: =IF(A10="","",ROUND(K10*H10/100,2)) | M10: =IF(A10="","",K10-L10) | N10: =IF(A10="","",IFERROR(ROUND(M10/B10,2),0))
D11: =IF(A11="","",Settings!$B$21) | F11: =IF(A11="","",IF(E11<>"",E11,D11)) | I11: =IF(A11="","",ROUND(B11*C11,2)) | J11: =IF(A11="","",ROUND(I11*F11,2)) | K11: =IF(A11="","",J11+G11) | L11: =IF(A11="","",ROUND(K11*H11/100,2)) | M11: =IF(A11="","",K11-L11) | N11: =IF(A11="","",IFERROR(ROUND(M11/B11,2),0))
D12: =IF(A12="","",Settings!$B$21) | F12: =IF(A12="","",IF(E12<>"",E12,D12)) | I12: =IF(A12="","",ROUND(B12*C12,2)) | J12: =IF(A12="","",ROUND(I12*F12,2)) | K12: =IF(A12="","",J12+G12) | L12: =IF(A12="","",ROUND(K12*H12/100,2)) | M12: =IF(A12="","",K12-L12) | N12: =IF(A12="","",IFERROR(ROUND(M12/B12,2),0))
D13: =IF(A13="","",Settings!$B$21) | F13: =IF(A13="","",IF(E13<>"",E13,D13)) | I13: =IF(A13="","",ROUND(B13*C13,2)) | J13: =IF(A13="","",ROUND(I13*F13,2)) | K13: =IF(A13="","",J13+G13) | L13: =IF(A13="","",ROUND(K13*H13/100,2)) | M13: =IF(A13="","",K13-L13) | N13: =IF(A13="","",IFERROR(ROUND(M13/B13,2),0))
D14: =IF(A14="","",Settings!$B$21) | F14: =IF(A14="","",IF(E14<>"",E14,D14)) | I14: =IF(A14="","",ROUND(B14*C14,2)) | J14: =IF(A14="","",ROUND(I14*F14,2)) | K14: =IF(A14="","",J14+G14) | L14: =IF(A14="","",ROUND(K14*H14/100,2)) | M14: =IF(A14="","",K14-L14) | N14: =IF(A14="","",IFERROR(ROUND(M14/B14,2),0))
D15: =IF(A15="","",Settings!$B$21) | F15: =IF(A15="","",IF(E15<>"",E15,D15)) | I15: =IF(A15="","",ROUND(B15*C15,2)) | J15: =IF(A15="","",ROUND(I15*F15,2)) | K15: =IF(A15="","",J15+G15) | L15: =IF(A15="","",ROUND(K15*H15/100,2)) | M15: =IF(A15="","",K15-L15) | N15: =IF(A15="","",IFERROR(ROUND(M15/B15,2),0))
D16: =IF(A16="","",Settings!$B$21) | F16: =IF(A16="","",IF(E16<>"",E16,D16)) | I16: =IF(A16="","",ROUND(B16*C16,2)) | J16: =IF(A16="","",ROUND(I16*F16,2)) | K16: =IF(A16="","",J16+G16) | L16: =IF(A16="","",ROUND(K16*H16/100,2)) | M16: =IF(A16="","",K16-L16) | N16: =IF(A16="","",IFERROR(ROUND(M16/B16,2),0))
D17: =IF(A17="","",Settings!$B$21) | F17: =IF(A17="","",IF(E17<>"",E17,D17)) | I17: =IF(A17="","",ROUND(B17*C17,2)) | J17: =IF(A17="","",ROUND(I17*F17,2)) | K17: =IF(A17="","",J17+G17) | L17: =IF(A17="","",ROUND(K17*H17/100,2)) | M17: =IF(A17="","",K17-L17) | N17: =IF(A17="","",IFERROR(ROUND(M17/B17,2),0))
D18: =IF(A18="","",Settings!$B$21) | F18: =IF(A18="","",IF(E18<>"",E18,D18)) | I18: =IF(A18="","",ROUND(B18*C18,2)) | J18: =IF(A18="","",ROUND(I18*F18,2)) | K18: =IF(A18="","",J18+G18) | L18: =IF(A18="","",ROUND(K18*H18/100,2)) | M18: =IF(A18="","",K18-L18) | N18: =IF(A18="","",IFERROR(ROUND(M18/B18,2),0))
D19: =IF(A19="","",Settings!$B$21) | F19: =IF(A19="","",IF(E19<>"",E19,D19)) | I19: =IF(A19="","",ROUND(B19*C19,2)) | J19: =IF(A19="","",ROUND(I19*F19,2)) | K19: =IF(A19="","",J19+G19) | L19: =IF(A19="","",ROUND(K19*H19/100,2)) | M19: =IF(A19="","",K19-L19) | N19: =IF(A19="","",IFERROR(ROUND(M19/B19,2),0))
D20: =IF(A20="","",Settings!$B$21) | F20: =IF(A20="","",IF(E20<>"",E20,D20)) | I20: =IF(A20="","",ROUND(B20*C20,2)) | J20: =IF(A20="","",ROUND(I20*F20,2)) | K20: =IF(A20="","",J20+G20) | L20: =IF(A20="","",ROUND(K20*H20/100,2)) | M20: =IF(A20="","",K20-L20) | N20: =IF(A20="","",IFERROR(ROUND(M20/B20,2),0))
... D24: =IF(A24="","",Settings!$B$21) | F24: =IF(A24="","",IF(E24<>"",E24,D24)) | I24: =IF(A24="","",ROUND(B24*C24,2)) | J24: =IF(A24="","",ROUND(I24*F24,2)) | K24: =IF(A24="","",J24+G24) | L24: =IF(A24="","",ROUND(K24*H24/100,2)) | M24: =IF(A24="","",K24-L24) | N24: =IF(A24="","",IFERROR(ROUND(M24/B24,2),0))
A25: Total | B25: =SUM(B5:B24) -> 30 | G25: =SUM(G5:G24) -> 700 | I25: =SUM(I5:I24) -> 156 | J25: =SUM(J5:J24) -> 13260 | K25: =SUM(K5:K24) -> 13960 | L25: =SUM(L5:L24) -> 981 | M25: =SUM(M5:M24) -> 12979

Sheet Capacity
A1: Capacity
A2: How many clients your billable hours can hold, and what they could earn.
A4: Billable hours per month | B4: =Settings!$B$19 -> 112 | C4: from Settings
A5: Admin share % of billable time | B5: 10 | C5: default 10: client emails, chasing documents, onboarding
A6: Usable hours per month | B6: =ROUND(B4*(1-B5/100),2) -> 100.8 | C6: billable hours × (1 − admin share %)
A7: Current clients from Package Builder | B7: ='Package Builder'!B35 -> 8 | C7: clients listed on the Package Builder
A8: or type your own number of clients | C8: optional override; leave empty to use the line above
A9: Clients used | B9: =IF(B8="",B7,B8) -> 8 | C9: your override if typed, otherwise the Package Builder figure
A10: Hours per client from Package Builder | B10: =IFERROR(ROUND('Package Builder'!F35/'Package Builder'!B35,2),0) -> 5.5 | C10: total hours ÷ clients
A11: or type your own hours per client | C11: optional override; leave empty to use the line above
A12: Hours per client used | B12: =IF(B11="",B10,B11) -> 5.5 | C12: your override if typed, otherwise the Package Builder figure
A13: Average fee from Package Builder | B13: =IFERROR(ROUND('Package Builder'!H35/'Package Builder'!B35,2),0) -> 477.5 | C13: monthly revenue at current fees ÷ clients
A14: or type your own average monthly fee | C14: optional override; leave empty to use the line above
A15: Average fee used | B15: =IF(B14="",B13,B14) -> 477.5 | C15: your override if typed, otherwise the Package Builder figure
A16: Max clients | B16: =IFERROR(INT(B6/B12),0) -> 18 | C16: usable hours ÷ hours per client, rounded down
A17: Hours used | B17: =ROUND(B9*B12,2) -> 44 | C17: clients × hours per client
A18: Spare hours per month | B18: =ROUND(B6-B17,2) -> 56.8 | C18: usable hours − hours used; negative means overbooked
A19: Open client slots | B19: =MAX(0,B16-B9) -> 10 | C19: max clients − clients used, never below zero
A20: Monthly revenue at capacity | B20: =ROUND(B16*B15,2) -> 8595 | C20: max clients × average fee
A21: Current monthly revenue | B21: =ROUND(B9*B15,2) -> 3820 | C21: clients × average fee
A22: Status | B22: =IF(B9>B16,"Overbooked by "&(B9-B16)&" clients",IF(B19>0,B19&" open client slots","At capacity")) -> 10 open client slots

Sheet Realization Log
A1: Realization Log
A2: One row per month, filled top down. The default rate comes from Settings; type your own standard rate in column D to override it for that month.
A4: Month | B4: Hours worked | C4: Default rate (Settings) | D4: or type your own rate | E4: Standard rate used | F4: Amount billed | G4: Amount collected | H4: Standard fees | I4: Billing realization % | J4: Collection realization % | K4: Overall realization % | L4: Write-offs | M4: Uncollected | N4: Effective rate
A5: 46023 | B5: 110 | C5: =IF(A5="","",Settings!$B$21) -> 90 | E5: =IF(A5="","",IF(D5<>"",D5,C5)) -> 90 | F5: 9200 | G5: 8800 | H5: =IF(A5="","",ROUND(B5*E5,2)) -> 9900 | I5: =IF(A5="","",IFERROR(ROUND(F5/H5*100,2),0)) -> 92.93 | J5: =IF(A5="","",IFERROR(ROUND(G5/F5*100,2),0)) -> 95.65 | K5: =IF(A5="","",IFERROR(ROUND(G5/H5*100,2),0)) -> 88.89 | L5: =IF(A5="","",H5-F5) -> 700 | M5: =IF(A5="","",F5-G5) -> 400 | N5: =IF(A5="","",IFERROR(ROUND(G5/B5,2),0)) -> 80
A6: 46054 | B6: 105 | C6: =IF(A6="","",Settings!$B$21) -> 90 | E6: =IF(A6="","",IF(D6<>"",D6,C6)) -> 90 | F6: 8900 | G6: 8700 | H6: =IF(A6="","",ROUND(B6*E6,2)) -> 9450 | I6: =IF(A6="","",IFERROR(ROUND(F6/H6*100,2),0)) -> 94.18 | J6: =IF(A6="","",IFERROR(ROUND(G6/F6*100,2),0)) -> 97.75 | K6: =IF(A6="","",IFERROR(ROUND(G6/H6*100,2),0)) -> 92.06 | L6: =IF(A6="","",H6-F6) -> 550 | M6: =IF(A6="","",F6-G6) -> 200 | N6: =IF(A6="","",IFERROR(ROUND(G6/B6,2),0)) -> 82.86
A7: 46082 | B7: 120 | C7: =IF(A7="","",Settings!$B$21) -> 90 | E7: =IF(A7="","",IF(D7<>"",D7,C7)) -> 90 | F7: 10300 | G7: 9500 | H7: =IF(A7="","",ROUND(B7*E7,2)) -> 10800 | I7: =IF(A7="","",IFERROR(ROUND(F7/H7*100,2),0)) -> 95.37 | J7: =IF(A7="","",IFERROR(ROUND(G7/F7*100,2),0)) -> 92.23 | K7: =IF(A7="","",IFERROR(ROUND(G7/H7*100,2),0)) -> 87.96 | L7: =IF(A7="","",H7-F7) -> 500 | M7: =IF(A7="","",F7-G7) -> 800 | N7: =IF(A7="","",IFERROR(ROUND(G7/B7,2),0)) -> 79.17
A8: 46113 | B8: 100 | C8: =IF(A8="","",Settings!$B$21) -> 90 | E8: =IF(A8="","",IF(D8<>"",D8,C8)) -> 90 | F8: 8600 | G8: 8400 | H8: =IF(A8="","",ROUND(B8*E8,2)) -> 9000 | I8: =IF(A8="","",IFERROR(ROUND(F8/H8*100,2),0)) -> 95.56 | J8: =IF(A8="","",IFERROR(ROUND(G8/F8*100,2),0)) -> 97.67 | K8: =IF(A8="","",IFERROR(ROUND(G8/H8*100,2),0)) -> 93.33 | L8: =IF(A8="","",H8-F8) -> 400 | M8: =IF(A8="","",F8-G8) -> 200 | N8: =IF(A8="","",IFERROR(ROUND(G8/B8,2),0)) -> 84
A9: 46143 | B9: 115 | C9: =IF(A9="","",Settings!$B$21) -> 90 | E9: =IF(A9="","",IF(D9<>"",D9,C9)) -> 90 | F9: 9800 | G9: 9600 | H9: =IF(A9="","",ROUND(B9*E9,2)) -> 10350 | I9: =IF(A9="","",IFERROR(ROUND(F9/H9*100,2),0)) -> 94.69 | J9: =IF(A9="","",IFERROR(ROUND(G9/F9*100,2),0)) -> 97.96 | K9: =IF(A9="","",IFERROR(ROUND(G9/H9*100,2),0)) -> 92.75 | L9: =IF(A9="","",H9-F9) -> 550 | M9: =IF(A9="","",F9-G9) -> 200 | N9: =IF(A9="","",IFERROR(ROUND(G9/B9,2),0)) -> 83.48
A10: 46174 | B10: 108 | C10: =IF(A10="","",Settings!$B$21) -> 90 | E10: =IF(A10="","",IF(D10<>"",D10,C10)) -> 90 | F10: 9300 | G10: 8900 | H10: =IF(A10="","",ROUND(B10*E10,2)) -> 9720 | I10: =IF(A10="","",IFERROR(ROUND(F10/H10*100,2),0)) -> 95.68 | J10: =IF(A10="","",IFERROR(ROUND(G10/F10*100,2),0)) -> 95.7 | K10: =IF(A10="","",IFERROR(ROUND(G10/H10*100,2),0)) -> 91.56 | L10: =IF(A10="","",H10-F10) -> 420 | M10: =IF(A10="","",F10-G10) -> 400 | N10: =IF(A10="","",IFERROR(ROUND(G10/B10,2),0)) -> 82.41
C11: =IF(A11="","",Settings!$B$21) | E11: =IF(A11="","",IF(D11<>"",D11,C11)) | H11: =IF(A11="","",ROUND(B11*E11,2)) | I11: =IF(A11="","",IFERROR(ROUND(F11/H11*100,2),0)) | J11: =IF(A11="","",IFERROR(ROUND(G11/F11*100,2),0)) | K11: =IF(A11="","",IFERROR(ROUND(G11/H11*100,2),0)) | L11: =IF(A11="","",H11-F11) | M11: =IF(A11="","",F11-G11) | N11: =IF(A11="","",IFERROR(ROUND(G11/B11,2),0))
C12: =IF(A12="","",Settings!$B$21) | E12: =IF(A12="","",IF(D12<>"",D12,C12)) | H12: =IF(A12="","",ROUND(B12*E12,2)) | I12: =IF(A12="","",IFERROR(ROUND(F12/H12*100,2),0)) | J12: =IF(A12="","",IFERROR(ROUND(G12/F12*100,2),0)) | K12: =IF(A12="","",IFERROR(ROUND(G12/H12*100,2),0)) | L12: =IF(A12="","",H12-F12) | M12: =IF(A12="","",F12-G12) | N12: =IF(A12="","",IFERROR(ROUND(G12/B12,2),0))
C13: =IF(A13="","",Settings!$B$21) | E13: =IF(A13="","",IF(D13<>"",D13,C13)) | H13: =IF(A13="","",ROUND(B13*E13,2)) | I13: =IF(A13="","",IFERROR(ROUND(F13/H13*100,2),0)) | J13: =IF(A13="","",IFERROR(ROUND(G13/F13*100,2),0)) | K13: =IF(A13="","",IFERROR(ROUND(G13/H13*100,2),0)) | L13: =IF(A13="","",H13-F13) | M13: =IF(A13="","",F13-G13) | N13: =IF(A13="","",IFERROR(ROUND(G13/B13,2),0))
C14: =IF(A14="","",Settings!$B$21) | E14: =IF(A14="","",IF(D14<>"",D14,C14)) | H14: =IF(A14="","",ROUND(B14*E14,2)) | I14: =IF(A14="","",IFERROR(ROUND(F14/H14*100,2),0)) | J14: =IF(A14="","",IFERROR(ROUND(G14/F14*100,2),0)) | K14: =IF(A14="","",IFERROR(ROUND(G14/H14*100,2),0)) | L14: =IF(A14="","",H14-F14) | M14: =IF(A14="","",F14-G14) | N14: =IF(A14="","",IFERROR(ROUND(G14/B14,2),0))
C15: =IF(A15="","",Settings!$B$21) | E15: =IF(A15="","",IF(D15<>"",D15,C15)) | H15: =IF(A15="","",ROUND(B15*E15,2)) | I15: =IF(A15="","",IFERROR(ROUND(F15/H15*100,2),0)) | J15: =IF(A15="","",IFERROR(ROUND(G15/F15*100,2),0)) | K15: =IF(A15="","",IFERROR(ROUND(G15/H15*100,2),0)) | L15: =IF(A15="","",H15-F15) | M15: =IF(A15="","",F15-G15) | N15: =IF(A15="","",IFERROR(ROUND(G15/B15,2),0))
C16: =IF(A16="","",Settings!$B$21) | E16: =IF(A16="","",IF(D16<>"",D16,C16)) | H16: =IF(A16="","",ROUND(B16*E16,2)) | I16: =IF(A16="","",IFERROR(ROUND(F16/H16*100,2),0)) | J16: =IF(A16="","",IFERROR(ROUND(G16/F16*100,2),0)) | K16: =IF(A16="","",IFERROR(ROUND(G16/H16*100,2),0)) | L16: =IF(A16="","",H16-F16) | M16: =IF(A16="","",F16-G16) | N16: =IF(A16="","",IFERROR(ROUND(G16/B16,2),0))
A17: Total | B17: =SUM(B5:B16) -> 658 | F17: =SUM(F5:F16) -> 56100 | G17: =SUM(G5:G16) -> 53900 | H17: =SUM(H5:H16) -> 59220 | I17: =IFERROR(ROUND(F17/H17*100,2),0) -> 94.73 | J17: =IFERROR(ROUND(G17/F17*100,2),0) -> 96.08 | K17: =IFERROR(ROUND(G17/H17*100,2),0) -> 91.02 | L17: =SUM(L5:L16) -> 3120 | M17: =SUM(M5:M16) -> 2200 | N17: =IFERROR(ROUND(G17/B17,2),0) -> 81.91

Sheet Summary
A1: Summary
A2: Cost-recovery hourly rate | B2: =Settings!$B$20 -> 48.21 | C2: from Settings
A3: Rate used for pricing | B3: =Settings!$B$21 -> 90 | C3: from Settings; keep it at or above the cost-recovery rate
A4: Clients on the Package Builder | B4: ='Package Builder'!B35 -> 8
A5: Clients priced below recommended | B5: =COUNTIF('Package Builder'!N5:N34,"<0") -> 4 | C5: gap column below zero
A6: Monthly revenue at current fees | B6: ='Package Builder'!H35 -> 3820
A7: Annual revenue at current fees | B7: ='Package Builder'!P35 -> 45840
A8: Monthly revenue at recommended fees | B8: ='Package Builder'!M35 -> 4491.47 | C8: if every client moved to the recommended fee
A9: Monthly uplift | B9: =B8-B6 -> 671.47 | C9: recommended − current; negative means you charge above recommended overall
A10: Annual uplift | B10: =ROUND(B9*12,2) -> 8057.64 | C10: monthly uplift × 12
A11: Highest effective hourly rate client | B11: =IFERROR(INDEX('Package Builder'!A5:A34,MATCH(MAX('Package Builder'!O5:O34),'Package Builder'!O5:O34,0)),"") -> Mason Family Trust | C11: current fee ÷ hours
A12: Lowest effective hourly rate client | B12: =IFERROR(INDEX('Package Builder'!A5:A34,MATCH(MIN('Package Builder'!O5:O34),'Package Builder'!O5:O34,0)),"") -> Nguyen Builders Ltd | C12: re-price first
A13: Open client slots | B13: =Capacity!B19 -> 10 | C13: from Capacity
A14: Spare hours per month | B14: =Capacity!B18 -> 56.8 | C14: from Capacity
A15: Year-to-date billing realization | B15: ='Realization Log'!I17 -> 94.73 | C15: Realization Log totals
A16: Year-to-date collection realization | B16: ='Realization Log'!J17 -> 96.08 | C16: Realization Log totals
A17: Year-to-date overall realization | B17: ='Realization Log'!K17 -> 91.02 | C17: Realization Log totals
A18: Year-to-date write-offs | B18: ='Realization Log'!L17 -> 3120 | C18: standard fees not billed
A19: Year-to-date uncollected | B19: ='Realization Log'!M17 -> 2200 | C19: billed but not collected
